Workbook
Name cHora: Config!$C$19
Name pCom: Config!$C$7
Name pFixo: Config!$C$14
Name pImp: Config!$C$6
Name pLucro: Config!$C$9
Name ProdNome: Produtos!$B$5:$B$304
Name pTax: Config!$C$8

Sheet Início
A1: Precificador de Produtos e Serviços
A2: Carvex XLS · Preço certo = lucro garantido
B4: O que esta planilha faz
B5: Calcule o preço de venda de cada produto e serviço considerando custo, impostos, comissão, taxa de cartão/marketplace, despesas fixas e o lucro que você quer. Descubra quais itens dão prejuízo e quanto custa dar desconto.
B7: Como começar (5 minutos)
B8: 1. Config | C8: Informe impostos, comissão, taxa de pagamento, lucro desejado, custos fixos mensais e faturamento médio. A planilha calcula o rateio de despesa fixa e o custo da sua hora.
B9: 2. Cadastre os produtos | C9: Em Produtos, informe o custo de cada item (compra ou produção) e, se quiser, o preço que pratica hoje.
B10: 3. Cadastre os serviços | C10: Em Serviços, informe horas gastas e materiais. O custo da hora vem da Config.
B11: 4. Leia o preço sugerido | C11: A coluna Preço sugerido já considera todos os custos e o lucro. A coluna Status avisa se seu preço atual dá PREJUÍZO.
B12: 5. Simule descontos | C12: Na aba Simulador, escolha o produto e o desconto e veja quanto precisa vender a mais para manter o lucro.
B14: Mapa das abas (clique para ir)
B15: Config | C15: Parâmetros gerais: impostos, comissão, taxa, lucro, custos fixos, custo da hora.
B16: Produtos | C16: Cadastro e preço de venda de produtos (até 300).
B17: Serviços | C17: Cadastro e preço de serviços (até 100).
B18: Simulador | C18: Quanto custa dar desconto: lucro por unidade e vendas extras necessárias.
B19: Resumo | C19: Quantos itens estão em prejuízo, margem média e gráfico de margem.
B21: Legenda de cores
B22: Amarelo | C22: Célula que VOCÊ preenche.
B23: Cinza | C23: Cálculo automático. Não digite aqui.
B24: Verde escuro | C24: Cabeçalho de coluna.
B26: Atenção
B27: • Todos os percentuais são sobre o PREÇO DE VENDA (não sobre o custo).
B28: • Se a soma dos percentuais chegar a 100%, o preço não pode ser calculado e a planilha mostra 'Revisar %'.
B29: • Nas colunas de % por item (amarelas), deixe em branco para usar o padrão da Config; digite 0% se o item não tem aquele custo.
B31: Carvex XLS · Precificador de Produtos e Serviços · versão 1.0 · Dúvidas: consulte o TUTORIAL.md e o MANUAL.md que acompanham o produto.

Sheet Config
A1: Configurações gerais
A2: Percentuais sobre o preço de venda. Valem para todos os itens, exceto quando você digita um percentual específico.
B4: Empresa
B5: Percentuais padrão (sobre o preço de venda)
B6: Impostos sobre a venda (%) | D6: Simples/Presumido: percentual efetivo do seu faturamento (confirme com seu contador).
B7: Comissão de vendedores (%) | D7: Média paga a vendedores/representantes.
B8: Taxa de pagamento / plataforma (%) | D8: Cartão, Pix, marketplace. Use a média ponderada dos seus canais.
B9: Lucro líquido desejado (%) | D9: Quanto deve sobrar de cada venda depois de pagar tudo.
B11: Despesas fixas
B12: Custos fixos mensais (R$) | D12: Aluguel, salários, energia, contador, sistemas... (sem pró-labore).
B13: Faturamento médio mensal (R$) | D13: Média dos últimos 6 meses. Se não souber, use uma estimativa realista.
B14: Despesa fixa rateada (%) | C14: =IFERROR(C12/C13,0) -> 0 | D14: Calculado: custos fixos / faturamento. É somado ao preço dos produtos.
B16: Serviços: custo da hora
B17: Pró-labore desejado por mês (R$) | D17: Quanto o dono precisa tirar por mês.
B18: Horas produtivas por mês | D18: Horas realmente vendáveis (ex.: 6h x 20 dias = 120). Não use 220h.
B19: Custo da hora (R$) | C19: =IFERROR((C12+C17)/C18,0) -> 0 | D19: Calculado: (custos fixos + pró-labore) / horas produtivas.
B21: Dica: sem esses números, o preço calculado fica errado. Se ainda não sabe, comece com estimativas e refine depois.

Sheet Produtos
A1: Produtos
A2: Preencha as colunas amarelas. Percentuais em branco usam o padrão da Config.
A4: Código | B4: Produto | C4: Categoria | D4: Custo de compra / produção (R$) | E4: Frete / embalagem por un. (R$) | F4: Imposto % (opcional) | G4: Comissão % (opcional) | H4: Taxa pagto % (opcional) | I4: Lucro % (opcional) | J4: Preço do concorrente (R$) | K4: Preço que pratico hoje (R$) | L4: Custo total (R$) | M4: % sobre o preço (soma) | N4: Preço calculado (exato) | O4: PREÇO SUGERIDO | P4: Markup sobre o custo | Q4: Preço mínimo (lucro zero) | R4: Lucro por un. no preço atual | S4: Margem líquida no preço atual | T4: Status | U4: Vs. concorrente
L5: =IF(OR($B5="",$D5=""),"",$D5+N($E5)) | M5: =IF($L5="","",IF($F5="",pImp,$F5)+IF($G5="",pCom,$G5)+IF($H5="",pTax,$H5)+pFixo+IF($I5="",pLucro,$I5)) | N5: =IF($L5="","",IF($M5>=1,"Revisar %",$L5/(1-$M5))) | O5: =IF(ISNUMBER($N5),ROUNDUP($N5,0)+IF(ROUNDUP($N5,0)-0.1>=$N5,-0.1,0.9),$N5) | P5: =IF(AND(ISNUMBER($O5),N($L5)>0),$O5/$L5,"") | Q5: =IF(ISNUMBER($N5),$L5/(1-($M5-IF($I5="",pLucro,$I5))),"") | R5: =IF(OR($K5="",NOT(ISNUMBER($N5))),"",$K5*(1-($M5-IF($I5="",pLucro,$I5)))-$L5) | S5: =IF($R5="","",$R5/$K5) | T5: =IF($L5="","",IF(NOT(ISNUMBER($N5)),"Revisar %",IF($K5="","Sem preço atual",IF($R5<0,"PREJUÍZO",IF($K5<$N5,"Abaixo do ideal","OK"))))) | U5: =IF(OR($J5="",NOT(ISNUMBER($O5))),"",IF($O5<=$J5,"Competitivo ("&ROUND(($O5/$J5-1)*100,1)&"%)","Acima do concorrente (+"&ROUND(($O5/$J5-1)*100,1)&"%)"))
L6: =IF(OR($B6="",$D6=""),"",$D6+N($E6)) | M6: =IF($L6="","",IF($F6="",pImp,$F6)+IF($G6="",pCom,$G6)+IF($H6="",pTax,$H6)+pFixo+IF($I6="",pLucro,$I6)) | N6: =IF($L6="","",IF($M6>=1,"Revisar %",$L6/(1-$M6))) | O6: =IF(ISNUMBER($N6),ROUNDUP($N6,0)+IF(ROUNDUP($N6,0)-0.1>=$N6,-0.1,0.9),$N6) | P6: =IF(AND(ISNUMBER($O6),N($L6)>0),$O6/$L6,"") | Q6: =IF(ISNUMBER($N6),$L6/(1-($M6-IF($I6="",pLucro,$I6))),"") | R6: =IF(OR($K6="",NOT(ISNUMBER($N6))),"",$K6*(1-($M6-IF($I6="",pLucro,$I6)))-$L6) | S6: =IF($R6="","",$R6/$K6) | T6: =IF($L6="","",IF(NOT(ISNUMBER($N6)),"Revisar %",IF($K6="","Sem preço atual",IF($R6<0,"PREJUÍZO",IF($K6<$N6,"Abaixo do ideal","OK"))))) | U6: =IF(OR($J6="",NOT(ISNUMBER($O6))),"",IF($O6<=$J6,"Competitivo ("&ROUND(($O6/$J6-1)*100,1)&"%)","Acima do concorrente (+"&ROUND(($O6/$J6-1)*100,1)&"%)"))
L7: =IF(OR($B7="",$D7=""),"",$D7+N($E7)) | M7: =IF($L7="","",IF($F7="",pImp,$F7)+IF($G7="",pCom,$G7)+IF($H7="",pTax,$H7)+pFixo+IF($I7="",pLucro,$I7)) | N7: =IF($L7="","",IF($M7>=1,"Revisar %",$L7/(1-$M7))) | O7: =IF(ISNUMBER($N7),ROUNDUP($N7,0)+IF(ROUNDUP($N7,0)-0.1>=$N7,-0.1,0.9),$N7) | P7: =IF(AND(ISNUMBER($O7),N($L7)>0),$O7/$L7,"") | Q7: =IF(ISNUMBER($N7),$L7/(1-($M7-IF($I7="",pLucro,$I7))),"") | R7: =IF(OR($K7="",NOT(ISNUMBER($N7))),"",$K7*(1-($M7-IF($I7="",pLucro,$I7)))-$L7) | S7: =IF($R7="","",$R7/$K7) | T7: =IF($L7="","",IF(NOT(ISNUMBER($N7)),"Revisar %",IF($K7="","Sem preço atual",IF($R7<0,"PREJUÍZO",IF($K7<$N7,"Abaixo do ideal","OK"))))) | U7: =IF(OR($J7="",NOT(ISNUMBER($O7))),"",IF($O7<=$J7,"Competitivo ("&ROUND(($O7/$J7-1)*100,1)&"%)","Acima do concorrente (+"&ROUND(($O7/$J7-1)*100,1)&"%)"))
L8: =IF(OR($B8="",$D8=""),"",$D8+N($E8)) | M8: =IF($L8="","",IF($F8="",pImp,$F8)+IF($G8="",pCom,$G8)+IF($H8="",pTax,$H8)+pFixo+IF($I8="",pLucro,$I8)) | N8: =IF($L8="","",IF($M8>=1,"Revisar %",$L8/(1-$M8))) | O8: =IF(ISNUMBER($N8),ROUNDUP($N8,0)+IF(ROUNDUP($N8,0)-0.1>=$N8,-0.1,0.9),$N8) | P8: =IF(AND(ISNUMBER($O8),N($L8)>0),$O8/$L8,"") | Q8: =IF(ISNUMBER($N8),$L8/(1-($M8-IF($I8="",pLucro,$I8))),"") | R8: =IF(OR($K8="",NOT(ISNUMBER($N8))),"",$K8*(1-($M8-IF($I8="",pLucro,$I8)))-$L8) | S8: =IF($R8="","",$R8/$K8) | T8: =IF($L8="","",IF(NOT(ISNUMBER($N8)),"Revisar %",IF($K8="","Sem preço atual",IF($R8<0,"PREJUÍZO",IF($K8<$N8,"Abaixo do ideal","OK"))))) | U8: =IF(OR($J8="",NOT(ISNUMBER($O8))),"",IF($O8<=$J8,"Competitivo ("&ROUND(($O8/$J8-1)*100,1)&"%)","Acima do concorrente (+"&ROUND(($O8/$J8-1)*100,1)&"%)"))
L9: =IF(OR($B9="",$D9=""),"",$D9+N($E9)) | M9: =IF($L9="","",IF($F9="",pImp,$F9)+IF($G9="",pCom,$G9)+IF($H9="",pTax,$H9)+pFixo+IF($I9="",pLucro,$I9)) | N9: =IF($L9="","",IF($M9>=1,"Revisar %",$L9/(1-$M9))) | O9: =IF(ISNUMBER($N9),ROUNDUP($N9,0)+IF(ROUNDUP($N9,0)-0.1>=$N9,-0.1,0.9),$N9) | P9: =IF(AND(ISNUMBER($O9),N($L9)>0),$O9/$L9,"") | Q9: =IF(ISNUMBER($N9),$L9/(1-($M9-IF($I9="",pLucro,$I9))),"") | R9: =IF(OR($K9="",NOT(ISNUMBER($N9))),"",$K9*(1-($M9-IF($I9="",pLucro,$I9)))-$L9) | S9: =IF($R9="","",$R9/$K9) | T9: =IF($L9="","",IF(NOT(ISNUMBER($N9)),"Revisar %",IF($K9="","Sem preço atual",IF($R9<0,"PREJUÍZO",IF($K9<$N9,"Abaixo do ideal","OK"))))) | U9: =IF(OR($J9="",NOT(ISNUMBER($O9))),"",IF($O9<=$J9,"Competitivo ("&ROUND(($O9/$J9-1)*100,1)&"%)","Acima do concorrente (+"&ROUND(($O9/$J9-1)*100,1)&"%)"))
L10: =IF(OR($B10="",$D10=""),"",$D10+N($E10)) | M10: =IF($L10="","",IF($F10="",pImp,$F10)+IF($G10="",pCom,$G10)+IF($H10="",pTax,$H10)+pFixo+IF($I10="",pLucro,$I10)) | N10: =IF($L10="","",IF($M10>=1,"Revisar %",$L10/(1-$M10))) | O10: =IF(ISNUMBER($N10),ROUNDUP($N10,0)+IF(ROUNDUP($N10,0)-0.1>=$N10,-0.1,0.9),$N10) | P10: =IF(AND(ISNUMBER($O10),N($L10)>0),$O10/$L10,"") | Q10: =IF(ISNUMBER($N10),$L10/(1-($M10-IF($I10="",pLucro,$I10))),"") | R10: =IF(OR($K10="",NOT(ISNUMBER($N10))),"",$K10*(1-($M10-IF($I10="",pLucro,$I10)))-$L10) | S10: =IF($R10="","",$R10/$K10) | T10: =IF($L10="","",IF(NOT(ISNUMBER($N10)),"Revisar %",IF($K10="","Sem preço atual",IF($R10<0,"PREJUÍZO",IF($K10<$N10,"Abaixo do ideal","OK"))))) | U10: =IF(OR($J10="",NOT(ISNUMBER($O10))),"",IF($O10<=$J10,"Competitivo ("&ROUND(($O10/$J10-1)*100,1)&"%)","Acima do concorrente (+"&ROUND(($O10/$J10-1)*100,1)&"%)"))
L11: =IF(OR($B11="",$D11=""),"",$D11+N($E11)) | M11: =IF($L11="","",IF($F11="",pImp,$F11)+IF($G11="",pCom,$G11)+IF($H11="",pTax,$H11)+pFixo+IF($I11="",pLucro,$I11)) | N11: =IF($L11="","",IF($M11>=1,"Revisar %",$L11/(1-$M11))) | O11: =IF(ISNUMBER($N11),ROUNDUP($N11,0)+IF(ROUNDUP($N11,0)-0.1>=$N11,-0.1,0.9),$N11) | P11: =IF(AND(ISNUMBER($O11),N($L11)>0),$O11/$L11,"") | Q11: =IF(ISNUMBER($N11),$L11/(1-($M11-IF($I11="",pLucro,$I11))),"") | R11: =IF(OR($K11="",NOT(ISNUMBER($N11))),"",$K11*(1-($M11-IF($I11="",pLucro,$I11)))-$L11) | S11: =IF($R11="","",$R11/$K11) | T11: =IF($L11="","",IF(NOT(ISNUMBER($N11)),"Revisar %",IF($K11="","Sem preço atual",IF($R11<0,"PREJUÍZO",IF($K11<$N11,"Abaixo do ideal","OK"))))) | U11: =IF(OR($J11="",NOT(ISNUMBER($O11))),"",IF($O11<=$J11,"Competitivo ("&ROUND(($O11/$J11-1)*100,1)&"%)","Acima do concorrente (+"&ROUND(($O11/$J11-1)*100,1)&"%)"))
L12: =IF(OR($B12="",$D12=""),"",$D12+N($E12)) | M12: =IF($L12="","",IF($F12="",pImp,$F12)+IF($G12="",pCom,$G12)+IF($H12="",pTax,$H12)+pFixo+IF($I12="",pLucro,$I12)) | N12: =IF($L12="","",IF($M12>=1,"Revisar %",$L12/(1-$M12))) | O12: =IF(ISNUMBER($N12),ROUNDUP($N12,0)+IF(ROUNDUP($N12,0)-0.1>=$N12,-0.1,0.9),$N12) | P12: =IF(AND(ISNUMBER($O12),N($L12)>0),$O12/$L12,"") | Q12: =IF(ISNUMBER($N12),$L12/(1-($M12-IF($I12="",pLucro,$I12))),"") | R12: =IF(OR($K12="",NOT(ISNUMBER($N12))),"",$K12*(1-($M12-IF($I12="",pLucro,$I12)))-$L12) | S12: =IF($R12="","",$R12/$K12) | T12: =IF($L12="","",IF(NOT(ISNUMBER($N12)),"Revisar %",IF($K12="","Sem preço atual",IF($R12<0,"PREJUÍZO",IF($K12<$N12,"Abaixo do ideal","OK"))))) | U12: =IF(OR($J12="",NOT(ISNUMBER($O12))),"",IF($O12<=$J12,"Competitivo ("&ROUND(($O12/$J12-1)*100,1)&"%)","Acima do concorrente (+"&ROUND(($O12/$J12-1)*100,1)&"%)"))
L13: =IF(OR($B13="",$D13=""),"",$D13+N($E13)) | M13: =IF($L13="","",IF($F13="",pImp,$F13)+IF($G13="",pCom,$G13)+IF($H13="",pTax,$H13)+pFixo+IF($I13="",pLucro,$I13)) | N13: =IF($L13="","",IF($M13>=1,"Revisar %",$L13/(1-$M13))) | O13: =IF(ISNUMBER($N13),ROUNDUP($N13,0)+IF(ROUNDUP($N13,0)-0.1>=$N13,-0.1,0.9),$N13) | P13: =IF(AND(ISNUMBER($O13),N($L13)>0),$O13/$L13,"") | Q13: =IF(ISNUMBER($N13),$L13/(1-($M13-IF($I13="",pLucro,$I13))),"") | R13: =IF(OR($K13="",NOT(ISNUMBER($N13))),"",$K13*(1-($M13-IF($I13="",pLucro,$I13)))-$L13) | S13: =IF($R13="","",$R13/$K13) | T13: =IF($L13="","",IF(NOT(ISNUMBER($N13)),"Revisar %",IF($K13="","Sem preço atual",IF($R13<0,"PREJUÍZO",IF($K13<$N13,"Abaixo do ideal","OK"))))) | U13: =IF(OR($J13="",NOT(ISNUMBER($O13))),"",IF($O13<=$J13,"Competitivo ("&ROUND(($O13/$J13-1)*100,1)&"%)","Acima do concorrente (+"&ROUND(($O13/$J13-1)*100,1)&"%)"))
L14: =IF(OR($B14="",$D14=""),"",$D14+N($E14)) | M14: =IF($L14="","",IF($F14="",pImp,$F14)+IF($G14="",pCom,$G14)+IF($H14="",pTax,$H14)+pFixo+IF($I14="",pLucro,$I14)) | N14: =IF($L14="","",IF($M14>=1,"Revisar %",$L14/(1-$M14))) | O14: =IF(ISNUMBER($N14),ROUNDUP($N14,0)+IF(ROUNDUP($N14,0)-0.1>=$N14,-0.1,0.9),$N14) | P14: =IF(AND(ISNUMBER($O14),N($L14)>0),$O14/$L14,"") | Q14: =IF(ISNUMBER($N14),$L14/(1-($M14-IF($I14="",pLucro,$I14))),"") | R14: =IF(OR($K14="",NOT(ISNUMBER($N14))),"",$K14*(1-($M14-IF($I14="",pLucro,$I14)))-$L14) | S14: =IF($R14="","",$R14/$K14) | T14: =IF($L14="","",IF(NOT(ISNUMBER($N14)),"Revisar %",IF($K14="","Sem preço atual",IF($R14<0,"PREJUÍZO",IF($K14<$N14,"Abaixo do ideal","OK"))))) | U14: =IF(OR($J14="",NOT(ISNUMBER($O14))),"",IF($O14<=$J14,"Competitivo ("&ROUND(($O14/$J14-1)*100,1)&"%)","Acima do concorrente (+"&ROUND(($O14/$J14-1)*100,1)&"%)"))
L15: =IF(OR($B15="",$D15=""),"",$D15+N($E15)) | M15: =IF($L15="","",IF($F15="",pImp,$F15)+IF($G15="",pCom,$G15)+IF($H15="",pTax,$H15)+pFixo+IF($I15="",pLucro,$I15)) | N15: =IF($L15="","",IF($M15>=1,"Revisar %",$L15/(1-$M15))) | O15: =IF(ISNUMBER($N15),ROUNDUP($N15,0)+IF(ROUNDUP($N15,0)-0.1>=$N15,-0.1,0.9),$N15) | P15: =IF(AND(ISNUMBER($O15),N($L15)>0),$O15/$L15,"") | Q15: =IF(ISNUMBER($N15),$L15/(1-($M15-IF($I15="",pLucro,$I15))),"") | R15: =IF(OR($K15="",NOT(ISNUMBER($N15))),"",$K15*(1-($M15-IF($I15="",pLucro,$I15)))-$L15) | S15: =IF($R15="","",$R15/$K15) | T15: =IF($L15="","",IF(NOT(ISNUMBER($N15)),"Revisar %",IF($K15="","Sem preço atual",IF($R15<0,"PREJUÍZO",IF($K15<$N15,"Abaixo do ideal","OK"))))) | U15: =IF(OR($J15="",NOT(ISNUMBER($O15))),"",IF($O15<=$J15,"Competitivo ("&ROUND(($O15/$J15-1)*100,1)&"%)","Acima do concorrente (+"&ROUND(($O15/$J15-1)*100,1)&"%)"))
L16: =IF(OR($B16="",$D16=""),"",$D16+N($E16)) | M16: =IF($L16="","",IF($F16="",pImp,$F16)+IF($G16="",pCom,$G16)+IF($H16="",pTax,$H16)+pFixo+IF($I16="",pLucro,$I16)) | N16: =IF($L16="","",IF($M16>=1,"Revisar %",$L16/(1-$M16))) | O16: =IF(ISNUMBER($N16),ROUNDUP($N16,0)+IF(ROUNDUP($N16,0)-0.1>=$N16,-0.1,0.9),$N16) | P16: =IF(AND(ISNUMBER($O16),N($L16)>0),$O16/$L16,"") | Q16: =IF(ISNUMBER($N16),$L16/(1-($M16-IF($I16="",pLucro,$I16))),"") | R16: =IF(OR($K16="",NOT(ISNUMBER($N16))),"",$K16*(1-($M16-IF($I16="",pLucro,$I16)))-$L16) | S16: =IF($R16="","",$R16/$K16) | T16: =IF($L16="","",IF(NOT(ISNUMBER($N16)),"Revisar %",IF($K16="","Sem preço atual",IF($R16<0,"PREJUÍZO",IF($K16<$N16,"Abaixo do ideal","OK"))))) | U16: =IF(OR($J16="",NOT(ISNUMBER($O16))),"",IF($O16<=$J16,"Competitivo ("&ROUND(($O16/$J16-1)*100,1)&"%)","Acima do concorrente (+"&ROUND(($O16/$J16-1)*100,1)&"%)"))
... L304: =IF(OR($B304="",$D304=""),"",$D304+N($E304)) | M304: =IF($L304="","",IF($F304="",pImp,$F304)+IF($G304="",pCom,$G304)+IF($H304="",pTax,$H304)+pFixo+IF($I304="",pLucro,$I304)) | N304: =IF($L304="","",IF($M304>=1,"Revisar %",$L304/(1-$M304))) | O304: =IF(ISNUMBER($N304),ROUNDUP($N304,0)+IF(ROUNDUP($N304,0)-0.1>=$N304,-0.1,0.9),$N304) | P304: =IF(AND(ISNUMBER($O304),N($L304)>0),$O304/$L304,"") | Q304: =IF(ISNUMBER($N304),$L304/(1-($M304-IF($I304="",pLucro,$I304))),"") | R304: =IF(OR($K304="",NOT(ISNUMBER($N304))),"",$K304*(1-($M304-IF($I304="",pLucro,$I304)))-$L304) | S304: =IF($R304="","",$R304/$K304) | T304: =IF($L304="","",IF(NOT(ISNUMBER($N304)),"Revisar %",IF($K304="","Sem preço atual",IF($R304<0,"PREJUÍZO",IF($K304<$N304,"Abaixo do ideal","OK"))))) | U304: =IF(OR($J304="",NOT(ISNUMBER($O304))),"",IF($O304<=$J304,"Competitivo ("&ROUND(($O304/$J304-1)*100,1)&"%)","Acima do concorrente (+"&ROUND(($O304/$J304-1)*100,1)&"%)"))

Sheet Serviços
A1: Serviços
A2: O custo da hora vem da Config (custos fixos + pró-labore / horas produtivas).
A4: Serviço | B4: Categoria | C4: Horas gastas | D4: Materiais (R$) | E4: Deslocamento / outros (R$) | F4: Imposto % (opcional) | G4: Comissão % (opcional) | H4: Taxa pagto % (opcional) | I4: Lucro % (opcional) | J4: Preço que pratico hoje (R$) | K4: Custo da mão de obra (R$) | L4: Custo total (R$) | M4: % sobre o preço (soma) | N4: Preço calculado (exato) | O4: PREÇO SUGERIDO | P4: Valor da hora no preço sugerido | Q4: Lucro no preço atual (R$) | R4: Margem no preço atual | S4: Status
K5: =IF(OR($A5="",$C5=""),"",$C5*cHora) | L5: =IF($K5="","",$K5+N($D5)+N($E5)) | M5: =IF($L5="","",IF($F5="",pImp,$F5)+IF($G5="",pCom,$G5)+IF($H5="",pTax,$H5)+IF($I5="",pLucro,$I5)) | N5: =IF($L5="","",IF($M5>=1,"Revisar %",$L5/(1-$M5))) | O5: =IF(ISNUMBER($N5),ROUNDUP($N5,0)+IF(ROUNDUP($N5,0)-0.1>=$N5,-0.1,0.9),$N5) | P5: =IF(AND(ISNUMBER($O5),N($C5)>0),$O5/$C5,"") | Q5: =IF(OR($J5="",NOT(ISNUMBER($N5))),"",$J5*(1-($M5-IF($I5="",pLucro,$I5)))-$L5) | R5: =IF($Q5="","",$Q5/$J5) | S5: =IF($L5="","",IF(NOT(ISNUMBER($N5)),"Revisar %",IF($J5="","Sem preço atual",IF($Q5<0,"PREJUÍZO",IF($J5<$N5,"Abaixo do ideal","OK")))))
K6: =IF(OR($A6="",$C6=""),"",$C6*cHora) | L6: =IF($K6="","",$K6+N($D6)+N($E6)) | M6: =IF($L6="","",IF($F6="",pImp,$F6)+IF($G6="",pCom,$G6)+IF($H6="",pTax,$H6)+IF($I6="",pLucro,$I6)) | N6: =IF($L6="","",IF($M6>=1,"Revisar %",$L6/(1-$M6))) | O6: =IF(ISNUMBER($N6),ROUNDUP($N6,0)+IF(ROUNDUP($N6,0)-0.1>=$N6,-0.1,0.9),$N6) | P6: =IF(AND(ISNUMBER($O6),N($C6)>0),$O6/$C6,"") | Q6: =IF(OR($J6="",NOT(ISNUMBER($N6))),"",$J6*(1-($M6-IF($I6="",pLucro,$I6)))-$L6) | R6: =IF($Q6="","",$Q6/$J6) | S6: =IF($L6="","",IF(NOT(ISNUMBER($N6)),"Revisar %",IF($J6="","Sem preço atual",IF($Q6<0,"PREJUÍZO",IF($J6<$N6,"Abaixo do ideal","OK")))))
K7: =IF(OR($A7="",$C7=""),"",$C7*cHora) | L7: =IF($K7="","",$K7+N($D7)+N($E7)) | M7: =IF($L7="","",IF($F7="",pImp,$F7)+IF($G7="",pCom,$G7)+IF($H7="",pTax,$H7)+IF($I7="",pLucro,$I7)) | N7: =IF($L7="","",IF($M7>=1,"Revisar %",$L7/(1-$M7))) | O7: =IF(ISNUMBER($N7),ROUNDUP($N7,0)+IF(ROUNDUP($N7,0)-0.1>=$N7,-0.1,0.9),$N7) | P7: =IF(AND(ISNUMBER($O7),N($C7)>0),$O7/$C7,"") | Q7: =IF(OR($J7="",NOT(ISNUMBER($N7))),"",$J7*(1-($M7-IF($I7="",pLucro,$I7)))-$L7) | R7: =IF($Q7="","",$Q7/$J7) | S7: =IF($L7="","",IF(NOT(ISNUMBER($N7)),"Revisar %",IF($J7="","Sem preço atual",IF($Q7<0,"PREJUÍZO",IF($J7<$N7,"Abaixo do ideal","OK")))))
K8: =IF(OR($A8="",$C8=""),"",$C8*cHora) | L8: =IF($K8="","",$K8+N($D8)+N($E8)) | M8: =IF($L8="","",IF($F8="",pImp,$F8)+IF($G8="",pCom,$G8)+IF($H8="",pTax,$H8)+IF($I8="",pLucro,$I8)) | N8: =IF($L8="","",IF($M8>=1,"Revisar %",$L8/(1-$M8))) | O8: =IF(ISNUMBER($N8),ROUNDUP($N8,0)+IF(ROUNDUP($N8,0)-0.1>=$N8,-0.1,0.9),$N8) | P8: =IF(AND(ISNUMBER($O8),N($C8)>0),$O8/$C8,"") | Q8: =IF(OR($J8="",NOT(ISNUMBER($N8))),"",$J8*(1-($M8-IF($I8="",pLucro,$I8)))-$L8) | R8: =IF($Q8="","",$Q8/$J8) | S8: =IF($L8="","",IF(NOT(ISNUMBER($N8)),"Revisar %",IF($J8="","Sem preço atual",IF($Q8<0,"PREJUÍZO",IF($J8<$N8,"Abaixo do ideal","OK")))))
K9: =IF(OR($A9="",$C9=""),"",$C9*cHora) | L9: =IF($K9="","",$K9+N($D9)+N($E9)) | M9: =IF($L9="","",IF($F9="",pImp,$F9)+IF($G9="",pCom,$G9)+IF($H9="",pTax,$H9)+IF($I9="",pLucro,$I9)) | N9: =IF($L9="","",IF($M9>=1,"Revisar %",$L9/(1-$M9))) | O9: =IF(ISNUMBER($N9),ROUNDUP($N9,0)+IF(ROUNDUP($N9,0)-0.1>=$N9,-0.1,0.9),$N9) | P9: =IF(AND(ISNUMBER($O9),N($C9)>0),$O9/$C9,"") | Q9: =IF(OR($J9="",NOT(ISNUMBER($N9))),"",$J9*(1-($M9-IF($I9="",pLucro,$I9)))-$L9) | R9: =IF($Q9="","",$Q9/$J9) | S9: =IF($L9="","",IF(NOT(ISNUMBER($N9)),"Revisar %",IF($J9="","Sem preço atual",IF($Q9<0,"PREJUÍZO",IF($J9<$N9,"Abaixo do ideal","OK")))))
K10: =IF(OR($A10="",$C10=""),"",$C10*cHora) | L10: =IF($K10="","",$K10+N($D10)+N($E10)) | M10: =IF($L10="","",IF($F10="",pImp,$F10)+IF($G10="",pCom,$G10)+IF($H10="",pTax,$H10)+IF($I10="",pLucro,$I10)) | N10: =IF($L10="","",IF($M10>=1,"Revisar %",$L10/(1-$M10))) | O10: =IF(ISNUMBER($N10),ROUNDUP($N10,0)+IF(ROUNDUP($N10,0)-0.1>=$N10,-0.1,0.9),$N10) | P10: =IF(AND(ISNUMBER($O10),N($C10)>0),$O10/$C10,"") | Q10: =IF(OR($J10="",NOT(ISNUMBER($N10))),"",$J10*(1-($M10-IF($I10="",pLucro,$I10)))-$L10) | R10: =IF($Q10="","",$Q10/$J10) | S10: =IF($L10="","",IF(NOT(ISNUMBER($N10)),"Revisar %",IF($J10="","Sem preço atual",IF($Q10<0,"PREJUÍZO",IF($J10<$N10,"Abaixo do ideal","OK")))))
K11: =IF(OR($A11="",$C11=""),"",$C11*cHora) | L11: =IF($K11="","",$K11+N($D11)+N($E11)) | M11: =IF($L11="","",IF($F11="",pImp,$F11)+IF($G11="",pCom,$G11)+IF($H11="",pTax,$H11)+IF($I11="",pLucro,$I11)) | N11: =IF($L11="","",IF($M11>=1,"Revisar %",$L11/(1-$M11))) | O11: =IF(ISNUMBER($N11),ROUNDUP($N11,0)+IF(ROUNDUP($N11,0)-0.1>=$N11,-0.1,0.9),$N11) | P11: =IF(AND(ISNUMBER($O11),N($C11)>0),$O11/$C11,"") | Q11: =IF(OR($J11="",NOT(ISNUMBER($N11))),"",$J11*(1-($M11-IF($I11="",pLucro,$I11)))-$L11) | R11: =IF($Q11="","",$Q11/$J11) | S11: =IF($L11="","",IF(NOT(ISNUMBER($N11)),"Revisar %",IF($J11="","Sem preço atual",IF($Q11<0,"PREJUÍZO",IF($J11<$N11,"Abaixo do ideal","OK")))))
K12: =IF(OR($A12="",$C12=""),"",$C12*cHora) | L12: =IF($K12="","",$K12+N($D12)+N($E12)) | M12: =IF($L12="","",IF($F12="",pImp,$F12)+IF($G12="",pCom,$G12)+IF($H12="",pTax,$H12)+IF($I12="",pLucro,$I12)) | N12: =IF($L12="","",IF($M12>=1,"Revisar %",$L12/(1-$M12))) | O12: =IF(ISNUMBER($N12),ROUNDUP($N12,0)+IF(ROUNDUP($N12,0)-0.1>=$N12,-0.1,0.9),$N12) | P12: =IF(AND(ISNUMBER($O12),N($C12)>0),$O12/$C12,"") | Q12: =IF(OR($J12="",NOT(ISNUMBER($N12))),"",$J12*(1-($M12-IF($I12="",pLucro,$I12)))-$L12) | R12: =IF($Q12="","",$Q12/$J12) | S12: =IF($L12="","",IF(NOT(ISNUMBER($N12)),"Revisar %",IF($J12="","Sem preço atual",IF($Q12<0,"PREJUÍZO",IF($J12<$N12,"Abaixo do ideal","OK")))))
K13: =IF(OR($A13="",$C13=""),"",$C13*cHora) | L13: =IF($K13="","",$K13+N($D13)+N($E13)) | M13: =IF($L13="","",IF($F13="",pImp,$F13)+IF($G13="",pCom,$G13)+IF($H13="",pTax,$H13)+IF($I13="",pLucro,$I13)) | N13: =IF($L13="","",IF($M13>=1,"Revisar %",$L13/(1-$M13))) | O13: =IF(ISNUMBER($N13),ROUNDUP($N13,0)+IF(ROUNDUP($N13,0)-0.1>=$N13,-0.1,0.9),$N13) | P13: =IF(AND(ISNUMBER($O13),N($C13)>0),$O13/$C13,"") | Q13: =IF(OR($J13="",NOT(ISNUMBER($N13))),"",$J13*(1-($M13-IF($I13="",pLucro,$I13)))-$L13) | R13: =IF($Q13="","",$Q13/$J13) | S13: =IF($L13="","",IF(NOT(ISNUMBER($N13)),"Revisar %",IF($J13="","Sem preço atual",IF($Q13<0,"PREJUÍZO",IF($J13<$N13,"Abaixo do ideal","OK")))))
K14: =IF(OR($A14="",$C14=""),"",$C14*cHora) | L14: =IF($K14="","",$K14+N($D14)+N($E14)) | M14: =IF($L14="","",IF($F14="",pImp,$F14)+IF($G14="",pCom,$G14)+IF($H14="",pTax,$H14)+IF($I14="",pLucro,$I14)) | N14: =IF($L14="","",IF($M14>=1,"Revisar %",$L14/(1-$M14))) | O14: =IF(ISNUMBER($N14),ROUNDUP($N14,0)+IF(ROUNDUP($N14,0)-0.1>=$N14,-0.1,0.9),$N14) | P14: =IF(AND(ISNUMBER($O14),N($C14)>0),$O14/$C14,"") | Q14: =IF(OR($J14="",NOT(ISNUMBER($N14))),"",$J14*(1-($M14-IF($I14="",pLucro,$I14)))-$L14) | R14: =IF($Q14="","",$Q14/$J14) | S14: =IF($L14="","",IF(NOT(ISNUMBER($N14)),"Revisar %",IF($J14="","Sem preço atual",IF($Q14<0,"PREJUÍZO",IF($J14<$N14,"Abaixo do ideal","OK")))))
K15: =IF(OR($A15="",$C15=""),"",$C15*cHora) | L15: =IF($K15="","",$K15+N($D15)+N($E15)) | M15: =IF($L15="","",IF($F15="",pImp,$F15)+IF($G15="",pCom,$G15)+IF($H15="",pTax,$H15)+IF($I15="",pLucro,$I15)) | N15: =IF($L15="","",IF($M15>=1,"Revisar %",$L15/(1-$M15))) | O15: =IF(ISNUMBER($N15),ROUNDUP($N15,0)+IF(ROUNDUP($N15,0)-0.1>=$N15,-0.1,0.9),$N15) | P15: =IF(AND(ISNUMBER($O15),N($C15)>0),$O15/$C15,"") | Q15: =IF(OR($J15="",NOT(ISNUMBER($N15))),"",$J15*(1-($M15-IF($I15="",pLucro,$I15)))-$L15) | R15: =IF($Q15="","",$Q15/$J15) | S15: =IF($L15="","",IF(NOT(ISNUMBER($N15)),"Revisar %",IF($J15="","Sem preço atual",IF($Q15<0,"PREJUÍZO",IF($J15<$N15,"Abaixo do ideal","OK")))))
K16: =IF(OR($A16="",$C16=""),"",$C16*cHora) | L16: =IF($K16="","",$K16+N($D16)+N($E16)) | M16: =IF($L16="","",IF($F16="",pImp,$F16)+IF($G16="",pCom,$G16)+IF($H16="",pTax,$H16)+IF($I16="",pLucro,$I16)) | N16: =IF($L16="","",IF($M16>=1,"Revisar %",$L16/(1-$M16))) | O16: =IF(ISNUMBER($N16),ROUNDUP($N16,0)+IF(ROUNDUP($N16,0)-0.1>=$N16,-0.1,0.9),$N16) | P16: =IF(AND(ISNUMBER($O16),N($C16)>0),$O16/$C16,"") | Q16: =IF(OR($J16="",NOT(ISNUMBER($N16))),"",$J16*(1-($M16-IF($I16="",pLucro,$I16)))-$L16) | R16: =IF($Q16="","",$Q16/$J16) | S16: =IF($L16="","",IF(NOT(ISNUMBER($N16)),"Revisar %",IF($J16="","Sem preço atual",IF($Q16<0,"PREJUÍZO",IF($J16<$N16,"Abaixo do ideal","OK")))))
... K104: =IF(OR($A104="",$C104=""),"",$C104*cHora) | L104: =IF($K104="","",$K104+N($D104)+N($E104)) | M104: =IF($L104="","",IF($F104="",pImp,$F104)+IF($G104="",pCom,$G104)+IF($H104="",pTax,$H104)+IF($I104="",pLucro,$I104)) | N104: =IF($L104="","",IF($M104>=1,"Revisar %",$L104/(1-$M104))) | O104: =IF(ISNUMBER($N104),ROUNDUP($N104,0)+IF(ROUNDUP($N104,0)-0.1>=$N104,-0.1,0.9),$N104) | P104: =IF(AND(ISNUMBER($O104),N($C104)>0),$O104/$C104,"") | Q104: =IF(OR($J104="",NOT(ISNUMBER($N104))),"",$J104*(1-($M104-IF($I104="",pLucro,$I104)))-$L104) | R104: =IF($Q104="","",$Q104/$J104) | S104: =IF($L104="","",IF(NOT(ISNUMBER($N104)),"Revisar %",IF($J104="","Sem preço atual",IF($Q104<0,"PREJUÍZO",IF($J104<$N104,"Abaixo do ideal","OK")))))

Sheet Simulador
A1: Simulador de desconto
A2: Descubra quanto precisa vender a mais para não perder lucro ao dar desconto.
B4: Escolha o produto
B5: Desconto que pretendo dar (%) | C5: 0.1
B6: Linha do produto na lista (apoio) | C6: =IFERROR(MATCH($C$4,ProdNome,0),"")
B8: Preço atual de venda (usa o praticado; se vazio, o sugerido) | C8: =IF($C$6="","",IF(N(INDEX(Produtos!$K$5:$K$304,$C$6))>0,INDEX(Produtos!$K$5:$K$304,$C$6),INDEX(Produtos!$O$5:$O$304,$C$6)))
B9: Custo total por unidade | C9: =IF($C$6="","",INDEX(Produtos!$L$5:$L$304,$C$6))
B10: % de impostos, taxas e rateio fixo sobre o preço | C10: =IF($C$6="","",INDEX(Produtos!$M$5:$M$304,$C$6)-IF(INDEX(Produtos!$I$5:$I$304,$C$6)="",pLucro,INDEX(Produtos!$I$5:$I$304,$C$6)))
B11: Lucro por unidade hoje | C11: =IF($C$6="","",C8*(1-C10)-C9)
B12: Preço com desconto | C12: =IF($C$6="","",C8*(1-$C$5))
B13: Lucro por unidade com desconto | C13: =IF($C$6="","",C12*(1-C10)-C9)
B14: Queda do lucro por unidade | C14: =IF(OR($C$6="",N(C11)<=0),"",1-C13/C11)
B15: Vendas a mais para manter o MESMO lucro total | C15: =IF($C$6="","",IF(C13<=0,"Impossível: dá prejuízo",IF(C11<=0,"",C11/C13-1)))
B17: Tabela de descontos para o produto escolhido
B18: Desconto | C18: Preço com desconto | D18: Lucro por unidade | E18: Queda do lucro | F18: Vendas a mais necessárias
B19: 0 | C19: =IF($C$6="","",$C$8*(1-B19)) | D19: =IF($C$6="","",C19*(1-$C$10)-$C$9) | E19: =IF(OR($C$6="",N($C$11)<=0),"",1-D19/$C$11) | F19: =IF($C$6="","",IF(D19<=0,"Impossível",IF(N($C$11)<=0,"",$C$11/D19-1)))
B20: 0.05 | C20: =IF($C$6="","",$C$8*(1-B20)) | D20: =IF($C$6="","",C20*(1-$C$10)-$C$9) | E20: =IF(OR($C$6="",N($C$11)<=0),"",1-D20/$C$11) | F20: =IF($C$6="","",IF(D20<=0,"Impossível",IF(N($C$11)<=0,"",$C$11/D20-1)))
B21: 0.1 | C21: =IF($C$6="","",$C$8*(1-B21)) | D21: =IF($C$6="","",C21*(1-$C$10)-$C$9) | E21: =IF(OR($C$6="",N($C$11)<=0),"",1-D21/$C$11) | F21: =IF($C$6="","",IF(D21<=0,"Impossível",IF(N($C$11)<=0,"",$C$11/D21-1)))
B22: 0.15 | C22: =IF($C$6="","",$C$8*(1-B22)) | D22: =IF($C$6="","",C22*(1-$C$10)-$C$9) | E22: =IF(OR($C$6="",N($C$11)<=0),"",1-D22/$C$11) | F22: =IF($C$6="","",IF(D22<=0,"Impossível",IF(N($C$11)<=0,"",$C$11/D22-1)))
B23: 0.2 | C23: =IF($C$6="","",$C$8*(1-B23)) | D23: =IF($C$6="","",C23*(1-$C$10)-$C$9) | E23: =IF(OR($C$6="",N($C$11)<=0),"",1-D23/$C$11) | F23: =IF($C$6="","",IF(D23<=0,"Impossível",IF(N($C$11)<=0,"",$C$11/D23-1)))
B24: 0.25 | C24: =IF($C$6="","",$C$8*(1-B24)) | D24: =IF($C$6="","",C24*(1-$C$10)-$C$9) | E24: =IF(OR($C$6="",N($C$11)<=0),"",1-D24/$C$11) | F24: =IF($C$6="","",IF(D24<=0,"Impossível",IF(N($C$11)<=0,"",$C$11/D24-1)))
B25: 0.3 | C25: =IF($C$6="","",$C$8*(1-B25)) | D25: =IF($C$6="","",C25*(1-$C$10)-$C$9) | E25: =IF(OR($C$6="",N($C$11)<=0),"",1-D25/$C$11) | F25: =IF($C$6="","",IF(D25<=0,"Impossível",IF(N($C$11)<=0,"",$C$11/D25-1)))
B27: Leitura: se o desconto exigir +50% de vendas e você não consegue vender 50% a mais, dar o desconto reduz o seu lucro total. Prefira benefícios que não reduzem o preço (frete, brinde, parcelamento).

Sheet Resumo
A1: Resumo
A2: Saúde geral da sua precificação.
A4: PRODUTOS CADASTRADOS | C4: EM PREJUÍZO | E4: ABAIXO DO IDEAL | G4: COM PREÇO OK
A5: =COUNTIF(Produtos!$L$5:$L$304,">0") -> 0 | C5: =COUNTIF(Produtos!$T$5:$T$304,"PREJUÍZO") -> 0 | E5: =COUNTIF(Produtos!$T$5:$T$304,"Abaixo do ideal") -> 0 | G5: =COUNTIF(Produtos!$T$5:$T$304,"OK") -> 0
A7: MARGEM MÉDIA ATUAL | C7: LUCRO DESEJADO | E7: SERVIÇOS EM PREJUÍZO | G7: CUSTO DA HORA
A8: =IFERROR(AVERAGE(Produtos!$S$5:$S$304),0) -> 0 | C8: =pLucro -> 0 | E8: =COUNTIF('Serviços'!$S$5:$S$104,"PREJUÍZO") -> 0 | G8: =cHora -> 0
A10: Margem líquida no preço atual (primeiros 20 produtos)
