Workbook
Name CatDesp: Config!$J$5:$J$34
Name ClienteNome: Config!$E$5:$E$104
Name ClienteTel: Config!$F$5:$F$104
Name DiasAlerta: Config!$C$8
Name Formas: Config!$L$5:$L$16
Name FornNome: Config!$H$5:$H$64
Name Hoje: Config!$C$5
Name Juros: Config!$C$7
Name Multa: Config!$C$6

Sheet Início
A1: Contas a Pagar e Receber
A2: Carvex XLS · Controle de vencimentos, cobrança e inadimplência
B4: O que esta planilha faz
B5: Registre o que você tem a receber e a pagar. A planilha mostra o status de cada conta, calcula multa e juros dos atrasados, monta a mensagem de cobrança pronta, ranqueia os clientes que mais devem e prevê o saldo das próximas 8 semanas.
B7: Como começar (5 minutos)
B8: 1. Config | C8: Informe multa, juros, quantos dias antes quer ser avisado e cadastre clientes (com telefone), fornecedores, categorias e formas de pagamento.
B9: 2. Lance as contas a receber | C9: Na aba Receber: cliente, descrição, vencimento e valor. Quando o cliente pagar, preencha a data e o valor pago.
B10: 3. Lance as contas a pagar | C10: Na aba Pagar: fornecedor, categoria, vencimento e valor. Ao pagar, preencha data e valor pago.
B11: 4. Cobre quem está atrasado | C11: Na aba Receber, a coluna Mensagem de cobrança já traz o texto pronto para copiar e enviar por WhatsApp.
B12: 5. Acompanhe o Painel | C12: Veja inadimplência, aging por faixa de atraso, maiores devedores e o saldo previsto semana a semana.
B14: Mapa das abas (clique para ir)
B15: Config | C15: Parâmetros e cadastros.
B16: Receber | C16: Contas a receber (até 1.000 linhas).
B17: Pagar | C17: Contas a pagar (até 1.000 linhas).
B18: Painel | C18: Indicadores, aging, ranking de devedores e previsão de 8 semanas.
B20: Legenda de cores
B21: Amarelo | C21: Célula que VOCÊ preenche.
B22: Cinza | C22: Cálculo automático. Não digite aqui.
B23: Verde escuro | C23: Cabeçalho de coluna.
B25: Atenção
B26: • Para pagamento parcial, preencha o valor pago menor que o valor da conta: o saldo continua em aberto.
B27: • Multa e juros são estimativas pela taxa informada na Config (juros pro rata por dia). Confira o que foi combinado em contrato.
B28: • O Painel usa a data de hoje da Config. No arquivo de exemplo a data é fixa (08/10/2026).
B30: Carvex XLS · Contas a Pagar e Receber com Inadimplência · versão 1.0 · Dúvidas: consulte o TUTORIAL.md e o MANUAL.md que acompanham o produto.

Sheet Config
A1: Configurações e cadastros
A2: Preencha as células amarelas.
B4: Empresa | E4: Clientes | F4: Telefone | H4: Fornecedores | J4: Categorias de despesa | L4: Formas de pagamento
B5: Data de hoje (referência) | C5: =TODAY() -> 46303 | J5: Fornecedores | L5: Pix
B6: Multa por atraso (%) | C6: 0.02 | J6: Aluguel | L6: Boleto
B7: Juros de mora ao mês (%) | C7: 0.01 | J7: Folha / pró-labore | L7: Cartão de crédito
B8: Avisar contas a pagar com até (dias) | C8: 7 | J8: Impostos | L8: Cartão de débito
J9: Energia e água | L9: Transferência
J10: Internet e telefone | L10: Dinheiro
J11: Marketing
J12: Sistemas e contador
J13: Manutenção
J14: Outras despesas

Sheet Receber
A1: Contas a Receber
A2: Preencha cliente, vencimento e valor. Ao receber, preencha data e valor pago.
A4: Cliente | B4: Descrição | C4: Emissão | D4: Vencimento | E4: Valor (R$) | F4: Data do pagamento | G4: Valor pago (R$) | H4: Forma | I4: STATUS | J4: Dias de atraso | K4: Faixa | L4: Saldo em aberto | M4: Multa + juros | N4: Total a cobrar hoje | O4: Mensagem de cobrança (copie e envie)
I5: =IF($E5="","",IF($L5<=0.005,"Pago",IF($D5="","Sem vencimento",IF($D5<Hoje,IF(N($G5)>0,"Vencido (parcial)","Vencido"),IF($D5=Hoje,"Vence hoje","A vencer"))))) -> 0 | J5: =IF(OR($E5="",$D5=""),"",IF(AND($L5>0.005,$D5<Hoje),Hoje-$D5,0)) -> 0 | K5: =IF($J5="","",IF($L5<=0.005,"Pago",IF($J5<=0,"A vencer",IF($J5<=15,"1-15 dias",IF($J5<=30,"16-30 dias",IF($J5<=60,"31-60 dias","Mais de 60 dias")))))) -> 0 | L5: =IF($E5="","",MAX(0,$E5-N($G5))) -> 0 | M5: =IF(OR($L5="",$J5=""),"",IF($J5>0,ROUND($L5*Multa+$L5*Juros/30*$J5,2),0)) -> 0 | N5: =IF($L5="","",IF($L5<=0.005,0,$L5+N($M5))) -> 0 | O5: =IF(OR($I5="Vencido",$I5="Vencido (parcial)"),"Olá, "&$A5&"! Consta em aberto '"&$B5&"' com vencimento em "&DAY($D5)&"/"&MONTH($D5)&"/"&YEAR($D5)&", no valor de R$ "&FIXED($N5,2)&" (com multa e juros). Podemos ajudar a regularizar hoje? Obrigado!",IF($I5="Vence hoje","Olá, "&$A5&"! Lembrete: '"&$B5&"' vence hoje, no valor de R$ "&FIXED($L5,2)&". Obrigado!","")) -> 0
I6: =IF($E6="","",IF($L6<=0.005,"Pago",IF($D6="","Sem vencimento",IF($D6<Hoje,IF(N($G6)>0,"Vencido (parcial)","Vencido"),IF($D6=Hoje,"Vence hoje","A vencer"))))) -> 0 | J6: =IF(OR($E6="",$D6=""),"",IF(AND($L6>0.005,$D6<Hoje),Hoje-$D6,0)) -> 0 | K6: =IF($J6="","",IF($L6<=0.005,"Pago",IF($J6<=0,"A vencer",IF($J6<=15,"1-15 dias",IF($J6<=30,"16-30 dias",IF($J6<=60,"31-60 dias","Mais de 60 dias")))))) -> 0 | L6: =IF($E6="","",MAX(0,$E6-N($G6))) -> 0 | M6: =IF(OR($L6="",$J6=""),"",IF($J6>0,ROUND($L6*Multa+$L6*Juros/30*$J6,2),0)) -> 0 | N6: =IF($L6="","",IF($L6<=0.005,0,$L6+N($M6))) -> 0 | O6: =IF(OR($I6="Vencido",$I6="Vencido (parcial)"),"Olá, "&$A6&"! Consta em aberto '"&$B6&"' com vencimento em "&DAY($D6)&"/"&MONTH($D6)&"/"&YEAR($D6)&", no valor de R$ "&FIXED($N6,2)&" (com multa e juros). Podemos ajudar a regularizar hoje? Obrigado!",IF($I6="Vence hoje","Olá, "&$A6&"! Lembrete: '"&$B6&"' vence hoje, no valor de R$ "&FIXED($L6,2)&". Obrigado!","")) -> 0
I7: =IF($E7="","",IF($L7<=0.005,"Pago",IF($D7="","Sem vencimento",IF($D7<Hoje,IF(N($G7)>0,"Vencido (parcial)","Vencido"),IF($D7=Hoje,"Vence hoje","A vencer"))))) -> 0 | J7: =IF(OR($E7="",$D7=""),"",IF(AND($L7>0.005,$D7<Hoje),Hoje-$D7,0)) -> 0 | K7: =IF($J7="","",IF($L7<=0.005,"Pago",IF($J7<=0,"A vencer",IF($J7<=15,"1-15 dias",IF($J7<=30,"16-30 dias",IF($J7<=60,"31-60 dias","Mais de 60 dias")))))) -> 0 | L7: =IF($E7="","",MAX(0,$E7-N($G7))) -> 0 | M7: =IF(OR($L7="",$J7=""),"",IF($J7>0,ROUND($L7*Multa+$L7*Juros/30*$J7,2),0)) -> 0 | N7: =IF($L7="","",IF($L7<=0.005,0,$L7+N($M7))) -> 0 | O7: =IF(OR($I7="Vencido",$I7="Vencido (parcial)"),"Olá, "&$A7&"! Consta em aberto '"&$B7&"' com vencimento em "&DAY($D7)&"/"&MONTH($D7)&"/"&YEAR($D7)&", no valor de R$ "&FIXED($N7,2)&" (com multa e juros). Podemos ajudar a regularizar hoje? Obrigado!",IF($I7="Vence hoje","Olá, "&$A7&"! Lembrete: '"&$B7&"' vence hoje, no valor de R$ "&FIXED($L7,2)&". Obrigado!","")) -> 0
I8: =IF($E8="","",IF($L8<=0.005,"Pago",IF($D8="","Sem vencimento",IF($D8<Hoje,IF(N($G8)>0,"Vencido (parcial)","Vencido"),IF($D8=Hoje,"Vence hoje","A vencer"))))) -> 0 | J8: =IF(OR($E8="",$D8=""),"",IF(AND($L8>0.005,$D8<Hoje),Hoje-$D8,0)) -> 0 | K8: =IF($J8="","",IF($L8<=0.005,"Pago",IF($J8<=0,"A vencer",IF($J8<=15,"1-15 dias",IF($J8<=30,"16-30 dias",IF($J8<=60,"31-60 dias","Mais de 60 dias")))))) -> 0 | L8: =IF($E8="","",MAX(0,$E8-N($G8))) -> 0 | M8: =IF(OR($L8="",$J8=""),"",IF($J8>0,ROUND($L8*Multa+$L8*Juros/30*$J8,2),0)) -> 0 | N8: =IF($L8="","",IF($L8<=0.005,0,$L8+N($M8))) -> 0 | O8: =IF(OR($I8="Vencido",$I8="Vencido (parcial)"),"Olá, "&$A8&"! Consta em aberto '"&$B8&"' com vencimento em "&DAY($D8)&"/"&MONTH($D8)&"/"&YEAR($D8)&", no valor de R$ "&FIXED($N8,2)&" (com multa e juros). Podemos ajudar a regularizar hoje? Obrigado!",IF($I8="Vence hoje","Olá, "&$A8&"! Lembrete: '"&$B8&"' vence hoje, no valor de R$ "&FIXED($L8,2)&". Obrigado!","")) -> 0
I9: =IF($E9="","",IF($L9<=0.005,"Pago",IF($D9="","Sem vencimento",IF($D9<Hoje,IF(N($G9)>0,"Vencido (parcial)","Vencido"),IF($D9=Hoje,"Vence hoje","A vencer"))))) -> 0 | J9: =IF(OR($E9="",$D9=""),"",IF(AND($L9>0.005,$D9<Hoje),Hoje-$D9,0)) -> 0 | K9: =IF($J9="","",IF($L9<=0.005,"Pago",IF($J9<=0,"A vencer",IF($J9<=15,"1-15 dias",IF($J9<=30,"16-30 dias",IF($J9<=60,"31-60 dias","Mais de 60 dias")))))) -> 0 | L9: =IF($E9="","",MAX(0,$E9-N($G9))) -> 0 | M9: =IF(OR($L9="",$J9=""),"",IF($J9>0,ROUND($L9*Multa+$L9*Juros/30*$J9,2),0)) -> 0 | N9: =IF($L9="","",IF($L9<=0.005,0,$L9+N($M9))) -> 0 | O9: =IF(OR($I9="Vencido",$I9="Vencido (parcial)"),"Olá, "&$A9&"! Consta em aberto '"&$B9&"' com vencimento em "&DAY($D9)&"/"&MONTH($D9)&"/"&YEAR($D9)&", no valor de R$ "&FIXED($N9,2)&" (com multa e juros). Podemos ajudar a regularizar hoje? Obrigado!",IF($I9="Vence hoje","Olá, "&$A9&"! Lembrete: '"&$B9&"' vence hoje, no valor de R$ "&FIXED($L9,2)&". Obrigado!","")) -> 0
I10: =IF($E10="","",IF($L10<=0.005,"Pago",IF($D10="","Sem vencimento",IF($D10<Hoje,IF(N($G10)>0,"Vencido (parcial)","Vencido"),IF($D10=Hoje,"Vence hoje","A vencer"))))) -> 0 | J10: =IF(OR($E10="",$D10=""),"",IF(AND($L10>0.005,$D10<Hoje),Hoje-$D10,0)) -> 0 | K10: =IF($J10="","",IF($L10<=0.005,"Pago",IF($J10<=0,"A vencer",IF($J10<=15,"1-15 dias",IF($J10<=30,"16-30 dias",IF($J10<=60,"31-60 dias","Mais de 60 dias")))))) -> 0 | L10: =IF($E10="","",MAX(0,$E10-N($G10))) -> 0 | M10: =IF(OR($L10="",$J10=""),"",IF($J10>0,ROUND($L10*Multa+$L10*Juros/30*$J10,2),0)) -> 0 | N10: =IF($L10="","",IF($L10<=0.005,0,$L10+N($M10))) -> 0 | O10: =IF(OR($I10="Vencido",$I10="Vencido (parcial)"),"Olá, "&$A10&"! Consta em aberto '"&$B10&"' com vencimento em "&DAY($D10)&"/"&MONTH($D10)&"/"&YEAR($D10)&", no valor de R$ "&FIXED($N10,2)&" (com multa e juros). Podemos ajudar a regularizar hoje? Obrigado!",IF($I10="Vence hoje","Olá, "&$A10&"! Lembrete: '"&$B10&"' vence hoje, no valor de R$ "&FIXED($L10,2)&". Obrigado!","")) -> 0
I11: =IF($E11="","",IF($L11<=0.005,"Pago",IF($D11="","Sem vencimento",IF($D11<Hoje,IF(N($G11)>0,"Vencido (parcial)","Vencido"),IF($D11=Hoje,"Vence hoje","A vencer"))))) -> 0 | J11: =IF(OR($E11="",$D11=""),"",IF(AND($L11>0.005,$D11<Hoje),Hoje-$D11,0)) -> 0 | K11: =IF($J11="","",IF($L11<=0.005,"Pago",IF($J11<=0,"A vencer",IF($J11<=15,"1-15 dias",IF($J11<=30,"16-30 dias",IF($J11<=60,"31-60 dias","Mais de 60 dias")))))) -> 0 | L11: =IF($E11="","",MAX(0,$E11-N($G11))) -> 0 | M11: =IF(OR($L11="",$J11=""),"",IF($J11>0,ROUND($L11*Multa+$L11*Juros/30*$J11,2),0)) -> 0 | N11: =IF($L11="","",IF($L11<=0.005,0,$L11+N($M11))) -> 0 | O11: =IF(OR($I11="Vencido",$I11="Vencido (parcial)"),"Olá, "&$A11&"! Consta em aberto '"&$B11&"' com vencimento em "&DAY($D11)&"/"&MONTH($D11)&"/"&YEAR($D11)&", no valor de R$ "&FIXED($N11,2)&" (com multa e juros). Podemos ajudar a regularizar hoje? Obrigado!",IF($I11="Vence hoje","Olá, "&$A11&"! Lembrete: '"&$B11&"' vence hoje, no valor de R$ "&FIXED($L11,2)&". Obrigado!","")) -> 0
I12: =IF($E12="","",IF($L12<=0.005,"Pago",IF($D12="","Sem vencimento",IF($D12<Hoje,IF(N($G12)>0,"Vencido (parcial)","Vencido"),IF($D12=Hoje,"Vence hoje","A vencer"))))) -> 0 | J12: =IF(OR($E12="",$D12=""),"",IF(AND($L12>0.005,$D12<Hoje),Hoje-$D12,0)) -> 0 | K12: =IF($J12="","",IF($L12<=0.005,"Pago",IF($J12<=0,"A vencer",IF($J12<=15,"1-15 dias",IF($J12<=30,"16-30 dias",IF($J12<=60,"31-60 dias","Mais de 60 dias")))))) -> 0 | L12: =IF($E12="","",MAX(0,$E12-N($G12))) -> 0 | M12: =IF(OR($L12="",$J12=""),"",IF($J12>0,ROUND($L12*Multa+$L12*Juros/30*$J12,2),0)) -> 0 | N12: =IF($L12="","",IF($L12<=0.005,0,$L12+N($M12))) -> 0 | O12: =IF(OR($I12="Vencido",$I12="Vencido (parcial)"),"Olá, "&$A12&"! Consta em aberto '"&$B12&"' com vencimento em "&DAY($D12)&"/"&MONTH($D12)&"/"&YEAR($D12)&", no valor de R$ "&FIXED($N12,2)&" (com multa e juros). Podemos ajudar a regularizar hoje? Obrigado!",IF($I12="Vence hoje","Olá, "&$A12&"! Lembrete: '"&$B12&"' vence hoje, no valor de R$ "&FIXED($L12,2)&". Obrigado!","")) -> 0
I13: =IF($E13="","",IF($L13<=0.005,"Pago",IF($D13="","Sem vencimento",IF($D13<Hoje,IF(N($G13)>0,"Vencido (parcial)","Vencido"),IF($D13=Hoje,"Vence hoje","A vencer"))))) -> 0 | J13: =IF(OR($E13="",$D13=""),"",IF(AND($L13>0.005,$D13<Hoje),Hoje-$D13,0)) -> 0 | K13: =IF($J13="","",IF($L13<=0.005,"Pago",IF($J13<=0,"A vencer",IF($J13<=15,"1-15 dias",IF($J13<=30,"16-30 dias",IF($J13<=60,"31-60 dias","Mais de 60 dias")))))) -> 0 | L13: =IF($E13="","",MAX(0,$E13-N($G13))) -> 0 | M13: =IF(OR($L13="",$J13=""),"",IF($J13>0,ROUND($L13*Multa+$L13*Juros/30*$J13,2),0)) -> 0 | N13: =IF($L13="","",IF($L13<=0.005,0,$L13+N($M13))) -> 0 | O13: =IF(OR($I13="Vencido",$I13="Vencido (parcial)"),"Olá, "&$A13&"! Consta em aberto '"&$B13&"' com vencimento em "&DAY($D13)&"/"&MONTH($D13)&"/"&YEAR($D13)&", no valor de R$ "&FIXED($N13,2)&" (com multa e juros). Podemos ajudar a regularizar hoje? Obrigado!",IF($I13="Vence hoje","Olá, "&$A13&"! Lembrete: '"&$B13&"' vence hoje, no valor de R$ "&FIXED($L13,2)&". Obrigado!","")) -> 0
I14: =IF($E14="","",IF($L14<=0.005,"Pago",IF($D14="","Sem vencimento",IF($D14<Hoje,IF(N($G14)>0,"Vencido (parcial)","Vencido"),IF($D14=Hoje,"Vence hoje","A vencer"))))) -> 0 | J14: =IF(OR($E14="",$D14=""),"",IF(AND($L14>0.005,$D14<Hoje),Hoje-$D14,0)) -> 0 | K14: =IF($J14="","",IF($L14<=0.005,"Pago",IF($J14<=0,"A vencer",IF($J14<=15,"1-15 dias",IF($J14<=30,"16-30 dias",IF($J14<=60,"31-60 dias","Mais de 60 dias")))))) -> 0 | L14: =IF($E14="","",MAX(0,$E14-N($G14))) -> 0 | M14: =IF(OR($L14="",$J14=""),"",IF($J14>0,ROUND($L14*Multa+$L14*Juros/30*$J14,2),0)) -> 0 | N14: =IF($L14="","",IF($L14<=0.005,0,$L14+N($M14))) -> 0 | O14: =IF(OR($I14="Vencido",$I14="Vencido (parcial)"),"Olá, "&$A14&"! Consta em aberto '"&$B14&"' com vencimento em "&DAY($D14)&"/"&MONTH($D14)&"/"&YEAR($D14)&", no valor de R$ "&FIXED($N14,2)&" (com multa e juros). Podemos ajudar a regularizar hoje? Obrigado!",IF($I14="Vence hoje","Olá, "&$A14&"! Lembrete: '"&$B14&"' vence hoje, no valor de R$ "&FIXED($L14,2)&". Obrigado!","")) -> 0
I15: =IF($E15="","",IF($L15<=0.005,"Pago",IF($D15="","Sem vencimento",IF($D15<Hoje,IF(N($G15)>0,"Vencido (parcial)","Vencido"),IF($D15=Hoje,"Vence hoje","A vencer"))))) -> 0 | J15: =IF(OR($E15="",$D15=""),"",IF(AND($L15>0.005,$D15<Hoje),Hoje-$D15,0)) -> 0 | K15: =IF($J15="","",IF($L15<=0.005,"Pago",IF($J15<=0,"A vencer",IF($J15<=15,"1-15 dias",IF($J15<=30,"16-30 dias",IF($J15<=60,"31-60 dias","Mais de 60 dias")))))) -> 0 | L15: =IF($E15="","",MAX(0,$E15-N($G15))) -> 0 | M15: =IF(OR($L15="",$J15=""),"",IF($J15>0,ROUND($L15*Multa+$L15*Juros/30*$J15,2),0)) -> 0 | N15: =IF($L15="","",IF($L15<=0.005,0,$L15+N($M15))) -> 0 | O15: =IF(OR($I15="Vencido",$I15="Vencido (parcial)"),"Olá, "&$A15&"! Consta em aberto '"&$B15&"' com vencimento em "&DAY($D15)&"/"&MONTH($D15)&"/"&YEAR($D15)&", no valor de R$ "&FIXED($N15,2)&" (com multa e juros). Podemos ajudar a regularizar hoje? Obrigado!",IF($I15="Vence hoje","Olá, "&$A15&"! Lembrete: '"&$B15&"' vence hoje, no valor de R$ "&FIXED($L15,2)&". Obrigado!","")) -> 0
I16: =IF($E16="","",IF($L16<=0.005,"Pago",IF($D16="","Sem vencimento",IF($D16<Hoje,IF(N($G16)>0,"Vencido (parcial)","Vencido"),IF($D16=Hoje,"Vence hoje","A vencer"))))) -> 0 | J16: =IF(OR($E16="",$D16=""),"",IF(AND($L16>0.005,$D16<Hoje),Hoje-$D16,0)) -> 0 | K16: =IF($J16="","",IF($L16<=0.005,"Pago",IF($J16<=0,"A vencer",IF($J16<=15,"1-15 dias",IF($J16<=30,"16-30 dias",IF($J16<=60,"31-60 dias","Mais de 60 dias")))))) -> 0 | L16: =IF($E16="","",MAX(0,$E16-N($G16))) -> 0 | M16: =IF(OR($L16="",$J16=""),"",IF($J16>0,ROUND($L16*Multa+$L16*Juros/30*$J16,2),0)) -> 0 | N16: =IF($L16="","",IF($L16<=0.005,0,$L16+N($M16))) -> 0 | O16: =IF(OR($I16="Vencido",$I16="Vencido (parcial)"),"Olá, "&$A16&"! Consta em aberto '"&$B16&"' com vencimento em "&DAY($D16)&"/"&MONTH($D16)&"/"&YEAR($D16)&", no valor de R$ "&FIXED($N16,2)&" (com multa e juros). Podemos ajudar a regularizar hoje? Obrigado!",IF($I16="Vence hoje","Olá, "&$A16&"! Lembrete: '"&$B16&"' vence hoje, no valor de R$ "&FIXED($L16,2)&". Obrigado!","")) -> 0
... I1004: =IF($E1004="","",IF($L1004<=0.005,"Pago",IF($D1004="","Sem vencimento",IF($D1004<Hoje,IF(N($G1004)>0,"Vencido (parcial)","Vencido"),IF($D1004=Hoje,"Vence hoje","A vencer"))))) -> 0 | J1004: =IF(OR($E1004="",$D1004=""),"",IF(AND($L1004>0.005,$D1004<Hoje),Hoje-$D1004,0)) -> 0 | K1004: =IF($J1004="","",IF($L1004<=0.005,"Pago",IF($J1004<=0,"A vencer",IF($J1004<=15,"1-15 dias",IF($J1004<=30,"16-30 dias",IF($J1004<=60,"31-60 dias","Mais de 60 dias")))))) -> 0 | L1004: =IF($E1004="","",MAX(0,$E1004-N($G1004))) -> 0 | M1004: =IF(OR($L1004="",$J1004=""),"",IF($J1004>0,ROUND($L1004*Multa+$L1004*Juros/30*$J1004,2),0)) -> 0 | N1004: =IF($L1004="","",IF($L1004<=0.005,0,$L1004+N($M1004))) -> 0 | O1004: =IF(OR($I1004="Vencido",$I1004="Vencido (parcial)"),"Olá, "&$A1004&"! Consta em aberto '"&$B1004&"' com vencimento em "&DAY($D1004)&"/"&MONTH($D1004)&"/"&YEAR($D1004)&", no valor de R$ "&FIXED($N1004,2)&" (com multa e juros). Podemos ajudar a regularizar hoje? Obrigado!",IF($I1004="Vence hoje","Olá, "&$A1004&"! Lembrete: '"&$B1004&"' vence hoje, no valor de R$ "&FIXED($L1004,2)&". Obrigado!","")) -> 0

Sheet Pagar
A1: Contas a Pagar
A2: Preencha fornecedor, categoria, vencimento e valor. Ao pagar, preencha data e valor pago.
A4: Fornecedor | B4: Descrição | C4: Categoria | D4: Vencimento | E4: Valor (R$) | F4: Data do pagamento | G4: Valor pago (R$) | H4: Forma | I4: STATUS | J4: Dias p/ vencer (negativo = atrasada) | K4: Saldo a pagar | L4: Ação
I5: =IF($E5="","",IF($K5<=0.005,"Pago",IF($D5="","Sem vencimento",IF($D5<Hoje,"Vencida",IF($D5=Hoje,"Vence hoje",IF($D5-Hoje<=DiasAlerta,"Vence em breve","A vencer")))))) -> 0 | J5: =IF(OR($E5="",$D5=""),"",IF($K5<=0.005,"",$D5-Hoje)) -> 0 | K5: =IF($E5="","",MAX(0,$E5-N($G5))) -> 0 | L5: =IF($I5="Vencida","PAGAR JÁ (multa e juros)",IF($I5="Vence hoje","Pagar hoje",IF($I5="Vence em breve","Programar pagamento",""))) -> 0
I6: =IF($E6="","",IF($K6<=0.005,"Pago",IF($D6="","Sem vencimento",IF($D6<Hoje,"Vencida",IF($D6=Hoje,"Vence hoje",IF($D6-Hoje<=DiasAlerta,"Vence em breve","A vencer")))))) -> 0 | J6: =IF(OR($E6="",$D6=""),"",IF($K6<=0.005,"",$D6-Hoje)) -> 0 | K6: =IF($E6="","",MAX(0,$E6-N($G6))) -> 0 | L6: =IF($I6="Vencida","PAGAR JÁ (multa e juros)",IF($I6="Vence hoje","Pagar hoje",IF($I6="Vence em breve","Programar pagamento",""))) -> 0
I7: =IF($E7="","",IF($K7<=0.005,"Pago",IF($D7="","Sem vencimento",IF($D7<Hoje,"Vencida",IF($D7=Hoje,"Vence hoje",IF($D7-Hoje<=DiasAlerta,"Vence em breve","A vencer")))))) -> 0 | J7: =IF(OR($E7="",$D7=""),"",IF($K7<=0.005,"",$D7-Hoje)) -> 0 | K7: =IF($E7="","",MAX(0,$E7-N($G7))) -> 0 | L7: =IF($I7="Vencida","PAGAR JÁ (multa e juros)",IF($I7="Vence hoje","Pagar hoje",IF($I7="Vence em breve","Programar pagamento",""))) -> 0
I8: =IF($E8="","",IF($K8<=0.005,"Pago",IF($D8="","Sem vencimento",IF($D8<Hoje,"Vencida",IF($D8=Hoje,"Vence hoje",IF($D8-Hoje<=DiasAlerta,"Vence em breve","A vencer")))))) -> 0 | J8: =IF(OR($E8="",$D8=""),"",IF($K8<=0.005,"",$D8-Hoje)) -> 0 | K8: =IF($E8="","",MAX(0,$E8-N($G8))) -> 0 | L8: =IF($I8="Vencida","PAGAR JÁ (multa e juros)",IF($I8="Vence hoje","Pagar hoje",IF($I8="Vence em breve","Programar pagamento",""))) -> 0
I9: =IF($E9="","",IF($K9<=0.005,"Pago",IF($D9="","Sem vencimento",IF($D9<Hoje,"Vencida",IF($D9=Hoje,"Vence hoje",IF($D9-Hoje<=DiasAlerta,"Vence em breve","A vencer")))))) -> 0 | J9: =IF(OR($E9="",$D9=""),"",IF($K9<=0.005,"",$D9-Hoje)) -> 0 | K9: =IF($E9="","",MAX(0,$E9-N($G9))) -> 0 | L9: =IF($I9="Vencida","PAGAR JÁ (multa e juros)",IF($I9="Vence hoje","Pagar hoje",IF($I9="Vence em breve","Programar pagamento",""))) -> 0
I10: =IF($E10="","",IF($K10<=0.005,"Pago",IF($D10="","Sem vencimento",IF($D10<Hoje,"Vencida",IF($D10=Hoje,"Vence hoje",IF($D10-Hoje<=DiasAlerta,"Vence em breve","A vencer")))))) -> 0 | J10: =IF(OR($E10="",$D10=""),"",IF($K10<=0.005,"",$D10-Hoje)) -> 0 | K10: =IF($E10="","",MAX(0,$E10-N($G10))) -> 0 | L10: =IF($I10="Vencida","PAGAR JÁ (multa e juros)",IF($I10="Vence hoje","Pagar hoje",IF($I10="Vence em breve","Programar pagamento",""))) -> 0
I11: =IF($E11="","",IF($K11<=0.005,"Pago",IF($D11="","Sem vencimento",IF($D11<Hoje,"Vencida",IF($D11=Hoje,"Vence hoje",IF($D11-Hoje<=DiasAlerta,"Vence em breve","A vencer")))))) -> 0 | J11: =IF(OR($E11="",$D11=""),"",IF($K11<=0.005,"",$D11-Hoje)) -> 0 | K11: =IF($E11="","",MAX(0,$E11-N($G11))) -> 0 | L11: =IF($I11="Vencida","PAGAR JÁ (multa e juros)",IF($I11="Vence hoje","Pagar hoje",IF($I11="Vence em breve","Programar pagamento",""))) -> 0
I12: =IF($E12="","",IF($K12<=0.005,"Pago",IF($D12="","Sem vencimento",IF($D12<Hoje,"Vencida",IF($D12=Hoje,"Vence hoje",IF($D12-Hoje<=DiasAlerta,"Vence em breve","A vencer")))))) -> 0 | J12: =IF(OR($E12="",$D12=""),"",IF($K12<=0.005,"",$D12-Hoje)) -> 0 | K12: =IF($E12="","",MAX(0,$E12-N($G12))) -> 0 | L12: =IF($I12="Vencida","PAGAR JÁ (multa e juros)",IF($I12="Vence hoje","Pagar hoje",IF($I12="Vence em breve","Programar pagamento",""))) -> 0
I13: =IF($E13="","",IF($K13<=0.005,"Pago",IF($D13="","Sem vencimento",IF($D13<Hoje,"Vencida",IF($D13=Hoje,"Vence hoje",IF($D13-Hoje<=DiasAlerta,"Vence em breve","A vencer")))))) -> 0 | J13: =IF(OR($E13="",$D13=""),"",IF($K13<=0.005,"",$D13-Hoje)) -> 0 | K13: =IF($E13="","",MAX(0,$E13-N($G13))) -> 0 | L13: =IF($I13="Vencida","PAGAR JÁ (multa e juros)",IF($I13="Vence hoje","Pagar hoje",IF($I13="Vence em breve","Programar pagamento",""))) -> 0
I14: =IF($E14="","",IF($K14<=0.005,"Pago",IF($D14="","Sem vencimento",IF($D14<Hoje,"Vencida",IF($D14=Hoje,"Vence hoje",IF($D14-Hoje<=DiasAlerta,"Vence em breve","A vencer")))))) -> 0 | J14: =IF(OR($E14="",$D14=""),"",IF($K14<=0.005,"",$D14-Hoje)) -> 0 | K14: =IF($E14="","",MAX(0,$E14-N($G14))) -> 0 | L14: =IF($I14="Vencida","PAGAR JÁ (multa e juros)",IF($I14="Vence hoje","Pagar hoje",IF($I14="Vence em breve","Programar pagamento",""))) -> 0
I15: =IF($E15="","",IF($K15<=0.005,"Pago",IF($D15="","Sem vencimento",IF($D15<Hoje,"Vencida",IF($D15=Hoje,"Vence hoje",IF($D15-Hoje<=DiasAlerta,"Vence em breve","A vencer")))))) -> 0 | J15: =IF(OR($E15="",$D15=""),"",IF($K15<=0.005,"",$D15-Hoje)) -> 0 | K15: =IF($E15="","",MAX(0,$E15-N($G15))) -> 0 | L15: =IF($I15="Vencida","PAGAR JÁ (multa e juros)",IF($I15="Vence hoje","Pagar hoje",IF($I15="Vence em breve","Programar pagamento",""))) -> 0
I16: =IF($E16="","",IF($K16<=0.005,"Pago",IF($D16="","Sem vencimento",IF($D16<Hoje,"Vencida",IF($D16=Hoje,"Vence hoje",IF($D16-Hoje<=DiasAlerta,"Vence em breve","A vencer")))))) -> 0 | J16: =IF(OR($E16="",$D16=""),"",IF($K16<=0.005,"",$D16-Hoje)) -> 0 | K16: =IF($E16="","",MAX(0,$E16-N($G16))) -> 0 | L16: =IF($I16="Vencida","PAGAR JÁ (multa e juros)",IF($I16="Vence hoje","Pagar hoje",IF($I16="Vence em breve","Programar pagamento",""))) -> 0
... I1004: =IF($E1004="","",IF($K1004<=0.005,"Pago",IF($D1004="","Sem vencimento",IF($D1004<Hoje,"Vencida",IF($D1004=Hoje,"Vence hoje",IF($D1004-Hoje<=DiasAlerta,"Vence em breve","A vencer")))))) -> 0 | J1004: =IF(OR($E1004="",$D1004=""),"",IF($K1004<=0.005,"",$D1004-Hoje)) -> 0 | K1004: =IF($E1004="","",MAX(0,$E1004-N($G1004))) -> 0 | L1004: =IF($I1004="Vencida","PAGAR JÁ (multa e juros)",IF($I1004="Vence hoje","Pagar hoje",IF($I1004="Vence em breve","Programar pagamento",""))) -> 0

Sheet Calc
A1: Cliente | B1: Em atraso (R$) | C1: Chave | D1: Telefone
A2: =IF(Config!E5="","",Config!E5) -> 0 | B2: =IF(A2="",0,SUMIFS(Receber!$L$5:$L$1004,Receber!$A$5:$A$1004,A2,Receber!$J$5:$J$1004,">0")) -> 0 | C2: =IF(B2>0,B2+ROW()/1000000000,"") -> 0 | D2: =IF(A2="","",Config!F5&"") -> 0
A3: =IF(Config!E6="","",Config!E6) -> 0 | B3: =IF(A3="",0,SUMIFS(Receber!$L$5:$L$1004,Receber!$A$5:$A$1004,A3,Receber!$J$5:$J$1004,">0")) -> 0 | C3: =IF(B3>0,B3+ROW()/1000000000,"") -> 0 | D3: =IF(A3="","",Config!F6&"") -> 0
A4: =IF(Config!E7="","",Config!E7) -> 0 | B4: =IF(A4="",0,SUMIFS(Receber!$L$5:$L$1004,Receber!$A$5:$A$1004,A4,Receber!$J$5:$J$1004,">0")) -> 0 | C4: =IF(B4>0,B4+ROW()/1000000000,"") -> 0 | D4: =IF(A4="","",Config!F7&"") -> 0
A5: =IF(Config!E8="","",Config!E8) -> 0 | B5: =IF(A5="",0,SUMIFS(Receber!$L$5:$L$1004,Receber!$A$5:$A$1004,A5,Receber!$J$5:$J$1004,">0")) -> 0 | C5: =IF(B5>0,B5+ROW()/1000000000,"") -> 0 | D5: =IF(A5="","",Config!F8&"") -> 0
A6: =IF(Config!E9="","",Config!E9) -> 0 | B6: =IF(A6="",0,SUMIFS(Receber!$L$5:$L$1004,Receber!$A$5:$A$1004,A6,Receber!$J$5:$J$1004,">0")) -> 0 | C6: =IF(B6>0,B6+ROW()/1000000000,"") -> 0 | D6: =IF(A6="","",Config!F9&"") -> 0
A7: =IF(Config!E10="","",Config!E10) -> 0 | B7: =IF(A7="",0,SUMIFS(Receber!$L$5:$L$1004,Receber!$A$5:$A$1004,A7,Receber!$J$5:$J$1004,">0")) -> 0 | C7: =IF(B7>0,B7+ROW()/1000000000,"") -> 0 | D7: =IF(A7="","",Config!F10&"") -> 0
A8: =IF(Config!E11="","",Config!E11) -> 0 | B8: =IF(A8="",0,SUMIFS(Receber!$L$5:$L$1004,Receber!$A$5:$A$1004,A8,Receber!$J$5:$J$1004,">0")) -> 0 | C8: =IF(B8>0,B8+ROW()/1000000000,"") -> 0 | D8: =IF(A8="","",Config!F11&"") -> 0
A9: =IF(Config!E12="","",Config!E12) -> 0 | B9: =IF(A9="",0,SUMIFS(Receber!$L$5:$L$1004,Receber!$A$5:$A$1004,A9,Receber!$J$5:$J$1004,">0")) -> 0 | C9: =IF(B9>0,B9+ROW()/1000000000,"") -> 0 | D9: =IF(A9="","",Config!F12&"") -> 0
A10: =IF(Config!E13="","",Config!E13) -> 0 | B10: =IF(A10="",0,SUMIFS(Receber!$L$5:$L$1004,Receber!$A$5:$A$1004,A10,Receber!$J$5:$J$1004,">0")) -> 0 | C10: =IF(B10>0,B10+ROW()/1000000000,"") -> 0 | D10: =IF(A10="","",Config!F13&"") -> 0
A11: =IF(Config!E14="","",Config!E14) -> 0 | B11: =IF(A11="",0,SUMIFS(Receber!$L$5:$L$1004,Receber!$A$5:$A$1004,A11,Receber!$J$5:$J$1004,">0")) -> 0 | C11: =IF(B11>0,B11+ROW()/1000000000,"") -> 0 | D11: =IF(A11="","",Config!F14&"") -> 0
A12: =IF(Config!E15="","",Config!E15) -> 0 | B12: =IF(A12="",0,SUMIFS(Receber!$L$5:$L$1004,Receber!$A$5:$A$1004,A12,Receber!$J$5:$J$1004,">0")) -> 0 | C12: =IF(B12>0,B12+ROW()/1000000000,"") -> 0 | D12: =IF(A12="","",Config!F15&"") -> 0
A13: =IF(Config!E16="","",Config!E16) -> 0 | B13: =IF(A13="",0,SUMIFS(Receber!$L$5:$L$1004,Receber!$A$5:$A$1004,A13,Receber!$J$5:$J$1004,">0")) -> 0 | C13: =IF(B13>0,B13+ROW()/1000000000,"") -> 0 | D13: =IF(A13="","",Config!F16&"") -> 0
... A101: =IF(Config!E104="","",Config!E104) -> 0 | B101: =IF(A101="",0,SUMIFS(Receber!$L$5:$L$1004,Receber!$A$5:$A$1004,A101,Receber!$J$5:$J$1004,">0")) -> 0 | C101: =IF(B101>0,B101+ROW()/1000000000,"") -> 0 | D101: =IF(A101="","",Config!F104&"") -> 0

Sheet Painel
A1: Painel de contas
A2: Inadimplência, vencimentos e previsão. Atualiza sozinho.
A4: A RECEBER EM ABERTO | D4: VENCIDO A RECEBER | G4: INADIMPLÊNCIA (% do aberto) | J4: RECEBIDO NO MÊS
A5: =SUM(Receber!$L$5:$L$1004) -> 0 | D5: =SUMIFS(Receber!$L$5:$L$1004,Receber!$J$5:$J$1004,">0") -> 0 | G5: =IFERROR(D5/A5,0) -> 0 | J5: =SUMIFS(Receber!$G$5:$G$1004,Receber!$F$5:$F$1004,">="&DATE(YEAR(Hoje),MONTH(Hoje),1),Receber!$F$5:$F$1004,"<="&DATE(YEAR(Hoje),MONTH(Hoje)+1,0)) -> 0
A7: A PAGAR EM ABERTO | D7: VENCIDO A PAGAR | G7: A PAGAR NOS PRÓXIMOS DIAS (alerta) | J7: PAGO NO MÊS
A8: =SUM(Pagar!$K$5:$K$1004) -> 0 | D8: =SUMIFS(Pagar!$K$5:$K$1004,Pagar!$I$5:$I$1004,"Vencida") -> 0 | G8: =SUMIFS(Pagar!$K$5:$K$1004,Pagar!$D$5:$D$1004,">="&Hoje,Pagar!$D$5:$D$1004,"<="&(Hoje+DiasAlerta)) -> 0 | J8: =SUMIFS(Pagar!$G$5:$G$1004,Pagar!$F$5:$F$1004,">="&DATE(YEAR(Hoje),MONTH(Hoje),1),Pagar!$F$5:$F$1004,"<="&DATE(YEAR(Hoje),MONTH(Hoje)+1,0)) -> 0
A10: Aging: quanto está atrasado e há quanto tempo | F10: Maiores devedores (em atraso)
A11: Faixa | B11: Títulos | C11: Valor em aberto | D11: % do total | F11: # | G11: Cliente | J11: Em atraso (R$) | L11: Telefone
A12: A vencer | B12: =COUNTIFS(Receber!$K$5:$K$1004,A12,Receber!$L$5:$L$1004,">0.005") -> 0 | C12: =SUMIFS(Receber!$L$5:$L$1004,Receber!$K$5:$K$1004,A12) -> 0 | D12: =IFERROR(C12/SUM($C$12:$C$16),0) -> 0 | F12: 1 | G12: =IF(M12="","",INDEX(Calc!$A$2:$A$101,MATCH(M12,Calc!$C$2:$C$101,0))) -> 0 | J12: =IF(M12="","",ROUND(M12,2)) -> 0 | L12: =IF(M12="","",INDEX(Calc!$D$2:$D$101,MATCH(M12,Calc!$C$2:$C$101,0))) -> 0 | M12: =IFERROR(LARGE(Calc!$C$2:$C$101,1),"") -> 0
A13: 1-15 dias | B13: =COUNTIFS(Receber!$K$5:$K$1004,A13,Receber!$L$5:$L$1004,">0.005") -> 0 | C13: =SUMIFS(Receber!$L$5:$L$1004,Receber!$K$5:$K$1004,A13) -> 0 | D13: =IFERROR(C13/SUM($C$12:$C$16),0) -> 0 | F13: 2 | G13: =IF(M13="","",INDEX(Calc!$A$2:$A$101,MATCH(M13,Calc!$C$2:$C$101,0))) -> 0 | J13: =IF(M13="","",ROUND(M13,2)) -> 0 | L13: =IF(M13="","",INDEX(Calc!$D$2:$D$101,MATCH(M13,Calc!$C$2:$C$101,0))) -> 0 | M13: =IFERROR(LARGE(Calc!$C$2:$C$101,2),"") -> 0
A14: 16-30 dias | B14: =COUNTIFS(Receber!$K$5:$K$1004,A14,Receber!$L$5:$L$1004,">0.005") -> 0 | C14: =SUMIFS(Receber!$L$5:$L$1004,Receber!$K$5:$K$1004,A14) -> 0 | D14: =IFERROR(C14/SUM($C$12:$C$16),0) -> 0 | F14: 3 | G14: =IF(M14="","",INDEX(Calc!$A$2:$A$101,MATCH(M14,Calc!$C$2:$C$101,0))) -> 0 | J14: =IF(M14="","",ROUND(M14,2)) -> 0 | L14: =IF(M14="","",INDEX(Calc!$D$2:$D$101,MATCH(M14,Calc!$C$2:$C$101,0))) -> 0 | M14: =IFERROR(LARGE(Calc!$C$2:$C$101,3),"") -> 0
A15: 31-60 dias | B15: =COUNTIFS(Receber!$K$5:$K$1004,A15,Receber!$L$5:$L$1004,">0.005") -> 0 | C15: =SUMIFS(Receber!$L$5:$L$1004,Receber!$K$5:$K$1004,A15) -> 0 | D15: =IFERROR(C15/SUM($C$12:$C$16),0) -> 0 | F15: 4 | G15: =IF(M15="","",INDEX(Calc!$A$2:$A$101,MATCH(M15,Calc!$C$2:$C$101,0))) -> 0 | J15: =IF(M15="","",ROUND(M15,2)) -> 0 | L15: =IF(M15="","",INDEX(Calc!$D$2:$D$101,MATCH(M15,Calc!$C$2:$C$101,0))) -> 0 | M15: =IFERROR(LARGE(Calc!$C$2:$C$101,4),"") -> 0
A16: Mais de 60 dias | B16: =COUNTIFS(Receber!$K$5:$K$1004,A16,Receber!$L$5:$L$1004,">0.005") -> 0 | C16: =SUMIFS(Receber!$L$5:$L$1004,Receber!$K$5:$K$1004,A16) -> 0 | D16: =IFERROR(C16/SUM($C$12:$C$16),0) -> 0 | F16: 5 | G16: =IF(M16="","",INDEX(Calc!$A$2:$A$101,MATCH(M16,Calc!$C$2:$C$101,0))) -> 0 | J16: =IF(M16="","",ROUND(M16,2)) -> 0 | L16: =IF(M16="","",INDEX(Calc!$D$2:$D$101,MATCH(M16,Calc!$C$2:$C$101,0))) -> 0 | M16: =IFERROR(LARGE(Calc!$C$2:$C$101,5),"") -> 0
A19: Previsão das próximas 8 semanas (somente contas em aberto)
A20: Semana | B20: Início | C20: Fim | D20: A receber | E20: A pagar | F20: Saldo da semana | G20: Saldo acumulado
A21: Em atraso | B21: - | C21: - | D21: =SUMIFS(Receber!$L$5:$L$1004,Receber!$D$5:$D$1004,"<"&Hoje) -> 0 | E21: =SUMIFS(Pagar!$K$5:$K$1004,Pagar!$D$5:$D$1004,"<"&Hoje) -> 0 | F21: =D21-E21 -> 0 | G21: =F21 -> 0
A22: Semana 1 | B22: =Hoje+0 -> 46303 | C22: =B22+6 -> 46309 | D22: =SUMIFS(Receber!$L$5:$L$1004,Receber!$D$5:$D$1004,">="&B22,Receber!$D$5:$D$1004,"<="&C22) -> 0 | E22: =SUMIFS(Pagar!$K$5:$K$1004,Pagar!$D$5:$D$1004,">="&B22,Pagar!$D$5:$D$1004,"<="&C22) -> 0 | F22: =D22-E22 -> 0 | G22: =G21+F22 -> 0
A23: Semana 2 | B23: =Hoje+7 -> 46310 | C23: =B23+6 -> 46316 | D23: =SUMIFS(Receber!$L$5:$L$1004,Receber!$D$5:$D$1004,">="&B23,Receber!$D$5:$D$1004,"<="&C23) -> 0 | E23: =SUMIFS(Pagar!$K$5:$K$1004,Pagar!$D$5:$D$1004,">="&B23,Pagar!$D$5:$D$1004,"<="&C23) -> 0 | F23: =D23-E23 -> 0 | G23: =G22+F23 -> 0
A24: Semana 3 | B24: =Hoje+14 -> 46317 | C24: =B24+6 -> 46323 | D24: =SUMIFS(Receber!$L$5:$L$1004,Receber!$D$5:$D$1004,">="&B24,Receber!$D$5:$D$1004,"<="&C24) -> 0 | E24: =SUMIFS(Pagar!$K$5:$K$1004,Pagar!$D$5:$D$1004,">="&B24,Pagar!$D$5:$D$1004,"<="&C24) -> 0 | F24: =D24-E24 -> 0 | G24: =G23+F24 -> 0
A25: Semana 4 | B25: =Hoje+21 -> 46324 | C25: =B25+6 -> 46330 | D25: =SUMIFS(Receber!$L$5:$L$1004,Receber!$D$5:$D$1004,">="&B25,Receber!$D$5:$D$1004,"<="&C25) -> 0 | E25: =SUMIFS(Pagar!$K$5:$K$1004,Pagar!$D$5:$D$1004,">="&B25,Pagar!$D$5:$D$1004,"<="&C25) -> 0 | F25: =D25-E25 -> 0 | G25: =G24+F25 -> 0
A26: Semana 5 | B26: =Hoje+28 -> 46331 | C26: =B26+6 -> 46337 | D26: =SUMIFS(Receber!$L$5:$L$1004,Receber!$D$5:$D$1004,">="&B26,Receber!$D$5:$D$1004,"<="&C26) -> 0 | E26: =SUMIFS(Pagar!$K$5:$K$1004,Pagar!$D$5:$D$1004,">="&B26,Pagar!$D$5:$D$1004,"<="&C26) -> 0 | F26: =D26-E26 -> 0 | G26: =G25+F26 -> 0
A27: Semana 6 | B27: =Hoje+35 -> 46338 | C27: =B27+6 -> 46344 | D27: =SUMIFS(Receber!$L$5:$L$1004,Receber!$D$5:$D$1004,">="&B27,Receber!$D$5:$D$1004,"<="&C27) -> 0 | E27: =SUMIFS(Pagar!$K$5:$K$1004,Pagar!$D$5:$D$1004,">="&B27,Pagar!$D$5:$D$1004,"<="&C27) -> 0 | F27: =D27-E27 -> 0 | G27: =G26+F27 -> 0
A28: Semana 7 | B28: =Hoje+42 -> 46345 | C28: =B28+6 -> 46351 | D28: =SUMIFS(Receber!$L$5:$L$1004,Receber!$D$5:$D$1004,">="&B28,Receber!$D$5:$D$1004,"<="&C28) -> 0 | E28: =SUMIFS(Pagar!$K$5:$K$1004,Pagar!$D$5:$D$1004,">="&B28,Pagar!$D$5:$D$1004,"<="&C28) -> 0 | F28: =D28-E28 -> 0 | G28: =G27+F28 -> 0
A29: Semana 8 | B29: =Hoje+49 -> 46352 | C29: =B29+6 -> 46358 | D29: =SUMIFS(Receber!$L$5:$L$1004,Receber!$D$5:$D$1004,">="&B29,Receber!$D$5:$D$1004,"<="&C29) -> 0 | E29: =SUMIFS(Pagar!$K$5:$K$1004,Pagar!$D$5:$D$1004,">="&B29,Pagar!$D$5:$D$1004,"<="&C29) -> 0 | F29: =D29-E29 -> 0 | G29: =G28+F29 -> 0
