Workbook
Name CliNome: Clientes!$A$5:$A$304
Name ComMec: Config!$C$8
Name EntCod: Entradas!$B$5:$B$1004
Name EntQtd: Entradas!$C$5:$C$1004
Name Formas: Config!$G$5:$G$14
Name HistPlaca: Histórico!$C$4
Name Hoje: Config!$C$5
Name ItCod: 'Itens da OS'!$B$5:$B$3004
Name ItCusto: 'Itens da OS'!$H$5:$H$3004
Name ItOS: 'Itens da OS'!$A$5:$A$3004
Name ItQtd: 'Itens da OS'!$C$5:$C$3004
Name ItStatus: 'Itens da OS'!$I$5:$I$3004
Name ItTotal: 'Itens da OS'!$G$5:$G$3004
Name MarkupPeca: Config!$C$7
Name Mecanicos: Config!$E$5:$E$14
Name OSNum: OS!$A$5:$A$1004
Name OSStatus: OS!$I$5:$I$1004
Name PecCod: Peças!$A$5:$A$504
Name PecCusto: Peças!$C$5:$C$504
Name PecDesc: Peças!$B$5:$B$504
Name PecPreco: Peças!$G$5:$G$504
Name PrazoMax: Config!$C$9
Name StatusOS: Config!$B$14:$B$20
Name ValorHora: Config!$C$6
Name VeicCli: Veículos!$D$5:$D$304
Name VeicModelo: Veículos!$B$5:$B$304
Name VeicPlaca: Veículos!$A$5:$A$304

Sheet Início
A1: Ordem de Serviço para Oficinas
A2: Carvex XLS · Cada peça na OS, cada real no caixa
B4: O que esta planilha faz
B5: Cadastre clientes, veículos e peças e abra as ordens de serviço. A planilha calcula mão de obra, peças, total, lucro de cada OS, dá baixa no estoque de peças, avisa OS atrasadas e o que falta receber, mostra o histórico por placa e o faturamento do mês.
B7: Como começar (5 minutos)
B8: 1. Config | C8: Informe o valor da hora de mão de obra, o markup padrão sobre as peças, a comissão dos mecânicos e o prazo máximo de uma OS (dias).
B9: 2. Cadastre clientes e veículos | C9: Em Clientes e Veículos: nome/telefone e placa/modelo/ano. Cada veículo pertence a um cliente.
B10: 3. Cadastre as peças | C10: Em Peças: código, custo e (opcional) preço fixo. Se o preço ficar vazio, a planilha usa custo + markup.
B11: 4. Abra a OS | C11: Em OS: número, data, placa, serviço, mecânico, status e horas. Em Itens da OS lance as peças usadas (mesmo número da OS).
B12: 5. Entregue e receba | C12: Ao entregar, mude o status para Entregue, informe data de entrega, forma de pagamento e valor recebido.
B14: Mapa das abas (clique para ir)
B15: Config | C15: Valor da hora, markup, comissão, prazo, mecânicos e formas de pagamento.
B16: Clientes | C16: Cadastro de clientes.
B17: Veículos | C17: Placa, modelo e dono.
B18: Peças | C18: Cadastro e estoque atual de peças.
B19: Entradas | C19: Compras de peças (repõem o estoque).
B20: OS | C20: Ordens de serviço, totais e lucro.
B21: Itens da OS | C21: Peças usadas em cada OS.
B22: Histórico | C22: Todas as OS de uma placa.
B23: Dashboard | C23: Faturamento, lucro, OS atrasadas e a receber.
B25: Legenda de cores
B26: Amarelo | C26: Célula que VOCÊ preenche.
B27: Cinza | C27: Cálculo automático. Não digite aqui.
B28: Verde escuro | C28: Cabeçalho de coluna.
B30: Atenção
B31: • O estoque de uma peça só baixa quando a OS sai do status 'Orçamento' (e não está 'Cancelada').
B32: • O faturamento do mês considera apenas OS com status Entregue e data de entrega no mês.
B33: • O número da OS deve ser único. Use o mesmo número em OS e em Itens da OS.
B35: Carvex XLS · Ordem de Serviço para Oficinas · versão 1.0 · Dúvidas: consulte o TUTORIAL.md e o MANUAL.md que acompanham o produto.

Sheet Config
A1: Configurações
A2: Preencha as células amarelas.
B4: Oficina | E4: Mecânicos | G4: Formas de pagamento
B5: Data de hoje (referência) | C5: =TODAY() -> 46303 | G5: Pix
B6: Valor da hora de mão de obra (R$) | G6: Dinheiro
B7: Markup padrão sobre o custo das peças (%) | C7: 0.4 | G7: Cartão de débito
B8: Comissão dos mecânicos sobre mão de obra (%) | G8: Cartão de crédito
B9: Prazo máximo de uma OS aberta (dias) | C9: 5 | G9: Boleto
G10: Transferência
B12: Status da OS: Orçamento, Aprovado, Em execução, Aguardando peça, Finalizado, Entregue, Cancelada (fixos).
B13: Lista de status
B14: Orçamento
B15: Aprovado
B16: Em execução
B17: Aguardando peça
B18: Finalizado
B19: Entregue
B20: Cancelada

Sheet Clientes
A1: Clientes
A2: Um cliente por linha.
A4: Nome do cliente | B4: Telefone | C4: Observação

Sheet Veículos
A1: Veículos
A2: Placa única. Escolha o cliente da lista.
A4: Placa | B4: Modelo | C4: Ano | D4: Cliente | E4: Observação

Sheet Peças
A1: Peças e estoque
A2: Preço vazio = custo + markup. O estoque atual é calculado pelas Entradas e pelas OS.
A4: Código | B4: Descrição | C4: Custo (R$) | D4: Preço de venda fixo (R$) | E4: Estoque inicial | F4: Estoque mínimo | G4: Preço de venda EFETIVO | H4: Entradas | I4: Usadas em OS | J4: ESTOQUE ATUAL | K4: Situação
G5: =IF($A5="","",IF($D5<>"",$D5,N($C5)*(1+MarkupPeca))) -> 0 | H5: =IF($A5="","",SUMIFS(EntQtd,EntCod,$A5)) -> 0 | I5: =IF($A5="","",SUMIFS(ItQtd,ItCod,$A5,ItStatus,"<>Orçamento",ItStatus,"<>Cancelada")) -> 0 | J5: =IF($A5="","",N($E5)+$H5-$I5) -> 0 | K5: =IF($A5="","",IF($J5<=0,"RUPTURA",IF($J5<=N($F5),"REPOR","OK"))) -> 0
G6: =IF($A6="","",IF($D6<>"",$D6,N($C6)*(1+MarkupPeca))) -> 0 | H6: =IF($A6="","",SUMIFS(EntQtd,EntCod,$A6)) -> 0 | I6: =IF($A6="","",SUMIFS(ItQtd,ItCod,$A6,ItStatus,"<>Orçamento",ItStatus,"<>Cancelada")) -> 0 | J6: =IF($A6="","",N($E6)+$H6-$I6) -> 0 | K6: =IF($A6="","",IF($J6<=0,"RUPTURA",IF($J6<=N($F6),"REPOR","OK"))) -> 0
G7: =IF($A7="","",IF($D7<>"",$D7,N($C7)*(1+MarkupPeca))) -> 0 | H7: =IF($A7="","",SUMIFS(EntQtd,EntCod,$A7)) -> 0 | I7: =IF($A7="","",SUMIFS(ItQtd,ItCod,$A7,ItStatus,"<>Orçamento",ItStatus,"<>Cancelada")) -> 0 | J7: =IF($A7="","",N($E7)+$H7-$I7) -> 0 | K7: =IF($A7="","",IF($J7<=0,"RUPTURA",IF($J7<=N($F7),"REPOR","OK"))) -> 0
G8: =IF($A8="","",IF($D8<>"",$D8,N($C8)*(1+MarkupPeca))) -> 0 | H8: =IF($A8="","",SUMIFS(EntQtd,EntCod,$A8)) -> 0 | I8: =IF($A8="","",SUMIFS(ItQtd,ItCod,$A8,ItStatus,"<>Orçamento",ItStatus,"<>Cancelada")) -> 0 | J8: =IF($A8="","",N($E8)+$H8-$I8) -> 0 | K8: =IF($A8="","",IF($J8<=0,"RUPTURA",IF($J8<=N($F8),"REPOR","OK"))) -> 0
G9: =IF($A9="","",IF($D9<>"",$D9,N($C9)*(1+MarkupPeca))) -> 0 | H9: =IF($A9="","",SUMIFS(EntQtd,EntCod,$A9)) -> 0 | I9: =IF($A9="","",SUMIFS(ItQtd,ItCod,$A9,ItStatus,"<>Orçamento",ItStatus,"<>Cancelada")) -> 0 | J9: =IF($A9="","",N($E9)+$H9-$I9) -> 0 | K9: =IF($A9="","",IF($J9<=0,"RUPTURA",IF($J9<=N($F9),"REPOR","OK"))) -> 0
G10: =IF($A10="","",IF($D10<>"",$D10,N($C10)*(1+MarkupPeca))) -> 0 | H10: =IF($A10="","",SUMIFS(EntQtd,EntCod,$A10)) -> 0 | I10: =IF($A10="","",SUMIFS(ItQtd,ItCod,$A10,ItStatus,"<>Orçamento",ItStatus,"<>Cancelada")) -> 0 | J10: =IF($A10="","",N($E10)+$H10-$I10) -> 0 | K10: =IF($A10="","",IF($J10<=0,"RUPTURA",IF($J10<=N($F10),"REPOR","OK"))) -> 0
G11: =IF($A11="","",IF($D11<>"",$D11,N($C11)*(1+MarkupPeca))) -> 0 | H11: =IF($A11="","",SUMIFS(EntQtd,EntCod,$A11)) -> 0 | I11: =IF($A11="","",SUMIFS(ItQtd,ItCod,$A11,ItStatus,"<>Orçamento",ItStatus,"<>Cancelada")) -> 0 | J11: =IF($A11="","",N($E11)+$H11-$I11) -> 0 | K11: =IF($A11="","",IF($J11<=0,"RUPTURA",IF($J11<=N($F11),"REPOR","OK"))) -> 0
G12: =IF($A12="","",IF($D12<>"",$D12,N($C12)*(1+MarkupPeca))) -> 0 | H12: =IF($A12="","",SUMIFS(EntQtd,EntCod,$A12)) -> 0 | I12: =IF($A12="","",SUMIFS(ItQtd,ItCod,$A12,ItStatus,"<>Orçamento",ItStatus,"<>Cancelada")) -> 0 | J12: =IF($A12="","",N($E12)+$H12-$I12) -> 0 | K12: =IF($A12="","",IF($J12<=0,"RUPTURA",IF($J12<=N($F12),"REPOR","OK"))) -> 0
G13: =IF($A13="","",IF($D13<>"",$D13,N($C13)*(1+MarkupPeca))) -> 0 | H13: =IF($A13="","",SUMIFS(EntQtd,EntCod,$A13)) -> 0 | I13: =IF($A13="","",SUMIFS(ItQtd,ItCod,$A13,ItStatus,"<>Orçamento",ItStatus,"<>Cancelada")) -> 0 | J13: =IF($A13="","",N($E13)+$H13-$I13) -> 0 | K13: =IF($A13="","",IF($J13<=0,"RUPTURA",IF($J13<=N($F13),"REPOR","OK"))) -> 0
G14: =IF($A14="","",IF($D14<>"",$D14,N($C14)*(1+MarkupPeca))) -> 0 | H14: =IF($A14="","",SUMIFS(EntQtd,EntCod,$A14)) -> 0 | I14: =IF($A14="","",SUMIFS(ItQtd,ItCod,$A14,ItStatus,"<>Orçamento",ItStatus,"<>Cancelada")) -> 0 | J14: =IF($A14="","",N($E14)+$H14-$I14) -> 0 | K14: =IF($A14="","",IF($J14<=0,"RUPTURA",IF($J14<=N($F14),"REPOR","OK"))) -> 0
G15: =IF($A15="","",IF($D15<>"",$D15,N($C15)*(1+MarkupPeca))) -> 0 | H15: =IF($A15="","",SUMIFS(EntQtd,EntCod,$A15)) -> 0 | I15: =IF($A15="","",SUMIFS(ItQtd,ItCod,$A15,ItStatus,"<>Orçamento",ItStatus,"<>Cancelada")) -> 0 | J15: =IF($A15="","",N($E15)+$H15-$I15) -> 0 | K15: =IF($A15="","",IF($J15<=0,"RUPTURA",IF($J15<=N($F15),"REPOR","OK"))) -> 0
G16: =IF($A16="","",IF($D16<>"",$D16,N($C16)*(1+MarkupPeca))) -> 0 | H16: =IF($A16="","",SUMIFS(EntQtd,EntCod,$A16)) -> 0 | I16: =IF($A16="","",SUMIFS(ItQtd,ItCod,$A16,ItStatus,"<>Orçamento",ItStatus,"<>Cancelada")) -> 0 | J16: =IF($A16="","",N($E16)+$H16-$I16) -> 0 | K16: =IF($A16="","",IF($J16<=0,"RUPTURA",IF($J16<=N($F16),"REPOR","OK"))) -> 0
... G504: =IF($A504="","",IF($D504<>"",$D504,N($C504)*(1+MarkupPeca))) -> 0 | H504: =IF($A504="","",SUMIFS(EntQtd,EntCod,$A504)) -> 0 | I504: =IF($A504="","",SUMIFS(ItQtd,ItCod,$A504,ItStatus,"<>Orçamento",ItStatus,"<>Cancelada")) -> 0 | J504: =IF($A504="","",N($E504)+$H504-$I504) -> 0 | K504: =IF($A504="","",IF($J504<=0,"RUPTURA",IF($J504<=N($F504),"REPOR","OK"))) -> 0

Sheet Entradas
A1: Entradas de peças (compras)
A2: Registre cada compra para repor o estoque.
A4: Data | B4: Código da peça | C4: Quantidade | D4: Custo unitário (R$) | E4: Fornecedor | F4: NF / pedido | G4: Descrição | H4: Total (R$)
G5: =IF($B5="","",IFERROR(INDEX(PecDesc,MATCH($B5,PecCod,0)),"Peça não cadastrada")) -> 0 | H5: =IF(OR($C5="",$D5=""),"",$C5*$D5) -> 0
G6: =IF($B6="","",IFERROR(INDEX(PecDesc,MATCH($B6,PecCod,0)),"Peça não cadastrada")) -> 0 | H6: =IF(OR($C6="",$D6=""),"",$C6*$D6) -> 0
G7: =IF($B7="","",IFERROR(INDEX(PecDesc,MATCH($B7,PecCod,0)),"Peça não cadastrada")) -> 0 | H7: =IF(OR($C7="",$D7=""),"",$C7*$D7) -> 0
G8: =IF($B8="","",IFERROR(INDEX(PecDesc,MATCH($B8,PecCod,0)),"Peça não cadastrada")) -> 0 | H8: =IF(OR($C8="",$D8=""),"",$C8*$D8) -> 0
G9: =IF($B9="","",IFERROR(INDEX(PecDesc,MATCH($B9,PecCod,0)),"Peça não cadastrada")) -> 0 | H9: =IF(OR($C9="",$D9=""),"",$C9*$D9) -> 0
G10: =IF($B10="","",IFERROR(INDEX(PecDesc,MATCH($B10,PecCod,0)),"Peça não cadastrada")) -> 0 | H10: =IF(OR($C10="",$D10=""),"",$C10*$D10) -> 0
G11: =IF($B11="","",IFERROR(INDEX(PecDesc,MATCH($B11,PecCod,0)),"Peça não cadastrada")) -> 0 | H11: =IF(OR($C11="",$D11=""),"",$C11*$D11) -> 0
G12: =IF($B12="","",IFERROR(INDEX(PecDesc,MATCH($B12,PecCod,0)),"Peça não cadastrada")) -> 0 | H12: =IF(OR($C12="",$D12=""),"",$C12*$D12) -> 0
G13: =IF($B13="","",IFERROR(INDEX(PecDesc,MATCH($B13,PecCod,0)),"Peça não cadastrada")) -> 0 | H13: =IF(OR($C13="",$D13=""),"",$C13*$D13) -> 0
G14: =IF($B14="","",IFERROR(INDEX(PecDesc,MATCH($B14,PecCod,0)),"Peça não cadastrada")) -> 0 | H14: =IF(OR($C14="",$D14=""),"",$C14*$D14) -> 0
G15: =IF($B15="","",IFERROR(INDEX(PecDesc,MATCH($B15,PecCod,0)),"Peça não cadastrada")) -> 0 | H15: =IF(OR($C15="",$D15=""),"",$C15*$D15) -> 0
G16: =IF($B16="","",IFERROR(INDEX(PecDesc,MATCH($B16,PecCod,0)),"Peça não cadastrada")) -> 0 | H16: =IF(OR($C16="",$D16=""),"",$C16*$D16) -> 0
... G1004: =IF($B1004="","",IFERROR(INDEX(PecDesc,MATCH($B1004,PecCod,0)),"Peça não cadastrada")) -> 0 | H1004: =IF(OR($C1004="",$D1004=""),"",$C1004*$D1004) -> 0

Sheet OS
A1: Ordens de Serviço
A2: Uma linha por OS. As peças usadas são lançadas na aba Itens da OS com o mesmo número.
A4: Nº OS | B4: Data de entrada | C4: Placa | D4: Cliente | E4: Modelo | F4: Km | G4: Serviço / defeito relatado | H4: Mecânico | I4: Status | J4: Horas de mão de obra | K4: Serviços de terceiros (R$) | L4: Desconto (R$) | M4: Data de entrega | N4: Forma de pagamento | O4: Valor recebido (R$) | P4: Mão de obra (R$) | Q4: Peças (R$) | R4: TOTAL DA OS | S4: Custo das peças | T4: Comissão do mecânico | U4: LUCRO BRUTO | V4: Margem | W4: Saldo a receber | X4: Dias na oficina | Y4: ALERTA | Z4: Mês (faturamento) | AA4: Seq. histórico
D5: =IF($C5="","",IFERROR(INDEX(VeicCli,MATCH($C5,VeicPlaca,0)),"Placa não cadastrada")) -> 0 | E5: =IF($C5="","",IFERROR(INDEX(VeicModelo,MATCH($C5,VeicPlaca,0)),"")) -> 0 | P5: =IF($A5="","",N($J5)*ValorHora) -> 0 | Q5: =IF($A5="","",SUMIFS(ItTotal,ItOS,$A5)) -> 0 | R5: =IF($A5="","",$P5+$Q5+N($K5)-N($L5)) -> 0 | S5: =IF($A5="","",SUMIFS(ItCusto,ItOS,$A5)) -> 0 | T5: =IF($A5="","",$P5*ComMec) -> 0 | U5: =IF($A5="","",$R5-$S5-$T5-N($K5)) -> 0 | V5: =IF(OR($A5="",N($R5)<=0),"",$U5/$R5) -> 0 | W5: =IF($A5="","",IF(OR($I5="Finalizado",$I5="Entregue"),MAX(0,$R5-N($O5)),0)) -> 0 | X5: =IF(OR($A5="",$B5=""),"",IF(OR($I5="Entregue",$I5="Cancelada"),"",Hoje-$B5)) -> 0 | Y5: =IF($A5="","",IF(AND(OR($I5="Aprovado",$I5="Em execução",$I5="Aguardando peça"),N($X5)>PrazoMax),"ATRASADA",IF(AND(OR($I5="Finalizado",$I5="Entregue"),$W5>0.005),"Cobrar",IF($I5="Orçamento","Aguardando aprovação","")))) -> 0 | Z5: =IF(AND($I5="Entregue",$M5<>""),DATE(YEAR($M5),MONTH($M5),1),"") -> 0 | AA5: =IF(AND($C5<>"",$C5=HistPlaca),COUNTIF($C$5:$C5,HistPlaca),"") -> 0
D6: =IF($C6="","",IFERROR(INDEX(VeicCli,MATCH($C6,VeicPlaca,0)),"Placa não cadastrada")) -> 0 | E6: =IF($C6="","",IFERROR(INDEX(VeicModelo,MATCH($C6,VeicPlaca,0)),"")) -> 0 | P6: =IF($A6="","",N($J6)*ValorHora) -> 0 | Q6: =IF($A6="","",SUMIFS(ItTotal,ItOS,$A6)) -> 0 | R6: =IF($A6="","",$P6+$Q6+N($K6)-N($L6)) -> 0 | S6: =IF($A6="","",SUMIFS(ItCusto,ItOS,$A6)) -> 0 | T6: =IF($A6="","",$P6*ComMec) -> 0 | U6: =IF($A6="","",$R6-$S6-$T6-N($K6)) -> 0 | V6: =IF(OR($A6="",N($R6)<=0),"",$U6/$R6) -> 0 | W6: =IF($A6="","",IF(OR($I6="Finalizado",$I6="Entregue"),MAX(0,$R6-N($O6)),0)) -> 0 | X6: =IF(OR($A6="",$B6=""),"",IF(OR($I6="Entregue",$I6="Cancelada"),"",Hoje-$B6)) -> 0 | Y6: =IF($A6="","",IF(AND(OR($I6="Aprovado",$I6="Em execução",$I6="Aguardando peça"),N($X6)>PrazoMax),"ATRASADA",IF(AND(OR($I6="Finalizado",$I6="Entregue"),$W6>0.005),"Cobrar",IF($I6="Orçamento","Aguardando aprovação","")))) -> 0 | Z6: =IF(AND($I6="Entregue",$M6<>""),DATE(YEAR($M6),MONTH($M6),1),"") -> 0 | AA6: =IF(AND($C6<>"",$C6=HistPlaca),COUNTIF($C$5:$C6,HistPlaca),"") -> 0
D7: =IF($C7="","",IFERROR(INDEX(VeicCli,MATCH($C7,VeicPlaca,0)),"Placa não cadastrada")) -> 0 | E7: =IF($C7="","",IFERROR(INDEX(VeicModelo,MATCH($C7,VeicPlaca,0)),"")) -> 0 | P7: =IF($A7="","",N($J7)*ValorHora) -> 0 | Q7: =IF($A7="","",SUMIFS(ItTotal,ItOS,$A7)) -> 0 | R7: =IF($A7="","",$P7+$Q7+N($K7)-N($L7)) -> 0 | S7: =IF($A7="","",SUMIFS(ItCusto,ItOS,$A7)) -> 0 | T7: =IF($A7="","",$P7*ComMec) -> 0 | U7: =IF($A7="","",$R7-$S7-$T7-N($K7)) -> 0 | V7: =IF(OR($A7="",N($R7)<=0),"",$U7/$R7) -> 0 | W7: =IF($A7="","",IF(OR($I7="Finalizado",$I7="Entregue"),MAX(0,$R7-N($O7)),0)) -> 0 | X7: =IF(OR($A7="",$B7=""),"",IF(OR($I7="Entregue",$I7="Cancelada"),"",Hoje-$B7)) -> 0 | Y7: =IF($A7="","",IF(AND(OR($I7="Aprovado",$I7="Em execução",$I7="Aguardando peça"),N($X7)>PrazoMax),"ATRASADA",IF(AND(OR($I7="Finalizado",$I7="Entregue"),$W7>0.005),"Cobrar",IF($I7="Orçamento","Aguardando aprovação","")))) -> 0 | Z7: =IF(AND($I7="Entregue",$M7<>""),DATE(YEAR($M7),MONTH($M7),1),"") -> 0 | AA7: =IF(AND($C7<>"",$C7=HistPlaca),COUNTIF($C$5:$C7,HistPlaca),"") -> 0
D8: =IF($C8="","",IFERROR(INDEX(VeicCli,MATCH($C8,VeicPlaca,0)),"Placa não cadastrada")) -> 0 | E8: =IF($C8="","",IFERROR(INDEX(VeicModelo,MATCH($C8,VeicPlaca,0)),"")) -> 0 | P8: =IF($A8="","",N($J8)*ValorHora) -> 0 | Q8: =IF($A8="","",SUMIFS(ItTotal,ItOS,$A8)) -> 0 | R8: =IF($A8="","",$P8+$Q8+N($K8)-N($L8)) -> 0 | S8: =IF($A8="","",SUMIFS(ItCusto,ItOS,$A8)) -> 0 | T8: =IF($A8="","",$P8*ComMec) -> 0 | U8: =IF($A8="","",$R8-$S8-$T8-N($K8)) -> 0 | V8: =IF(OR($A8="",N($R8)<=0),"",$U8/$R8) -> 0 | W8: =IF($A8="","",IF(OR($I8="Finalizado",$I8="Entregue"),MAX(0,$R8-N($O8)),0)) -> 0 | X8: =IF(OR($A8="",$B8=""),"",IF(OR($I8="Entregue",$I8="Cancelada"),"",Hoje-$B8)) -> 0 | Y8: =IF($A8="","",IF(AND(OR($I8="Aprovado",$I8="Em execução",$I8="Aguardando peça"),N($X8)>PrazoMax),"ATRASADA",IF(AND(OR($I8="Finalizado",$I8="Entregue"),$W8>0.005),"Cobrar",IF($I8="Orçamento","Aguardando aprovação","")))) -> 0 | Z8: =IF(AND($I8="Entregue",$M8<>""),DATE(YEAR($M8),MONTH($M8),1),"") -> 0 | AA8: =IF(AND($C8<>"",$C8=HistPlaca),COUNTIF($C$5:$C8,HistPlaca),"") -> 0
D9: =IF($C9="","",IFERROR(INDEX(VeicCli,MATCH($C9,VeicPlaca,0)),"Placa não cadastrada")) -> 0 | E9: =IF($C9="","",IFERROR(INDEX(VeicModelo,MATCH($C9,VeicPlaca,0)),"")) -> 0 | P9: =IF($A9="","",N($J9)*ValorHora) -> 0 | Q9: =IF($A9="","",SUMIFS(ItTotal,ItOS,$A9)) -> 0 | R9: =IF($A9="","",$P9+$Q9+N($K9)-N($L9)) -> 0 | S9: =IF($A9="","",SUMIFS(ItCusto,ItOS,$A9)) -> 0 | T9: =IF($A9="","",$P9*ComMec) -> 0 | U9: =IF($A9="","",$R9-$S9-$T9-N($K9)) -> 0 | V9: =IF(OR($A9="",N($R9)<=0),"",$U9/$R9) -> 0 | W9: =IF($A9="","",IF(OR($I9="Finalizado",$I9="Entregue"),MAX(0,$R9-N($O9)),0)) -> 0 | X9: =IF(OR($A9="",$B9=""),"",IF(OR($I9="Entregue",$I9="Cancelada"),"",Hoje-$B9)) -> 0 | Y9: =IF($A9="","",IF(AND(OR($I9="Aprovado",$I9="Em execução",$I9="Aguardando peça"),N($X9)>PrazoMax),"ATRASADA",IF(AND(OR($I9="Finalizado",$I9="Entregue"),$W9>0.005),"Cobrar",IF($I9="Orçamento","Aguardando aprovação","")))) -> 0 | Z9: =IF(AND($I9="Entregue",$M9<>""),DATE(YEAR($M9),MONTH($M9),1),"") -> 0 | AA9: =IF(AND($C9<>"",$C9=HistPlaca),COUNTIF($C$5:$C9,HistPlaca),"") -> 0
D10: =IF($C10="","",IFERROR(INDEX(VeicCli,MATCH($C10,VeicPlaca,0)),"Placa não cadastrada")) -> 0 | E10: =IF($C10="","",IFERROR(INDEX(VeicModelo,MATCH($C10,VeicPlaca,0)),"")) -> 0 | P10: =IF($A10="","",N($J10)*ValorHora) -> 0 | Q10: =IF($A10="","",SUMIFS(ItTotal,ItOS,$A10)) -> 0 | R10: =IF($A10="","",$P10+$Q10+N($K10)-N($L10)) -> 0 | S10: =IF($A10="","",SUMIFS(ItCusto,ItOS,$A10)) -> 0 | T10: =IF($A10="","",$P10*ComMec) -> 0 | U10: =IF($A10="","",$R10-$S10-$T10-N($K10)) -> 0 | V10: =IF(OR($A10="",N($R10)<=0),"",$U10/$R10) -> 0 | W10: =IF($A10="","",IF(OR($I10="Finalizado",$I10="Entregue"),MAX(0,$R10-N($O10)),0)) -> 0 | X10: =IF(OR($A10="",$B10=""),"",IF(OR($I10="Entregue",$I10="Cancelada"),"",Hoje-$B10)) -> 0 | Y10: =IF($A10="","",IF(AND(OR($I10="Aprovado",$I10="Em execução",$I10="Aguardando peça"),N($X10)>PrazoMax),"ATRASADA",IF(AND(OR($I10="Finalizado",$I10="Entregue"),$W10>0.005),"Cobrar",IF($I10="Orçamento","Aguardando aprovação","")))) -> 0 | Z10: =IF(AND($I10="Entregue",$M10<>""),DATE(YEAR($M10),MONTH($M10),1),"") -> 0 | AA10: =IF(AND($C10<>"",$C10=HistPlaca),COUNTIF($C$5:$C10,HistPlaca),"") -> 0
D11: =IF($C11="","",IFERROR(INDEX(VeicCli,MATCH($C11,VeicPlaca,0)),"Placa não cadastrada")) -> 0 | E11: =IF($C11="","",IFERROR(INDEX(VeicModelo,MATCH($C11,VeicPlaca,0)),"")) -> 0 | P11: =IF($A11="","",N($J11)*ValorHora) -> 0 | Q11: =IF($A11="","",SUMIFS(ItTotal,ItOS,$A11)) -> 0 | R11: =IF($A11="","",$P11+$Q11+N($K11)-N($L11)) -> 0 | S11: =IF($A11="","",SUMIFS(ItCusto,ItOS,$A11)) -> 0 | T11: =IF($A11="","",$P11*ComMec) -> 0 | U11: =IF($A11="","",$R11-$S11-$T11-N($K11)) -> 0 | V11: =IF(OR($A11="",N($R11)<=0),"",$U11/$R11) -> 0 | W11: =IF($A11="","",IF(OR($I11="Finalizado",$I11="Entregue"),MAX(0,$R11-N($O11)),0)) -> 0 | X11: =IF(OR($A11="",$B11=""),"",IF(OR($I11="Entregue",$I11="Cancelada"),"",Hoje-$B11)) -> 0 | Y11: =IF($A11="","",IF(AND(OR($I11="Aprovado",$I11="Em execução",$I11="Aguardando peça"),N($X11)>PrazoMax),"ATRASADA",IF(AND(OR($I11="Finalizado",$I11="Entregue"),$W11>0.005),"Cobrar",IF($I11="Orçamento","Aguardando aprovação","")))) -> 0 | Z11: =IF(AND($I11="Entregue",$M11<>""),DATE(YEAR($M11),MONTH($M11),1),"") -> 0 | AA11: =IF(AND($C11<>"",$C11=HistPlaca),COUNTIF($C$5:$C11,HistPlaca),"") -> 0
D12: =IF($C12="","",IFERROR(INDEX(VeicCli,MATCH($C12,VeicPlaca,0)),"Placa não cadastrada")) -> 0 | E12: =IF($C12="","",IFERROR(INDEX(VeicModelo,MATCH($C12,VeicPlaca,0)),"")) -> 0 | P12: =IF($A12="","",N($J12)*ValorHora) -> 0 | Q12: =IF($A12="","",SUMIFS(ItTotal,ItOS,$A12)) -> 0 | R12: =IF($A12="","",$P12+$Q12+N($K12)-N($L12)) -> 0 | S12: =IF($A12="","",SUMIFS(ItCusto,ItOS,$A12)) -> 0 | T12: =IF($A12="","",$P12*ComMec) -> 0 | U12: =IF($A12="","",$R12-$S12-$T12-N($K12)) -> 0 | V12: =IF(OR($A12="",N($R12)<=0),"",$U12/$R12) -> 0 | W12: =IF($A12="","",IF(OR($I12="Finalizado",$I12="Entregue"),MAX(0,$R12-N($O12)),0)) -> 0 | X12: =IF(OR($A12="",$B12=""),"",IF(OR($I12="Entregue",$I12="Cancelada"),"",Hoje-$B12)) -> 0 | Y12: =IF($A12="","",IF(AND(OR($I12="Aprovado",$I12="Em execução",$I12="Aguardando peça"),N($X12)>PrazoMax),"ATRASADA",IF(AND(OR($I12="Finalizado",$I12="Entregue"),$W12>0.005),"Cobrar",IF($I12="Orçamento","Aguardando aprovação","")))) -> 0 | Z12: =IF(AND($I12="Entregue",$M12<>""),DATE(YEAR($M12),MONTH($M12),1),"") -> 0 | AA12: =IF(AND($C12<>"",$C12=HistPlaca),COUNTIF($C$5:$C12,HistPlaca),"") -> 0
D13: =IF($C13="","",IFERROR(INDEX(VeicCli,MATCH($C13,VeicPlaca,0)),"Placa não cadastrada")) -> 0 | E13: =IF($C13="","",IFERROR(INDEX(VeicModelo,MATCH($C13,VeicPlaca,0)),"")) -> 0 | P13: =IF($A13="","",N($J13)*ValorHora) -> 0 | Q13: =IF($A13="","",SUMIFS(ItTotal,ItOS,$A13)) -> 0 | R13: =IF($A13="","",$P13+$Q13+N($K13)-N($L13)) -> 0 | S13: =IF($A13="","",SUMIFS(ItCusto,ItOS,$A13)) -> 0 | T13: =IF($A13="","",$P13*ComMec) -> 0 | U13: =IF($A13="","",$R13-$S13-$T13-N($K13)) -> 0 | V13: =IF(OR($A13="",N($R13)<=0),"",$U13/$R13) -> 0 | W13: =IF($A13="","",IF(OR($I13="Finalizado",$I13="Entregue"),MAX(0,$R13-N($O13)),0)) -> 0 | X13: =IF(OR($A13="",$B13=""),"",IF(OR($I13="Entregue",$I13="Cancelada"),"",Hoje-$B13)) -> 0 | Y13: =IF($A13="","",IF(AND(OR($I13="Aprovado",$I13="Em execução",$I13="Aguardando peça"),N($X13)>PrazoMax),"ATRASADA",IF(AND(OR($I13="Finalizado",$I13="Entregue"),$W13>0.005),"Cobrar",IF($I13="Orçamento","Aguardando aprovação","")))) -> 0 | Z13: =IF(AND($I13="Entregue",$M13<>""),DATE(YEAR($M13),MONTH($M13),1),"") -> 0 | AA13: =IF(AND($C13<>"",$C13=HistPlaca),COUNTIF($C$5:$C13,HistPlaca),"") -> 0
D14: =IF($C14="","",IFERROR(INDEX(VeicCli,MATCH($C14,VeicPlaca,0)),"Placa não cadastrada")) -> 0 | E14: =IF($C14="","",IFERROR(INDEX(VeicModelo,MATCH($C14,VeicPlaca,0)),"")) -> 0 | P14: =IF($A14="","",N($J14)*ValorHora) -> 0 | Q14: =IF($A14="","",SUMIFS(ItTotal,ItOS,$A14)) -> 0 | R14: =IF($A14="","",$P14+$Q14+N($K14)-N($L14)) -> 0 | S14: =IF($A14="","",SUMIFS(ItCusto,ItOS,$A14)) -> 0 | T14: =IF($A14="","",$P14*ComMec) -> 0 | U14: =IF($A14="","",$R14-$S14-$T14-N($K14)) -> 0 | V14: =IF(OR($A14="",N($R14)<=0),"",$U14/$R14) -> 0 | W14: =IF($A14="","",IF(OR($I14="Finalizado",$I14="Entregue"),MAX(0,$R14-N($O14)),0)) -> 0 | X14: =IF(OR($A14="",$B14=""),"",IF(OR($I14="Entregue",$I14="Cancelada"),"",Hoje-$B14)) -> 0 | Y14: =IF($A14="","",IF(AND(OR($I14="Aprovado",$I14="Em execução",$I14="Aguardando peça"),N($X14)>PrazoMax),"ATRASADA",IF(AND(OR($I14="Finalizado",$I14="Entregue"),$W14>0.005),"Cobrar",IF($I14="Orçamento","Aguardando aprovação","")))) -> 0 | Z14: =IF(AND($I14="Entregue",$M14<>""),DATE(YEAR($M14),MONTH($M14),1),"") -> 0 | AA14: =IF(AND($C14<>"",$C14=HistPlaca),COUNTIF($C$5:$C14,HistPlaca),"") -> 0
D15: =IF($C15="","",IFERROR(INDEX(VeicCli,MATCH($C15,VeicPlaca,0)),"Placa não cadastrada")) -> 0 | E15: =IF($C15="","",IFERROR(INDEX(VeicModelo,MATCH($C15,VeicPlaca,0)),"")) -> 0 | P15: =IF($A15="","",N($J15)*ValorHora) -> 0 | Q15: =IF($A15="","",SUMIFS(ItTotal,ItOS,$A15)) -> 0 | R15: =IF($A15="","",$P15+$Q15+N($K15)-N($L15)) -> 0 | S15: =IF($A15="","",SUMIFS(ItCusto,ItOS,$A15)) -> 0 | T15: =IF($A15="","",$P15*ComMec) -> 0 | U15: =IF($A15="","",$R15-$S15-$T15-N($K15)) -> 0 | V15: =IF(OR($A15="",N($R15)<=0),"",$U15/$R15) -> 0 | W15: =IF($A15="","",IF(OR($I15="Finalizado",$I15="Entregue"),MAX(0,$R15-N($O15)),0)) -> 0 | X15: =IF(OR($A15="",$B15=""),"",IF(OR($I15="Entregue",$I15="Cancelada"),"",Hoje-$B15)) -> 0 | Y15: =IF($A15="","",IF(AND(OR($I15="Aprovado",$I15="Em execução",$I15="Aguardando peça"),N($X15)>PrazoMax),"ATRASADA",IF(AND(OR($I15="Finalizado",$I15="Entregue"),$W15>0.005),"Cobrar",IF($I15="Orçamento","Aguardando aprovação","")))) -> 0 | Z15: =IF(AND($I15="Entregue",$M15<>""),DATE(YEAR($M15),MONTH($M15),1),"") -> 0 | AA15: =IF(AND($C15<>"",$C15=HistPlaca),COUNTIF($C$5:$C15,HistPlaca),"") -> 0
D16: =IF($C16="","",IFERROR(INDEX(VeicCli,MATCH($C16,VeicPlaca,0)),"Placa não cadastrada")) -> 0 | E16: =IF($C16="","",IFERROR(INDEX(VeicModelo,MATCH($C16,VeicPlaca,0)),"")) -> 0 | P16: =IF($A16="","",N($J16)*ValorHora) -> 0 | Q16: =IF($A16="","",SUMIFS(ItTotal,ItOS,$A16)) -> 0 | R16: =IF($A16="","",$P16+$Q16+N($K16)-N($L16)) -> 0 | S16: =IF($A16="","",SUMIFS(ItCusto,ItOS,$A16)) -> 0 | T16: =IF($A16="","",$P16*ComMec) -> 0 | U16: =IF($A16="","",$R16-$S16-$T16-N($K16)) -> 0 | V16: =IF(OR($A16="",N($R16)<=0),"",$U16/$R16) -> 0 | W16: =IF($A16="","",IF(OR($I16="Finalizado",$I16="Entregue"),MAX(0,$R16-N($O16)),0)) -> 0 | X16: =IF(OR($A16="",$B16=""),"",IF(OR($I16="Entregue",$I16="Cancelada"),"",Hoje-$B16)) -> 0 | Y16: =IF($A16="","",IF(AND(OR($I16="Aprovado",$I16="Em execução",$I16="Aguardando peça"),N($X16)>PrazoMax),"ATRASADA",IF(AND(OR($I16="Finalizado",$I16="Entregue"),$W16>0.005),"Cobrar",IF($I16="Orçamento","Aguardando aprovação","")))) -> 0 | Z16: =IF(AND($I16="Entregue",$M16<>""),DATE(YEAR($M16),MONTH($M16),1),"") -> 0 | AA16: =IF(AND($C16<>"",$C16=HistPlaca),COUNTIF($C$5:$C16,HistPlaca),"") -> 0
... D1004: =IF($C1004="","",IFERROR(INDEX(VeicCli,MATCH($C1004,VeicPlaca,0)),"Placa não cadastrada")) -> 0 | E1004: =IF($C1004="","",IFERROR(INDEX(VeicModelo,MATCH($C1004,VeicPlaca,0)),"")) -> 0 | P1004: =IF($A1004="","",N($J1004)*ValorHora) -> 0 | Q1004: =IF($A1004="","",SUMIFS(ItTotal,ItOS,$A1004)) -> 0 | R1004: =IF($A1004="","",$P1004+$Q1004+N($K1004)-N($L1004)) -> 0 | S1004: =IF($A1004="","",SUMIFS(ItCusto,ItOS,$A1004)) -> 0 | T1004: =IF($A1004="","",$P1004*ComMec) -> 0 | U1004: =IF($A1004="","",$R1004-$S1004-$T1004-N($K1004)) -> 0 | V1004: =IF(OR($A1004="",N($R1004)<=0),"",$U1004/$R1004) -> 0 | W1004: =IF($A1004="","",IF(OR($I1004="Finalizado",$I1004="Entregue"),MAX(0,$R1004-N($O1004)),0)) -> 0 | X1004: =IF(OR($A1004="",$B1004=""),"",IF(OR($I1004="Entregue",$I1004="Cancelada"),"",Hoje-$B1004)) -> 0 | Y1004: =IF($A1004="","",IF(AND(OR($I1004="Aprovado",$I1004="Em execução",$I1004="Aguardando peça"),N($X1004)>PrazoMax),"ATRASADA",IF(AND(OR($I1004="Finalizado",$I1004="Entregue"),$W1004>0.005),"Cobrar",IF($I1004="Orçamento","Aguardando aprovação","")))) -> 0 | Z1004: =IF(AND($I1004="Entregue",$M1004<>""),DATE(YEAR($M1004),MONTH($M1004),1),"") -> 0 | AA1004: =IF(AND($C1004<>"",$C1004=HistPlaca),COUNTIF($C$5:$C1004,HistPlaca),"") -> 0

Sheet Itens da OS
A1: Itens (peças) da OS
A2: Uma linha por peça usada. O preço vem da aba Peças (ou digite um preço diferente).
A4: Nº OS | B4: Código da peça | C4: Quantidade | D4: Preço unitário (opcional) | E4: Descrição | F4: Preço efetivo | G4: Total (R$) | H4: Custo (R$) | I4: Status da OS | J4: Conferência
E5: =IF($B5="","",IFERROR(INDEX(PecDesc,MATCH($B5,PecCod,0)),"Peça não cadastrada")) -> 0 | F5: =IF($B5="","",IF($D5<>"",$D5,IFERROR(INDEX(PecPreco,MATCH($B5,PecCod,0)),0))) -> 0 | G5: =IF(OR($B5="",$C5=""),"",$C5*$F5) -> 0 | H5: =IF(OR($B5="",$C5=""),"",$C5*IFERROR(INDEX(PecCusto,MATCH($B5,PecCod,0)),0)) -> 0 | I5: =IF($A5="","",IFERROR(INDEX(OSStatus,MATCH($A5,OSNum,0)),"OS inexistente")) -> 0 | J5: =IF($A5="","",IF($I5="OS inexistente","OS inexistente",IF($E5="Peça não cadastrada","Peça não cadastrada","OK"))) -> 0
E6: =IF($B6="","",IFERROR(INDEX(PecDesc,MATCH($B6,PecCod,0)),"Peça não cadastrada")) -> 0 | F6: =IF($B6="","",IF($D6<>"",$D6,IFERROR(INDEX(PecPreco,MATCH($B6,PecCod,0)),0))) -> 0 | G6: =IF(OR($B6="",$C6=""),"",$C6*$F6) -> 0 | H6: =IF(OR($B6="",$C6=""),"",$C6*IFERROR(INDEX(PecCusto,MATCH($B6,PecCod,0)),0)) -> 0 | I6: =IF($A6="","",IFERROR(INDEX(OSStatus,MATCH($A6,OSNum,0)),"OS inexistente")) -> 0 | J6: =IF($A6="","",IF($I6="OS inexistente","OS inexistente",IF($E6="Peça não cadastrada","Peça não cadastrada","OK"))) -> 0
E7: =IF($B7="","",IFERROR(INDEX(PecDesc,MATCH($B7,PecCod,0)),"Peça não cadastrada")) -> 0 | F7: =IF($B7="","",IF($D7<>"",$D7,IFERROR(INDEX(PecPreco,MATCH($B7,PecCod,0)),0))) -> 0 | G7: =IF(OR($B7="",$C7=""),"",$C7*$F7) -> 0 | H7: =IF(OR($B7="",$C7=""),"",$C7*IFERROR(INDEX(PecCusto,MATCH($B7,PecCod,0)),0)) -> 0 | I7: =IF($A7="","",IFERROR(INDEX(OSStatus,MATCH($A7,OSNum,0)),"OS inexistente")) -> 0 | J7: =IF($A7="","",IF($I7="OS inexistente","OS inexistente",IF($E7="Peça não cadastrada","Peça não cadastrada","OK"))) -> 0
E8: =IF($B8="","",IFERROR(INDEX(PecDesc,MATCH($B8,PecCod,0)),"Peça não cadastrada")) -> 0 | F8: =IF($B8="","",IF($D8<>"",$D8,IFERROR(INDEX(PecPreco,MATCH($B8,PecCod,0)),0))) -> 0 | G8: =IF(OR($B8="",$C8=""),"",$C8*$F8) -> 0 | H8: =IF(OR($B8="",$C8=""),"",$C8*IFERROR(INDEX(PecCusto,MATCH($B8,PecCod,0)),0)) -> 0 | I8: =IF($A8="","",IFERROR(INDEX(OSStatus,MATCH($A8,OSNum,0)),"OS inexistente")) -> 0 | J8: =IF($A8="","",IF($I8="OS inexistente","OS inexistente",IF($E8="Peça não cadastrada","Peça não cadastrada","OK"))) -> 0
E9: =IF($B9="","",IFERROR(INDEX(PecDesc,MATCH($B9,PecCod,0)),"Peça não cadastrada")) -> 0 | F9: =IF($B9="","",IF($D9<>"",$D9,IFERROR(INDEX(PecPreco,MATCH($B9,PecCod,0)),0))) -> 0 | G9: =IF(OR($B9="",$C9=""),"",$C9*$F9) -> 0 | H9: =IF(OR($B9="",$C9=""),"",$C9*IFERROR(INDEX(PecCusto,MATCH($B9,PecCod,0)),0)) -> 0 | I9: =IF($A9="","",IFERROR(INDEX(OSStatus,MATCH($A9,OSNum,0)),"OS inexistente")) -> 0 | J9: =IF($A9="","",IF($I9="OS inexistente","OS inexistente",IF($E9="Peça não cadastrada","Peça não cadastrada","OK"))) -> 0
E10: =IF($B10="","",IFERROR(INDEX(PecDesc,MATCH($B10,PecCod,0)),"Peça não cadastrada")) -> 0 | F10: =IF($B10="","",IF($D10<>"",$D10,IFERROR(INDEX(PecPreco,MATCH($B10,PecCod,0)),0))) -> 0 | G10: =IF(OR($B10="",$C10=""),"",$C10*$F10) -> 0 | H10: =IF(OR($B10="",$C10=""),"",$C10*IFERROR(INDEX(PecCusto,MATCH($B10,PecCod,0)),0)) -> 0 | I10: =IF($A10="","",IFERROR(INDEX(OSStatus,MATCH($A10,OSNum,0)),"OS inexistente")) -> 0 | J10: =IF($A10="","",IF($I10="OS inexistente","OS inexistente",IF($E10="Peça não cadastrada","Peça não cadastrada","OK"))) -> 0
E11: =IF($B11="","",IFERROR(INDEX(PecDesc,MATCH($B11,PecCod,0)),"Peça não cadastrada")) -> 0 | F11: =IF($B11="","",IF($D11<>"",$D11,IFERROR(INDEX(PecPreco,MATCH($B11,PecCod,0)),0))) -> 0 | G11: =IF(OR($B11="",$C11=""),"",$C11*$F11) -> 0 | H11: =IF(OR($B11="",$C11=""),"",$C11*IFERROR(INDEX(PecCusto,MATCH($B11,PecCod,0)),0)) -> 0 | I11: =IF($A11="","",IFERROR(INDEX(OSStatus,MATCH($A11,OSNum,0)),"OS inexistente")) -> 0 | J11: =IF($A11="","",IF($I11="OS inexistente","OS inexistente",IF($E11="Peça não cadastrada","Peça não cadastrada","OK"))) -> 0
E12: =IF($B12="","",IFERROR(INDEX(PecDesc,MATCH($B12,PecCod,0)),"Peça não cadastrada")) -> 0 | F12: =IF($B12="","",IF($D12<>"",$D12,IFERROR(INDEX(PecPreco,MATCH($B12,PecCod,0)),0))) -> 0 | G12: =IF(OR($B12="",$C12=""),"",$C12*$F12) -> 0 | H12: =IF(OR($B12="",$C12=""),"",$C12*IFERROR(INDEX(PecCusto,MATCH($B12,PecCod,0)),0)) -> 0 | I12: =IF($A12="","",IFERROR(INDEX(OSStatus,MATCH($A12,OSNum,0)),"OS inexistente")) -> 0 | J12: =IF($A12="","",IF($I12="OS inexistente","OS inexistente",IF($E12="Peça não cadastrada","Peça não cadastrada","OK"))) -> 0
E13: =IF($B13="","",IFERROR(INDEX(PecDesc,MATCH($B13,PecCod,0)),"Peça não cadastrada")) -> 0 | F13: =IF($B13="","",IF($D13<>"",$D13,IFERROR(INDEX(PecPreco,MATCH($B13,PecCod,0)),0))) -> 0 | G13: =IF(OR($B13="",$C13=""),"",$C13*$F13) -> 0 | H13: =IF(OR($B13="",$C13=""),"",$C13*IFERROR(INDEX(PecCusto,MATCH($B13,PecCod,0)),0)) -> 0 | I13: =IF($A13="","",IFERROR(INDEX(OSStatus,MATCH($A13,OSNum,0)),"OS inexistente")) -> 0 | J13: =IF($A13="","",IF($I13="OS inexistente","OS inexistente",IF($E13="Peça não cadastrada","Peça não cadastrada","OK"))) -> 0
E14: =IF($B14="","",IFERROR(INDEX(PecDesc,MATCH($B14,PecCod,0)),"Peça não cadastrada")) -> 0 | F14: =IF($B14="","",IF($D14<>"",$D14,IFERROR(INDEX(PecPreco,MATCH($B14,PecCod,0)),0))) -> 0 | G14: =IF(OR($B14="",$C14=""),"",$C14*$F14) -> 0 | H14: =IF(OR($B14="",$C14=""),"",$C14*IFERROR(INDEX(PecCusto,MATCH($B14,PecCod,0)),0)) -> 0 | I14: =IF($A14="","",IFERROR(INDEX(OSStatus,MATCH($A14,OSNum,0)),"OS inexistente")) -> 0 | J14: =IF($A14="","",IF($I14="OS inexistente","OS inexistente",IF($E14="Peça não cadastrada","Peça não cadastrada","OK"))) -> 0
E15: =IF($B15="","",IFERROR(INDEX(PecDesc,MATCH($B15,PecCod,0)),"Peça não cadastrada")) -> 0 | F15: =IF($B15="","",IF($D15<>"",$D15,IFERROR(INDEX(PecPreco,MATCH($B15,PecCod,0)),0))) -> 0 | G15: =IF(OR($B15="",$C15=""),"",$C15*$F15) -> 0 | H15: =IF(OR($B15="",$C15=""),"",$C15*IFERROR(INDEX(PecCusto,MATCH($B15,PecCod,0)),0)) -> 0 | I15: =IF($A15="","",IFERROR(INDEX(OSStatus,MATCH($A15,OSNum,0)),"OS inexistente")) -> 0 | J15: =IF($A15="","",IF($I15="OS inexistente","OS inexistente",IF($E15="Peça não cadastrada","Peça não cadastrada","OK"))) -> 0
E16: =IF($B16="","",IFERROR(INDEX(PecDesc,MATCH($B16,PecCod,0)),"Peça não cadastrada")) -> 0 | F16: =IF($B16="","",IF($D16<>"",$D16,IFERROR(INDEX(PecPreco,MATCH($B16,PecCod,0)),0))) -> 0 | G16: =IF(OR($B16="",$C16=""),"",$C16*$F16) -> 0 | H16: =IF(OR($B16="",$C16=""),"",$C16*IFERROR(INDEX(PecCusto,MATCH($B16,PecCod,0)),0)) -> 0 | I16: =IF($A16="","",IFERROR(INDEX(OSStatus,MATCH($A16,OSNum,0)),"OS inexistente")) -> 0 | J16: =IF($A16="","",IF($I16="OS inexistente","OS inexistente",IF($E16="Peça não cadastrada","Peça não cadastrada","OK"))) -> 0
... E3004: =IF($B3004="","",IFERROR(INDEX(PecDesc,MATCH($B3004,PecCod,0)),"Peça não cadastrada")) -> 0 | F3004: =IF($B3004="","",IF($D3004<>"",$D3004,IFERROR(INDEX(PecPreco,MATCH($B3004,PecCod,0)),0))) -> 0 | G3004: =IF(OR($B3004="",$C3004=""),"",$C3004*$F3004) -> 0 | H3004: =IF(OR($B3004="",$C3004=""),"",$C3004*IFERROR(INDEX(PecCusto,MATCH($B3004,PecCod,0)),0)) -> 0 | I3004: =IF($A3004="","",IFERROR(INDEX(OSStatus,MATCH($A3004,OSNum,0)),"OS inexistente")) -> 0 | J3004: =IF($A3004="","",IF($I3004="OS inexistente","OS inexistente",IF($E3004="Peça não cadastrada","Peça não cadastrada","OK"))) -> 0

Sheet Histórico
A1: Histórico do veículo
A2: Escolha a placa e veja todas as OS dele (até 25).
B4: Placa: | D4: Cliente: | E4: =IFERROR(INDEX(VeicCli,MATCH($C$4,VeicPlaca,0)),"") -> 0 | H4: OS no total: | I4: =COUNTIF(OS!$C$5:$C$1004,$C$4) -> 0
D5: Modelo: | E5: =IFERROR(INDEX(VeicModelo,MATCH($C$4,VeicPlaca,0)),"") -> 0 | H5: Total gasto: | I5: =SUMIFS(OS!$R$5:$R$1004,OS!$C$5:$C$1004,$C$4,OS!$I$5:$I$1004,"<>Cancelada",OS!$I$5:$I$1004,"<>Orçamento") -> 0
A7: # | B7: Nº OS | C7: Data | D7: Km | E7: Status | F7: Serviço | G7: Mecânico | H7: Total (R$)
A8: 1 | B8: =IFERROR(INDEX(OS!$A$5:$A$1004,MATCH($A8,OS!$AA$5:$AA$1004,0)),"") -> 0 | C8: =IFERROR(INDEX(OS!$B$5:$B$1004,MATCH($A8,OS!$AA$5:$AA$1004,0)),"") -> 0 | D8: =IFERROR(INDEX(OS!$F$5:$F$1004,MATCH($A8,OS!$AA$5:$AA$1004,0)),"") -> 0 | E8: =IFERROR(INDEX(OS!$I$5:$I$1004,MATCH($A8,OS!$AA$5:$AA$1004,0))&"","") -> 0 | F8: =IFERROR(INDEX(OS!$G$5:$G$1004,MATCH($A8,OS!$AA$5:$AA$1004,0))&"","") -> 0 | G8: =IFERROR(INDEX(OS!$H$5:$H$1004,MATCH($A8,OS!$AA$5:$AA$1004,0))&"","") -> 0 | H8: =IFERROR(INDEX(OS!$R$5:$R$1004,MATCH($A8,OS!$AA$5:$AA$1004,0)),"") -> 0
A9: 2 | B9: =IFERROR(INDEX(OS!$A$5:$A$1004,MATCH($A9,OS!$AA$5:$AA$1004,0)),"") -> 0 | C9: =IFERROR(INDEX(OS!$B$5:$B$1004,MATCH($A9,OS!$AA$5:$AA$1004,0)),"") -> 0 | D9: =IFERROR(INDEX(OS!$F$5:$F$1004,MATCH($A9,OS!$AA$5:$AA$1004,0)),"") -> 0 | E9: =IFERROR(INDEX(OS!$I$5:$I$1004,MATCH($A9,OS!$AA$5:$AA$1004,0))&"","") -> 0 | F9: =IFERROR(INDEX(OS!$G$5:$G$1004,MATCH($A9,OS!$AA$5:$AA$1004,0))&"","") -> 0 | G9: =IFERROR(INDEX(OS!$H$5:$H$1004,MATCH($A9,OS!$AA$5:$AA$1004,0))&"","") -> 0 | H9: =IFERROR(INDEX(OS!$R$5:$R$1004,MATCH($A9,OS!$AA$5:$AA$1004,0)),"") -> 0
A10: 3 | B10: =IFERROR(INDEX(OS!$A$5:$A$1004,MATCH($A10,OS!$AA$5:$AA$1004,0)),"") -> 0 | C10: =IFERROR(INDEX(OS!$B$5:$B$1004,MATCH($A10,OS!$AA$5:$AA$1004,0)),"") -> 0 | D10: =IFERROR(INDEX(OS!$F$5:$F$1004,MATCH($A10,OS!$AA$5:$AA$1004,0)),"") -> 0 | E10: =IFERROR(INDEX(OS!$I$5:$I$1004,MATCH($A10,OS!$AA$5:$AA$1004,0))&"","") -> 0 | F10: =IFERROR(INDEX(OS!$G$5:$G$1004,MATCH($A10,OS!$AA$5:$AA$1004,0))&"","") -> 0 | G10: =IFERROR(INDEX(OS!$H$5:$H$1004,MATCH($A10,OS!$AA$5:$AA$1004,0))&"","") -> 0 | H10: =IFERROR(INDEX(OS!$R$5:$R$1004,MATCH($A10,OS!$AA$5:$AA$1004,0)),"") -> 0
A11: 4 | B11: =IFERROR(INDEX(OS!$A$5:$A$1004,MATCH($A11,OS!$AA$5:$AA$1004,0)),"") -> 0 | C11: =IFERROR(INDEX(OS!$B$5:$B$1004,MATCH($A11,OS!$AA$5:$AA$1004,0)),"") -> 0 | D11: =IFERROR(INDEX(OS!$F$5:$F$1004,MATCH($A11,OS!$AA$5:$AA$1004,0)),"") -> 0 | E11: =IFERROR(INDEX(OS!$I$5:$I$1004,MATCH($A11,OS!$AA$5:$AA$1004,0))&"","") -> 0 | F11: =IFERROR(INDEX(OS!$G$5:$G$1004,MATCH($A11,OS!$AA$5:$AA$1004,0))&"","") -> 0 | G11: =IFERROR(INDEX(OS!$H$5:$H$1004,MATCH($A11,OS!$AA$5:$AA$1004,0))&"","") -> 0 | H11: =IFERROR(INDEX(OS!$R$5:$R$1004,MATCH($A11,OS!$AA$5:$AA$1004,0)),"") -> 0
A12: 5 | B12: =IFERROR(INDEX(OS!$A$5:$A$1004,MATCH($A12,OS!$AA$5:$AA$1004,0)),"") -> 0 | C12: =IFERROR(INDEX(OS!$B$5:$B$1004,MATCH($A12,OS!$AA$5:$AA$1004,0)),"") -> 0 | D12: =IFERROR(INDEX(OS!$F$5:$F$1004,MATCH($A12,OS!$AA$5:$AA$1004,0)),"") -> 0 | E12: =IFERROR(INDEX(OS!$I$5:$I$1004,MATCH($A12,OS!$AA$5:$AA$1004,0))&"","") -> 0 | F12: =IFERROR(INDEX(OS!$G$5:$G$1004,MATCH($A12,OS!$AA$5:$AA$1004,0))&"","") -> 0 | G12: =IFERROR(INDEX(OS!$H$5:$H$1004,MATCH($A12,OS!$AA$5:$AA$1004,0))&"","") -> 0 | H12: =IFERROR(INDEX(OS!$R$5:$R$1004,MATCH($A12,OS!$AA$5:$AA$1004,0)),"") -> 0
A13: 6 | B13: =IFERROR(INDEX(OS!$A$5:$A$1004,MATCH($A13,OS!$AA$5:$AA$1004,0)),"") -> 0 | C13: =IFERROR(INDEX(OS!$B$5:$B$1004,MATCH($A13,OS!$AA$5:$AA$1004,0)),"") -> 0 | D13: =IFERROR(INDEX(OS!$F$5:$F$1004,MATCH($A13,OS!$AA$5:$AA$1004,0)),"") -> 0 | E13: =IFERROR(INDEX(OS!$I$5:$I$1004,MATCH($A13,OS!$AA$5:$AA$1004,0))&"","") -> 0 | F13: =IFERROR(INDEX(OS!$G$5:$G$1004,MATCH($A13,OS!$AA$5:$AA$1004,0))&"","") -> 0 | G13: =IFERROR(INDEX(OS!$H$5:$H$1004,MATCH($A13,OS!$AA$5:$AA$1004,0))&"","") -> 0 | H13: =IFERROR(INDEX(OS!$R$5:$R$1004,MATCH($A13,OS!$AA$5:$AA$1004,0)),"") -> 0
A14: 7 | B14: =IFERROR(INDEX(OS!$A$5:$A$1004,MATCH($A14,OS!$AA$5:$AA$1004,0)),"") -> 0 | C14: =IFERROR(INDEX(OS!$B$5:$B$1004,MATCH($A14,OS!$AA$5:$AA$1004,0)),"") -> 0 | D14: =IFERROR(INDEX(OS!$F$5:$F$1004,MATCH($A14,OS!$AA$5:$AA$1004,0)),"") -> 0 | E14: =IFERROR(INDEX(OS!$I$5:$I$1004,MATCH($A14,OS!$AA$5:$AA$1004,0))&"","") -> 0 | F14: =IFERROR(INDEX(OS!$G$5:$G$1004,MATCH($A14,OS!$AA$5:$AA$1004,0))&"","") -> 0 | G14: =IFERROR(INDEX(OS!$H$5:$H$1004,MATCH($A14,OS!$AA$5:$AA$1004,0))&"","") -> 0 | H14: =IFERROR(INDEX(OS!$R$5:$R$1004,MATCH($A14,OS!$AA$5:$AA$1004,0)),"") -> 0
A15: 8 | B15: =IFERROR(INDEX(OS!$A$5:$A$1004,MATCH($A15,OS!$AA$5:$AA$1004,0)),"") -> 0 | C15: =IFERROR(INDEX(OS!$B$5:$B$1004,MATCH($A15,OS!$AA$5:$AA$1004,0)),"") -> 0 | D15: =IFERROR(INDEX(OS!$F$5:$F$1004,MATCH($A15,OS!$AA$5:$AA$1004,0)),"") -> 0 | E15: =IFERROR(INDEX(OS!$I$5:$I$1004,MATCH($A15,OS!$AA$5:$AA$1004,0))&"","") -> 0 | F15: =IFERROR(INDEX(OS!$G$5:$G$1004,MATCH($A15,OS!$AA$5:$AA$1004,0))&"","") -> 0 | G15: =IFERROR(INDEX(OS!$H$5:$H$1004,MATCH($A15,OS!$AA$5:$AA$1004,0))&"","") -> 0 | H15: =IFERROR(INDEX(OS!$R$5:$R$1004,MATCH($A15,OS!$AA$5:$AA$1004,0)),"") -> 0
A16: 9 | B16: =IFERROR(INDEX(OS!$A$5:$A$1004,MATCH($A16,OS!$AA$5:$AA$1004,0)),"") -> 0 | C16: =IFERROR(INDEX(OS!$B$5:$B$1004,MATCH($A16,OS!$AA$5:$AA$1004,0)),"") -> 0 | D16: =IFERROR(INDEX(OS!$F$5:$F$1004,MATCH($A16,OS!$AA$5:$AA$1004,0)),"") -> 0 | E16: =IFERROR(INDEX(OS!$I$5:$I$1004,MATCH($A16,OS!$AA$5:$AA$1004,0))&"","") -> 0 | F16: =IFERROR(INDEX(OS!$G$5:$G$1004,MATCH($A16,OS!$AA$5:$AA$1004,0))&"","") -> 0 | G16: =IFERROR(INDEX(OS!$H$5:$H$1004,MATCH($A16,OS!$AA$5:$AA$1004,0))&"","") -> 0 | H16: =IFERROR(INDEX(OS!$R$5:$R$1004,MATCH($A16,OS!$AA$5:$AA$1004,0)),"") -> 0
A17: 10 | B17: =IFERROR(INDEX(OS!$A$5:$A$1004,MATCH($A17,OS!$AA$5:$AA$1004,0)),"") -> 0 | C17: =IFERROR(INDEX(OS!$B$5:$B$1004,MATCH($A17,OS!$AA$5:$AA$1004,0)),"") -> 0 | D17: =IFERROR(INDEX(OS!$F$5:$F$1004,MATCH($A17,OS!$AA$5:$AA$1004,0)),"") -> 0 | E17: =IFERROR(INDEX(OS!$I$5:$I$1004,MATCH($A17,OS!$AA$5:$AA$1004,0))&"","") -> 0 | F17: =IFERROR(INDEX(OS!$G$5:$G$1004,MATCH($A17,OS!$AA$5:$AA$1004,0))&"","") -> 0 | G17: =IFERROR(INDEX(OS!$H$5:$H$1004,MATCH($A17,OS!$AA$5:$AA$1004,0))&"","") -> 0 | H17: =IFERROR(INDEX(OS!$R$5:$R$1004,MATCH($A17,OS!$AA$5:$AA$1004,0)),"") -> 0
A18: 11 | B18: =IFERROR(INDEX(OS!$A$5:$A$1004,MATCH($A18,OS!$AA$5:$AA$1004,0)),"") -> 0 | C18: =IFERROR(INDEX(OS!$B$5:$B$1004,MATCH($A18,OS!$AA$5:$AA$1004,0)),"") -> 0 | D18: =IFERROR(INDEX(OS!$F$5:$F$1004,MATCH($A18,OS!$AA$5:$AA$1004,0)),"") -> 0 | E18: =IFERROR(INDEX(OS!$I$5:$I$1004,MATCH($A18,OS!$AA$5:$AA$1004,0))&"","") -> 0 | F18: =IFERROR(INDEX(OS!$G$5:$G$1004,MATCH($A18,OS!$AA$5:$AA$1004,0))&"","") -> 0 | G18: =IFERROR(INDEX(OS!$H$5:$H$1004,MATCH($A18,OS!$AA$5:$AA$1004,0))&"","") -> 0 | H18: =IFERROR(INDEX(OS!$R$5:$R$1004,MATCH($A18,OS!$AA$5:$AA$1004,0)),"") -> 0
A19: 12 | B19: =IFERROR(INDEX(OS!$A$5:$A$1004,MATCH($A19,OS!$AA$5:$AA$1004,0)),"") -> 0 | C19: =IFERROR(INDEX(OS!$B$5:$B$1004,MATCH($A19,OS!$AA$5:$AA$1004,0)),"") -> 0 | D19: =IFERROR(INDEX(OS!$F$5:$F$1004,MATCH($A19,OS!$AA$5:$AA$1004,0)),"") -> 0 | E19: =IFERROR(INDEX(OS!$I$5:$I$1004,MATCH($A19,OS!$AA$5:$AA$1004,0))&"","") -> 0 | F19: =IFERROR(INDEX(OS!$G$5:$G$1004,MATCH($A19,OS!$AA$5:$AA$1004,0))&"","") -> 0 | G19: =IFERROR(INDEX(OS!$H$5:$H$1004,MATCH($A19,OS!$AA$5:$AA$1004,0))&"","") -> 0 | H19: =IFERROR(INDEX(OS!$R$5:$R$1004,MATCH($A19,OS!$AA$5:$AA$1004,0)),"") -> 0
... A32: 25 | B32: =IFERROR(INDEX(OS!$A$5:$A$1004,MATCH($A32,OS!$AA$5:$AA$1004,0)),"") -> 0 | C32: =IFERROR(INDEX(OS!$B$5:$B$1004,MATCH($A32,OS!$AA$5:$AA$1004,0)),"") -> 0 | D32: =IFERROR(INDEX(OS!$F$5:$F$1004,MATCH($A32,OS!$AA$5:$AA$1004,0)),"") -> 0 | E32: =IFERROR(INDEX(OS!$I$5:$I$1004,MATCH($A32,OS!$AA$5:$AA$1004,0))&"","") -> 0 | F32: =IFERROR(INDEX(OS!$G$5:$G$1004,MATCH($A32,OS!$AA$5:$AA$1004,0))&"","") -> 0 | G32: =IFERROR(INDEX(OS!$H$5:$H$1004,MATCH($A32,OS!$AA$5:$AA$1004,0))&"","") -> 0 | H32: =IFERROR(INDEX(OS!$R$5:$R$1004,MATCH($A32,OS!$AA$5:$AA$1004,0)),"") -> 0

Sheet Dashboard
A1: Dashboard da oficina
A2: Mês de referência = mês da data de hoje.
A4: FATURAMENTO DO MÊS | C4: OS ENTREGUES NO MÊS | E4: TICKET MÉDIO | G4: LUCRO BRUTO DO MÊS | I4: MARGEM DO MÊS
A5: =SUMIFS(OS!$R$5:$R$1004,OS!$Z$5:$Z$1004,DATE(YEAR(Hoje),MONTH(Hoje),1)) -> 0 | C5: =COUNTIFS(OS!$Z$5:$Z$1004,DATE(YEAR(Hoje),MONTH(Hoje),1)) -> 0 | E5: =IFERROR(A5/C5,0) -> 0 | G5: =SUMIFS(OS!$U$5:$U$1004,OS!$Z$5:$Z$1004,DATE(YEAR(Hoje),MONTH(Hoje),1)) -> 0 | I5: =IFERROR(G5/A5,0) -> 0
A7: OS EM ANDAMENTO | C7: AGUARDANDO PEÇA | E7: A RECEBER | G7: OS ATRASADAS | I7: ORÇAMENTOS PENDENTES (R$)
A8: =COUNTIF(OS!$I$5:$I$1004,"Aprovado")+COUNTIF(OS!$I$5:$I$1004,"Em execução")+COUNTIF(OS!$I$5:$I$1004,"Aguardando peça") -> 0 | C8: =COUNTIF(OS!$I$5:$I$1004,"Aguardando peça") -> 0 | E8: =SUM(OS!$W$5:$W$1004) -> 0 | G8: =COUNTIF(OS!$Y$5:$Y$1004,"ATRASADA") -> 0 | I8: =SUMIFS(OS!$R$5:$R$1004,OS!$I$5:$I$1004,"Orçamento") -> 0
A10: PEÇAS EM RUPTURA | C10: PEÇAS A REPOR | E10: ESTOQUE DE PEÇAS (custo) | G10: CLIENTES | I10: VEÍCULOS
A11: =COUNTIF(Peças!$K$5:$K$504,"RUPTURA") -> 0 | C11: =COUNTIF(Peças!$K$5:$K$504,"REPOR") -> 0 | E11: =SUMPRODUCT(Peças!$J$5:$J$504,Peças!$C$5:$C$504) -> 0 | G11: =SUMPRODUCT(--(Clientes!$A$5:$A$304<>"")) -> 0 | I11: =SUMPRODUCT(--(VeicPlaca<>"")) -> 0
A13: Faturamento por mês (ano da data de hoje) | F13: Mecânicos no mês
A14: Mês | B14: Faturamento | C14: Lucro bruto | D14: OS entregues | F14: Mecânico | H14: OS entregues | I14: Mão de obra | J14: Comissão
A15: =DATE(YEAR(Hoje),1,1) -> 46023 | B15: =SUMIFS(OS!$R$5:$R$1004,OS!$Z$5:$Z$1004,A15) -> 0 | C15: =SUMIFS(OS!$U$5:$U$1004,OS!$Z$5:$Z$1004,A15) -> 0 | D15: =COUNTIFS(OS!$Z$5:$Z$1004,A15) -> 0 | F15: =IF(INDEX(Mecanicos,1)="","",INDEX(Mecanicos,1)) -> 0 | H15: =IF($F15="","",COUNTIFS(OS!$H$5:$H$1004,$F15,OS!$Z$5:$Z$1004,DATE(YEAR(Hoje),MONTH(Hoje),1))) -> 0 | I15: =IF($F15="","",SUMIFS(OS!$P$5:$P$1004,OS!$H$5:$H$1004,$F15,OS!$Z$5:$Z$1004,DATE(YEAR(Hoje),MONTH(Hoje),1))) -> 0 | J15: =IF($F15="","",SUMIFS(OS!$T$5:$T$1004,OS!$H$5:$H$1004,$F15,OS!$Z$5:$Z$1004,DATE(YEAR(Hoje),MONTH(Hoje),1))) -> 0
A16: =DATE(YEAR(Hoje),2,1) -> 46054 | B16: =SUMIFS(OS!$R$5:$R$1004,OS!$Z$5:$Z$1004,A16) -> 0 | C16: =SUMIFS(OS!$U$5:$U$1004,OS!$Z$5:$Z$1004,A16) -> 0 | D16: =COUNTIFS(OS!$Z$5:$Z$1004,A16) -> 0 | F16: =IF(INDEX(Mecanicos,2)="","",INDEX(Mecanicos,2)) -> 0 | H16: =IF($F16="","",COUNTIFS(OS!$H$5:$H$1004,$F16,OS!$Z$5:$Z$1004,DATE(YEAR(Hoje),MONTH(Hoje),1))) -> 0 | I16: =IF($F16="","",SUMIFS(OS!$P$5:$P$1004,OS!$H$5:$H$1004,$F16,OS!$Z$5:$Z$1004,DATE(YEAR(Hoje),MONTH(Hoje),1))) -> 0 | J16: =IF($F16="","",SUMIFS(OS!$T$5:$T$1004,OS!$H$5:$H$1004,$F16,OS!$Z$5:$Z$1004,DATE(YEAR(Hoje),MONTH(Hoje),1))) -> 0
A17: =DATE(YEAR(Hoje),3,1) -> 46082 | B17: =SUMIFS(OS!$R$5:$R$1004,OS!$Z$5:$Z$1004,A17) -> 0 | C17: =SUMIFS(OS!$U$5:$U$1004,OS!$Z$5:$Z$1004,A17) -> 0 | D17: =COUNTIFS(OS!$Z$5:$Z$1004,A17) -> 0 | F17: =IF(INDEX(Mecanicos,3)="","",INDEX(Mecanicos,3)) -> 0 | H17: =IF($F17="","",COUNTIFS(OS!$H$5:$H$1004,$F17,OS!$Z$5:$Z$1004,DATE(YEAR(Hoje),MONTH(Hoje),1))) -> 0 | I17: =IF($F17="","",SUMIFS(OS!$P$5:$P$1004,OS!$H$5:$H$1004,$F17,OS!$Z$5:$Z$1004,DATE(YEAR(Hoje),MONTH(Hoje),1))) -> 0 | J17: =IF($F17="","",SUMIFS(OS!$T$5:$T$1004,OS!$H$5:$H$1004,$F17,OS!$Z$5:$Z$1004,DATE(YEAR(Hoje),MONTH(Hoje),1))) -> 0
A18: =DATE(YEAR(Hoje),4,1) -> 46113 | B18: =SUMIFS(OS!$R$5:$R$1004,OS!$Z$5:$Z$1004,A18) -> 0 | C18: =SUMIFS(OS!$U$5:$U$1004,OS!$Z$5:$Z$1004,A18) -> 0 | D18: =COUNTIFS(OS!$Z$5:$Z$1004,A18) -> 0 | F18: =IF(INDEX(Mecanicos,4)="","",INDEX(Mecanicos,4)) -> 0 | H18: =IF($F18="","",COUNTIFS(OS!$H$5:$H$1004,$F18,OS!$Z$5:$Z$1004,DATE(YEAR(Hoje),MONTH(Hoje),1))) -> 0 | I18: =IF($F18="","",SUMIFS(OS!$P$5:$P$1004,OS!$H$5:$H$1004,$F18,OS!$Z$5:$Z$1004,DATE(YEAR(Hoje),MONTH(Hoje),1))) -> 0 | J18: =IF($F18="","",SUMIFS(OS!$T$5:$T$1004,OS!$H$5:$H$1004,$F18,OS!$Z$5:$Z$1004,DATE(YEAR(Hoje),MONTH(Hoje),1))) -> 0
A19: =DATE(YEAR(Hoje),5,1) -> 46143 | B19: =SUMIFS(OS!$R$5:$R$1004,OS!$Z$5:$Z$1004,A19) -> 0 | C19: =SUMIFS(OS!$U$5:$U$1004,OS!$Z$5:$Z$1004,A19) -> 0 | D19: =COUNTIFS(OS!$Z$5:$Z$1004,A19) -> 0 | F19: =IF(INDEX(Mecanicos,5)="","",INDEX(Mecanicos,5)) -> 0 | H19: =IF($F19="","",COUNTIFS(OS!$H$5:$H$1004,$F19,OS!$Z$5:$Z$1004,DATE(YEAR(Hoje),MONTH(Hoje),1))) -> 0 | I19: =IF($F19="","",SUMIFS(OS!$P$5:$P$1004,OS!$H$5:$H$1004,$F19,OS!$Z$5:$Z$1004,DATE(YEAR(Hoje),MONTH(Hoje),1))) -> 0 | J19: =IF($F19="","",SUMIFS(OS!$T$5:$T$1004,OS!$H$5:$H$1004,$F19,OS!$Z$5:$Z$1004,DATE(YEAR(Hoje),MONTH(Hoje),1))) -> 0
A20: =DATE(YEAR(Hoje),6,1) -> 46174 | B20: =SUMIFS(OS!$R$5:$R$1004,OS!$Z$5:$Z$1004,A20) -> 0 | C20: =SUMIFS(OS!$U$5:$U$1004,OS!$Z$5:$Z$1004,A20) -> 0 | D20: =COUNTIFS(OS!$Z$5:$Z$1004,A20) -> 0 | F20: =IF(INDEX(Mecanicos,6)="","",INDEX(Mecanicos,6)) -> 0 | H20: =IF($F20="","",COUNTIFS(OS!$H$5:$H$1004,$F20,OS!$Z$5:$Z$1004,DATE(YEAR(Hoje),MONTH(Hoje),1))) -> 0 | I20: =IF($F20="","",SUMIFS(OS!$P$5:$P$1004,OS!$H$5:$H$1004,$F20,OS!$Z$5:$Z$1004,DATE(YEAR(Hoje),MONTH(Hoje),1))) -> 0 | J20: =IF($F20="","",SUMIFS(OS!$T$5:$T$1004,OS!$H$5:$H$1004,$F20,OS!$Z$5:$Z$1004,DATE(YEAR(Hoje),MONTH(Hoje),1))) -> 0
A21: =DATE(YEAR(Hoje),7,1) -> 46204 | B21: =SUMIFS(OS!$R$5:$R$1004,OS!$Z$5:$Z$1004,A21) -> 0 | C21: =SUMIFS(OS!$U$5:$U$1004,OS!$Z$5:$Z$1004,A21) -> 0 | D21: =COUNTIFS(OS!$Z$5:$Z$1004,A21) -> 0 | F21: =IF(INDEX(Mecanicos,7)="","",INDEX(Mecanicos,7)) -> 0 | H21: =IF($F21="","",COUNTIFS(OS!$H$5:$H$1004,$F21,OS!$Z$5:$Z$1004,DATE(YEAR(Hoje),MONTH(Hoje),1))) -> 0 | I21: =IF($F21="","",SUMIFS(OS!$P$5:$P$1004,OS!$H$5:$H$1004,$F21,OS!$Z$5:$Z$1004,DATE(YEAR(Hoje),MONTH(Hoje),1))) -> 0 | J21: =IF($F21="","",SUMIFS(OS!$T$5:$T$1004,OS!$H$5:$H$1004,$F21,OS!$Z$5:$Z$1004,DATE(YEAR(Hoje),MONTH(Hoje),1))) -> 0
A22: =DATE(YEAR(Hoje),8,1) -> 46235 | B22: =SUMIFS(OS!$R$5:$R$1004,OS!$Z$5:$Z$1004,A22) -> 0 | C22: =SUMIFS(OS!$U$5:$U$1004,OS!$Z$5:$Z$1004,A22) -> 0 | D22: =COUNTIFS(OS!$Z$5:$Z$1004,A22) -> 0 | F22: =IF(INDEX(Mecanicos,8)="","",INDEX(Mecanicos,8)) -> 0 | H22: =IF($F22="","",COUNTIFS(OS!$H$5:$H$1004,$F22,OS!$Z$5:$Z$1004,DATE(YEAR(Hoje),MONTH(Hoje),1))) -> 0 | I22: =IF($F22="","",SUMIFS(OS!$P$5:$P$1004,OS!$H$5:$H$1004,$F22,OS!$Z$5:$Z$1004,DATE(YEAR(Hoje),MONTH(Hoje),1))) -> 0 | J22: =IF($F22="","",SUMIFS(OS!$T$5:$T$1004,OS!$H$5:$H$1004,$F22,OS!$Z$5:$Z$1004,DATE(YEAR(Hoje),MONTH(Hoje),1))) -> 0
A23: =DATE(YEAR(Hoje),9,1) -> 46266 | B23: =SUMIFS(OS!$R$5:$R$1004,OS!$Z$5:$Z$1004,A23) -> 0 | C23: =SUMIFS(OS!$U$5:$U$1004,OS!$Z$5:$Z$1004,A23) -> 0 | D23: =COUNTIFS(OS!$Z$5:$Z$1004,A23) -> 0 | F23: =IF(INDEX(Mecanicos,9)="","",INDEX(Mecanicos,9)) -> 0 | H23: =IF($F23="","",COUNTIFS(OS!$H$5:$H$1004,$F23,OS!$Z$5:$Z$1004,DATE(YEAR(Hoje),MONTH(Hoje),1))) -> 0 | I23: =IF($F23="","",SUMIFS(OS!$P$5:$P$1004,OS!$H$5:$H$1004,$F23,OS!$Z$5:$Z$1004,DATE(YEAR(Hoje),MONTH(Hoje),1))) -> 0 | J23: =IF($F23="","",SUMIFS(OS!$T$5:$T$1004,OS!$H$5:$H$1004,$F23,OS!$Z$5:$Z$1004,DATE(YEAR(Hoje),MONTH(Hoje),1))) -> 0
A24: =DATE(YEAR(Hoje),10,1) -> 46296 | B24: =SUMIFS(OS!$R$5:$R$1004,OS!$Z$5:$Z$1004,A24) -> 0 | C24: =SUMIFS(OS!$U$5:$U$1004,OS!$Z$5:$Z$1004,A24) -> 0 | D24: =COUNTIFS(OS!$Z$5:$Z$1004,A24) -> 0 | F24: =IF(INDEX(Mecanicos,10)="","",INDEX(Mecanicos,10)) -> 0 | H24: =IF($F24="","",COUNTIFS(OS!$H$5:$H$1004,$F24,OS!$Z$5:$Z$1004,DATE(YEAR(Hoje),MONTH(Hoje),1))) -> 0 | I24: =IF($F24="","",SUMIFS(OS!$P$5:$P$1004,OS!$H$5:$H$1004,$F24,OS!$Z$5:$Z$1004,DATE(YEAR(Hoje),MONTH(Hoje),1))) -> 0 | J24: =IF($F24="","",SUMIFS(OS!$T$5:$T$1004,OS!$H$5:$H$1004,$F24,OS!$Z$5:$Z$1004,DATE(YEAR(Hoje),MONTH(Hoje),1))) -> 0
A25: =DATE(YEAR(Hoje),11,1) -> 46327 | B25: =SUMIFS(OS!$R$5:$R$1004,OS!$Z$5:$Z$1004,A25) -> 0 | C25: =SUMIFS(OS!$U$5:$U$1004,OS!$Z$5:$Z$1004,A25) -> 0 | D25: =COUNTIFS(OS!$Z$5:$Z$1004,A25) -> 0
A26: =DATE(YEAR(Hoje),12,1) -> 46357 | B26: =SUMIFS(OS!$R$5:$R$1004,OS!$Z$5:$Z$1004,A26) -> 0 | C26: =SUMIFS(OS!$U$5:$U$1004,OS!$Z$5:$Z$1004,A26) -> 0 | D26: =COUNTIFS(OS!$Z$5:$Z$1004,A26) -> 0
