Workbook
Name CatCusto: Config!$E$5:$E$24
Name Contrato: Config!$C$6
Name CustoCat: Custos!$C$5:$C$1504
Name CustoData: Custos!$A$5:$A$1504
Name CustoEtapa: Custos!$B$5:$B$1504
Name CustoMes: Custos!$I$5:$I$1504
Name CustoStatus: Custos!$G$5:$G$1504
Name CustoValor: Custos!$F$5:$F$1504
Name DataFim: Config!$C$8
Name DataIni: Config!$C$7
Name EtapaLista: Cronograma!$A$5:$A$24
Name Forn: Config!$G$5:$G$24
Name Hoje: Config!$C$10
Name MargemAlvo: Config!$C$9
Name OrcCat: Orçamento!$C$5:$C$304
Name OrcEtapa: Orçamento!$A$5:$A$304
Name OrcTotal: Orçamento!$G$5:$G$304

Sheet Início
A1: Controle de Obras
A2: Carvex XLS · Descubra o estouro de custo e prazo enquanto ainda dá tempo de agir
B4: ESTE É O ARQUIVO DE EXEMPLO: todos os dados são fictícios. Use-o para entender como a planilha funciona e comece a sua pela PLANILHA-LIMPA.xlsx.
B6: O que esta planilha faz
B7: Monte o orçamento por etapa, lance os custos reais e atualize o % físico de cada etapa. A planilha compara orçado x realizado, projeta o custo final da obra, calcula a margem prevista, mostra o cronograma em Gantt e controla as medições recebidas.
B9: Como começar (5 minutos)
B10: 1. Config | C10: Informe o nome da obra, o valor do contrato, as datas de início e fim previstas e a margem mínima que você aceita.
B11: 2. Cronograma | C11: Liste as etapas (até 20) com início e fim previstos. Atualize o % físico executado toda semana.
B12: 3. Orçamento | C12: Para cada etapa, liste os itens: categoria, unidade, quantidade e custo unitário. O total orçado é calculado.
B13: 4. Custos | C13: Lance cada nota, compra, folha ou serviço pago com data, etapa e categoria. Marque Pago ou A pagar.
B14: 5. Medições | C14: Registre as medições (faturamentos) à obra e os recebimentos. Veja tudo no Resumo.
B16: Mapa das abas (clique para ir)
B17: Config | C17: Dados da obra, contrato e parâmetros.
B18: Cronograma | C18: Etapas, datas, % físico e Gantt automático.
B19: Orçamento | C19: Itens orçados por etapa e categoria.
B20: Custos | C20: Custos reais lançados.
B21: Medições | C21: Faturamentos e recebimentos da obra.
B22: Resumo | C22: Margem prevista, custo projetado, orçado x realizado e fluxo.
B24: Legenda de cores
B25: Amarelo | C25: Célula que VOCÊ preenche.
B26: Cinza | C26: Cálculo automático. Não digite aqui.
B27: Verde escuro | C27: Cabeçalho de coluna.
B29: Atenção
B30: • O nome da etapa deve ser igual no Cronograma, Orçamento e Custos (use a lista suspensa).
B31: • Atualize o % físico com a realidade do canteiro: é ele que permite projetar o custo final (custo real / % físico).
B32: • Projeção de custo é uma estimativa. Revise com o engenheiro responsável antes de decidir.
B34: Carvex XLS · Controle de Obras (Orçado x Realizado) · versão 1.0 · Dúvidas: consulte o TUTORIAL.md e o MANUAL.md que acompanham o produto.

Sheet Config
A1: Dados da obra
A2: Preencha as células amarelas. | E2: EXEMPLO - dados fictícios
B4: Obra | C4: Reforma Comercial Exemplo | E4: Categorias de custo | G4: Fornecedores
B5: Cliente | C5: Cliente Exemplo | E5: Material | G5: Depósito de Materiais Exemplo
B6: Valor do contrato (R$) | C6: 480000 | E6: Mão de obra | G6: Concreteira Exemplo
B7: Início previsto | C7: 46146 | E7: Equipamentos | G7: Elétrica Exemplo
B8: Fim previsto | C8: 46374 | E8: Subempreitada | G8: Hidráulica Exemplo
B9: Margem mínima aceitável (%) | C9: 0.15 | E9: Projetos e taxas | G9: Equipe de Pedreiros A
B10: Data de hoje (referência) | C10: 46303 | E10: Outros | G10: Equipe de Acabamento B
G11: Locadora Exemplo
G12: Esquadrias Exemplo
G13: Tintas Exemplo
G14: Escritório de Projetos Exemplo

Sheet Cronograma
A1: Cronograma e Gantt
A2: Verde claro = previsto. Verde escuro = executado (% físico). Coluna destacada = semana atual. | AZ2: EXEMPLO - dados fictícios
A4: Etapa | B4: Início previsto | C4: Fim previsto | D4: % físico executado | E4: Início real | F4: Fim real | G4: Duração (dias) | H4: % do tempo decorrido | I4: Físico - tempo | J4: SITUAÇÃO | K4: Peso no orçamento | M4: =IF(DataIni="","",DataIni-WEEKDAY(DataIni,2)+1) -> 46146 | N4: =IF(M4="","",M4+7) -> 46153 | O4: =IF(N4="","",N4+7) -> 46160 | P4: =IF(O4="","",O4+7) -> 46167 | Q4: =IF(P4="","",P4+7) -> 46174 | R4: =IF(Q4="","",Q4+7) -> 46181 | S4: =IF(R4="","",R4+7) -> 46188 | T4: =IF(S4="","",S4+7) -> 46195 | U4: =IF(T4="","",T4+7) -> 46202 | ... AZ4: =IF(AY4="","",AY4+7) -> 46419
A5: Serviços preliminares | B5: 46146 | C5: 46164 | D5: 1 | E5: 46146 | F5: 46167 | G5: =IF(OR($B5="",$C5=""),"",$C5-$B5+1) -> 19 | H5: =IF($G5="","",MAX(0,MIN(1,(Hoje-$B5+1)/$G5))) -> 1 | I5: =IF($H5="","",N($D5)-$H5) -> 0 | J5: =IF($A5="","",IF(N($D5)>=1,"Concluída",IF(Hoje<$B5,"A iniciar",IF(N($D5)<$H5-0.1,"ATRASADA","Em dia")))) -> Concluída | K5: =IF($A5="","",IFERROR(SUMIFS(OrcTotal,OrcEtapa,$A5)/SUM(OrcTotal),0)) -> 0.045918363
A6: Fundação | B6: 46160 | C6: 46199 | D6: 1 | E6: 46162 | F6: 46206 | G6: =IF(OR($B6="",$C6=""),"",$C6-$B6+1) -> 40 | H6: =IF($G6="","",MAX(0,MIN(1,(Hoje-$B6+1)/$G6))) -> 1 | I6: =IF($H6="","",N($D6)-$H6) -> 0 | J6: =IF($A6="","",IF(N($D6)>=1,"Concluída",IF(Hoje<$B6,"A iniciar",IF(N($D6)<$H6-0.1,"ATRASADA","Em dia")))) -> Concluída | K6: =IF($A6="","",IFERROR(SUMIFS(OrcTotal,OrcEtapa,$A6)/SUM(OrcTotal),0)) -> 0.13265305
A7: Estrutura | B7: 46195 | C7: 46241 | D7: 1 | E7: 46202 | F7: 46248 | G7: =IF(OR($B7="",$C7=""),"",$C7-$B7+1) -> 47 | H7: =IF($G7="","",MAX(0,MIN(1,(Hoje-$B7+1)/$G7))) -> 1 | I7: =IF($H7="","",N($D7)-$H7) -> 0 | J7: =IF($A7="","",IF(N($D7)>=1,"Concluída",IF(Hoje<$B7,"A iniciar",IF(N($D7)<$H7-0.1,"ATRASADA","Em dia")))) -> Concluída | K7: =IF($A7="","",IFERROR(SUMIFS(OrcTotal,OrcEtapa,$A7)/SUM(OrcTotal),0)) -> 0.19897957
A8: Alvenaria | B8: 46230 | C8: 46269 | D8: 1 | E8: 46237 | F8: 46276 | G8: =IF(OR($B8="",$C8=""),"",$C8-$B8+1) -> 40 | H8: =IF($G8="","",MAX(0,MIN(1,(Hoje-$B8+1)/$G8))) -> 1 | I8: =IF($H8="","",N($D8)-$H8) -> 0 | J8: =IF($A8="","",IF(N($D8)>=1,"Concluída",IF(Hoje<$B8,"A iniciar",IF(N($D8)<$H8-0.1,"ATRASADA","Em dia")))) -> Concluída | K8: =IF($A8="","",IFERROR(SUMIFS(OrcTotal,OrcEtapa,$A8)/SUM(OrcTotal),0)) -> 0.11734713
A9: Instalações elétricas | B9: 46258 | C9: 46290 | D9: 0.8 | E9: 46265 | G9: =IF(OR($B9="",$C9=""),"",$C9-$B9+1) -> 33 | H9: =IF($G9="","",MAX(0,MIN(1,(Hoje-$B9+1)/$G9))) -> 1 | I9: =IF($H9="","",N($D9)-$H9) -> -0.2 | J9: =IF($A9="","",IF(N($D9)>=1,"Concluída",IF(Hoje<$B9,"A iniciar",IF(N($D9)<$H9-0.1,"ATRASADA","Em dia")))) -> ATRASADA | K9: =IF($A9="","",IFERROR(SUMIFS(OrcTotal,OrcEtapa,$A9)/SUM(OrcTotal),0)) -> 0.079081523
A10: Instalações hidráulicas | B10: 46258 | C10: 46290 | D10: 1 | E10: 46265 | F10: 46293 | G10: =IF(OR($B10="",$C10=""),"",$C10-$B10+1) -> 33 | H10: =IF($G10="","",MAX(0,MIN(1,(Hoje-$B10+1)/$G10))) -> 1 | I10: =IF($H10="","",N($D10)-$H10) -> 0 | J10: =IF($A10="","",IF(N($D10)>=1,"Concluída",IF(Hoje<$B10,"A iniciar",IF(N($D10)<$H10-0.1,"ATRASADA","Em dia")))) -> Concluída | K10: =IF($A10="","",IFERROR(SUMIFS(OrcTotal,OrcEtapa,$A10)/SUM(OrcTotal),0)) -> 0.06632632
A11: Revestimentos | B11: 46279 | C11: 46325 | D11: 0.45 | E11: 46281 | G11: =IF(OR($B11="",$C11=""),"",$C11-$B11+1) -> 47 | H11: =IF($G11="","",MAX(0,MIN(1,(Hoje-$B11+1)/$G11))) -> 0.53191489 | I11: =IF($H11="","",N($D11)-$H11) -> -0.081914894 | J11: =IF($A11="","",IF(N($D11)>=1,"Concluída",IF(Hoje<$B11,"A iniciar",IF(N($D11)<$H11-0.1,"ATRASADA","Em dia")))) -> Em dia | K11: =IF($A11="","",IFERROR(SUMIFS(OrcTotal,OrcEtapa,$A11)/SUM(OrcTotal),0)) -> 0.13265305
A12: Esquadrias | B12: 46300 | C12: 46332 | D12: 0.1 | E12: 46301 | G12: =IF(OR($B12="",$C12=""),"",$C12-$B12+1) -> 33 | H12: =IF($G12="","",MAX(0,MIN(1,(Hoje-$B12+1)/$G12))) -> 0.12121212 | I12: =IF($H12="","",N($D12)-$H12) -> -0.021212121 | J12: =IF($A12="","",IF(N($D12)>=1,"Concluída",IF(Hoje<$B12,"A iniciar",IF(N($D12)<$H12-0.1,"ATRASADA","Em dia")))) -> Em dia | K12: =IF($A12="","",IFERROR(SUMIFS(OrcTotal,OrcEtapa,$A12)/SUM(OrcTotal),0)) -> 0.086734889
A13: Pintura | B13: 46328 | C13: 46353 | D13: 0 | G13: =IF(OR($B13="",$C13=""),"",$C13-$B13+1) -> 26 | H13: =IF($G13="","",MAX(0,MIN(1,(Hoje-$B13+1)/$G13))) -> 0 | I13: =IF($H13="","",N($D13)-$H13) -> 0 | J13: =IF($A13="","",IF(N($D13)>=1,"Concluída",IF(Hoje<$B13,"A iniciar",IF(N($D13)<$H13-0.1,"ATRASADA","Em dia")))) -> A iniciar | K13: =IF($A13="","",IFERROR(SUMIFS(OrcTotal,OrcEtapa,$A13)/SUM(OrcTotal),0)) -> 0.061224484
A14: Acabamentos e limpeza | B14: 46349 | C14: 46374 | D14: 0 | G14: =IF(OR($B14="",$C14=""),"",$C14-$B14+1) -> 26 | H14: =IF($G14="","",MAX(0,MIN(1,(Hoje-$B14+1)/$G14))) -> 0 | I14: =IF($H14="","",N($D14)-$H14) -> 0 | J14: =IF($A14="","",IF(N($D14)>=1,"Concluída",IF(Hoje<$B14,"A iniciar",IF(N($D14)<$H14-0.1,"ATRASADA","Em dia")))) -> A iniciar | K14: =IF($A14="","",IFERROR(SUMIFS(OrcTotal,OrcEtapa,$A14)/SUM(OrcTotal),0)) -> 0.079081625
G15: =IF(OR($B15="",$C15=""),"",$C15-$B15+1) | H15: =IF($G15="","",MAX(0,MIN(1,(Hoje-$B15+1)/$G15))) | I15: =IF($H15="","",N($D15)-$H15) | J15: =IF($A15="","",IF(N($D15)>=1,"Concluída",IF(Hoje<$B15,"A iniciar",IF(N($D15)<$H15-0.1,"ATRASADA","Em dia")))) | K15: =IF($A15="","",IFERROR(SUMIFS(OrcTotal,OrcEtapa,$A15)/SUM(OrcTotal),0))
G16: =IF(OR($B16="",$C16=""),"",$C16-$B16+1) | H16: =IF($G16="","",MAX(0,MIN(1,(Hoje-$B16+1)/$G16))) | I16: =IF($H16="","",N($D16)-$H16) | J16: =IF($A16="","",IF(N($D16)>=1,"Concluída",IF(Hoje<$B16,"A iniciar",IF(N($D16)<$H16-0.1,"ATRASADA","Em dia")))) | K16: =IF($A16="","",IFERROR(SUMIFS(OrcTotal,OrcEtapa,$A16)/SUM(OrcTotal),0))
G17: =IF(OR($B17="",$C17=""),"",$C17-$B17+1) | H17: =IF($G17="","",MAX(0,MIN(1,(Hoje-$B17+1)/$G17))) | I17: =IF($H17="","",N($D17)-$H17) | J17: =IF($A17="","",IF(N($D17)>=1,"Concluída",IF(Hoje<$B17,"A iniciar",IF(N($D17)<$H17-0.1,"ATRASADA","Em dia")))) | K17: =IF($A17="","",IFERROR(SUMIFS(OrcTotal,OrcEtapa,$A17)/SUM(OrcTotal),0))
G18: =IF(OR($B18="",$C18=""),"",$C18-$B18+1) | H18: =IF($G18="","",MAX(0,MIN(1,(Hoje-$B18+1)/$G18))) | I18: =IF($H18="","",N($D18)-$H18) | J18: =IF($A18="","",IF(N($D18)>=1,"Concluída",IF(Hoje<$B18,"A iniciar",IF(N($D18)<$H18-0.1,"ATRASADA","Em dia")))) | K18: =IF($A18="","",IFERROR(SUMIFS(OrcTotal,OrcEtapa,$A18)/SUM(OrcTotal),0))
G19: =IF(OR($B19="",$C19=""),"",$C19-$B19+1) | H19: =IF($G19="","",MAX(0,MIN(1,(Hoje-$B19+1)/$G19))) | I19: =IF($H19="","",N($D19)-$H19) | J19: =IF($A19="","",IF(N($D19)>=1,"Concluída",IF(Hoje<$B19,"A iniciar",IF(N($D19)<$H19-0.1,"ATRASADA","Em dia")))) | K19: =IF($A19="","",IFERROR(SUMIFS(OrcTotal,OrcEtapa,$A19)/SUM(OrcTotal),0))
G20: =IF(OR($B20="",$C20=""),"",$C20-$B20+1) | H20: =IF($G20="","",MAX(0,MIN(1,(Hoje-$B20+1)/$G20))) | I20: =IF($H20="","",N($D20)-$H20) | J20: =IF($A20="","",IF(N($D20)>=1,"Concluída",IF(Hoje<$B20,"A iniciar",IF(N($D20)<$H20-0.1,"ATRASADA","Em dia")))) | K20: =IF($A20="","",IFERROR(SUMIFS(OrcTotal,OrcEtapa,$A20)/SUM(OrcTotal),0))
G21: =IF(OR($B21="",$C21=""),"",$C21-$B21+1) | H21: =IF($G21="","",MAX(0,MIN(1,(Hoje-$B21+1)/$G21))) | I21: =IF($H21="","",N($D21)-$H21) | J21: =IF($A21="","",IF(N($D21)>=1,"Concluída",IF(Hoje<$B21,"A iniciar",IF(N($D21)<$H21-0.1,"ATRASADA","Em dia")))) | K21: =IF($A21="","",IFERROR(SUMIFS(OrcTotal,OrcEtapa,$A21)/SUM(OrcTotal),0))
G22: =IF(OR($B22="",$C22=""),"",$C22-$B22+1) | H22: =IF($G22="","",MAX(0,MIN(1,(Hoje-$B22+1)/$G22))) | I22: =IF($H22="","",N($D22)-$H22) | J22: =IF($A22="","",IF(N($D22)>=1,"Concluída",IF(Hoje<$B22,"A iniciar",IF(N($D22)<$H22-0.1,"ATRASADA","Em dia")))) | K22: =IF($A22="","",IFERROR(SUMIFS(OrcTotal,OrcEtapa,$A22)/SUM(OrcTotal),0))
G23: =IF(OR($B23="",$C23=""),"",$C23-$B23+1) | H23: =IF($G23="","",MAX(0,MIN(1,(Hoje-$B23+1)/$G23))) | I23: =IF($H23="","",N($D23)-$H23) | J23: =IF($A23="","",IF(N($D23)>=1,"Concluída",IF(Hoje<$B23,"A iniciar",IF(N($D23)<$H23-0.1,"ATRASADA","Em dia")))) | K23: =IF($A23="","",IFERROR(SUMIFS(OrcTotal,OrcEtapa,$A23)/SUM(OrcTotal),0))
G24: =IF(OR($B24="",$C24=""),"",$C24-$B24+1) | H24: =IF($G24="","",MAX(0,MIN(1,(Hoje-$B24+1)/$G24))) | I24: =IF($H24="","",N($D24)-$H24) | J24: =IF($A24="","",IF(N($D24)>=1,"Concluída",IF(Hoje<$B24,"A iniciar",IF(N($D24)<$H24-0.1,"ATRASADA","Em dia")))) | K24: =IF($A24="","",IFERROR(SUMIFS(OrcTotal,OrcEtapa,$A24)/SUM(OrcTotal),0))

Sheet Orçamento
A1: Orçamento por etapa
A2: Custo orçado (sem BDI). Total = quantidade x custo unitário. | H2: EXEMPLO - dados fictícios
F3: Total orçado: | G3: =SUM(G5:G304) -> 392000.04
A4: Etapa | B4: Item / serviço | C4: Categoria | D4: Un. | E4: Quantidade | F4: Custo unitário (R$) | G4: TOTAL ORÇADO (R$)
A5: Serviços preliminares | B5: Serviços preliminares - mão de obra | C5: Mão de obra | D5: vb | E5: 80 | F5: 101.25 | G5: =IF(OR($E5="",$F5=""),"",$E5*$F5) -> 8100
A6: Serviços preliminares | B6: Serviços preliminares - subempreitada | C6: Subempreitada | D6: m³ | E6: 80 | F6: 90 | G6: =IF(OR($E6="",$F6=""),"",$E6*$F6) -> 7200
A7: Serviços preliminares | B7: Serviços preliminares - material | C7: Material | D7: vb | E7: 24 | F7: 112.5 | G7: =IF(OR($E7="",$F7=""),"",$E7*$F7) -> 2700
A8: Fundação | B8: Fundação - mão de obra | C8: Mão de obra | D8: h | E8: 40 | F8: 585 | G8: =IF(OR($E8="",$F8=""),"",$E8*$F8) -> 23400
A9: Fundação | B9: Fundação - material | C9: Material | D9: m³ | E9: 200 | F9: 104 | G9: =IF(OR($E9="",$F9=""),"",$E9*$F9) -> 20800
A10: Fundação | B10: Fundação - equipamentos | C10: Equipamentos | D10: vb | E10: 80 | F10: 97.5 | G10: =IF(OR($E10="",$F10=""),"",$E10*$F10) -> 7800
A11: Estrutura | B11: Estrutura - subempreitada | C11: Subempreitada | D11: h | E11: 12 | F11: 2925 | G11: =IF(OR($E11="",$F11=""),"",$E11*$F11) -> 35100
A12: Estrutura | B12: Estrutura - equipamentos | C12: Equipamentos | D12: h | E12: 120 | F12: 260 | G12: =IF(OR($E12="",$F12=""),"",$E12*$F12) -> 31200
A13: Estrutura | B13: Estrutura - material | C13: Material | D13: un | E13: 200 | F13: 58.5 | G13: =IF(OR($E13="",$F13=""),"",$E13*$F13) -> 11700
A14: Alvenaria | B14: Alvenaria - mão de obra | C14: Mão de obra | D14: m² | E14: 200 | F14: 103.5 | G14: =IF(OR($E14="",$F14=""),"",$E14*$F14) -> 20700
A15: Alvenaria | B15: Alvenaria - material | C15: Material | D15: vb | E15: 24 | F15: 766.67 | G15: =IF(OR($E15="",$F15=""),"",$E15*$F15) -> 18400.08
A16: Alvenaria | B16: Alvenaria - subempreitada | C16: Subempreitada | D16: kg | E16: 12 | F16: 575 | G16: =IF(OR($E16="",$F16=""),"",$E16*$F16) -> 6900
... A34: Acabamentos e limpeza | B34: Acabamentos e limpeza - equipamentos | C34: Equipamentos | D34: m² | E34: 40 | F34: 116.25 | G34: =IF(OR($E34="",$F34=""),"",$E34*$F34) -> 4650
G35: =IF(OR($E35="",$F35=""),"",$E35*$F35)
G36: =IF(OR($E36="",$F36=""),"",$E36*$F36)
G37: =IF(OR($E37="",$F37=""),"",$E37*$F37)
G38: =IF(OR($E38="",$F38=""),"",$E38*$F38)
G39: =IF(OR($E39="",$F39=""),"",$E39*$F39)
G40: =IF(OR($E40="",$F40=""),"",$E40*$F40)
G41: =IF(OR($E41="",$F41=""),"",$E41*$F41)
G42: =IF(OR($E42="",$F42=""),"",$E42*$F42)
G43: =IF(OR($E43="",$F43=""),"",$E43*$F43)
G44: =IF(OR($E44="",$F44=""),"",$E44*$F44)
G45: =IF(OR($E45="",$F45=""),"",$E45*$F45)
G46: =IF(OR($E46="",$F46=""),"",$E46*$F46)
... G304: =IF(OR($E304="",$F304=""),"",$E304*$F304)

Sheet Custos
A1: Custos reais da obra
A2: Lance cada pagamento/nota. Marque 'A pagar' o que ainda não saiu do caixa. | J2: EXEMPLO - dados fictícios
A4: Data | B4: Etapa | C4: Categoria | D4: Fornecedor | E4: Descrição | F4: Valor (R$) | G4: Status | H4: Vencimento | I4: Mês | J4: Conferência
A5: 46148 | B5: Serviços preliminares | C5: Mão de obra | D5: Tintas Exemplo | E5: Pagamento serviços preliminares (1/5) | F5: 5079.24 | G5: Pago | H5: 46163 | I5: =IF($A5="","",DATE(YEAR($A5),MONTH($A5),1)) -> 46143 | J5: =IF($A5="","",IF(OR($B5="",$C5="",$F5="",$G5=""),"Preencher tudo",IF(COUNTIF(EtapaLista,$B5)=0,"Etapa inválida","OK"))) -> OK
A6: 46152 | B6: Serviços preliminares | C6: Subempreitada | D6: Depósito de Materiais Exemplo | E6: Pagamento serviços preliminares (2/5) | F6: 2942.93 | G6: Pago | H6: 46167 | I6: =IF($A6="","",DATE(YEAR($A6),MONTH($A6),1)) -> 46143 | J6: =IF($A6="","",IF(OR($B6="",$C6="",$F6="",$G6=""),"Preencher tudo",IF(COUNTIF(EtapaLista,$B6)=0,"Etapa inválida","OK"))) -> OK
A7: 46156 | B7: Serviços preliminares | C7: Material | D7: Esquadrias Exemplo | E7: Pagamento serviços preliminares (3/5) | F7: 2575.04 | G7: Pago | H7: 46171 | I7: =IF($A7="","",DATE(YEAR($A7),MONTH($A7),1)) -> 46143 | J7: =IF($A7="","",IF(OR($B7="",$C7="",$F7="",$G7=""),"Preencher tudo",IF(COUNTIF(EtapaLista,$B7)=0,"Etapa inválida","OK"))) -> OK
A8: 46162 | B8: Serviços preliminares | C8: Mão de obra | D8: Depósito de Materiais Exemplo | E8: Pagamento serviços preliminares (4/5) | F8: 4887.34 | G8: Pago | H8: 46177 | I8: =IF($A8="","",DATE(YEAR($A8),MONTH($A8),1)) -> 46143 | J8: =IF($A8="","",IF(OR($B8="",$C8="",$F8="",$G8=""),"Preencher tudo",IF(COUNTIF(EtapaLista,$B8)=0,"Etapa inválida","OK"))) -> OK
A9: 46167 | B9: Serviços preliminares | C9: Subempreitada | D9: Hidráulica Exemplo | E9: Pagamento serviços preliminares (5/5) | F9: 2875.45 | G9: Pago | H9: 46182 | I9: =IF($A9="","",DATE(YEAR($A9),MONTH($A9),1)) -> 46143 | J9: =IF($A9="","",IF(OR($B9="",$C9="",$F9="",$G9=""),"Preencher tudo",IF(COUNTIF(EtapaLista,$B9)=0,"Etapa inválida","OK"))) -> OK
A10: 46171 | B10: Fundação | C10: Mão de obra | D10: Tintas Exemplo | E10: Pagamento fundação (1/4) | F10: 10442.48 | G10: Pago | H10: 46186 | I10: =IF($A10="","",DATE(YEAR($A10),MONTH($A10),1)) -> 46143 | J10: =IF($A10="","",IF(OR($B10="",$C10="",$F10="",$G10=""),"Preencher tudo",IF(COUNTIF(EtapaLista,$B10)=0,"Etapa inválida","OK"))) -> OK
A11: 46184 | B11: Fundação | C11: Material | D11: Equipe de Pedreiros A | E11: Pagamento fundação (2/4) | F11: 11934.65 | G11: Pago | H11: 46199 | I11: =IF($A11="","",DATE(YEAR($A11),MONTH($A11),1)) -> 46174 | J11: =IF($A11="","",IF(OR($B11="",$C11="",$F11="",$G11=""),"Preencher tudo",IF(COUNTIF(EtapaLista,$B11)=0,"Etapa inválida","OK"))) -> OK
A12: 46194 | B12: Fundação | C12: Equipamentos | D12: Esquadrias Exemplo | E12: Pagamento fundação (3/4) | F12: 16127.59 | G12: Pago | H12: 46209 | I12: =IF($A12="","",DATE(YEAR($A12),MONTH($A12),1)) -> 46174 | J12: =IF($A12="","",IF(OR($B12="",$C12="",$F12="",$G12=""),"Preencher tudo",IF(COUNTIF(EtapaLista,$B12)=0,"Etapa inválida","OK"))) -> OK
A13: 46206 | B13: Fundação | C13: Mão de obra | D13: Depósito de Materiais Exemplo | E13: Pagamento fundação (4/4) | F13: 16615.28 | G13: Pago | H13: 46221 | I13: =IF($A13="","",DATE(YEAR($A13),MONTH($A13),1)) -> 46204 | J13: =IF($A13="","",IF(OR($B13="",$C13="",$F13="",$G13=""),"Preencher tudo",IF(COUNTIF(EtapaLista,$B13)=0,"Etapa inválida","OK"))) -> OK
A14: 46213 | B14: Estrutura | C14: Subempreitada | D14: Depósito de Materiais Exemplo | E14: Pagamento estrutura (1/4) | F14: 19781.5 | G14: Pago | H14: 46228 | I14: =IF($A14="","",DATE(YEAR($A14),MONTH($A14),1)) -> 46204 | J14: =IF($A14="","",IF(OR($B14="",$C14="",$F14="",$G14=""),"Preencher tudo",IF(COUNTIF(EtapaLista,$B14)=0,"Etapa inválida","OK"))) -> OK
A15: 46225 | B15: Estrutura | C15: Equipamentos | D15: Esquadrias Exemplo | E15: Pagamento estrutura (2/4) | F15: 22835.32 | G15: Pago | H15: 46240 | I15: =IF($A15="","",DATE(YEAR($A15),MONTH($A15),1)) -> 46204 | J15: =IF($A15="","",IF(OR($B15="",$C15="",$F15="",$G15=""),"Preencher tudo",IF(COUNTIF(EtapaLista,$B15)=0,"Etapa inválida","OK"))) -> OK
A16: 46234 | B16: Estrutura | C16: Material | D16: Elétrica Exemplo | E16: Pagamento estrutura (3/4) | F16: 22823.92 | G16: Pago | H16: 46249 | I16: =IF($A16="","",DATE(YEAR($A16),MONTH($A16),1)) -> 46204 | J16: =IF($A16="","",IF(OR($B16="",$C16="",$F16="",$G16=""),"Preencher tudo",IF(COUNTIF(EtapaLista,$B16)=0,"Etapa inválida","OK"))) -> OK
... A42: 46302 | B42: Esquadrias | C42: Mão de obra | D42: Tintas Exemplo | E42: Pagamento esquadrias (5/5) | F42: 907.77 | G42: A pagar | H42: 46317 | I42: =IF($A42="","",DATE(YEAR($A42),MONTH($A42),1)) -> 46296 | J42: =IF($A42="","",IF(OR($B42="",$C42="",$F42="",$G42=""),"Preencher tudo",IF(COUNTIF(EtapaLista,$B42)=0,"Etapa inválida","OK"))) -> OK
I43: =IF($A43="","",DATE(YEAR($A43),MONTH($A43),1)) | J43: =IF($A43="","",IF(OR($B43="",$C43="",$F43="",$G43=""),"Preencher tudo",IF(COUNTIF(EtapaLista,$B43)=0,"Etapa inválida","OK")))
I44: =IF($A44="","",DATE(YEAR($A44),MONTH($A44),1)) | J44: =IF($A44="","",IF(OR($B44="",$C44="",$F44="",$G44=""),"Preencher tudo",IF(COUNTIF(EtapaLista,$B44)=0,"Etapa inválida","OK")))
I45: =IF($A45="","",DATE(YEAR($A45),MONTH($A45),1)) | J45: =IF($A45="","",IF(OR($B45="",$C45="",$F45="",$G45=""),"Preencher tudo",IF(COUNTIF(EtapaLista,$B45)=0,"Etapa inválida","OK")))
I46: =IF($A46="","",DATE(YEAR($A46),MONTH($A46),1)) | J46: =IF($A46="","",IF(OR($B46="",$C46="",$F46="",$G46=""),"Preencher tudo",IF(COUNTIF(EtapaLista,$B46)=0,"Etapa inválida","OK")))
I47: =IF($A47="","",DATE(YEAR($A47),MONTH($A47),1)) | J47: =IF($A47="","",IF(OR($B47="",$C47="",$F47="",$G47=""),"Preencher tudo",IF(COUNTIF(EtapaLista,$B47)=0,"Etapa inválida","OK")))
I48: =IF($A48="","",DATE(YEAR($A48),MONTH($A48),1)) | J48: =IF($A48="","",IF(OR($B48="",$C48="",$F48="",$G48=""),"Preencher tudo",IF(COUNTIF(EtapaLista,$B48)=0,"Etapa inválida","OK")))
I49: =IF($A49="","",DATE(YEAR($A49),MONTH($A49),1)) | J49: =IF($A49="","",IF(OR($B49="",$C49="",$F49="",$G49=""),"Preencher tudo",IF(COUNTIF(EtapaLista,$B49)=0,"Etapa inválida","OK")))
I50: =IF($A50="","",DATE(YEAR($A50),MONTH($A50),1)) | J50: =IF($A50="","",IF(OR($B50="",$C50="",$F50="",$G50=""),"Preencher tudo",IF(COUNTIF(EtapaLista,$B50)=0,"Etapa inválida","OK")))
I51: =IF($A51="","",DATE(YEAR($A51),MONTH($A51),1)) | J51: =IF($A51="","",IF(OR($B51="",$C51="",$F51="",$G51=""),"Preencher tudo",IF(COUNTIF(EtapaLista,$B51)=0,"Etapa inválida","OK")))
I52: =IF($A52="","",DATE(YEAR($A52),MONTH($A52),1)) | J52: =IF($A52="","",IF(OR($B52="",$C52="",$F52="",$G52=""),"Preencher tudo",IF(COUNTIF(EtapaLista,$B52)=0,"Etapa inválida","OK")))
I53: =IF($A53="","",DATE(YEAR($A53),MONTH($A53),1)) | J53: =IF($A53="","",IF(OR($B53="",$C53="",$F53="",$G53=""),"Preencher tudo",IF(COUNTIF(EtapaLista,$B53)=0,"Etapa inválida","OK")))
I54: =IF($A54="","",DATE(YEAR($A54),MONTH($A54),1)) | J54: =IF($A54="","",IF(OR($B54="",$C54="",$F54="",$G54=""),"Preencher tudo",IF(COUNTIF(EtapaLista,$B54)=0,"Etapa inválida","OK")))
... I1504: =IF($A1504="","",DATE(YEAR($A1504),MONTH($A1504),1)) | J1504: =IF($A1504="","",IF(OR($B1504="",$C1504="",$F1504="",$G1504=""),"Preencher tudo",IF(COUNTIF(EtapaLista,$B1504)=0,"Etapa inválida","OK")))

Sheet Medições
A1: Medições e recebimentos
A2: Cada medição é um faturamento ao cliente. Preencha data e valor ao receber. | I2: EXEMPLO - dados fictícios
A4: Nº | B4: Data da medição | C4: Descrição | D4: Valor medido (R$) | E4: Vencimento | F4: Data do recebimento | G4: Valor recebido (R$) | H4: Saldo a receber | I4: Situação
A5: 1 | B5: 46171 | C5: Medição 1: serviços preliminares e início da fundação | D5: 48000 | E5: 46188 | F5: 46188 | G5: 48000 | H5: =IF($D5="","",MAX(0,$D5-N($G5))) -> 0 | I5: =IF($D5="","",IF($H5<=0.005,"Recebida",IF(AND($E5<>"",$E5<Hoje),"ATRASADA","A receber"))) -> Recebida
A6: 2 | B6: 46203 | C6: Medição 2: fundação concluída | D6: 72000 | E6: 46218 | F6: 46219 | G6: 72000 | H6: =IF($D6="","",MAX(0,$D6-N($G6))) -> 0 | I6: =IF($D6="","",IF($H6<=0.005,"Recebida",IF(AND($E6<>"",$E6<Hoje),"ATRASADA","A receber"))) -> Recebida
A7: 3 | B7: 46234 | C7: Medição 3: estrutura 70% | D7: 90000 | E7: 46248 | F7: 46248 | G7: 90000 | H7: =IF($D7="","",MAX(0,$D7-N($G7))) -> 0 | I7: =IF($D7="","",IF($H7<=0.005,"Recebida",IF(AND($E7<>"",$E7<Hoje),"ATRASADA","A receber"))) -> Recebida
A8: 4 | B8: 46265 | C8: Medição 4: estrutura concluída e alvenaria 40% | D8: 78000 | E8: 46280 | F8: 46283 | G8: 78000 | H8: =IF($D8="","",MAX(0,$D8-N($G8))) -> 0 | I8: =IF($D8="","",IF($H8<=0.005,"Recebida",IF(AND($E8<>"",$E8<Hoje),"ATRASADA","A receber"))) -> Recebida
A9: 5 | B9: 46295 | C9: Medição 5: alvenaria e instalações | D9: 82000 | E9: 46302 | H9: =IF($D9="","",MAX(0,$D9-N($G9))) -> 82000 | I9: =IF($D9="","",IF($H9<=0.005,"Recebida",IF(AND($E9<>"",$E9<Hoje),"ATRASADA","A receber"))) -> ATRASADA
A10: 6 | B10: 46325 | C10: Medição 6: revestimentos (prevista) | D10: 60000 | E10: 46339 | H10: =IF($D10="","",MAX(0,$D10-N($G10))) -> 60000 | I10: =IF($D10="","",IF($H10<=0.005,"Recebida",IF(AND($E10<>"",$E10<Hoje),"ATRASADA","A receber"))) -> A receber
H11: =IF($D11="","",MAX(0,$D11-N($G11))) | I11: =IF($D11="","",IF($H11<=0.005,"Recebida",IF(AND($E11<>"",$E11<Hoje),"ATRASADA","A receber")))
H12: =IF($D12="","",MAX(0,$D12-N($G12))) | I12: =IF($D12="","",IF($H12<=0.005,"Recebida",IF(AND($E12<>"",$E12<Hoje),"ATRASADA","A receber")))
H13: =IF($D13="","",MAX(0,$D13-N($G13))) | I13: =IF($D13="","",IF($H13<=0.005,"Recebida",IF(AND($E13<>"",$E13<Hoje),"ATRASADA","A receber")))
H14: =IF($D14="","",MAX(0,$D14-N($G14))) | I14: =IF($D14="","",IF($H14<=0.005,"Recebida",IF(AND($E14<>"",$E14<Hoje),"ATRASADA","A receber")))
H15: =IF($D15="","",MAX(0,$D15-N($G15))) | I15: =IF($D15="","",IF($H15<=0.005,"Recebida",IF(AND($E15<>"",$E15<Hoje),"ATRASADA","A receber")))
H16: =IF($D16="","",MAX(0,$D16-N($G16))) | I16: =IF($D16="","",IF($H16<=0.005,"Recebida",IF(AND($E16<>"",$E16<Hoje),"ATRASADA","A receber")))
H17: =IF($D17="","",MAX(0,$D17-N($G17))) | I17: =IF($D17="","",IF($H17<=0.005,"Recebida",IF(AND($E17<>"",$E17<Hoje),"ATRASADA","A receber")))
H18: =IF($D18="","",MAX(0,$D18-N($G18))) | I18: =IF($D18="","",IF($H18<=0.005,"Recebida",IF(AND($E18<>"",$E18<Hoje),"ATRASADA","A receber")))
H19: =IF($D19="","",MAX(0,$D19-N($G19))) | I19: =IF($D19="","",IF($H19<=0.005,"Recebida",IF(AND($E19<>"",$E19<Hoje),"ATRASADA","A receber")))
H20: =IF($D20="","",MAX(0,$D20-N($G20))) | I20: =IF($D20="","",IF($H20<=0.005,"Recebida",IF(AND($E20<>"",$E20<Hoje),"ATRASADA","A receber")))
H21: =IF($D21="","",MAX(0,$D21-N($G21))) | I21: =IF($D21="","",IF($H21<=0.005,"Recebida",IF(AND($E21<>"",$E21<Hoje),"ATRASADA","A receber")))
H22: =IF($D22="","",MAX(0,$D22-N($G22))) | I22: =IF($D22="","",IF($H22<=0.005,"Recebida",IF(AND($E22<>"",$E22<Hoje),"ATRASADA","A receber")))
... H64: =IF($D64="","",MAX(0,$D64-N($G64))) | I64: =IF($D64="","",IF($H64<=0.005,"Recebida",IF(AND($E64<>"",$E64<Hoje),"ATRASADA","A receber")))

Sheet Resumo
A1: Resumo da obra
A2: Orçado x realizado, custo projetado e margem prevista. Atualiza sozinho. | J2: EXEMPLO - dados fictícios
A4: VALOR DO CONTRATO | B4: ORÇADO | D4: REALIZADO | F4: % CUSTO CONSUMIDO | H4: % FÍSICO DA OBRA
A5: =Contrato -> 480000 | B5: =B35 -> 392000.04 | D5: =C35 -> 295103.98 | F5: =IFERROR(C35/B35,0) -> 0.7528162 | H5: =D35 -> 0.69285701
A7: CUSTO FINAL PROJETADO | B7: MARGEM PREVISTA (R$) | D7: MARGEM PREVISTA (%) | F7: MARGEM ORÇADA (%) | H7: ALERTA
A8: =E35 -> 425600.06 | B8: =A5-A8 -> 54399.94 | D8: =IF(A5=0,0,B8/A5) -> 0.11333321 | F8: =IF(A5=0,0,(A5-B5)/A5) -> 0.18333325 | H8: =IF(A5=0,"-",IF(B8<0,"OBRA NO PREJUÍZO",IF(D8<MargemAlvo,"Margem abaixo da meta","Margem dentro da meta"))) -> Margem abaixo da meta
A10: RECEBIDO (medições) | B10: PAGO (custos) | D10: SALDO DE CAIXA DA OBRA | F10: A RECEBER (medições) | H10: ETAPAS ATRASADAS
A11: =SUM(Medições!$G$5:$G$64) -> 288000 | B11: =SUMIFS(CustoValor,CustoStatus,"Pago") -> 270451.04 | D11: =A11-B11 -> 17548.96 | F11: =SUM(Medições!$H$5:$H$64) -> 142000 | H11: =COUNTIF(Cronograma!$J$5:$J$24,"ATRASADA") -> 1
A13: Etapas: orçado, realizado e custo projetado
A14: Etapa | B14: Orçado | C14: Realizado | D14: % físico | E14: Custo projetado (EAC) | F14: Desvio projetado (R$) | G14: Desvio % | H14: Situação
A15: =IF(Cronograma!A5="","",Cronograma!A5) -> Serviços preliminares | B15: =IF($A15="","",SUMIFS(OrcTotal,OrcEtapa,$A15)) -> 18000 | C15: =IF($A15="","",SUMIFS(CustoValor,CustoEtapa,$A15)) -> 18360 | D15: =IF($A15="","",N(Cronograma!D5)) -> 1 | E15: =IF($A15="","",IF($D15>=0.05,$C15/$D15,$B15)) -> 18360 | F15: =IF($A15="","",$E15-$B15) -> 360 | G15: =IF(OR($A15="",N($B15)=0),"",$F15/$B15) -> 0.02 | H15: =IF($A15="","",Cronograma!J5) -> Concluída
A16: =IF(Cronograma!A6="","",Cronograma!A6) -> Fundação | B16: =IF($A16="","",SUMIFS(OrcTotal,OrcEtapa,$A16)) -> 52000 | C16: =IF($A16="","",SUMIFS(CustoValor,CustoEtapa,$A16)) -> 55120 | D16: =IF($A16="","",N(Cronograma!D6)) -> 1 | E16: =IF($A16="","",IF($D16>=0.05,$C16/$D16,$B16)) -> 55120 | F16: =IF($A16="","",$E16-$B16) -> 3120 | G16: =IF(OR($A16="",N($B16)=0),"",$F16/$B16) -> 0.06 | H16: =IF($A16="","",Cronograma!J6) -> Concluída
A17: =IF(Cronograma!A7="","",Cronograma!A7) -> Estrutura | B17: =IF($A17="","",SUMIFS(OrcTotal,OrcEtapa,$A17)) -> 78000 | C17: =IF($A17="","",SUMIFS(CustoValor,CustoEtapa,$A17)) -> 85020 | D17: =IF($A17="","",N(Cronograma!D7)) -> 1 | E17: =IF($A17="","",IF($D17>=0.05,$C17/$D17,$B17)) -> 85020 | F17: =IF($A17="","",$E17-$B17) -> 7020 | G17: =IF(OR($A17="",N($B17)=0),"",$F17/$B17) -> 0.09 | H17: =IF($A17="","",Cronograma!J7) -> Concluída
A18: =IF(Cronograma!A8="","",Cronograma!A8) -> Alvenaria | B18: =IF($A18="","",SUMIFS(OrcTotal,OrcEtapa,$A18)) -> 46000.08 | C18: =IF($A18="","",SUMIFS(CustoValor,CustoEtapa,$A18)) -> 51520.09 | D18: =IF($A18="","",N(Cronograma!D8)) -> 1 | E18: =IF($A18="","",IF($D18>=0.05,$C18/$D18,$B18)) -> 51520.09 | F18: =IF($A18="","",$E18-$B18) -> 5520.01 | G18: =IF(OR($A18="",N($B18)=0),"",$F18/$B18) -> 0.12000001 | H18: =IF($A18="","",Cronograma!J8) -> Concluída
A19: =IF(Cronograma!A9="","",Cronograma!A9) -> Instalações elétricas | B19: =IF($A19="","",SUMIFS(OrcTotal,OrcEtapa,$A19)) -> 30999.96 | C19: =IF($A19="","",SUMIFS(CustoValor,CustoEtapa,$A19)) -> 29263.96 | D19: =IF($A19="","",N(Cronograma!D9)) -> 0.8 | E19: =IF($A19="","",IF($D19>=0.05,$C19/$D19,$B19)) -> 36579.95 | F19: =IF($A19="","",$E19-$B19) -> 5579.99 | G19: =IF(OR($A19="",N($B19)=0),"",$F19/$B19) -> 0.17999991 | H19: =IF($A19="","",Cronograma!J9) -> ATRASADA
A20: =IF(Cronograma!A10="","",Cronograma!A10) -> Instalações hidráulicas | B20: =IF($A20="","",SUMIFS(OrcTotal,OrcEtapa,$A20)) -> 25999.92 | C20: =IF($A20="","",SUMIFS(CustoValor,CustoEtapa,$A20)) -> 25999.92 | D20: =IF($A20="","",N(Cronograma!D10)) -> 1 | E20: =IF($A20="","",IF($D20>=0.05,$C20/$D20,$B20)) -> 25999.92 | F20: =IF($A20="","",$E20-$B20) -> 0 | G20: =IF(OR($A20="",N($B20)=0),"",$F20/$B20) -> 0 | H20: =IF($A20="","",Cronograma!J10) -> Concluída
A21: =IF(Cronograma!A11="","",Cronograma!A11) -> Revestimentos | B21: =IF($A21="","",SUMIFS(OrcTotal,OrcEtapa,$A21)) -> 52000 | C21: =IF($A21="","",SUMIFS(CustoValor,CustoEtapa,$A21)) -> 25740 | D21: =IF($A21="","",N(Cronograma!D11)) -> 0.45 | E21: =IF($A21="","",IF($D21>=0.05,$C21/$D21,$B21)) -> 57200 | F21: =IF($A21="","",$E21-$B21) -> 5200 | G21: =IF(OR($A21="",N($B21)=0),"",$F21/$B21) -> 0.1 | H21: =IF($A21="","",Cronograma!J11) -> Em dia
A22: =IF(Cronograma!A12="","",Cronograma!A12) -> Esquadrias | B22: =IF($A22="","",SUMIFS(OrcTotal,OrcEtapa,$A22)) -> 34000.08 | C22: =IF($A22="","",SUMIFS(CustoValor,CustoEtapa,$A22)) -> 4080.01 | D22: =IF($A22="","",N(Cronograma!D12)) -> 0.1 | E22: =IF($A22="","",IF($D22>=0.05,$C22/$D22,$B22)) -> 40800.1 | F22: =IF($A22="","",$E22-$B22) -> 6800.02 | G22: =IF(OR($A22="",N($B22)=0),"",$F22/$B22) -> 0.20000012 | H22: =IF($A22="","",Cronograma!J12) -> Em dia
A23: =IF(Cronograma!A13="","",Cronograma!A13) -> Pintura | B23: =IF($A23="","",SUMIFS(OrcTotal,OrcEtapa,$A23)) -> 24000 | C23: =IF($A23="","",SUMIFS(CustoValor,CustoEtapa,$A23)) -> 0 | D23: =IF($A23="","",N(Cronograma!D13)) -> 0 | E23: =IF($A23="","",IF($D23>=0.05,$C23/$D23,$B23)) -> 24000 | F23: =IF($A23="","",$E23-$B23) -> 0 | G23: =IF(OR($A23="",N($B23)=0),"",$F23/$B23) -> 0 | H23: =IF($A23="","",Cronograma!J13) -> A iniciar
A24: =IF(Cronograma!A14="","",Cronograma!A14) -> Acabamentos e limpeza | B24: =IF($A24="","",SUMIFS(OrcTotal,OrcEtapa,$A24)) -> 31000 | C24: =IF($A24="","",SUMIFS(CustoValor,CustoEtapa,$A24)) -> 0 | D24: =IF($A24="","",N(Cronograma!D14)) -> 0 | E24: =IF($A24="","",IF($D24>=0.05,$C24/$D24,$B24)) -> 31000 | F24: =IF($A24="","",$E24-$B24) -> 0 | G24: =IF(OR($A24="",N($B24)=0),"",$F24/$B24) -> 0 | H24: =IF($A24="","",Cronograma!J14) -> A iniciar
A25: =IF(Cronograma!A15="","",Cronograma!A15) | B25: =IF($A25="","",SUMIFS(OrcTotal,OrcEtapa,$A25)) | C25: =IF($A25="","",SUMIFS(CustoValor,CustoEtapa,$A25)) | D25: =IF($A25="","",N(Cronograma!D15)) | E25: =IF($A25="","",IF($D25>=0.05,$C25/$D25,$B25)) | F25: =IF($A25="","",$E25-$B25) | G25: =IF(OR($A25="",N($B25)=0),"",$F25/$B25) | H25: =IF($A25="","",Cronograma!J15)
A26: =IF(Cronograma!A16="","",Cronograma!A16) | B26: =IF($A26="","",SUMIFS(OrcTotal,OrcEtapa,$A26)) | C26: =IF($A26="","",SUMIFS(CustoValor,CustoEtapa,$A26)) | D26: =IF($A26="","",N(Cronograma!D16)) | E26: =IF($A26="","",IF($D26>=0.05,$C26/$D26,$B26)) | F26: =IF($A26="","",$E26-$B26) | G26: =IF(OR($A26="",N($B26)=0),"",$F26/$B26) | H26: =IF($A26="","",Cronograma!J16)
... A34: =IF(Cronograma!A24="","",Cronograma!A24) | B34: =IF($A34="","",SUMIFS(OrcTotal,OrcEtapa,$A34)) | C34: =IF($A34="","",SUMIFS(CustoValor,CustoEtapa,$A34)) | D34: =IF($A34="","",N(Cronograma!D24)) | E34: =IF($A34="","",IF($D34>=0.05,$C34/$D34,$B34)) | F34: =IF($A34="","",$E34-$B34) | G34: =IF(OR($A34="",N($B34)=0),"",$F34/$B34) | H34: =IF($A34="","",Cronograma!J24)
A35: TOTAL DA OBRA | B35: =SUM(OrcTotal) -> 392000.04 | C35: =SUM(CustoValor) -> 295103.98 | D35: =IFERROR(SUMPRODUCT(B15:B34,D15:D34)/SUM(B15:B34),0) -> 0.69285701 | E35: =SUM(E15:E34)+(C35-SUM(C15:C34)) -> 425600.06 | F35: =E35-B35 -> 33600.02 | G35: =IF(B35=0,0,F35/B35) -> 0.085714328
A38: Custos por categoria
A39: Categoria | B39: Orçado | C39: Realizado | D39: % do realizado
A40: =IF(INDEX(CatCusto,1)="","",INDEX(CatCusto,1)) -> Material | B40: =IF($A40="","",SUMIFS(OrcTotal,OrcCat,$A40)) -> 116050.08 | C40: =IF($A40="","",SUMIFS(CustoValor,CustoCat,$A40)) -> 81276.09 | D40: =IF(OR($A40="",$C$35=0),"",C40/$C$35) -> 0.27541509
A41: =IF(INDEX(CatCusto,2)="","",INDEX(CatCusto,2)) -> Mão de obra | B41: =IF($A41="","",SUMIFS(OrcTotal,OrcCat,$A41)) -> 85800 | C41: =IF($A41="","",SUMIFS(CustoValor,CustoCat,$A41)) -> 76821.13 | D41: =IF(OR($A41="",$C$35=0),"",C41/$C$35) -> 0.26031885
A42: =IF(INDEX(CatCusto,3)="","",INDEX(CatCusto,3)) -> Equipamentos | B42: =IF($A42="","",SUMIFS(OrcTotal,OrcCat,$A42)) -> 86100 | C42: =IF($A42="","",SUMIFS(CustoValor,CustoCat,$A42)) -> 63533.85 | D42: =IF(OR($A42="",$C$35=0),"",C42/$C$35) -> 0.2152931
A43: =IF(INDEX(CatCusto,4)="","",INDEX(CatCusto,4)) -> Subempreitada | B43: =IF($A43="","",SUMIFS(OrcTotal,OrcCat,$A43)) -> 104049.96 | C43: =IF($A43="","",SUMIFS(CustoValor,CustoCat,$A43)) -> 73472.91 | D43: =IF(OR($A43="",$C$35=0),"",C43/$C$35) -> 0.24897296
A44: =IF(INDEX(CatCusto,5)="","",INDEX(CatCusto,5)) -> Projetos e taxas | B44: =IF($A44="","",SUMIFS(OrcTotal,OrcCat,$A44)) -> 0 | C44: =IF($A44="","",SUMIFS(CustoValor,CustoCat,$A44)) -> 0 | D44: =IF(OR($A44="",$C$35=0),"",C44/$C$35) -> 0
A45: =IF(INDEX(CatCusto,6)="","",INDEX(CatCusto,6)) -> Outros | B45: =IF($A45="","",SUMIFS(OrcTotal,OrcCat,$A45)) -> 0 | C45: =IF($A45="","",SUMIFS(CustoValor,CustoCat,$A45)) -> 0 | D45: =IF(OR($A45="",$C$35=0),"",C45/$C$35) -> 0
