Workbook
Name Ano: Config!$C$5
Name ContaComp: Config!$C$10:$C$19
Name ContaNome: Config!$B$10:$B$19
Name MetaLucro: Config!$C$6

Sheet Início
A1: DRE e Ponto de Equilíbrio
A2: Carvex XLS · Descubra o lucro real e quanto precisa vender para pagar as contas
B4: ESTE É O ARQUIVO DE EXEMPLO: todos os dados são fictícios. Use-o para entender como a planilha funciona e comece a sua pela PLANILHA-LIMPA.xlsx.
B6: O que esta planilha faz
B7: Lance receitas, custos e despesas escolhendo a conta do DRE. A planilha monta a Demonstração do Resultado mês a mês, calcula a margem de contribuição, o ponto de equilíbrio, a margem de segurança e o faturamento necessário para atingir o lucro que você deseja.
B9: Como começar (5 minutos)
B10: 1. Config | C10: Informe empresa, ano e o lucro líquido mensal que você deseja. Leia a lista de contas para saber o que lançar em cada uma.
B11: 2. Lance tudo em Lançamentos | C11: Data, conta do DRE, descrição e valor (sempre positivo). Use a data de competência (quando a venda ou o custo ocorreu).
B12: 3. Abra a aba DRE | C12: Veja mês a mês a receita, a margem de contribuição, o resultado operacional e o lucro líquido.
B13: 4. Abra a aba Ponto de Equilíbrio | C13: Veja quanto você precisa faturar por mês para não ter prejuízo e quanto precisa para atingir sua meta de lucro.
B14: 5. Revise mensalmente | C14: Feche o mês até o dia 10, comparando o lucro com a meta.
B16: Mapa das abas (clique para ir)
B17: Config | C17: Parâmetros e lista de contas.
B18: Lançamentos | C18: Todos os lançamentos (até 1.500 linhas).
B19: DRE | C19: Demonstração do Resultado mês a mês, com % da receita bruta.
B20: Ponto de Equilíbrio | C20: Indicadores, ponto de equilíbrio por mês e gráficos.
B22: Legenda de cores
B23: Amarelo | C23: Célula que VOCÊ preenche.
B24: Cinza | C24: Cálculo automático. Não digite aqui.
B25: Verde escuro | C25: Cabeçalho de coluna.
B27: Atenção
B28: • O DRE usa regime de competência (quando vendeu/gastou), diferente do Fluxo de Caixa (quando recebeu/pagou).
B29: • Não renomeie as contas da Config: elas são a estrutura do DRE. Detalhe pela coluna Descrição.
B30: • Esta planilha é uma ferramenta gerencial. Não substitui a contabilidade oficial.
B32: Carvex XLS · DRE e Ponto de Equilíbrio · versão 1.0 · Dúvidas: consulte o TUTORIAL.md e o MANUAL.md que acompanham o produto.

Sheet Config
A1: Configurações
A2: Preencha as células amarelas. | E2: EXEMPLO - dados fictícios
B4: Empresa | C4: Empresa Exemplo
B5: Ano do DRE | C5: 2026
B6: Lucro líquido desejado por mês (R$) | C6: 8000
B9: Conta do DRE | C9: Comportamento | D9: O que lançar aqui
B10: Receita bruta | C10: Receita | D10: Vendas e serviços faturados no mês (competência).
B11: Deduções e impostos sobre vendas | C11: Variável | D11: Simples/ICMS/ISS/PIS/COFINS sobre vendas, devoluções e descontos.
B12: Custos variáveis (CMV / insumos) | C12: Variável | D12: Mercadorias, matéria-prima, embalagens e serviços de terceiros ligados à venda.
B13: Comissões e taxas de venda | C13: Variável | D13: Comissão de vendedores, taxas de cartão e de marketplace.
B14: Despesas com pessoal | C14: Fixo | D14: Salários, encargos, benefícios e pró-labore.
B15: Despesas administrativas | C15: Fixo | D15: Aluguel, energia, internet, contador, sistemas, manutenção.
B16: Despesas comerciais e marketing | C16: Fixo | D16: Anúncios, brindes, eventos, material de divulgação.
B17: Receitas financeiras | C17: Receita financeira | D17: Rendimentos de aplicações e juros recebidos.
B18: Despesas financeiras | C18: Fixo | D18: Juros, tarifas bancárias, IOF e parcelas de juros de empréstimos.
B19: IRPJ / CSLL | C19: Imposto sobre lucro | D19: Imposto sobre o lucro (apenas Lucro Presumido/Real; no Simples costuma estar nas deduções).
B21: Fixo = não muda com o volume de vendas. Variável = cresce junto com as vendas.

Sheet Lançamentos
A1: Lançamentos
A2: Valores sempre positivos. A conta define se soma ou subtrai no DRE. | G2: EXEMPLO - dados fictícios
A4: Data (competência) | B4: Conta do DRE | C4: Descrição | D4: Valor (R$) | E4: Ano | F4: Mês | G4: Comportamento
A5: 46029 | B5: Receita bruta | C5: Faturamento semana 1 | D5: 28516.76 | E5: =IF($A5="","",YEAR($A5)) -> 2026 | F5: =IF($A5="","",MONTH($A5)) -> 1 | G5: =IF($B5="","",IFERROR(INDEX(ContaComp,MATCH($B5,ContaNome,0)),"Conta inválida")) -> Receita
A6: 46036 | B6: Receita bruta | C6: Faturamento semana 2 | D6: 20261.91 | E6: =IF($A6="","",YEAR($A6)) -> 2026 | F6: =IF($A6="","",MONTH($A6)) -> 1 | G6: =IF($B6="","",IFERROR(INDEX(ContaComp,MATCH($B6,ContaNome,0)),"Conta inválida")) -> Receita
A7: 46043 | B7: Receita bruta | C7: Faturamento semana 3 | D7: 16509.7 | E7: =IF($A7="","",YEAR($A7)) -> 2026 | F7: =IF($A7="","",MONTH($A7)) -> 1 | G7: =IF($B7="","",IFERROR(INDEX(ContaComp,MATCH($B7,ContaNome,0)),"Conta inválida")) -> Receita
A8: 46050 | B8: Receita bruta | C8: Faturamento semana 4 | D8: 9755.73 | E8: =IF($A8="","",YEAR($A8)) -> 2026 | F8: =IF($A8="","",MONTH($A8)) -> 1 | G8: =IF($B8="","",IFERROR(INDEX(ContaComp,MATCH($B8,ContaNome,0)),"Conta inválida")) -> Receita
A9: 46050 | B9: Deduções e impostos sobre vendas | C9: Simples Nacional | D9: 5553.26 | E9: =IF($A9="","",YEAR($A9)) -> 2026 | F9: =IF($A9="","",MONTH($A9)) -> 1 | G9: =IF($B9="","",IFERROR(INDEX(ContaComp,MATCH($B9,ContaNome,0)),"Conta inválida")) -> Variável
A10: 46034 | B10: Custos variáveis (CMV / insumos) | C10: Compra de mercadorias/insumos | D10: 18737.34 | E10: =IF($A10="","",YEAR($A10)) -> 2026 | F10: =IF($A10="","",MONTH($A10)) -> 1 | G10: =IF($B10="","",IFERROR(INDEX(ContaComp,MATCH($B10,ContaNome,0)),"Conta inválida")) -> Variável
A11: 46046 | B11: Custos variáveis (CMV / insumos) | C11: Compra de mercadorias/insumos (2ª) | D11: 8030.29 | E11: =IF($A11="","",YEAR($A11)) -> 2026 | F11: =IF($A11="","",MONTH($A11)) -> 1 | G11: =IF($B11="","",IFERROR(INDEX(ContaComp,MATCH($B11,ContaNome,0)),"Conta inválida")) -> Variável
A12: 46050 | B12: Comissões e taxas de venda | C12: Taxas de cartão e comissões | D12: 2476.46 | E12: =IF($A12="","",YEAR($A12)) -> 2026 | F12: =IF($A12="","",MONTH($A12)) -> 1 | G12: =IF($B12="","",IFERROR(INDEX(ContaComp,MATCH($B12,ContaNome,0)),"Conta inválida")) -> Variável
A13: 46027 | B13: Despesas com pessoal | C13: Folha de pagamento e encargos | D13: 24800 | E13: =IF($A13="","",YEAR($A13)) -> 2026 | F13: =IF($A13="","",MONTH($A13)) -> 1 | G13: =IF($B13="","",IFERROR(INDEX(ContaComp,MATCH($B13,ContaNome,0)),"Conta inválida")) -> Fixo
A14: 46028 | B14: Despesas com pessoal | C14: Pró-labore | D14: 7000 | E14: =IF($A14="","",YEAR($A14)) -> 2026 | F14: =IF($A14="","",MONTH($A14)) -> 1 | G14: =IF($B14="","",IFERROR(INDEX(ContaComp,MATCH($B14,ContaNome,0)),"Conta inválida")) -> Fixo
A15: 46032 | B15: Despesas administrativas | C15: Aluguel | D15: 5200 | E15: =IF($A15="","",YEAR($A15)) -> 2026 | F15: =IF($A15="","",MONTH($A15)) -> 1 | G15: =IF($B15="","",IFERROR(INDEX(ContaComp,MATCH($B15,ContaNome,0)),"Conta inválida")) -> Fixo
A16: 46037 | B16: Despesas administrativas | C16: Energia, internet e sistemas | D16: 2633.13 | E16: =IF($A16="","",YEAR($A16)) -> 2026 | F16: =IF($A16="","",MONTH($A16)) -> 1 | G16: =IF($B16="","",IFERROR(INDEX(ContaComp,MATCH($B16,ContaNome,0)),"Conta inválida")) -> Fixo
... A142: 46293 | B142: Receitas financeiras | C142: Rendimento da reserva | D142: 304.62 | E142: =IF($A142="","",YEAR($A142)) -> 2026 | F142: =IF($A142="","",MONTH($A142)) -> 9 | G142: =IF($B142="","",IFERROR(INDEX(ContaComp,MATCH($B142,ContaNome,0)),"Conta inválida")) -> Receita financeira
E143: =IF($A143="","",YEAR($A143)) | F143: =IF($A143="","",MONTH($A143)) | G143: =IF($B143="","",IFERROR(INDEX(ContaComp,MATCH($B143,ContaNome,0)),"Conta inválida"))
E144: =IF($A144="","",YEAR($A144)) | F144: =IF($A144="","",MONTH($A144)) | G144: =IF($B144="","",IFERROR(INDEX(ContaComp,MATCH($B144,ContaNome,0)),"Conta inválida"))
E145: =IF($A145="","",YEAR($A145)) | F145: =IF($A145="","",MONTH($A145)) | G145: =IF($B145="","",IFERROR(INDEX(ContaComp,MATCH($B145,ContaNome,0)),"Conta inválida"))
E146: =IF($A146="","",YEAR($A146)) | F146: =IF($A146="","",MONTH($A146)) | G146: =IF($B146="","",IFERROR(INDEX(ContaComp,MATCH($B146,ContaNome,0)),"Conta inválida"))
E147: =IF($A147="","",YEAR($A147)) | F147: =IF($A147="","",MONTH($A147)) | G147: =IF($B147="","",IFERROR(INDEX(ContaComp,MATCH($B147,ContaNome,0)),"Conta inválida"))
E148: =IF($A148="","",YEAR($A148)) | F148: =IF($A148="","",MONTH($A148)) | G148: =IF($B148="","",IFERROR(INDEX(ContaComp,MATCH($B148,ContaNome,0)),"Conta inválida"))
E149: =IF($A149="","",YEAR($A149)) | F149: =IF($A149="","",MONTH($A149)) | G149: =IF($B149="","",IFERROR(INDEX(ContaComp,MATCH($B149,ContaNome,0)),"Conta inválida"))
E150: =IF($A150="","",YEAR($A150)) | F150: =IF($A150="","",MONTH($A150)) | G150: =IF($B150="","",IFERROR(INDEX(ContaComp,MATCH($B150,ContaNome,0)),"Conta inválida"))
E151: =IF($A151="","",YEAR($A151)) | F151: =IF($A151="","",MONTH($A151)) | G151: =IF($B151="","",IFERROR(INDEX(ContaComp,MATCH($B151,ContaNome,0)),"Conta inválida"))
E152: =IF($A152="","",YEAR($A152)) | F152: =IF($A152="","",MONTH($A152)) | G152: =IF($B152="","",IFERROR(INDEX(ContaComp,MATCH($B152,ContaNome,0)),"Conta inválida"))
E153: =IF($A153="","",YEAR($A153)) | F153: =IF($A153="","",MONTH($A153)) | G153: =IF($B153="","",IFERROR(INDEX(ContaComp,MATCH($B153,ContaNome,0)),"Conta inválida"))
E154: =IF($A154="","",YEAR($A154)) | F154: =IF($A154="","",MONTH($A154)) | G154: =IF($B154="","",IFERROR(INDEX(ContaComp,MATCH($B154,ContaNome,0)),"Conta inválida"))
... E1504: =IF($A1504="","",YEAR($A1504)) | F1504: =IF($A1504="","",MONTH($A1504)) | G1504: =IF($B1504="","",IFERROR(INDEX(ContaComp,MATCH($B1504,ContaNome,0)),"Conta inválida"))

Sheet DRE
A1: DRE: Demonstração do Resultado do Exercício
A2: Calculada automaticamente a partir dos lançamentos. % = sobre a receita bruta. | O2: EXEMPLO - dados fictícios
A4: Linha | B4: =DATE(Ano,1,1) -> 46023 | C4: =DATE(Ano,2,1) -> 46054 | D4: =DATE(Ano,3,1) -> 46082 | E4: =DATE(Ano,4,1) -> 46113 | F4: =DATE(Ano,5,1) -> 46143 | G4: =DATE(Ano,6,1) -> 46174 | H4: =DATE(Ano,7,1) -> 46204 | I4: =DATE(Ano,8,1) -> 46235 | J4: =DATE(Ano,9,1) -> 46266 | K4: =DATE(Ano,10,1) -> 46296 | L4: =DATE(Ano,11,1) -> 46327 | M4: =DATE(Ano,12,1) -> 46357 | N4: Total do ano | O4: % da receita bruta
A5: Receita bruta | B5: =SUMIFS('Lançamentos'!$D$5:$D$1504,'Lançamentos'!$B$5:$B$1504,"Receita bruta",'Lançamentos'!$E$5:$E$1504,Ano,'Lançamentos'!$F$5:$F$1504,MONTH(B$4)) -> 75044.1 | C5: =SUMIFS('Lançamentos'!$D$5:$D$1504,'Lançamentos'!$B$5:$B$1504,"Receita bruta",'Lançamentos'!$E$5:$E$1504,Ano,'Lançamentos'!$F$5:$F$1504,MONTH(C$4)) -> 65899.68 | D5: =SUMIFS('Lançamentos'!$D$5:$D$1504,'Lançamentos'!$B$5:$B$1504,"Receita bruta",'Lançamentos'!$E$5:$E$1504,Ano,'Lançamentos'!$F$5:$F$1504,MONTH(D$4)) -> 93386.43 | E5: =SUMIFS('Lançamentos'!$D$5:$D$1504,'Lançamentos'!$B$5:$B$1504,"Receita bruta",'Lançamentos'!$E$5:$E$1504,Ano,'Lançamentos'!$F$5:$F$1504,MONTH(E$4)) -> 96441.92 | F5: =SUMIFS('Lançamentos'!$D$5:$D$1504,'Lançamentos'!$B$5:$B$1504,"Receita bruta",'Lançamentos'!$E$5:$E$1504,Ano,'Lançamentos'!$F$5:$F$1504,MONTH(F$4)) -> 104557 | G5: =SUMIFS('Lançamentos'!$D$5:$D$1504,'Lançamentos'!$B$5:$B$1504,"Receita bruta",'Lançamentos'!$E$5:$E$1504,Ano,'Lançamentos'!$F$5:$F$1504,MONTH(G$4)) -> 113584.48 | H5: =SUMIFS('Lançamentos'!$D$5:$D$1504,'Lançamentos'!$B$5:$B$1504,"Receita bruta",'Lançamentos'!$E$5:$E$1504,Ano,'Lançamentos'!$F$5:$F$1504,MONTH(H$4)) -> 111117.92 | I5: =SUMIFS('Lançamentos'!$D$5:$D$1504,'Lançamentos'!$B$5:$B$1504,"Receita bruta",'Lançamentos'!$E$5:$E$1504,Ano,'Lançamentos'!$F$5:$F$1504,MONTH(I$4)) -> 121072.33 | ... M5: =SUMIFS('Lançamentos'!$D$5:$D$1504,'Lançamentos'!$B$5:$B$1504,"Receita bruta",'Lançamentos'!$E$5:$E$1504,Ano,'Lançamentos'!$F$5:$F$1504,MONTH(M$4)) -> 0 | N5: =SUM(B5:M5) -> 905211.51 | O5: =IF($N$5=0,0,N5/$N$5) -> 1
A6: (-) Deduções e impostos sobre vendas | B6: =SUMIFS('Lançamentos'!$D$5:$D$1504,'Lançamentos'!$B$5:$B$1504,"Deduções e impostos sobre vendas",'Lançamentos'!$E$5:$E$1504,Ano,'Lançamentos'!$F$5:$F$1504,MONTH(B$4)) -> 5553.26 | C6: =SUMIFS('Lançamentos'!$D$5:$D$1504,'Lançamentos'!$B$5:$B$1504,"Deduções e impostos sobre vendas",'Lançamentos'!$E$5:$E$1504,Ano,'Lançamentos'!$F$5:$F$1504,MONTH(C$4)) -> 4876.58 | D6: =SUMIFS('Lançamentos'!$D$5:$D$1504,'Lançamentos'!$B$5:$B$1504,"Deduções e impostos sobre vendas",'Lançamentos'!$E$5:$E$1504,Ano,'Lançamentos'!$F$5:$F$1504,MONTH(D$4)) -> 6910.6 | E6: =SUMIFS('Lançamentos'!$D$5:$D$1504,'Lançamentos'!$B$5:$B$1504,"Deduções e impostos sobre vendas",'Lançamentos'!$E$5:$E$1504,Ano,'Lançamentos'!$F$5:$F$1504,MONTH(E$4)) -> 7136.7 | F6: =SUMIFS('Lançamentos'!$D$5:$D$1504,'Lançamentos'!$B$5:$B$1504,"Deduções e impostos sobre vendas",'Lançamentos'!$E$5:$E$1504,Ano,'Lançamentos'!$F$5:$F$1504,MONTH(F$4)) -> 7737.22 | G6: =SUMIFS('Lançamentos'!$D$5:$D$1504,'Lançamentos'!$B$5:$B$1504,"Deduções e impostos sobre vendas",'Lançamentos'!$E$5:$E$1504,Ano,'Lançamentos'!$F$5:$F$1504,MONTH(G$4)) -> 8405.25 | H6: =SUMIFS('Lançamentos'!$D$5:$D$1504,'Lançamentos'!$B$5:$B$1504,"Deduções e impostos sobre vendas",'Lançamentos'!$E$5:$E$1504,Ano,'Lançamentos'!$F$5:$F$1504,MONTH(H$4)) -> 8222.73 | I6: =SUMIFS('Lançamentos'!$D$5:$D$1504,'Lançamentos'!$B$5:$B$1504,"Deduções e impostos sobre vendas",'Lançamentos'!$E$5:$E$1504,Ano,'Lançamentos'!$F$5:$F$1504,MONTH(I$4)) -> 8959.35 | ... M6: =SUMIFS('Lançamentos'!$D$5:$D$1504,'Lançamentos'!$B$5:$B$1504,"Deduções e impostos sobre vendas",'Lançamentos'!$E$5:$E$1504,Ano,'Lançamentos'!$F$5:$F$1504,MONTH(M$4)) -> 0 | N6: =SUM(B6:M6) -> 66985.66 | O6: =IF($N$5=0,0,N6/$N$5) -> 0.074000009
A7: = RECEITA LÍQUIDA | B7: =B5-B6 -> 69490.84 | C7: =C5-C6 -> 61023.1 | D7: =D5-D6 -> 86475.83 | E7: =E5-E6 -> 89305.22 | F7: =F5-F6 -> 96819.78 | G7: =G5-G6 -> 105179.23 | H7: =H5-H6 -> 102895.19 | I7: =I5-I6 -> 112112.98 | ... N7: =N5-N6 -> 838225.85 | O7: =IF($N$5=0,0,N7/$N$5) -> 0.92599999
A8: (-) Custos variáveis (CMV / insumos) | B8: =SUMIFS('Lançamentos'!$D$5:$D$1504,'Lançamentos'!$B$5:$B$1504,"Custos variáveis (CMV / insumos)",'Lançamentos'!$E$5:$E$1504,Ano,'Lançamentos'!$F$5:$F$1504,MONTH(B$4)) -> 26767.63 | C8: =SUMIFS('Lançamentos'!$D$5:$D$1504,'Lançamentos'!$B$5:$B$1504,"Custos variáveis (CMV / insumos)",'Lançamentos'!$E$5:$E$1504,Ano,'Lançamentos'!$F$5:$F$1504,MONTH(C$4)) -> 23717.8 | D8: =SUMIFS('Lançamentos'!$D$5:$D$1504,'Lançamentos'!$B$5:$B$1504,"Custos variáveis (CMV / insumos)",'Lançamentos'!$E$5:$E$1504,Ano,'Lançamentos'!$F$5:$F$1504,MONTH(D$4)) -> 34309.44 | E8: =SUMIFS('Lançamentos'!$D$5:$D$1504,'Lançamentos'!$B$5:$B$1504,"Custos variáveis (CMV / insumos)",'Lançamentos'!$E$5:$E$1504,Ano,'Lançamentos'!$F$5:$F$1504,MONTH(E$4)) -> 34857.09 | F8: =SUMIFS('Lançamentos'!$D$5:$D$1504,'Lançamentos'!$B$5:$B$1504,"Custos variáveis (CMV / insumos)",'Lançamentos'!$E$5:$E$1504,Ano,'Lançamentos'!$F$5:$F$1504,MONTH(F$4)) -> 39038.2 | G8: =SUMIFS('Lançamentos'!$D$5:$D$1504,'Lançamentos'!$B$5:$B$1504,"Custos variáveis (CMV / insumos)",'Lançamentos'!$E$5:$E$1504,Ano,'Lançamentos'!$F$5:$F$1504,MONTH(G$4)) -> 42284.68 | H8: =SUMIFS('Lançamentos'!$D$5:$D$1504,'Lançamentos'!$B$5:$B$1504,"Custos variáveis (CMV / insumos)",'Lançamentos'!$E$5:$E$1504,Ano,'Lançamentos'!$F$5:$F$1504,MONTH(H$4)) -> 40644.5 | I8: =SUMIFS('Lançamentos'!$D$5:$D$1504,'Lançamentos'!$B$5:$B$1504,"Custos variáveis (CMV / insumos)",'Lançamentos'!$E$5:$E$1504,Ano,'Lançamentos'!$F$5:$F$1504,MONTH(I$4)) -> 44160.44 | ... M8: =SUMIFS('Lançamentos'!$D$5:$D$1504,'Lançamentos'!$B$5:$B$1504,"Custos variáveis (CMV / insumos)",'Lançamentos'!$E$5:$E$1504,Ano,'Lançamentos'!$F$5:$F$1504,MONTH(M$4)) -> 0 | N8: =SUM(B8:M8) -> 333427.95 | O8: =IF($N$5=0,0,N8/$N$5) -> 0.36834259
A9: (-) Comissões e taxas de venda | B9: =SUMIFS('Lançamentos'!$D$5:$D$1504,'Lançamentos'!$B$5:$B$1504,"Comissões e taxas de venda",'Lançamentos'!$E$5:$E$1504,Ano,'Lançamentos'!$F$5:$F$1504,MONTH(B$4)) -> 2476.46 | C9: =SUMIFS('Lançamentos'!$D$5:$D$1504,'Lançamentos'!$B$5:$B$1504,"Comissões e taxas de venda",'Lançamentos'!$E$5:$E$1504,Ano,'Lançamentos'!$F$5:$F$1504,MONTH(C$4)) -> 2174.69 | D9: =SUMIFS('Lançamentos'!$D$5:$D$1504,'Lançamentos'!$B$5:$B$1504,"Comissões e taxas de venda",'Lançamentos'!$E$5:$E$1504,Ano,'Lançamentos'!$F$5:$F$1504,MONTH(D$4)) -> 3081.75 | E9: =SUMIFS('Lançamentos'!$D$5:$D$1504,'Lançamentos'!$B$5:$B$1504,"Comissões e taxas de venda",'Lançamentos'!$E$5:$E$1504,Ano,'Lançamentos'!$F$5:$F$1504,MONTH(E$4)) -> 3182.58 | F9: =SUMIFS('Lançamentos'!$D$5:$D$1504,'Lançamentos'!$B$5:$B$1504,"Comissões e taxas de venda",'Lançamentos'!$E$5:$E$1504,Ano,'Lançamentos'!$F$5:$F$1504,MONTH(F$4)) -> 3450.38 | G9: =SUMIFS('Lançamentos'!$D$5:$D$1504,'Lançamentos'!$B$5:$B$1504,"Comissões e taxas de venda",'Lançamentos'!$E$5:$E$1504,Ano,'Lançamentos'!$F$5:$F$1504,MONTH(G$4)) -> 3748.29 | H9: =SUMIFS('Lançamentos'!$D$5:$D$1504,'Lançamentos'!$B$5:$B$1504,"Comissões e taxas de venda",'Lançamentos'!$E$5:$E$1504,Ano,'Lançamentos'!$F$5:$F$1504,MONTH(H$4)) -> 3666.89 | I9: =SUMIFS('Lançamentos'!$D$5:$D$1504,'Lançamentos'!$B$5:$B$1504,"Comissões e taxas de venda",'Lançamentos'!$E$5:$E$1504,Ano,'Lançamentos'!$F$5:$F$1504,MONTH(I$4)) -> 3995.39 | ... M9: =SUMIFS('Lançamentos'!$D$5:$D$1504,'Lançamentos'!$B$5:$B$1504,"Comissões e taxas de venda",'Lançamentos'!$E$5:$E$1504,Ano,'Lançamentos'!$F$5:$F$1504,MONTH(M$4)) -> 0 | N9: =SUM(B9:M9) -> 29871.98 | O9: =IF($N$5=0,0,N9/$N$5) -> 0.033
A10: = MARGEM DE CONTRIBUIÇÃO | B10: =B7-B8-B9 -> 40246.75 | C10: =C7-C8-C9 -> 35130.61 | D10: =D7-D8-D9 -> 49084.64 | E10: =E7-E8-E9 -> 51265.55 | F10: =F7-F8-F9 -> 54331.2 | G10: =G7-G8-G9 -> 59146.26 | H10: =H7-H8-H9 -> 58583.8 | I10: =I7-I8-I9 -> 63957.15 | ... N10: =N7-N8-N9 -> 474925.92 | O10: =IF($N$5=0,0,N10/$N$5) -> 0.5246574
A11: Margem de contribuição (%) | B11: =IF(B5=0,0,B10/B5) -> 0.53630798 | C11: =IF(C5=0,0,C10/C5) -> 0.53309227 | D11: =IF(D5=0,0,D10/D5) -> 0.52560784 | E11: =IF(E5=0,0,E10/E5) -> 0.53156916 | F11: =IF(F5=0,0,F10/F5) -> 0.51963235 | G11: =IF(G5=0,0,G10/G5) -> 0.52072484 | H11: =IF(H5=0,0,H10/H5) -> 0.52722189 | I11: =IF(I5=0,0,I10/I5) -> 0.52825571 | ... N11: =IF(N5=0,0,N10/N5) -> 0.5246574
A12: (-) Despesas com pessoal | B12: =SUMIFS('Lançamentos'!$D$5:$D$1504,'Lançamentos'!$B$5:$B$1504,"Despesas com pessoal",'Lançamentos'!$E$5:$E$1504,Ano,'Lançamentos'!$F$5:$F$1504,MONTH(B$4)) -> 31800 | C12: =SUMIFS('Lançamentos'!$D$5:$D$1504,'Lançamentos'!$B$5:$B$1504,"Despesas com pessoal",'Lançamentos'!$E$5:$E$1504,Ano,'Lançamentos'!$F$5:$F$1504,MONTH(C$4)) -> 31800 | D12: =SUMIFS('Lançamentos'!$D$5:$D$1504,'Lançamentos'!$B$5:$B$1504,"Despesas com pessoal",'Lançamentos'!$E$5:$E$1504,Ano,'Lançamentos'!$F$5:$F$1504,MONTH(D$4)) -> 31800 | E12: =SUMIFS('Lançamentos'!$D$5:$D$1504,'Lançamentos'!$B$5:$B$1504,"Despesas com pessoal",'Lançamentos'!$E$5:$E$1504,Ano,'Lançamentos'!$F$5:$F$1504,MONTH(E$4)) -> 31800 | F12: =SUMIFS('Lançamentos'!$D$5:$D$1504,'Lançamentos'!$B$5:$B$1504,"Despesas com pessoal",'Lançamentos'!$E$5:$E$1504,Ano,'Lançamentos'!$F$5:$F$1504,MONTH(F$4)) -> 31800 | G12: =SUMIFS('Lançamentos'!$D$5:$D$1504,'Lançamentos'!$B$5:$B$1504,"Despesas com pessoal",'Lançamentos'!$E$5:$E$1504,Ano,'Lançamentos'!$F$5:$F$1504,MONTH(G$4)) -> 31800 | H12: =SUMIFS('Lançamentos'!$D$5:$D$1504,'Lançamentos'!$B$5:$B$1504,"Despesas com pessoal",'Lançamentos'!$E$5:$E$1504,Ano,'Lançamentos'!$F$5:$F$1504,MONTH(H$4)) -> 31800 | I12: =SUMIFS('Lançamentos'!$D$5:$D$1504,'Lançamentos'!$B$5:$B$1504,"Despesas com pessoal",'Lançamentos'!$E$5:$E$1504,Ano,'Lançamentos'!$F$5:$F$1504,MONTH(I$4)) -> 31800 | ... M12: =SUMIFS('Lançamentos'!$D$5:$D$1504,'Lançamentos'!$B$5:$B$1504,"Despesas com pessoal",'Lançamentos'!$E$5:$E$1504,Ano,'Lançamentos'!$F$5:$F$1504,MONTH(M$4)) -> 0 | N12: =SUM(B12:M12) -> 286200 | O12: =IF($N$5=0,0,N12/$N$5) -> 0.3161692
A13: (-) Despesas administrativas | B13: =SUMIFS('Lançamentos'!$D$5:$D$1504,'Lançamentos'!$B$5:$B$1504,"Despesas administrativas",'Lançamentos'!$E$5:$E$1504,Ano,'Lançamentos'!$F$5:$F$1504,MONTH(B$4)) -> 9233.13 | C13: =SUMIFS('Lançamentos'!$D$5:$D$1504,'Lançamentos'!$B$5:$B$1504,"Despesas administrativas",'Lançamentos'!$E$5:$E$1504,Ano,'Lançamentos'!$F$5:$F$1504,MONTH(C$4)) -> 9347.46 | D13: =SUMIFS('Lançamentos'!$D$5:$D$1504,'Lançamentos'!$B$5:$B$1504,"Despesas administrativas",'Lançamentos'!$E$5:$E$1504,Ano,'Lançamentos'!$F$5:$F$1504,MONTH(D$4)) -> 8948.59 | E13: =SUMIFS('Lançamentos'!$D$5:$D$1504,'Lançamentos'!$B$5:$B$1504,"Despesas administrativas",'Lançamentos'!$E$5:$E$1504,Ano,'Lançamentos'!$F$5:$F$1504,MONTH(E$4)) -> 9287.19 | F13: =SUMIFS('Lançamentos'!$D$5:$D$1504,'Lançamentos'!$B$5:$B$1504,"Despesas administrativas",'Lançamentos'!$E$5:$E$1504,Ano,'Lançamentos'!$F$5:$F$1504,MONTH(F$4)) -> 9061.92 | G13: =SUMIFS('Lançamentos'!$D$5:$D$1504,'Lançamentos'!$B$5:$B$1504,"Despesas administrativas",'Lançamentos'!$E$5:$E$1504,Ano,'Lançamentos'!$F$5:$F$1504,MONTH(G$4)) -> 8937.11 | H13: =SUMIFS('Lançamentos'!$D$5:$D$1504,'Lançamentos'!$B$5:$B$1504,"Despesas administrativas",'Lançamentos'!$E$5:$E$1504,Ano,'Lançamentos'!$F$5:$F$1504,MONTH(H$4)) -> 8936.96 | I13: =SUMIFS('Lançamentos'!$D$5:$D$1504,'Lançamentos'!$B$5:$B$1504,"Despesas administrativas",'Lançamentos'!$E$5:$E$1504,Ano,'Lançamentos'!$F$5:$F$1504,MONTH(I$4)) -> 9380.54 | ... M13: =SUMIFS('Lançamentos'!$D$5:$D$1504,'Lançamentos'!$B$5:$B$1504,"Despesas administrativas",'Lançamentos'!$E$5:$E$1504,Ano,'Lançamentos'!$F$5:$F$1504,MONTH(M$4)) -> 0 | N13: =SUM(B13:M13) -> 82346.23 | O13: =IF($N$5=0,0,N13/$N$5) -> 0.090969049
A14: (-) Despesas comerciais e marketing | B14: =SUMIFS('Lançamentos'!$D$5:$D$1504,'Lançamentos'!$B$5:$B$1504,"Despesas comerciais e marketing",'Lançamentos'!$E$5:$E$1504,Ano,'Lançamentos'!$F$5:$F$1504,MONTH(B$4)) -> 4723.85 | C14: =SUMIFS('Lançamentos'!$D$5:$D$1504,'Lançamentos'!$B$5:$B$1504,"Despesas comerciais e marketing",'Lançamentos'!$E$5:$E$1504,Ano,'Lançamentos'!$F$5:$F$1504,MONTH(C$4)) -> 4716.5 | D14: =SUMIFS('Lançamentos'!$D$5:$D$1504,'Lançamentos'!$B$5:$B$1504,"Despesas comerciais e marketing",'Lançamentos'!$E$5:$E$1504,Ano,'Lançamentos'!$F$5:$F$1504,MONTH(D$4)) -> 4345.5 | E14: =SUMIFS('Lançamentos'!$D$5:$D$1504,'Lançamentos'!$B$5:$B$1504,"Despesas comerciais e marketing",'Lançamentos'!$E$5:$E$1504,Ano,'Lançamentos'!$F$5:$F$1504,MONTH(E$4)) -> 4586.12 | F14: =SUMIFS('Lançamentos'!$D$5:$D$1504,'Lançamentos'!$B$5:$B$1504,"Despesas comerciais e marketing",'Lançamentos'!$E$5:$E$1504,Ano,'Lançamentos'!$F$5:$F$1504,MONTH(F$4)) -> 4852.44 | G14: =SUMIFS('Lançamentos'!$D$5:$D$1504,'Lançamentos'!$B$5:$B$1504,"Despesas comerciais e marketing",'Lançamentos'!$E$5:$E$1504,Ano,'Lançamentos'!$F$5:$F$1504,MONTH(G$4)) -> 4547.74 | H14: =SUMIFS('Lançamentos'!$D$5:$D$1504,'Lançamentos'!$B$5:$B$1504,"Despesas comerciais e marketing",'Lançamentos'!$E$5:$E$1504,Ano,'Lançamentos'!$F$5:$F$1504,MONTH(H$4)) -> 3869.17 | I14: =SUMIFS('Lançamentos'!$D$5:$D$1504,'Lançamentos'!$B$5:$B$1504,"Despesas comerciais e marketing",'Lançamentos'!$E$5:$E$1504,Ano,'Lançamentos'!$F$5:$F$1504,MONTH(I$4)) -> 4497.63 | ... M14: =SUMIFS('Lançamentos'!$D$5:$D$1504,'Lançamentos'!$B$5:$B$1504,"Despesas comerciais e marketing",'Lançamentos'!$E$5:$E$1504,Ano,'Lançamentos'!$F$5:$F$1504,MONTH(M$4)) -> 0 | N14: =SUM(B14:M14) -> 40785.78 | O14: =IF($N$5=0,0,N14/$N$5) -> 0.04505663
A15: = RESULTADO OPERACIONAL | B15: =B10-B12-B13-B14 -> -5510.23 | C15: =C10-C12-C13-C14 -> -10733.35 | D15: =D10-D12-D13-D14 -> 3990.55 | E15: =E10-E12-E13-E14 -> 5592.24 | F15: =F10-F12-F13-F14 -> 8616.84 | G15: =G10-G12-G13-G14 -> 13861.41 | H15: =H10-H12-H13-H14 -> 13977.67 | I15: =I10-I12-I13-I14 -> 18278.98 | ... N15: =N10-N12-N13-N14 -> 65593.91 | O15: =IF($N$5=0,0,N15/$N$5) -> 0.072462523
A16: (+) Receitas financeiras | B16: =SUMIFS('Lançamentos'!$D$5:$D$1504,'Lançamentos'!$B$5:$B$1504,"Receitas financeiras",'Lançamentos'!$E$5:$E$1504,Ano,'Lançamentos'!$F$5:$F$1504,MONTH(B$4)) -> 0 | C16: =SUMIFS('Lançamentos'!$D$5:$D$1504,'Lançamentos'!$B$5:$B$1504,"Receitas financeiras",'Lançamentos'!$E$5:$E$1504,Ano,'Lançamentos'!$F$5:$F$1504,MONTH(C$4)) -> 0 | D16: =SUMIFS('Lançamentos'!$D$5:$D$1504,'Lançamentos'!$B$5:$B$1504,"Receitas financeiras",'Lançamentos'!$E$5:$E$1504,Ano,'Lançamentos'!$F$5:$F$1504,MONTH(D$4)) -> 509.66 | E16: =SUMIFS('Lançamentos'!$D$5:$D$1504,'Lançamentos'!$B$5:$B$1504,"Receitas financeiras",'Lançamentos'!$E$5:$E$1504,Ano,'Lançamentos'!$F$5:$F$1504,MONTH(E$4)) -> 0 | F16: =SUMIFS('Lançamentos'!$D$5:$D$1504,'Lançamentos'!$B$5:$B$1504,"Receitas financeiras",'Lançamentos'!$E$5:$E$1504,Ano,'Lançamentos'!$F$5:$F$1504,MONTH(F$4)) -> 0 | G16: =SUMIFS('Lançamentos'!$D$5:$D$1504,'Lançamentos'!$B$5:$B$1504,"Receitas financeiras",'Lançamentos'!$E$5:$E$1504,Ano,'Lançamentos'!$F$5:$F$1504,MONTH(G$4)) -> 380 | H16: =SUMIFS('Lançamentos'!$D$5:$D$1504,'Lançamentos'!$B$5:$B$1504,"Receitas financeiras",'Lançamentos'!$E$5:$E$1504,Ano,'Lançamentos'!$F$5:$F$1504,MONTH(H$4)) -> 0 | I16: =SUMIFS('Lançamentos'!$D$5:$D$1504,'Lançamentos'!$B$5:$B$1504,"Receitas financeiras",'Lançamentos'!$E$5:$E$1504,Ano,'Lançamentos'!$F$5:$F$1504,MONTH(I$4)) -> 0 | ... M16: =SUMIFS('Lançamentos'!$D$5:$D$1504,'Lançamentos'!$B$5:$B$1504,"Receitas financeiras",'Lançamentos'!$E$5:$E$1504,Ano,'Lançamentos'!$F$5:$F$1504,MONTH(M$4)) -> 0 | N16: =SUM(B16:M16) -> 1194.28 | O16: =IF($N$5=0,0,N16/$N$5) -> 0.0013193381
A17: (-) Despesas financeiras | B17: =SUMIFS('Lançamentos'!$D$5:$D$1504,'Lançamentos'!$B$5:$B$1504,"Despesas financeiras",'Lançamentos'!$E$5:$E$1504,Ano,'Lançamentos'!$F$5:$F$1504,MONTH(B$4)) -> 1153.35 | C17: =SUMIFS('Lançamentos'!$D$5:$D$1504,'Lançamentos'!$B$5:$B$1504,"Despesas financeiras",'Lançamentos'!$E$5:$E$1504,Ano,'Lançamentos'!$F$5:$F$1504,MONTH(C$4)) -> 1107.55 | D17: =SUMIFS('Lançamentos'!$D$5:$D$1504,'Lançamentos'!$B$5:$B$1504,"Despesas financeiras",'Lançamentos'!$E$5:$E$1504,Ano,'Lançamentos'!$F$5:$F$1504,MONTH(D$4)) -> 1266.05 | E17: =SUMIFS('Lançamentos'!$D$5:$D$1504,'Lançamentos'!$B$5:$B$1504,"Despesas financeiras",'Lançamentos'!$E$5:$E$1504,Ano,'Lançamentos'!$F$5:$F$1504,MONTH(E$4)) -> 1157.5 | F17: =SUMIFS('Lançamentos'!$D$5:$D$1504,'Lançamentos'!$B$5:$B$1504,"Despesas financeiras",'Lançamentos'!$E$5:$E$1504,Ano,'Lançamentos'!$F$5:$F$1504,MONTH(F$4)) -> 1151.65 | G17: =SUMIFS('Lançamentos'!$D$5:$D$1504,'Lançamentos'!$B$5:$B$1504,"Despesas financeiras",'Lançamentos'!$E$5:$E$1504,Ano,'Lançamentos'!$F$5:$F$1504,MONTH(G$4)) -> 1494.81 | H17: =SUMIFS('Lançamentos'!$D$5:$D$1504,'Lançamentos'!$B$5:$B$1504,"Despesas financeiras",'Lançamentos'!$E$5:$E$1504,Ano,'Lançamentos'!$F$5:$F$1504,MONTH(H$4)) -> 1410.36 | I17: =SUMIFS('Lançamentos'!$D$5:$D$1504,'Lançamentos'!$B$5:$B$1504,"Despesas financeiras",'Lançamentos'!$E$5:$E$1504,Ano,'Lançamentos'!$F$5:$F$1504,MONTH(I$4)) -> 1226.83 | ... M17: =SUMIFS('Lançamentos'!$D$5:$D$1504,'Lançamentos'!$B$5:$B$1504,"Despesas financeiras",'Lançamentos'!$E$5:$E$1504,Ano,'Lançamentos'!$F$5:$F$1504,MONTH(M$4)) -> 0 | N17: =SUM(B17:M17) -> 11268.91 | O17: =IF($N$5=0,0,N17/$N$5) -> 0.012448925
A18: = RESULTADO ANTES DO IR | B18: =B15+B16-B17 -> -6663.58 | C18: =C15+C16-C17 -> -11840.9 | D18: =D15+D16-D17 -> 3234.16 | E18: =E15+E16-E17 -> 4434.74 | F18: =F15+F16-F17 -> 7465.19 | G18: =G15+G16-G17 -> 12746.6 | H18: =H15+H16-H17 -> 12567.31 | I18: =I15+I16-I17 -> 17052.15 | ... N18: =N15+N16-N17 -> 55519.28 | O18: =IF($N$5=0,0,N18/$N$5) -> 0.061332936
A19: (-) IRPJ / CSLL | B19: =SUMIFS('Lançamentos'!$D$5:$D$1504,'Lançamentos'!$B$5:$B$1504,"IRPJ / CSLL",'Lançamentos'!$E$5:$E$1504,Ano,'Lançamentos'!$F$5:$F$1504,MONTH(B$4)) -> 0 | C19: =SUMIFS('Lançamentos'!$D$5:$D$1504,'Lançamentos'!$B$5:$B$1504,"IRPJ / CSLL",'Lançamentos'!$E$5:$E$1504,Ano,'Lançamentos'!$F$5:$F$1504,MONTH(C$4)) -> 0 | D19: =SUMIFS('Lançamentos'!$D$5:$D$1504,'Lançamentos'!$B$5:$B$1504,"IRPJ / CSLL",'Lançamentos'!$E$5:$E$1504,Ano,'Lançamentos'!$F$5:$F$1504,MONTH(D$4)) -> 0 | E19: =SUMIFS('Lançamentos'!$D$5:$D$1504,'Lançamentos'!$B$5:$B$1504,"IRPJ / CSLL",'Lançamentos'!$E$5:$E$1504,Ano,'Lançamentos'!$F$5:$F$1504,MONTH(E$4)) -> 0 | F19: =SUMIFS('Lançamentos'!$D$5:$D$1504,'Lançamentos'!$B$5:$B$1504,"IRPJ / CSLL",'Lançamentos'!$E$5:$E$1504,Ano,'Lançamentos'!$F$5:$F$1504,MONTH(F$4)) -> 0 | G19: =SUMIFS('Lançamentos'!$D$5:$D$1504,'Lançamentos'!$B$5:$B$1504,"IRPJ / CSLL",'Lançamentos'!$E$5:$E$1504,Ano,'Lançamentos'!$F$5:$F$1504,MONTH(G$4)) -> 0 | H19: =SUMIFS('Lançamentos'!$D$5:$D$1504,'Lançamentos'!$B$5:$B$1504,"IRPJ / CSLL",'Lançamentos'!$E$5:$E$1504,Ano,'Lançamentos'!$F$5:$F$1504,MONTH(H$4)) -> 0 | I19: =SUMIFS('Lançamentos'!$D$5:$D$1504,'Lançamentos'!$B$5:$B$1504,"IRPJ / CSLL",'Lançamentos'!$E$5:$E$1504,Ano,'Lançamentos'!$F$5:$F$1504,MONTH(I$4)) -> 0 | ... M19: =SUMIFS('Lançamentos'!$D$5:$D$1504,'Lançamentos'!$B$5:$B$1504,"IRPJ / CSLL",'Lançamentos'!$E$5:$E$1504,Ano,'Lançamentos'!$F$5:$F$1504,MONTH(M$4)) -> 0 | N19: =SUM(B19:M19) -> 0 | O19: =IF($N$5=0,0,N19/$N$5) -> 0
A20: = LUCRO LÍQUIDO | B20: =B18-B19 -> -6663.58 | C20: =C18-C19 -> -11840.9 | D20: =D18-D19 -> 3234.16 | E20: =E18-E19 -> 4434.74 | F20: =F18-F19 -> 7465.19 | G20: =G18-G19 -> 12746.6 | H20: =H18-H19 -> 12567.31 | I20: =I18-I19 -> 17052.15 | ... N20: =N18-N19 -> 55519.28 | O20: =IF($N$5=0,0,N20/$N$5) -> 0.061332936
A21: Margem líquida (%) | B21: =IF(B5=0,0,B20/B5) -> -0.088795522 | C21: =IF(C5=0,0,C20/C5) -> -0.17968069 | D21: =IF(D5=0,0,D20/D5) -> 0.034632012 | E21: =IF(E5=0,0,E20/E5) -> 0.045983531 | F21: =IF(F5=0,0,F20/F5) -> 0.07139828 | G21: =IF(G5=0,0,G20/G5) -> 0.11222132 | H21: =IF(H5=0,0,H20/H5) -> 0.11309886 | I21: =IF(I5=0,0,I20/I5) -> 0.14084267 | ... N21: =IF(N5=0,0,N20/N5) -> 0.061332936

Sheet Ponto de Equilíbrio
A1: Ponto de Equilíbrio
A2: Quanto precisa faturar para não ter prejuízo e para atingir a meta de lucro. | J2: EXEMPLO - dados fictícios
A4: RECEITA BRUTA NO ANO | C4: LUCRO LÍQUIDO NO ANO | E4: MARGEM LÍQUIDA | G4: MARGEM DE CONTRIBUIÇÃO | I4: PONTO DE EQUILÍBRIO / MÊS
A5: =DRE!N5 -> 905211.51 | C5: =DRE!N20 -> 55519.28 | E5: =DRE!N21 -> 0.061332936 | G5: =DRE!N11 -> 0.5246574 | I5: =IFERROR(C8/G5,0) -> 89074.194
A7: MARGEM DE SEGURANÇA | C7: CUSTOS FIXOS MÉDIOS / MÊS | E7: FATURAMENTO P/ META DE LUCRO | G7: MESES ACIMA DO PE | I7: MESES ABAIXO DO PE
A8: =IF(A5=0,0,1-(I5*COUNTIF(B12:B23,">0"))/A5) -> 0.11438626 | C8: =IFERROR(E24/COUNTIF(B12:B23,">0"),0) -> 46733.436 | E8: =IFERROR((C8+MetaLucro)/G5,0) -> 104322.24 | G8: =COUNTIF(I12:I23,"Acima do PE") -> 7 | I8: =COUNTIF(I12:I23,"ABAIXO do PE") -> 2
A11: Mês | B11: Receita bruta | C11: Margem de contribuição | D11: MC % | E11: Custos fixos | F11: Ponto de equilíbrio (R$) | G11: Receita - PE | H11: Margem de segurança | I11: Situação | J11: Lucro líquido
A12: =DATE(Ano,1,1) -> 46023 | B12: =INDEX(DRE!$B$5:$M$5,MONTH($A12)) -> 75044.1 | C12: =INDEX(DRE!$B$10:$M$10,MONTH($A12)) -> 40246.75 | D12: =IF(B12=0,0,C12/B12) -> 0.53630798 | E12: =INDEX(DRE!$B$12:$M$12,MONTH($A12))+INDEX(DRE!$B$13:$M$13,MONTH($A12))+INDEX(DRE!$B$14:$M$14,MONTH($A12))+INDEX(DRE!$B$17:$M$17,MONTH($A12)) -> 46910.33 | F12: =IF(OR(B12=0,D12<=0),"",E12/D12) -> 87469.013 | G12: =IF(F12="","",B12-F12) -> -12424.913 | H12: =IF(F12="","",G12/B12) -> -0.16556815 | I12: =IF(B12=0,"",IF(F12="","MC negativa",IF(B12>=F12,"Acima do PE","ABAIXO do PE"))) -> ABAIXO do PE | J12: =INDEX(DRE!$B$20:$M$20,MONTH($A12)) -> -6663.58
A13: =DATE(Ano,2,1) -> 46054 | B13: =INDEX(DRE!$B$5:$M$5,MONTH($A13)) -> 65899.68 | C13: =INDEX(DRE!$B$10:$M$10,MONTH($A13)) -> 35130.61 | D13: =IF(B13=0,0,C13/B13) -> 0.53309227 | E13: =INDEX(DRE!$B$12:$M$12,MONTH($A13))+INDEX(DRE!$B$13:$M$13,MONTH($A13))+INDEX(DRE!$B$14:$M$14,MONTH($A13))+INDEX(DRE!$B$17:$M$17,MONTH($A13)) -> 46971.51 | F13: =IF(OR(B13=0,D13<=0),"",E13/D13) -> 88111.407 | G13: =IF(F13="","",B13-F13) -> -22211.727 | H13: =IF(F13="","",G13/B13) -> -0.33705364 | I13: =IF(B13=0,"",IF(F13="","MC negativa",IF(B13>=F13,"Acima do PE","ABAIXO do PE"))) -> ABAIXO do PE | J13: =INDEX(DRE!$B$20:$M$20,MONTH($A13)) -> -11840.9
A14: =DATE(Ano,3,1) -> 46082 | B14: =INDEX(DRE!$B$5:$M$5,MONTH($A14)) -> 93386.43 | C14: =INDEX(DRE!$B$10:$M$10,MONTH($A14)) -> 49084.64 | D14: =IF(B14=0,0,C14/B14) -> 0.52560784 | E14: =INDEX(DRE!$B$12:$M$12,MONTH($A14))+INDEX(DRE!$B$13:$M$13,MONTH($A14))+INDEX(DRE!$B$14:$M$14,MONTH($A14))+INDEX(DRE!$B$17:$M$17,MONTH($A14)) -> 46360.14 | F14: =IF(OR(B14=0,D14<=0),"",E14/D14) -> 88202.908 | G14: =IF(F14="","",B14-F14) -> 5183.5224 | H14: =IF(F14="","",G14/B14) -> 0.055506162 | I14: =IF(B14=0,"",IF(F14="","MC negativa",IF(B14>=F14,"Acima do PE","ABAIXO do PE"))) -> Acima do PE | J14: =INDEX(DRE!$B$20:$M$20,MONTH($A14)) -> 3234.16
A15: =DATE(Ano,4,1) -> 46113 | B15: =INDEX(DRE!$B$5:$M$5,MONTH($A15)) -> 96441.92 | C15: =INDEX(DRE!$B$10:$M$10,MONTH($A15)) -> 51265.55 | D15: =IF(B15=0,0,C15/B15) -> 0.53156916 | E15: =INDEX(DRE!$B$12:$M$12,MONTH($A15))+INDEX(DRE!$B$13:$M$13,MONTH($A15))+INDEX(DRE!$B$14:$M$14,MONTH($A15))+INDEX(DRE!$B$17:$M$17,MONTH($A15)) -> 46830.81 | F15: =IF(OR(B15=0,D15<=0),"",E15/D15) -> 88099.186 | G15: =IF(F15="","",B15-F15) -> 8342.7339 | H15: =IF(F15="","",G15/B15) -> 0.086505265 | I15: =IF(B15=0,"",IF(F15="","MC negativa",IF(B15>=F15,"Acima do PE","ABAIXO do PE"))) -> Acima do PE | J15: =INDEX(DRE!$B$20:$M$20,MONTH($A15)) -> 4434.74
A16: =DATE(Ano,5,1) -> 46143 | B16: =INDEX(DRE!$B$5:$M$5,MONTH($A16)) -> 104557 | C16: =INDEX(DRE!$B$10:$M$10,MONTH($A16)) -> 54331.2 | D16: =IF(B16=0,0,C16/B16) -> 0.51963235 | E16: =INDEX(DRE!$B$12:$M$12,MONTH($A16))+INDEX(DRE!$B$13:$M$13,MONTH($A16))+INDEX(DRE!$B$14:$M$14,MONTH($A16))+INDEX(DRE!$B$17:$M$17,MONTH($A16)) -> 46866.01 | F16: =IF(OR(B16=0,D16<=0),"",E16/D16) -> 90190.708 | G16: =IF(F16="","",B16-F16) -> 14366.292 | H16: =IF(F16="","",G16/B16) -> 0.13740153 | I16: =IF(B16=0,"",IF(F16="","MC negativa",IF(B16>=F16,"Acima do PE","ABAIXO do PE"))) -> Acima do PE | J16: =INDEX(DRE!$B$20:$M$20,MONTH($A16)) -> 7465.19
A17: =DATE(Ano,6,1) -> 46174 | B17: =INDEX(DRE!$B$5:$M$5,MONTH($A17)) -> 113584.48 | C17: =INDEX(DRE!$B$10:$M$10,MONTH($A17)) -> 59146.26 | D17: =IF(B17=0,0,C17/B17) -> 0.52072484 | E17: =INDEX(DRE!$B$12:$M$12,MONTH($A17))+INDEX(DRE!$B$13:$M$13,MONTH($A17))+INDEX(DRE!$B$14:$M$14,MONTH($A17))+INDEX(DRE!$B$17:$M$17,MONTH($A17)) -> 46779.66 | F17: =IF(OR(B17=0,D17<=0),"",E17/D17) -> 89835.661 | G17: =IF(F17="","",B17-F17) -> 23748.819 | H17: =IF(F17="","",G17/B17) -> 0.20908507 | I17: =IF(B17=0,"",IF(F17="","MC negativa",IF(B17>=F17,"Acima do PE","ABAIXO do PE"))) -> Acima do PE | J17: =INDEX(DRE!$B$20:$M$20,MONTH($A17)) -> 12746.6
A18: =DATE(Ano,7,1) -> 46204 | B18: =INDEX(DRE!$B$5:$M$5,MONTH($A18)) -> 111117.92 | C18: =INDEX(DRE!$B$10:$M$10,MONTH($A18)) -> 58583.8 | D18: =IF(B18=0,0,C18/B18) -> 0.52722189 | E18: =INDEX(DRE!$B$12:$M$12,MONTH($A18))+INDEX(DRE!$B$13:$M$13,MONTH($A18))+INDEX(DRE!$B$14:$M$14,MONTH($A18))+INDEX(DRE!$B$17:$M$17,MONTH($A18)) -> 46016.49 | F18: =IF(OR(B18=0,D18<=0),"",E18/D18) -> 87281.068 | G18: =IF(F18="","",B18-F18) -> 23836.852 | H18: =IF(F18="","",G18/B18) -> 0.21451852 | I18: =IF(B18=0,"",IF(F18="","MC negativa",IF(B18>=F18,"Acima do PE","ABAIXO do PE"))) -> Acima do PE | J18: =INDEX(DRE!$B$20:$M$20,MONTH($A18)) -> 12567.31
A19: =DATE(Ano,8,1) -> 46235 | B19: =INDEX(DRE!$B$5:$M$5,MONTH($A19)) -> 121072.33 | C19: =INDEX(DRE!$B$10:$M$10,MONTH($A19)) -> 63957.15 | D19: =IF(B19=0,0,C19/B19) -> 0.52825571 | E19: =INDEX(DRE!$B$12:$M$12,MONTH($A19))+INDEX(DRE!$B$13:$M$13,MONTH($A19))+INDEX(DRE!$B$14:$M$14,MONTH($A19))+INDEX(DRE!$B$17:$M$17,MONTH($A19)) -> 46905 | F19: =IF(OR(B19=0,D19<=0),"",E19/D19) -> 88792.225 | G19: =IF(F19="","",B19-F19) -> 32280.105 | H19: =IF(F19="","",G19/B19) -> 0.26661835 | I19: =IF(B19=0,"",IF(F19="","MC negativa",IF(B19>=F19,"Acima do PE","ABAIXO do PE"))) -> Acima do PE | J19: =INDEX(DRE!$B$20:$M$20,MONTH($A19)) -> 17052.15
A20: =DATE(Ano,9,1) -> 46266 | B20: =INDEX(DRE!$B$5:$M$5,MONTH($A20)) -> 124107.65 | C20: =INDEX(DRE!$B$10:$M$10,MONTH($A20)) -> 63179.96 | D20: =IF(B20=0,0,C20/B20) -> 0.50907386 | E20: =INDEX(DRE!$B$12:$M$12,MONTH($A20))+INDEX(DRE!$B$13:$M$13,MONTH($A20))+INDEX(DRE!$B$14:$M$14,MONTH($A20))+INDEX(DRE!$B$17:$M$17,MONTH($A20)) -> 46960.97 | F20: =IF(OR(B20=0,D20<=0),"",E20/D20) -> 92247.852 | G20: =IF(F20="","",B20-F20) -> 31859.798 | H20: =IF(F20="","",G20/B20) -> 0.25671099 | I20: =IF(B20=0,"",IF(F20="","MC negativa",IF(B20>=F20,"Acima do PE","ABAIXO do PE"))) -> Acima do PE | J20: =INDEX(DRE!$B$20:$M$20,MONTH($A20)) -> 16523.61
A21: =DATE(Ano,10,1) -> 46296 | B21: =INDEX(DRE!$B$5:$M$5,MONTH($A21)) -> 0 | C21: =INDEX(DRE!$B$10:$M$10,MONTH($A21)) -> 0 | D21: =IF(B21=0,0,C21/B21) -> 0 | E21: =INDEX(DRE!$B$12:$M$12,MONTH($A21))+INDEX(DRE!$B$13:$M$13,MONTH($A21))+INDEX(DRE!$B$14:$M$14,MONTH($A21))+INDEX(DRE!$B$17:$M$17,MONTH($A21)) -> 0 | F21: =IF(OR(B21=0,D21<=0),"",E21/D21) | G21: =IF(F21="","",B21-F21) | H21: =IF(F21="","",G21/B21) | I21: =IF(B21=0,"",IF(F21="","MC negativa",IF(B21>=F21,"Acima do PE","ABAIXO do PE"))) | J21: =INDEX(DRE!$B$20:$M$20,MONTH($A21)) -> 0
A22: =DATE(Ano,11,1) -> 46327 | B22: =INDEX(DRE!$B$5:$M$5,MONTH($A22)) -> 0 | C22: =INDEX(DRE!$B$10:$M$10,MONTH($A22)) -> 0 | D22: =IF(B22=0,0,C22/B22) -> 0 | E22: =INDEX(DRE!$B$12:$M$12,MONTH($A22))+INDEX(DRE!$B$13:$M$13,MONTH($A22))+INDEX(DRE!$B$14:$M$14,MONTH($A22))+INDEX(DRE!$B$17:$M$17,MONTH($A22)) -> 0 | F22: =IF(OR(B22=0,D22<=0),"",E22/D22) | G22: =IF(F22="","",B22-F22) | H22: =IF(F22="","",G22/B22) | I22: =IF(B22=0,"",IF(F22="","MC negativa",IF(B22>=F22,"Acima do PE","ABAIXO do PE"))) | J22: =INDEX(DRE!$B$20:$M$20,MONTH($A22)) -> 0
A23: =DATE(Ano,12,1) -> 46357 | B23: =INDEX(DRE!$B$5:$M$5,MONTH($A23)) -> 0 | C23: =INDEX(DRE!$B$10:$M$10,MONTH($A23)) -> 0 | D23: =IF(B23=0,0,C23/B23) -> 0 | E23: =INDEX(DRE!$B$12:$M$12,MONTH($A23))+INDEX(DRE!$B$13:$M$13,MONTH($A23))+INDEX(DRE!$B$14:$M$14,MONTH($A23))+INDEX(DRE!$B$17:$M$17,MONTH($A23)) -> 0 | F23: =IF(OR(B23=0,D23<=0),"",E23/D23) | G23: =IF(F23="","",B23-F23) | H23: =IF(F23="","",G23/B23) | I23: =IF(B23=0,"",IF(F23="","MC negativa",IF(B23>=F23,"Acima do PE","ABAIXO do PE"))) | J23: =INDEX(DRE!$B$20:$M$20,MONTH($A23)) -> 0
A24: Ano | B24: =SUM(B12:B23) -> 905211.51 | C24: =SUM(C12:C23) -> 474925.92 | D24: =IF(B24=0,0,C24/B24) -> 0.5246574 | E24: =SUM(E12:E23) -> 420600.92 | J24: =SUM(J12:J23) -> 55519.28
