Workbook
Name Ano: Config!$C$5
Name CatNome: Config!$B$12:$B$51
Name CatTipo: Config!$C$12:$C$51
Name Contas: Config!$F$12:$F$23
Name Hoje: Config!$C$7
Name MetaReserva: Config!$C$8
Name SaldoIni: Config!$C$6

Sheet Início
A1: Fluxo de Caixa Inteligente
A2: Carvex XLS · Saiba quanto realmente sobra no fim do mês
B4: ESTE É O ARQUIVO DE EXEMPLO: todos os dados são fictícios. Use-o para entender como a planilha funciona e comece a sua pela PLANILHA-LIMPA.xlsx.
B6: O que esta planilha faz
B7: Registre cada entrada e saída (já realizada ou prevista) e a planilha mostra o saldo atual, o saldo projetado mês a mês, se o caixa vai ficar negativo, quantos meses de reserva você tem e para onde vai o seu dinheiro.
B9: Como começar (5 minutos)
B10: 1. Abra a aba Config | C10: Preencha o nome da empresa, o ano de análise e o saldo inicial (quanto havia em caixa + bancos em 1º de janeiro).
B11: 2. Revise as categorias | C11: Na Config, ajuste a lista de categorias ao seu negócio. Cada categoria é de um Tipo (Entrada ou Saída).
B12: 3. Lance os movimentos | C12: Na aba Lançamentos, uma linha por movimento: data, tipo, categoria, descrição, conta, valor e status.
B13: 4. Use Previsto e Realizado | C13: Contas que ainda vão acontecer entram como 'Previsto'. Quando acontecerem, troque para 'Realizado'.
B14: 5. Leia o Dashboard | C14: Veja o saldo atual, o saldo projetado e a coluna Alerta da aba Mensal. Vermelho = atenção.
B16: Mapa das abas (clique para ir)
B17: Config | C17: Dados da empresa, ano, saldo inicial e lista de categorias (você pode renomear e criar categorias).
B18: Lançamentos | C18: Onde você registra TODAS as entradas e saídas (previstas ou realizadas).
B19: Mensal | C19: Relatório mês a mês: entradas, saídas, resultado, saldo realizado e saldo projetado.
B20: Dashboard | C20: Indicadores e gráficos: saldo atual, meses de reserva, maiores despesas.
B22: Legenda de cores
B23: Amarelo | C23: Célula que VOCÊ preenche.
B24: Cinza | C24: Cálculo automático. Não digite aqui.
B25: Verde escuro | C25: Cabeçalho de coluna.
B27: Atenção
B28: • Digite sempre valores POSITIVOS; a planilha usa o campo Tipo para somar ou subtrair.
B29: • Não digite nas células cinza (cálculo automático). Cada linha usa as colunas H a K como apoio.
B30: • A coluna Conferência avisa quando a categoria não combina com o Tipo (ex.: 'Aluguel' marcado como Entrada).
B32: Carvex XLS · Fluxo de Caixa Inteligente · versão 1.0 · Dúvidas: consulte o TUTORIAL.md e o MANUAL.md que acompanham o produto.

Sheet Config
A1: Configurações
A2: Preencha as células amarelas. As categorias alimentam as listas da aba Lançamentos. | F2: EXEMPLO - dados fictícios
B4: Empresa | C4: Empresa Exemplo Ltda
B5: Ano de análise | C5: 2026
B6: Saldo inicial do ano (R$) | C6: 18000
B7: Data de hoje (referência) | C7: 46303 | D7: fixa no exemplo
B8: Meta de reserva (meses de despesas) | C8: 3
B10: Categorias (edite livremente; máximo 40)
B11: Categoria | C11: Tipo | D11: Natureza | F11: Contas (caixa / bancos)
B12: Vendas de produtos | C12: Entrada | D12: Operacional | F12: Caixa
B13: Prestação de serviços | C13: Entrada | D13: Operacional | F13: Banco principal
B14: Outras receitas | C14: Entrada | D14: Não operacional | F14: Maquininha de cartão
B15: Aporte de sócio | C15: Entrada | D15: Não operacional | F15: Poupança / reserva
B16: Empréstimos recebidos | C16: Entrada | D16: Não operacional
B17: Fornecedores / mercadorias | C17: Saída | D17: Variável
B18: Impostos | C18: Saída | D18: Variável
B19: Comissões e taxas | C19: Saída | D19: Variável
B20: Frete e logística | C20: Saída | D20: Variável
B21: Manutenção | C21: Saída | D21: Variável
B22: Folha de pagamento | C22: Saída | D22: Fixo
B23: Aluguel | C23: Saída | D23: Fixo
B24: Energia, água e internet | C24: Saída | D24: Fixo
B25: Marketing | C25: Saída | D25: Fixo
B26: Contador e sistemas | C26: Saída | D26: Fixo
B27: Pró-labore / retiradas | C27: Saída | D27: Pessoal
... B30: Outras despesas | C30: Saída | D30: Variável

Sheet Lançamentos
A1: Lançamentos
A2: Uma linha por entrada ou saída. Valores sempre positivos. Previsto = ainda vai acontecer. | K2: EXEMPLO - dados fictícios
A4: Data | B4: Tipo | C4: Categoria | D4: Descrição | E4: Conta | F4: Valor (R$) | G4: Status | H4: Ano | I4: Mês | J4: Valor líquido | K4: Conferência
A5: 46024 | B5: Entrada | C5: Aporte de sócio | D5: Aporte para capital de giro | E5: Banco principal | F5: 15000 | G5: Realizado | H5: =IF($A5="","",YEAR($A5)) -> 2026 | I5: =IF($A5="","",MONTH($A5)) -> 1 | J5: =IF(OR($A5="",$F5=""),"",IF($B5="Entrada",$F5,-$F5)) -> 15000 | K5: =IF($A5="","",IF(OR($B5="",$C5="",$F5="",$G5=""),"Preencher tudo",IF(IFERROR(INDEX(CatTipo,MATCH($C5,CatNome,0)),"")<>$B5,"Categoria x Tipo?","OK"))) -> OK
A6: 46027 | B6: Saída | C6: Fornecedores / mercadorias | D6: Compra de mercadorias - fornecedor A | E6: Banco principal | F6: 8653.19 | G6: Realizado | H6: =IF($A6="","",YEAR($A6)) -> 2026 | I6: =IF($A6="","",MONTH($A6)) -> 1 | J6: =IF(OR($A6="",$F6=""),"",IF($B6="Entrada",$F6,-$F6)) -> -8653.19 | K6: =IF($A6="","",IF(OR($B6="",$C6="",$F6="",$G6=""),"Preencher tudo",IF(IFERROR(INDEX(CatTipo,MATCH($C6,CatNome,0)),"")<>$B6,"Categoria x Tipo?","OK"))) -> OK
A7: 46027 | B7: Saída | C7: Folha de pagamento | D7: Salários e encargos | E7: Banco principal | F7: 11800 | G7: Realizado | H7: =IF($A7="","",YEAR($A7)) -> 2026 | I7: =IF($A7="","",MONTH($A7)) -> 1 | J7: =IF(OR($A7="",$F7=""),"",IF($B7="Entrada",$F7,-$F7)) -> -11800 | K7: =IF($A7="","",IF(OR($B7="",$C7="",$F7="",$G7=""),"Preencher tudo",IF(IFERROR(INDEX(CatTipo,MATCH($C7,CatNome,0)),"")<>$B7,"Categoria x Tipo?","OK"))) -> OK
A8: 46028 | B8: Saída | C8: Pró-labore / retiradas | D8: Pró-labore do sócio | E8: Banco principal | F8: 6000 | G8: Realizado | H8: =IF($A8="","",YEAR($A8)) -> 2026 | I8: =IF($A8="","",MONTH($A8)) -> 1 | J8: =IF(OR($A8="",$F8=""),"",IF($B8="Entrada",$F8,-$F8)) -> -6000 | K8: =IF($A8="","",IF(OR($B8="",$C8="",$F8="",$G8=""),"Preencher tudo",IF(IFERROR(INDEX(CatTipo,MATCH($C8,CatNome,0)),"")<>$B8,"Categoria x Tipo?","OK"))) -> OK
A9: 46029 | B9: Entrada | C9: Vendas de produtos | D9: Vendas semana 1 | E9: Caixa | F9: 8549.04 | G9: Realizado | H9: =IF($A9="","",YEAR($A9)) -> 2026 | I9: =IF($A9="","",MONTH($A9)) -> 1 | J9: =IF(OR($A9="",$F9=""),"",IF($B9="Entrada",$F9,-$F9)) -> 8549.04 | K9: =IF($A9="","",IF(OR($B9="",$C9="",$F9="",$G9=""),"Preencher tudo",IF(IFERROR(INDEX(CatTipo,MATCH($C9,CatNome,0)),"")<>$B9,"Categoria x Tipo?","OK"))) -> OK
A10: 46030 | B10: Saída | C10: Marketing | D10: Anúncios online | E10: Banco principal | F10: 1641.09 | G10: Realizado | H10: =IF($A10="","",YEAR($A10)) -> 2026 | I10: =IF($A10="","",MONTH($A10)) -> 1 | J10: =IF(OR($A10="",$F10=""),"",IF($B10="Entrada",$F10,-$F10)) -> -1641.09 | K10: =IF($A10="","",IF(OR($B10="",$C10="",$F10="",$G10=""),"Preencher tudo",IF(IFERROR(INDEX(CatTipo,MATCH($C10,CatNome,0)),"")<>$B10,"Categoria x Tipo?","OK"))) -> OK
A11: 46032 | B11: Saída | C11: Aluguel | D11: Aluguel da loja | E11: Banco principal | F11: 4200 | G11: Realizado | H11: =IF($A11="","",YEAR($A11)) -> 2026 | I11: =IF($A11="","",MONTH($A11)) -> 1 | J11: =IF(OR($A11="",$F11=""),"",IF($B11="Entrada",$F11,-$F11)) -> -4200 | K11: =IF($A11="","",IF(OR($B11="",$C11="",$F11="",$G11=""),"Preencher tudo",IF(IFERROR(INDEX(CatTipo,MATCH($C11,CatNome,0)),"")<>$B11,"Categoria x Tipo?","OK"))) -> OK
A12: 46032 | B12: Saída | C12: Empréstimos / financiamentos | D12: Parcela capital de giro | E12: Banco principal | F12: 2100 | G12: Realizado | H12: =IF($A12="","",YEAR($A12)) -> 2026 | I12: =IF($A12="","",MONTH($A12)) -> 1 | J12: =IF(OR($A12="",$F12=""),"",IF($B12="Entrada",$F12,-$F12)) -> -2100 | K12: =IF($A12="","",IF(OR($B12="",$C12="",$F12="",$G12=""),"Preencher tudo",IF(IFERROR(INDEX(CatTipo,MATCH($C12,CatNome,0)),"")<>$B12,"Categoria x Tipo?","OK"))) -> OK
A13: 46034 | B13: Saída | C13: Frete e logística | D13: Fretes de entrega | E13: Banco principal | F13: 897.52 | G13: Realizado | H13: =IF($A13="","",YEAR($A13)) -> 2026 | I13: =IF($A13="","",MONTH($A13)) -> 1 | J13: =IF(OR($A13="",$F13=""),"",IF($B13="Entrada",$F13,-$F13)) -> -897.52 | K13: =IF($A13="","",IF(OR($B13="",$C13="",$F13="",$G13=""),"Preencher tudo",IF(IFERROR(INDEX(CatTipo,MATCH($C13,CatNome,0)),"")<>$B13,"Categoria x Tipo?","OK"))) -> OK
A14: 46036 | B14: Entrada | C14: Vendas de produtos | D14: Vendas semana 2 | E14: Caixa | F14: 11197.17 | G14: Realizado | H14: =IF($A14="","",YEAR($A14)) -> 2026 | I14: =IF($A14="","",MONTH($A14)) -> 1 | J14: =IF(OR($A14="",$F14=""),"",IF($B14="Entrada",$F14,-$F14)) -> 11197.17 | K14: =IF($A14="","",IF(OR($B14="",$C14="",$F14="",$G14=""),"Preencher tudo",IF(IFERROR(INDEX(CatTipo,MATCH($C14,CatNome,0)),"")<>$B14,"Categoria x Tipo?","OK"))) -> OK
A15: 46037 | B15: Entrada | C15: Prestação de serviços | D15: Serviços de instalação | E15: Banco principal | F15: 7353.77 | G15: Realizado | H15: =IF($A15="","",YEAR($A15)) -> 2026 | I15: =IF($A15="","",MONTH($A15)) -> 1 | J15: =IF(OR($A15="",$F15=""),"",IF($B15="Entrada",$F15,-$F15)) -> 7353.77 | K15: =IF($A15="","",IF(OR($B15="",$C15="",$F15="",$G15=""),"Preencher tudo",IF(IFERROR(INDEX(CatTipo,MATCH($C15,CatNome,0)),"")<>$B15,"Categoria x Tipo?","OK"))) -> OK
A16: 46037 | B16: Saída | C16: Energia, água e internet | D16: Contas de consumo | E16: Banco principal | F16: 1409.23 | G16: Realizado | H16: =IF($A16="","",YEAR($A16)) -> 2026 | I16: =IF($A16="","",MONTH($A16)) -> 1 | J16: =IF(OR($A16="",$F16=""),"",IF($B16="Entrada",$F16,-$F16)) -> -1409.23 | K16: =IF($A16="","",IF(OR($B16="",$C16="",$F16="",$G16=""),"Preencher tudo",IF(IFERROR(INDEX(CatTipo,MATCH($C16,CatNome,0)),"")<>$B16,"Categoria x Tipo?","OK"))) -> OK
... A215: 46384 | B215: Entrada | C215: Vendas de produtos | D215: Vendas semana 4 | E215: Caixa | F215: 14372.19 | G215: Previsto | H215: =IF($A215="","",YEAR($A215)) -> 2026 | I215: =IF($A215="","",MONTH($A215)) -> 12 | J215: =IF(OR($A215="",$F215=""),"",IF($B215="Entrada",$F215,-$F215)) -> 14372.19 | K215: =IF($A215="","",IF(OR($B215="",$C215="",$F215="",$G215=""),"Preencher tudo",IF(IFERROR(INDEX(CatTipo,MATCH($C215,CatNome,0)),"")<>$B215,"Categoria x Tipo?","OK"))) -> OK
H216: =IF($A216="","",YEAR($A216)) -> 0 | I216: =IF($A216="","",MONTH($A216)) -> 0 | J216: =IF(OR($A216="",$F216=""),"",IF($B216="Entrada",$F216,-$F216)) -> 0 | K216: =IF($A216="","",IF(OR($B216="",$C216="",$F216="",$G216=""),"Preencher tudo",IF(IFERROR(INDEX(CatTipo,MATCH($C216,CatNome,0)),"")<>$B216,"Categoria x Tipo?","OK"))) -> 0
H217: =IF($A217="","",YEAR($A217)) -> 0 | I217: =IF($A217="","",MONTH($A217)) -> 0 | J217: =IF(OR($A217="",$F217=""),"",IF($B217="Entrada",$F217,-$F217)) -> 0 | K217: =IF($A217="","",IF(OR($B217="",$C217="",$F217="",$G217=""),"Preencher tudo",IF(IFERROR(INDEX(CatTipo,MATCH($C217,CatNome,0)),"")<>$B217,"Categoria x Tipo?","OK"))) -> 0
H218: =IF($A218="","",YEAR($A218)) -> 0 | I218: =IF($A218="","",MONTH($A218)) -> 0 | J218: =IF(OR($A218="",$F218=""),"",IF($B218="Entrada",$F218,-$F218)) -> 0 | K218: =IF($A218="","",IF(OR($B218="",$C218="",$F218="",$G218=""),"Preencher tudo",IF(IFERROR(INDEX(CatTipo,MATCH($C218,CatNome,0)),"")<>$B218,"Categoria x Tipo?","OK"))) -> 0
H219: =IF($A219="","",YEAR($A219)) -> 0 | I219: =IF($A219="","",MONTH($A219)) -> 0 | J219: =IF(OR($A219="",$F219=""),"",IF($B219="Entrada",$F219,-$F219)) -> 0 | K219: =IF($A219="","",IF(OR($B219="",$C219="",$F219="",$G219=""),"Preencher tudo",IF(IFERROR(INDEX(CatTipo,MATCH($C219,CatNome,0)),"")<>$B219,"Categoria x Tipo?","OK"))) -> 0
H220: =IF($A220="","",YEAR($A220)) -> 0 | I220: =IF($A220="","",MONTH($A220)) -> 0 | J220: =IF(OR($A220="",$F220=""),"",IF($B220="Entrada",$F220,-$F220)) -> 0 | K220: =IF($A220="","",IF(OR($B220="",$C220="",$F220="",$G220=""),"Preencher tudo",IF(IFERROR(INDEX(CatTipo,MATCH($C220,CatNome,0)),"")<>$B220,"Categoria x Tipo?","OK"))) -> 0
H221: =IF($A221="","",YEAR($A221)) -> 0 | I221: =IF($A221="","",MONTH($A221)) -> 0 | J221: =IF(OR($A221="",$F221=""),"",IF($B221="Entrada",$F221,-$F221)) -> 0 | K221: =IF($A221="","",IF(OR($B221="",$C221="",$F221="",$G221=""),"Preencher tudo",IF(IFERROR(INDEX(CatTipo,MATCH($C221,CatNome,0)),"")<>$B221,"Categoria x Tipo?","OK"))) -> 0
H222: =IF($A222="","",YEAR($A222)) -> 0 | I222: =IF($A222="","",MONTH($A222)) -> 0 | J222: =IF(OR($A222="",$F222=""),"",IF($B222="Entrada",$F222,-$F222)) -> 0 | K222: =IF($A222="","",IF(OR($B222="",$C222="",$F222="",$G222=""),"Preencher tudo",IF(IFERROR(INDEX(CatTipo,MATCH($C222,CatNome,0)),"")<>$B222,"Categoria x Tipo?","OK"))) -> 0
H223: =IF($A223="","",YEAR($A223)) -> 0 | I223: =IF($A223="","",MONTH($A223)) -> 0 | J223: =IF(OR($A223="",$F223=""),"",IF($B223="Entrada",$F223,-$F223)) -> 0 | K223: =IF($A223="","",IF(OR($B223="",$C223="",$F223="",$G223=""),"Preencher tudo",IF(IFERROR(INDEX(CatTipo,MATCH($C223,CatNome,0)),"")<>$B223,"Categoria x Tipo?","OK"))) -> 0
H224: =IF($A224="","",YEAR($A224)) -> 0 | I224: =IF($A224="","",MONTH($A224)) -> 0 | J224: =IF(OR($A224="",$F224=""),"",IF($B224="Entrada",$F224,-$F224)) -> 0 | K224: =IF($A224="","",IF(OR($B224="",$C224="",$F224="",$G224=""),"Preencher tudo",IF(IFERROR(INDEX(CatTipo,MATCH($C224,CatNome,0)),"")<>$B224,"Categoria x Tipo?","OK"))) -> 0
H225: =IF($A225="","",YEAR($A225)) -> 0 | I225: =IF($A225="","",MONTH($A225)) -> 0 | J225: =IF(OR($A225="",$F225=""),"",IF($B225="Entrada",$F225,-$F225)) -> 0 | K225: =IF($A225="","",IF(OR($B225="",$C225="",$F225="",$G225=""),"Preencher tudo",IF(IFERROR(INDEX(CatTipo,MATCH($C225,CatNome,0)),"")<>$B225,"Categoria x Tipo?","OK"))) -> 0
H226: =IF($A226="","",YEAR($A226)) -> 0 | I226: =IF($A226="","",MONTH($A226)) -> 0 | J226: =IF(OR($A226="",$F226=""),"",IF($B226="Entrada",$F226,-$F226)) -> 0 | K226: =IF($A226="","",IF(OR($B226="",$C226="",$F226="",$G226=""),"Preencher tudo",IF(IFERROR(INDEX(CatTipo,MATCH($C226,CatNome,0)),"")<>$B226,"Categoria x Tipo?","OK"))) -> 0
H227: =IF($A227="","",YEAR($A227)) -> 0 | I227: =IF($A227="","",MONTH($A227)) -> 0 | J227: =IF(OR($A227="",$F227=""),"",IF($B227="Entrada",$F227,-$F227)) -> 0 | K227: =IF($A227="","",IF(OR($B227="",$C227="",$F227="",$G227=""),"Preencher tudo",IF(IFERROR(INDEX(CatTipo,MATCH($C227,CatNome,0)),"")<>$B227,"Categoria x Tipo?","OK"))) -> 0
... H1004: =IF($A1004="","",YEAR($A1004)) -> 0 | I1004: =IF($A1004="","",MONTH($A1004)) -> 0 | J1004: =IF(OR($A1004="",$F1004=""),"",IF($B1004="Entrada",$F1004,-$F1004)) -> 0 | K1004: =IF($A1004="","",IF(OR($B1004="",$C1004="",$F1004="",$G1004=""),"Preencher tudo",IF(IFERROR(INDEX(CatTipo,MATCH($C1004,CatNome,0)),"")<>$B1004,"Categoria x Tipo?","OK"))) -> 0

Sheet Mensal
A1: Relatório mensal
A2: Realizado x Previsto. O saldo projetado soma o que já aconteceu com o que ainda vai acontecer. | K2: EXEMPLO - dados fictícios
A4: Mês | B4: Entradas realizadas | C4: Saídas realizadas | D4: Resultado do mês | E4: Saldo realizado (fim do mês) | F4: Entradas previstas | G4: Saídas previstas | H4: Resultado projetado | I4: Saldo projetado (fim do mês) | J4: Margem realizada | K4: Alerta
A5: =DATE(Ano,1,1) -> 46023 | B5: =SUMIFS('Lançamentos'!$F$5:$F$1004,'Lançamentos'!$B$5:$B$1004,"Entrada",'Lançamentos'!$G$5:$G$1004,"Realizado",'Lançamentos'!$H$5:$H$1004,Ano,'Lançamentos'!$I$5:$I$1004,MONTH($A5)) -> 63989.77 | C5: =SUMIFS('Lançamentos'!$F$5:$F$1004,'Lançamentos'!$B$5:$B$1004,"Saída",'Lançamentos'!$G$5:$G$1004,"Realizado",'Lançamentos'!$H$5:$H$1004,Ano,'Lançamentos'!$I$5:$I$1004,MONTH($A5)) -> 46233.09 | D5: =B5-C5 -> 17756.68 | E5: =SaldoIni+D5 -> 35756.68 | F5: =SUMIFS('Lançamentos'!$F$5:$F$1004,'Lançamentos'!$B$5:$B$1004,"Entrada",'Lançamentos'!$G$5:$G$1004,"Previsto",'Lançamentos'!$H$5:$H$1004,Ano,'Lançamentos'!$I$5:$I$1004,MONTH($A5)) -> 0 | G5: =SUMIFS('Lançamentos'!$F$5:$F$1004,'Lançamentos'!$B$5:$B$1004,"Saída",'Lançamentos'!$G$5:$G$1004,"Previsto",'Lançamentos'!$H$5:$H$1004,Ano,'Lançamentos'!$I$5:$I$1004,MONTH($A5)) -> 0 | H5: =(B5+F5)-(C5+G5) -> 17756.68 | I5: =SaldoIni+H5 -> 35756.68 | J5: =IF(B5=0,"",D5/B5) -> 0.27749248 | K5: =IF(I5<0,"SALDO NEGATIVO",IF(H5<0,"Mês no vermelho","OK")) -> OK
A6: =DATE(Ano,2,1) -> 46054 | B6: =SUMIFS('Lançamentos'!$F$5:$F$1004,'Lançamentos'!$B$5:$B$1004,"Entrada",'Lançamentos'!$G$5:$G$1004,"Realizado",'Lançamentos'!$H$5:$H$1004,Ano,'Lançamentos'!$I$5:$I$1004,MONTH($A6)) -> 40254.31 | C6: =SUMIFS('Lançamentos'!$F$5:$F$1004,'Lançamentos'!$B$5:$B$1004,"Saída",'Lançamentos'!$G$5:$G$1004,"Realizado",'Lançamentos'!$H$5:$H$1004,Ano,'Lançamentos'!$I$5:$I$1004,MONTH($A6)) -> 46696.98 | D6: =B6-C6 -> -6442.67 | E6: =E5+D6 -> 29314.01 | F6: =SUMIFS('Lançamentos'!$F$5:$F$1004,'Lançamentos'!$B$5:$B$1004,"Entrada",'Lançamentos'!$G$5:$G$1004,"Previsto",'Lançamentos'!$H$5:$H$1004,Ano,'Lançamentos'!$I$5:$I$1004,MONTH($A6)) -> 0 | G6: =SUMIFS('Lançamentos'!$F$5:$F$1004,'Lançamentos'!$B$5:$B$1004,"Saída",'Lançamentos'!$G$5:$G$1004,"Previsto",'Lançamentos'!$H$5:$H$1004,Ano,'Lançamentos'!$I$5:$I$1004,MONTH($A6)) -> 0 | H6: =(B6+F6)-(C6+G6) -> -6442.67 | I6: =I5+H6 -> 29314.01 | J6: =IF(B6=0,"",D6/B6) -> -0.1600492 | K6: =IF(I6<0,"SALDO NEGATIVO",IF(H6<0,"Mês no vermelho","OK")) -> Mês no vermelho
A7: =DATE(Ano,3,1) -> 46082 | B7: =SUMIFS('Lançamentos'!$F$5:$F$1004,'Lançamentos'!$B$5:$B$1004,"Entrada",'Lançamentos'!$G$5:$G$1004,"Realizado",'Lançamentos'!$H$5:$H$1004,Ano,'Lançamentos'!$I$5:$I$1004,MONTH($A7)) -> 53321.93 | C7: =SUMIFS('Lançamentos'!$F$5:$F$1004,'Lançamentos'!$B$5:$B$1004,"Saída",'Lançamentos'!$G$5:$G$1004,"Realizado",'Lançamentos'!$H$5:$H$1004,Ano,'Lançamentos'!$I$5:$I$1004,MONTH($A7)) -> 47533.36 | D7: =B7-C7 -> 5788.57 | E7: =E6+D7 -> 35102.58 | F7: =SUMIFS('Lançamentos'!$F$5:$F$1004,'Lançamentos'!$B$5:$B$1004,"Entrada",'Lançamentos'!$G$5:$G$1004,"Previsto",'Lançamentos'!$H$5:$H$1004,Ano,'Lançamentos'!$I$5:$I$1004,MONTH($A7)) -> 0 | G7: =SUMIFS('Lançamentos'!$F$5:$F$1004,'Lançamentos'!$B$5:$B$1004,"Saída",'Lançamentos'!$G$5:$G$1004,"Previsto",'Lançamentos'!$H$5:$H$1004,Ano,'Lançamentos'!$I$5:$I$1004,MONTH($A7)) -> 0 | H7: =(B7+F7)-(C7+G7) -> 5788.57 | I7: =I6+H7 -> 35102.58 | J7: =IF(B7=0,"",D7/B7) -> 0.1085589 | K7: =IF(I7<0,"SALDO NEGATIVO",IF(H7<0,"Mês no vermelho","OK")) -> OK
A8: =DATE(Ano,4,1) -> 46113 | B8: =SUMIFS('Lançamentos'!$F$5:$F$1004,'Lançamentos'!$B$5:$B$1004,"Entrada",'Lançamentos'!$G$5:$G$1004,"Realizado",'Lançamentos'!$H$5:$H$1004,Ano,'Lançamentos'!$I$5:$I$1004,MONTH($A8)) -> 58002.05 | C8: =SUMIFS('Lançamentos'!$F$5:$F$1004,'Lançamentos'!$B$5:$B$1004,"Saída",'Lançamentos'!$G$5:$G$1004,"Realizado",'Lançamentos'!$H$5:$H$1004,Ano,'Lançamentos'!$I$5:$I$1004,MONTH($A8)) -> 53111.75 | D8: =B8-C8 -> 4890.3 | E8: =E7+D8 -> 39992.88 | F8: =SUMIFS('Lançamentos'!$F$5:$F$1004,'Lançamentos'!$B$5:$B$1004,"Entrada",'Lançamentos'!$G$5:$G$1004,"Previsto",'Lançamentos'!$H$5:$H$1004,Ano,'Lançamentos'!$I$5:$I$1004,MONTH($A8)) -> 0 | G8: =SUMIFS('Lançamentos'!$F$5:$F$1004,'Lançamentos'!$B$5:$B$1004,"Saída",'Lançamentos'!$G$5:$G$1004,"Previsto",'Lançamentos'!$H$5:$H$1004,Ano,'Lançamentos'!$I$5:$I$1004,MONTH($A8)) -> 0 | H8: =(B8+F8)-(C8+G8) -> 4890.3 | I8: =I7+H8 -> 39992.88 | J8: =IF(B8=0,"",D8/B8) -> 0.084312537 | K8: =IF(I8<0,"SALDO NEGATIVO",IF(H8<0,"Mês no vermelho","OK")) -> OK
A9: =DATE(Ano,5,1) -> 46143 | B9: =SUMIFS('Lançamentos'!$F$5:$F$1004,'Lançamentos'!$B$5:$B$1004,"Entrada",'Lançamentos'!$G$5:$G$1004,"Realizado",'Lançamentos'!$H$5:$H$1004,Ano,'Lançamentos'!$I$5:$I$1004,MONTH($A9)) -> 60390.1 | C9: =SUMIFS('Lançamentos'!$F$5:$F$1004,'Lançamentos'!$B$5:$B$1004,"Saída",'Lançamentos'!$G$5:$G$1004,"Realizado",'Lançamentos'!$H$5:$H$1004,Ano,'Lançamentos'!$I$5:$I$1004,MONTH($A9)) -> 50394.22 | D9: =B9-C9 -> 9995.88 | E9: =E8+D9 -> 49988.76 | F9: =SUMIFS('Lançamentos'!$F$5:$F$1004,'Lançamentos'!$B$5:$B$1004,"Entrada",'Lançamentos'!$G$5:$G$1004,"Previsto",'Lançamentos'!$H$5:$H$1004,Ano,'Lançamentos'!$I$5:$I$1004,MONTH($A9)) -> 0 | G9: =SUMIFS('Lançamentos'!$F$5:$F$1004,'Lançamentos'!$B$5:$B$1004,"Saída",'Lançamentos'!$G$5:$G$1004,"Previsto",'Lançamentos'!$H$5:$H$1004,Ano,'Lançamentos'!$I$5:$I$1004,MONTH($A9)) -> 0 | H9: =(B9+F9)-(C9+G9) -> 9995.88 | I9: =I8+H9 -> 49988.76 | J9: =IF(B9=0,"",D9/B9) -> 0.16552183 | K9: =IF(I9<0,"SALDO NEGATIVO",IF(H9<0,"Mês no vermelho","OK")) -> OK
A10: =DATE(Ano,6,1) -> 46174 | B10: =SUMIFS('Lançamentos'!$F$5:$F$1004,'Lançamentos'!$B$5:$B$1004,"Entrada",'Lançamentos'!$G$5:$G$1004,"Realizado",'Lançamentos'!$H$5:$H$1004,Ano,'Lançamentos'!$I$5:$I$1004,MONTH($A10)) -> 54820.79 | C10: =SUMIFS('Lançamentos'!$F$5:$F$1004,'Lançamentos'!$B$5:$B$1004,"Saída",'Lançamentos'!$G$5:$G$1004,"Realizado",'Lançamentos'!$H$5:$H$1004,Ano,'Lançamentos'!$I$5:$I$1004,MONTH($A10)) -> 48052.49 | D10: =B10-C10 -> 6768.3 | E10: =E9+D10 -> 56757.06 | F10: =SUMIFS('Lançamentos'!$F$5:$F$1004,'Lançamentos'!$B$5:$B$1004,"Entrada",'Lançamentos'!$G$5:$G$1004,"Previsto",'Lançamentos'!$H$5:$H$1004,Ano,'Lançamentos'!$I$5:$I$1004,MONTH($A10)) -> 0 | G10: =SUMIFS('Lançamentos'!$F$5:$F$1004,'Lançamentos'!$B$5:$B$1004,"Saída",'Lançamentos'!$G$5:$G$1004,"Previsto",'Lançamentos'!$H$5:$H$1004,Ano,'Lançamentos'!$I$5:$I$1004,MONTH($A10)) -> 0 | H10: =(B10+F10)-(C10+G10) -> 6768.3 | I10: =I9+H10 -> 56757.06 | J10: =IF(B10=0,"",D10/B10) -> 0.12346229 | K10: =IF(I10<0,"SALDO NEGATIVO",IF(H10<0,"Mês no vermelho","OK")) -> OK
A11: =DATE(Ano,7,1) -> 46204 | B11: =SUMIFS('Lançamentos'!$F$5:$F$1004,'Lançamentos'!$B$5:$B$1004,"Entrada",'Lançamentos'!$G$5:$G$1004,"Realizado",'Lançamentos'!$H$5:$H$1004,Ano,'Lançamentos'!$I$5:$I$1004,MONTH($A11)) -> 58286.86 | C11: =SUMIFS('Lançamentos'!$F$5:$F$1004,'Lançamentos'!$B$5:$B$1004,"Saída",'Lançamentos'!$G$5:$G$1004,"Realizado",'Lançamentos'!$H$5:$H$1004,Ano,'Lançamentos'!$I$5:$I$1004,MONTH($A11)) -> 49515.01 | D11: =B11-C11 -> 8771.85 | E11: =E10+D11 -> 65528.91 | F11: =SUMIFS('Lançamentos'!$F$5:$F$1004,'Lançamentos'!$B$5:$B$1004,"Entrada",'Lançamentos'!$G$5:$G$1004,"Previsto",'Lançamentos'!$H$5:$H$1004,Ano,'Lançamentos'!$I$5:$I$1004,MONTH($A11)) -> 0 | G11: =SUMIFS('Lançamentos'!$F$5:$F$1004,'Lançamentos'!$B$5:$B$1004,"Saída",'Lançamentos'!$G$5:$G$1004,"Previsto",'Lançamentos'!$H$5:$H$1004,Ano,'Lançamentos'!$I$5:$I$1004,MONTH($A11)) -> 0 | H11: =(B11+F11)-(C11+G11) -> 8771.85 | I11: =I10+H11 -> 65528.91 | J11: =IF(B11=0,"",D11/B11) -> 0.15049447 | K11: =IF(I11<0,"SALDO NEGATIVO",IF(H11<0,"Mês no vermelho","OK")) -> OK
A12: =DATE(Ano,8,1) -> 46235 | B12: =SUMIFS('Lançamentos'!$F$5:$F$1004,'Lançamentos'!$B$5:$B$1004,"Entrada",'Lançamentos'!$G$5:$G$1004,"Realizado",'Lançamentos'!$H$5:$H$1004,Ano,'Lançamentos'!$I$5:$I$1004,MONTH($A12)) -> 63824.33 | C12: =SUMIFS('Lançamentos'!$F$5:$F$1004,'Lançamentos'!$B$5:$B$1004,"Saída",'Lançamentos'!$G$5:$G$1004,"Realizado",'Lançamentos'!$H$5:$H$1004,Ano,'Lançamentos'!$I$5:$I$1004,MONTH($A12)) -> 49937.95 | D12: =B12-C12 -> 13886.38 | E12: =E11+D12 -> 79415.29 | F12: =SUMIFS('Lançamentos'!$F$5:$F$1004,'Lançamentos'!$B$5:$B$1004,"Entrada",'Lançamentos'!$G$5:$G$1004,"Previsto",'Lançamentos'!$H$5:$H$1004,Ano,'Lançamentos'!$I$5:$I$1004,MONTH($A12)) -> 0 | G12: =SUMIFS('Lançamentos'!$F$5:$F$1004,'Lançamentos'!$B$5:$B$1004,"Saída",'Lançamentos'!$G$5:$G$1004,"Previsto",'Lançamentos'!$H$5:$H$1004,Ano,'Lançamentos'!$I$5:$I$1004,MONTH($A12)) -> 0 | H12: =(B12+F12)-(C12+G12) -> 13886.38 | I12: =I11+H12 -> 79415.29 | J12: =IF(B12=0,"",D12/B12) -> 0.21757189 | K12: =IF(I12<0,"SALDO NEGATIVO",IF(H12<0,"Mês no vermelho","OK")) -> OK
A13: =DATE(Ano,9,1) -> 46266 | B13: =SUMIFS('Lançamentos'!$F$5:$F$1004,'Lançamentos'!$B$5:$B$1004,"Entrada",'Lançamentos'!$G$5:$G$1004,"Realizado",'Lançamentos'!$H$5:$H$1004,Ano,'Lançamentos'!$I$5:$I$1004,MONTH($A13)) -> 62682.3 | C13: =SUMIFS('Lançamentos'!$F$5:$F$1004,'Lançamentos'!$B$5:$B$1004,"Saída",'Lançamentos'!$G$5:$G$1004,"Realizado",'Lançamentos'!$H$5:$H$1004,Ano,'Lançamentos'!$I$5:$I$1004,MONTH($A13)) -> 52393.47 | D13: =B13-C13 -> 10288.83 | E13: =E12+D13 -> 89704.12 | F13: =SUMIFS('Lançamentos'!$F$5:$F$1004,'Lançamentos'!$B$5:$B$1004,"Entrada",'Lançamentos'!$G$5:$G$1004,"Previsto",'Lançamentos'!$H$5:$H$1004,Ano,'Lançamentos'!$I$5:$I$1004,MONTH($A13)) -> 0 | G13: =SUMIFS('Lançamentos'!$F$5:$F$1004,'Lançamentos'!$B$5:$B$1004,"Saída",'Lançamentos'!$G$5:$G$1004,"Previsto",'Lançamentos'!$H$5:$H$1004,Ano,'Lançamentos'!$I$5:$I$1004,MONTH($A13)) -> 0 | H13: =(B13+F13)-(C13+G13) -> 10288.83 | I13: =I12+H13 -> 89704.12 | J13: =IF(B13=0,"",D13/B13) -> 0.16414251 | K13: =IF(I13<0,"SALDO NEGATIVO",IF(H13<0,"Mês no vermelho","OK")) -> OK
A14: =DATE(Ano,10,1) -> 46296 | B14: =SUMIFS('Lançamentos'!$F$5:$F$1004,'Lançamentos'!$B$5:$B$1004,"Entrada",'Lançamentos'!$G$5:$G$1004,"Realizado",'Lançamentos'!$H$5:$H$1004,Ano,'Lançamentos'!$I$5:$I$1004,MONTH($A14)) -> 11498.85 | C14: =SUMIFS('Lançamentos'!$F$5:$F$1004,'Lançamentos'!$B$5:$B$1004,"Saída",'Lançamentos'!$G$5:$G$1004,"Realizado",'Lançamentos'!$H$5:$H$1004,Ano,'Lançamentos'!$I$5:$I$1004,MONTH($A14)) -> 29820.96 | D14: =B14-C14 -> -18322.11 | E14: =E13+D14 -> 71382.01 | F14: =SUMIFS('Lançamentos'!$F$5:$F$1004,'Lançamentos'!$B$5:$B$1004,"Entrada",'Lançamentos'!$G$5:$G$1004,"Previsto",'Lançamentos'!$H$5:$H$1004,Ano,'Lançamentos'!$I$5:$I$1004,MONTH($A14)) -> 50073.07 | G14: =SUMIFS('Lançamentos'!$F$5:$F$1004,'Lançamentos'!$B$5:$B$1004,"Saída",'Lançamentos'!$G$5:$G$1004,"Previsto",'Lançamentos'!$H$5:$H$1004,Ano,'Lançamentos'!$I$5:$I$1004,MONTH($A14)) -> 19667.6 | H14: =(B14+F14)-(C14+G14) -> 12083.36 | I14: =I13+H14 -> 101787.48 | J14: =IF(B14=0,"",D14/B14) -> -1.5933863 | K14: =IF(I14<0,"SALDO NEGATIVO",IF(H14<0,"Mês no vermelho","OK")) -> OK
A15: =DATE(Ano,11,1) -> 46327 | B15: =SUMIFS('Lançamentos'!$F$5:$F$1004,'Lançamentos'!$B$5:$B$1004,"Entrada",'Lançamentos'!$G$5:$G$1004,"Realizado",'Lançamentos'!$H$5:$H$1004,Ano,'Lançamentos'!$I$5:$I$1004,MONTH($A15)) -> 0 | C15: =SUMIFS('Lançamentos'!$F$5:$F$1004,'Lançamentos'!$B$5:$B$1004,"Saída",'Lançamentos'!$G$5:$G$1004,"Realizado",'Lançamentos'!$H$5:$H$1004,Ano,'Lançamentos'!$I$5:$I$1004,MONTH($A15)) -> 0 | D15: =B15-C15 -> 0 | E15: =E14+D15 -> 71382.01 | F15: =SUMIFS('Lançamentos'!$F$5:$F$1004,'Lançamentos'!$B$5:$B$1004,"Entrada",'Lançamentos'!$G$5:$G$1004,"Previsto",'Lançamentos'!$H$5:$H$1004,Ano,'Lançamentos'!$I$5:$I$1004,MONTH($A15)) -> 66691.59 | G15: =SUMIFS('Lançamentos'!$F$5:$F$1004,'Lançamentos'!$B$5:$B$1004,"Saída",'Lançamentos'!$G$5:$G$1004,"Previsto",'Lançamentos'!$H$5:$H$1004,Ano,'Lançamentos'!$I$5:$I$1004,MONTH($A15)) -> 57906.61 | H15: =(B15+F15)-(C15+G15) -> 8784.98 | I15: =I14+H15 -> 110572.46 | J15: =IF(B15=0,"",D15/B15) -> 0 | K15: =IF(I15<0,"SALDO NEGATIVO",IF(H15<0,"Mês no vermelho","OK")) -> OK
A16: =DATE(Ano,12,1) -> 46357 | B16: =SUMIFS('Lançamentos'!$F$5:$F$1004,'Lançamentos'!$B$5:$B$1004,"Entrada",'Lançamentos'!$G$5:$G$1004,"Realizado",'Lançamentos'!$H$5:$H$1004,Ano,'Lançamentos'!$I$5:$I$1004,MONTH($A16)) -> 0 | C16: =SUMIFS('Lançamentos'!$F$5:$F$1004,'Lançamentos'!$B$5:$B$1004,"Saída",'Lançamentos'!$G$5:$G$1004,"Realizado",'Lançamentos'!$H$5:$H$1004,Ano,'Lançamentos'!$I$5:$I$1004,MONTH($A16)) -> 0 | D16: =B16-C16 -> 0 | E16: =E15+D16 -> 71382.01 | F16: =SUMIFS('Lançamentos'!$F$5:$F$1004,'Lançamentos'!$B$5:$B$1004,"Entrada",'Lançamentos'!$G$5:$G$1004,"Previsto",'Lançamentos'!$H$5:$H$1004,Ano,'Lançamentos'!$I$5:$I$1004,MONTH($A16)) -> 71261.99 | G16: =SUMIFS('Lançamentos'!$F$5:$F$1004,'Lançamentos'!$B$5:$B$1004,"Saída",'Lançamentos'!$G$5:$G$1004,"Previsto",'Lançamentos'!$H$5:$H$1004,Ano,'Lançamentos'!$I$5:$I$1004,MONTH($A16)) -> 56660.81 | H16: =(B16+F16)-(C16+G16) -> 14601.18 | I16: =I15+H16 -> 125173.64 | J16: =IF(B16=0,"",D16/B16) -> 0 | K16: =IF(I16<0,"SALDO NEGATIVO",IF(H16<0,"Mês no vermelho","OK")) -> OK
A17: Total | B17: =SUM(B5:B16) -> 527071.29 | C17: =SUM(C5:C16) -> 473689.28 | D17: =SUM(D5:D16) -> 53382.01 | E17: =E16 -> 71382.01 | F17: =SUM(F5:F16) -> 188026.65 | G17: =SUM(G5:G16) -> 134235.02 | H17: =SUM(H5:H16) -> 107173.64 | I17: =I16 -> 125173.64 | J17: =IF(B17=0,"",D17/B17) -> 0.10128044
A19: Como ler: 'Saldo realizado' só considera o que já aconteceu. 'Saldo projetado' inclui o que está Previsto. Se o projetado ficar negativo em algum mês, aja antes: antecipe recebimentos, renegocie prazos ou reduza gastos.

Sheet Calc
A1: Categoria | B1: Tipo | C1: Saída realizada no ano | D1: Chave de ordenação
A2: =IF(Config!B12="","",Config!B12) -> Vendas de produtos | B2: =IF(Config!C12="","",Config!C12) -> Entrada | C2: =IF(A2="",0,IF(B2<>"Saída",0,SUMIFS('Lançamentos'!$F$5:$F$1004,'Lançamentos'!$C$5:$C$1004,A2,'Lançamentos'!$B$5:$B$1004,"Saída",'Lançamentos'!$G$5:$G$1004,"Realizado",'Lançamentos'!$H$5:$H$1004,Ano))) -> 0 | D2: =IF(C2>0,C2+ROW()/1000000000,"") -> 0
A3: =IF(Config!B13="","",Config!B13) -> Prestação de serviços | B3: =IF(Config!C13="","",Config!C13) -> Entrada | C3: =IF(A3="",0,IF(B3<>"Saída",0,SUMIFS('Lançamentos'!$F$5:$F$1004,'Lançamentos'!$C$5:$C$1004,A3,'Lançamentos'!$B$5:$B$1004,"Saída",'Lançamentos'!$G$5:$G$1004,"Realizado",'Lançamentos'!$H$5:$H$1004,Ano))) -> 0 | D3: =IF(C3>0,C3+ROW()/1000000000,"") -> 0
A4: =IF(Config!B14="","",Config!B14) -> Outras receitas | B4: =IF(Config!C14="","",Config!C14) -> Entrada | C4: =IF(A4="",0,IF(B4<>"Saída",0,SUMIFS('Lançamentos'!$F$5:$F$1004,'Lançamentos'!$C$5:$C$1004,A4,'Lançamentos'!$B$5:$B$1004,"Saída",'Lançamentos'!$G$5:$G$1004,"Realizado",'Lançamentos'!$H$5:$H$1004,Ano))) -> 0 | D4: =IF(C4>0,C4+ROW()/1000000000,"") -> 0
A5: =IF(Config!B15="","",Config!B15) -> Aporte de sócio | B5: =IF(Config!C15="","",Config!C15) -> Entrada | C5: =IF(A5="",0,IF(B5<>"Saída",0,SUMIFS('Lançamentos'!$F$5:$F$1004,'Lançamentos'!$C$5:$C$1004,A5,'Lançamentos'!$B$5:$B$1004,"Saída",'Lançamentos'!$G$5:$G$1004,"Realizado",'Lançamentos'!$H$5:$H$1004,Ano))) -> 0 | D5: =IF(C5>0,C5+ROW()/1000000000,"") -> 0
A6: =IF(Config!B16="","",Config!B16) -> Empréstimos recebidos | B6: =IF(Config!C16="","",Config!C16) -> Entrada | C6: =IF(A6="",0,IF(B6<>"Saída",0,SUMIFS('Lançamentos'!$F$5:$F$1004,'Lançamentos'!$C$5:$C$1004,A6,'Lançamentos'!$B$5:$B$1004,"Saída",'Lançamentos'!$G$5:$G$1004,"Realizado",'Lançamentos'!$H$5:$H$1004,Ano))) -> 0 | D6: =IF(C6>0,C6+ROW()/1000000000,"") -> 0
A7: =IF(Config!B17="","",Config!B17) -> Fornecedores / mercadorias | B7: =IF(Config!C17="","",Config!C17) -> Saída | C7: =IF(A7="",0,IF(B7<>"Saída",0,SUMIFS('Lançamentos'!$F$5:$F$1004,'Lançamentos'!$C$5:$C$1004,A7,'Lançamentos'!$B$5:$B$1004,"Saída",'Lançamentos'!$G$5:$G$1004,"Realizado",'Lançamentos'!$H$5:$H$1004,Ano))) -> 144480.97 | D7: =IF(C7>0,C7+ROW()/1000000000,"") -> 144480.97
A8: =IF(Config!B18="","",Config!B18) -> Impostos | B8: =IF(Config!C18="","",Config!C18) -> Saída | C8: =IF(A8="",0,IF(B8<>"Saída",0,SUMIFS('Lançamentos'!$F$5:$F$1004,'Lançamentos'!$C$5:$C$1004,A8,'Lançamentos'!$B$5:$B$1004,"Saída",'Lançamentos'!$G$5:$G$1004,"Realizado",'Lançamentos'!$H$5:$H$1004,Ano))) -> 23927.92 | D8: =IF(C8>0,C8+ROW()/1000000000,"") -> 23927.92
A9: =IF(Config!B19="","",Config!B19) -> Comissões e taxas | B9: =IF(Config!C19="","",Config!C19) -> Saída | C9: =IF(A9="",0,IF(B9<>"Saída",0,SUMIFS('Lançamentos'!$F$5:$F$1004,'Lançamentos'!$C$5:$C$1004,A9,'Lançamentos'!$B$5:$B$1004,"Saída",'Lançamentos'!$G$5:$G$1004,"Realizado",'Lançamentos'!$H$5:$H$1004,Ano))) -> 11754.08 | D9: =IF(C9>0,C9+ROW()/1000000000,"") -> 11754.08
A10: =IF(Config!B20="","",Config!B20) -> Frete e logística | B10: =IF(Config!C20="","",Config!C20) -> Saída | C10: =IF(A10="",0,IF(B10<>"Saída",0,SUMIFS('Lançamentos'!$F$5:$F$1004,'Lançamentos'!$C$5:$C$1004,A10,'Lançamentos'!$B$5:$B$1004,"Saída",'Lançamentos'!$G$5:$G$1004,"Realizado",'Lançamentos'!$H$5:$H$1004,Ano))) -> 9760.37 | D10: =IF(C10>0,C10+ROW()/1000000000,"") -> 9760.37
A11: =IF(Config!B21="","",Config!B21) -> Manutenção | B11: =IF(Config!C21="","",Config!C21) -> Saída | C11: =IF(A11="",0,IF(B11<>"Saída",0,SUMIFS('Lançamentos'!$F$5:$F$1004,'Lançamentos'!$C$5:$C$1004,A11,'Lançamentos'!$B$5:$B$1004,"Saída",'Lançamentos'!$G$5:$G$1004,"Realizado",'Lançamentos'!$H$5:$H$1004,Ano))) -> 3312.85 | D11: =IF(C11>0,C11+ROW()/1000000000,"") -> 3312.85
A12: =IF(Config!B22="","",Config!B22) -> Folha de pagamento | B12: =IF(Config!C22="","",Config!C22) -> Saída | C12: =IF(A12="",0,IF(B12<>"Saída",0,SUMIFS('Lançamentos'!$F$5:$F$1004,'Lançamentos'!$C$5:$C$1004,A12,'Lançamentos'!$B$5:$B$1004,"Saída",'Lançamentos'!$G$5:$G$1004,"Realizado",'Lançamentos'!$H$5:$H$1004,Ano))) -> 118000 | D12: =IF(C12>0,C12+ROW()/1000000000,"") -> 118000
A13: =IF(Config!B23="","",Config!B23) -> Aluguel | B13: =IF(Config!C23="","",Config!C23) -> Saída | C13: =IF(A13="",0,IF(B13<>"Saída",0,SUMIFS('Lançamentos'!$F$5:$F$1004,'Lançamentos'!$C$5:$C$1004,A13,'Lançamentos'!$B$5:$B$1004,"Saída",'Lançamentos'!$G$5:$G$1004,"Realizado",'Lançamentos'!$H$5:$H$1004,Ano))) -> 37800 | D13: =IF(C13>0,C13+ROW()/1000000000,"") -> 37800
... A41: =IF(Config!B51="","",Config!B51) -> 0 | B41: =IF(Config!C51="","",Config!C51) -> 0 | C41: =IF(A41="",0,IF(B41<>"Saída",0,SUMIFS('Lançamentos'!$F$5:$F$1004,'Lançamentos'!$C$5:$C$1004,A41,'Lançamentos'!$B$5:$B$1004,"Saída",'Lançamentos'!$G$5:$G$1004,"Realizado",'Lançamentos'!$H$5:$H$1004,Ano))) -> 0 | D41: =IF(C41>0,C41+ROW()/1000000000,"") -> 0

Sheet Dashboard
A1: Dashboard
A2: Visão rápida da saúde financeira. Atualiza sozinho conforme você lança. | L2: EXEMPLO - dados fictícios
A4: SALDO ATUAL (realizado) | D4: ENTRADAS NO ANO | G4: SAÍDAS NO ANO | J4: RESULTADO NO ANO
A5: =SaldoIni+SUMIFS('Lançamentos'!$J$5:$J$1004,'Lançamentos'!$G$5:$G$1004,"Realizado",'Lançamentos'!$H$5:$H$1004,Ano) -> 71382.01 | D5: =Mensal!B17 -> 527071.29 | G5: =Mensal!C17 -> 473689.28 | J5: =Mensal!D17 -> 53382.01
A7: MARGEM NO ANO | D7: SALDO PROJETADO (dez) | G7: MESES DE RESERVA | J7: SITUAÇÃO DA RESERVA
A8: =IF(Mensal!B17=0,0,Mensal!D17/Mensal!B17) -> 0.10128044 | D8: =Mensal!I16 -> 125173.64 | G8: =IFERROR(A5/(Mensal!C17/MAX(1,COUNTIF(Mensal!C5:C16,">0"))),0) -> 1.5069374 | J8: =IF(G8>=MetaReserva,"Reserva saudável",IF(G8>=1,"Abaixo da meta","CRÍTICO: <1 mês")) -> Abaixo da meta
A10: Maiores saídas do ano (realizado)
A11: # | B11: Categoria | D11: Valor | E11: % das saídas | F11: chave
A12: 1 | B12: =IF(F12="","",INDEX(Calc!$A$2:$A$41,MATCH(F12,Calc!$D$2:$D$41,0))) -> Fornecedores / mercadorias | D12: =IF(F12="","",ROUND(F12,2)) -> 144480.97 | E12: =IF(OR(F12="",Mensal!$C$17=0),"",D12/Mensal!$C$17) -> 0.30501212 | F12: =IFERROR(LARGE(Calc!$D$2:$D$41,1),"") -> 144480.97
A13: 2 | B13: =IF(F13="","",INDEX(Calc!$A$2:$A$41,MATCH(F13,Calc!$D$2:$D$41,0))) -> Folha de pagamento | D13: =IF(F13="","",ROUND(F13,2)) -> 118000 | E13: =IF(OR(F13="",Mensal!$C$17=0),"",D13/Mensal!$C$17) -> 0.24910845 | F13: =IFERROR(LARGE(Calc!$D$2:$D$41,2),"") -> 118000
A14: 3 | B14: =IF(F14="","",INDEX(Calc!$A$2:$A$41,MATCH(F14,Calc!$D$2:$D$41,0))) -> Pró-labore / retiradas | D14: =IF(F14="","",ROUND(F14,2)) -> 60000 | E14: =IF(OR(F14="",Mensal!$C$17=0),"",D14/Mensal!$C$17) -> 0.12666531 | F14: =IFERROR(LARGE(Calc!$D$2:$D$41,3),"") -> 60000
A15: 4 | B15: =IF(F15="","",INDEX(Calc!$A$2:$A$41,MATCH(F15,Calc!$D$2:$D$41,0))) -> Aluguel | D15: =IF(F15="","",ROUND(F15,2)) -> 37800 | E15: =IF(OR(F15="",Mensal!$C$17=0),"",D15/Mensal!$C$17) -> 0.079799146 | F15: =IFERROR(LARGE(Calc!$D$2:$D$41,4),"") -> 37800
A16: 5 | B16: =IF(F16="","",INDEX(Calc!$A$2:$A$41,MATCH(F16,Calc!$D$2:$D$41,0))) -> Impostos | D16: =IF(F16="","",ROUND(F16,2)) -> 23927.92 | E16: =IF(OR(F16="",Mensal!$C$17=0),"",D16/Mensal!$C$17) -> 0.050513957 | F16: =IFERROR(LARGE(Calc!$D$2:$D$41,5),"") -> 23927.92
A17: 6 | B17: =IF(F17="","",INDEX(Calc!$A$2:$A$41,MATCH(F17,Calc!$D$2:$D$41,0))) -> Empréstimos / financiamentos | D17: =IF(F17="","",ROUND(F17,2)) -> 18900 | E17: =IF(OR(F17="",Mensal!$C$17=0),"",D17/Mensal!$C$17) -> 0.039899573 | F17: =IFERROR(LARGE(Calc!$D$2:$D$41,6),"") -> 18900
A18: 7 | B18: =IF(F18="","",INDEX(Calc!$A$2:$A$41,MATCH(F18,Calc!$D$2:$D$41,0))) -> Marketing | D18: =IF(F18="","",ROUND(F18,2)) -> 16008.25 | E18: =IF(OR(F18="",Mensal!$C$17=0),"",D18/Mensal!$C$17) -> 0.033794833 | F18: =IFERROR(LARGE(Calc!$D$2:$D$41,7),"") -> 16008.25
A19: 8 | B19: =IF(F19="","",INDEX(Calc!$A$2:$A$41,MATCH(F19,Calc!$D$2:$D$41,0))) -> Contador e sistemas | D19: =IF(F19="","",ROUND(F19,2)) -> 12150 | E19: =IF(OR(F19="",Mensal!$C$17=0),"",D19/Mensal!$C$17) -> 0.025649725 | F19: =IFERROR(LARGE(Calc!$D$2:$D$41,8),"") -> 12150
