Workbook
Name Ano: Config!$C$8
Name CatPrato: Config!$F$5:$F$16
Name CMVMeta: Config!$C$5
Name ImpTaxa: Config!$C$6
Name InsBruto: Insumos!$G$5:$G$304
Name InsNome: Insumos!$B$5:$B$304
Name InsUnid: Insumos!$C$5:$C$304
Name InsUtil: Insumos!$H$5:$H$304
Name MCmed: Calc!$B$2
Name MesRef: Config!$C$7
Name Motivos: Config!$G$5:$G$16
Name NPratos: Calc!$B$1
Name PratoCusto: Pratos!$G$5:$G$104
Name PratoNome: Pratos!$A$5:$A$104
Name PratoQtd: Pratos!$E$5:$E$104
Name Unidades: Config!$E$5:$E$16

Sheet Início
A1: Ficha Técnica e CMV
A2: Carvex XLS · Saiba quanto custa cada prato e onde seu dinheiro está sumindo
B4: O que esta planilha faz
B5: Cadastre seus insumos e monte a ficha técnica de cada prato. A planilha calcula o custo por porção, o CMV de cada prato, o preço sugerido para atingir sua meta, classifica o cardápio (estrela, burro de carga, quebra-cabeça e cão) e compara o CMV real do mês com o CMV teórico.
B7: Como começar (5 minutos)
B8: 1. Config | C8: Informe a meta de CMV (ex.: 32%), impostos e taxas sobre a venda e o mês de referência.
B9: 2. Cadastre os insumos | C9: Em Insumos: preço da embalagem, quantidade que vem nela e o fator de correção (perda na limpeza, quando houver).
B10: 3. Cadastre os pratos | C10: Em Pratos: nome, rendimento (porções), preço de venda e quantidade vendida no mês.
B11: 4. Monte as fichas | C11: Em Fichas: para cada prato, liste os insumos e a quantidade LÍQUIDA que vai em 1 receita.
B12: 5. Feche o mês | C12: Em CMV Mensal, informe estoque inicial, compras, estoque final e receita. Compare com o CMV teórico e registre o desperdício.
B14: Mapa das abas (clique para ir)
B15: Config | C15: Meta de CMV, impostos/taxas, mês de referência e listas.
B16: Insumos | C16: Preço e custo útil de cada ingrediente.
B17: Pratos | C17: Custo, CMV, preço sugerido e classificação de cada prato.
B18: Fichas | C18: Receitas: insumos e quantidades de cada prato.
B19: CMV Mensal | C19: CMV real x teórico e perdas por mês.
B20: Desperdício | C20: Registro diário de perdas por motivo.
B21: Dashboard | C21: Indicadores, piores pratos e gráficos.
B23: Legenda de cores
B24: Amarelo | C24: Célula que VOCÊ preenche.
B25: Cinza | C25: Cálculo automático. Não digite aqui.
B26: Verde escuro | C26: Cabeçalho de coluna.
B28: Atenção
B29: • Use SEMPRE a mesma unidade do insumo na ficha (se o insumo é em kg, informe 0,150 para 150 g).
B30: • Fator de correção = peso bruto / peso líquido. Ex.: 1 kg de frango rende 870 g limpos: FC = 1,15. Sem perda, deixe 1.
B31: • CMV real = (estoque inicial + compras - estoque final) / receita. Faça contagem física do estoque no 1º dia do mês.
B33: Carvex XLS · Ficha Técnica e CMV para Restaurantes · versão 1.0 · Dúvidas: consulte o TUTORIAL.md e o MANUAL.md que acompanham o produto.

Sheet Config
A1: Configurações
A2: Preencha as células amarelas.
B4: Restaurante | E4: Unidades | F4: Categorias de prato | G4: Motivos de desperdício
B5: Meta de CMV (% da venda) | C5: 0.32 | E5: kg | F5: Pratos principais | G5: Vencimento
B6: Impostos + taxas sobre a venda (%) | E6: g | F6: Lanches | G6: Erro de preparo
B7: Mês de referência (1º dia do mês) | E7: L | F7: Porções | G7: Sobra de produção
B8: Ano do CMV mensal | C8: 2026 | E8: ml | F8: Sobremesas | G8: Queda / quebra
B9: Dica: CMV saudável costuma ficar entre 25% e 40% do faturamento, conforme o tipo de operação. | E9: un | F9: Bebidas | G9: Devolução do cliente
E10: dz | F10: Entradas | G10: Outros
E11: pct

Sheet Insumos
A1: Insumos (ingredientes)
A2: Atualize o preço sempre que o fornecedor reajustar: todas as fichas recalculam sozinhas.
A4: Código | B4: Insumo | C4: Unidade | D4: Preço da embalagem (R$) | E4: Qtd na embalagem | F4: Fator de correção (FC) | G4: Custo por unidade (bruto) | H4: Custo por unidade ÚTIL | I4: Atualizado em
G5: =IF(OR($B5="",$D5="",N($E5)<=0),"",$D5/$E5) -> 0 | H5: =IF($G5="","",$G5*IF($F5="",1,$F5)) -> 0
G6: =IF(OR($B6="",$D6="",N($E6)<=0),"",$D6/$E6) -> 0 | H6: =IF($G6="","",$G6*IF($F6="",1,$F6)) -> 0
G7: =IF(OR($B7="",$D7="",N($E7)<=0),"",$D7/$E7) -> 0 | H7: =IF($G7="","",$G7*IF($F7="",1,$F7)) -> 0
G8: =IF(OR($B8="",$D8="",N($E8)<=0),"",$D8/$E8) -> 0 | H8: =IF($G8="","",$G8*IF($F8="",1,$F8)) -> 0
G9: =IF(OR($B9="",$D9="",N($E9)<=0),"",$D9/$E9) -> 0 | H9: =IF($G9="","",$G9*IF($F9="",1,$F9)) -> 0
G10: =IF(OR($B10="",$D10="",N($E10)<=0),"",$D10/$E10) -> 0 | H10: =IF($G10="","",$G10*IF($F10="",1,$F10)) -> 0
G11: =IF(OR($B11="",$D11="",N($E11)<=0),"",$D11/$E11) -> 0 | H11: =IF($G11="","",$G11*IF($F11="",1,$F11)) -> 0
G12: =IF(OR($B12="",$D12="",N($E12)<=0),"",$D12/$E12) -> 0 | H12: =IF($G12="","",$G12*IF($F12="",1,$F12)) -> 0
G13: =IF(OR($B13="",$D13="",N($E13)<=0),"",$D13/$E13) -> 0 | H13: =IF($G13="","",$G13*IF($F13="",1,$F13)) -> 0
G14: =IF(OR($B14="",$D14="",N($E14)<=0),"",$D14/$E14) -> 0 | H14: =IF($G14="","",$G14*IF($F14="",1,$F14)) -> 0
G15: =IF(OR($B15="",$D15="",N($E15)<=0),"",$D15/$E15) -> 0 | H15: =IF($G15="","",$G15*IF($F15="",1,$F15)) -> 0
G16: =IF(OR($B16="",$D16="",N($E16)<=0),"",$D16/$E16) -> 0 | H16: =IF($G16="","",$G16*IF($F16="",1,$F16)) -> 0
... G304: =IF(OR($B304="",$D304="",N($E304)<=0),"",$D304/$E304) -> 0 | H304: =IF($G304="","",$G304*IF($F304="",1,$F304)) -> 0

Sheet Fichas
A1: Fichas técnicas (receitas)
A2: Uma linha por insumo de cada prato. Quantidade LÍQUIDA, na unidade do insumo.
A4: Prato | B4: Insumo | C4: Quantidade na receita | D4: Observação | E4: Unidade | F4: Custo útil unitário | G4: Custo do item | H4: Conferência
E5: =IF($B5="","",IFERROR(INDEX(InsUnid,MATCH($B5,InsNome,0)),"")) -> 0 | F5: =IF($B5="","",IFERROR(INDEX(InsUtil,MATCH($B5,InsNome,0)),"")) -> 0 | G5: =IF(OR($A5="",$C5="",$F5=""),"",$C5*$F5) -> 0 | H5: =IF($A5="","",IF($B5="","Escolha o insumo",IF($F5="","Insumo sem custo",IF(COUNTIF(PratoNome,$A5)=0,"Prato não cadastrado",IF($C5="","Falta quantidade","OK"))))) -> 0
E6: =IF($B6="","",IFERROR(INDEX(InsUnid,MATCH($B6,InsNome,0)),"")) -> 0 | F6: =IF($B6="","",IFERROR(INDEX(InsUtil,MATCH($B6,InsNome,0)),"")) -> 0 | G6: =IF(OR($A6="",$C6="",$F6=""),"",$C6*$F6) -> 0 | H6: =IF($A6="","",IF($B6="","Escolha o insumo",IF($F6="","Insumo sem custo",IF(COUNTIF(PratoNome,$A6)=0,"Prato não cadastrado",IF($C6="","Falta quantidade","OK"))))) -> 0
E7: =IF($B7="","",IFERROR(INDEX(InsUnid,MATCH($B7,InsNome,0)),"")) -> 0 | F7: =IF($B7="","",IFERROR(INDEX(InsUtil,MATCH($B7,InsNome,0)),"")) -> 0 | G7: =IF(OR($A7="",$C7="",$F7=""),"",$C7*$F7) -> 0 | H7: =IF($A7="","",IF($B7="","Escolha o insumo",IF($F7="","Insumo sem custo",IF(COUNTIF(PratoNome,$A7)=0,"Prato não cadastrado",IF($C7="","Falta quantidade","OK"))))) -> 0
E8: =IF($B8="","",IFERROR(INDEX(InsUnid,MATCH($B8,InsNome,0)),"")) -> 0 | F8: =IF($B8="","",IFERROR(INDEX(InsUtil,MATCH($B8,InsNome,0)),"")) -> 0 | G8: =IF(OR($A8="",$C8="",$F8=""),"",$C8*$F8) -> 0 | H8: =IF($A8="","",IF($B8="","Escolha o insumo",IF($F8="","Insumo sem custo",IF(COUNTIF(PratoNome,$A8)=0,"Prato não cadastrado",IF($C8="","Falta quantidade","OK"))))) -> 0
E9: =IF($B9="","",IFERROR(INDEX(InsUnid,MATCH($B9,InsNome,0)),"")) -> 0 | F9: =IF($B9="","",IFERROR(INDEX(InsUtil,MATCH($B9,InsNome,0)),"")) -> 0 | G9: =IF(OR($A9="",$C9="",$F9=""),"",$C9*$F9) -> 0 | H9: =IF($A9="","",IF($B9="","Escolha o insumo",IF($F9="","Insumo sem custo",IF(COUNTIF(PratoNome,$A9)=0,"Prato não cadastrado",IF($C9="","Falta quantidade","OK"))))) -> 0
E10: =IF($B10="","",IFERROR(INDEX(InsUnid,MATCH($B10,InsNome,0)),"")) -> 0 | F10: =IF($B10="","",IFERROR(INDEX(InsUtil,MATCH($B10,InsNome,0)),"")) -> 0 | G10: =IF(OR($A10="",$C10="",$F10=""),"",$C10*$F10) -> 0 | H10: =IF($A10="","",IF($B10="","Escolha o insumo",IF($F10="","Insumo sem custo",IF(COUNTIF(PratoNome,$A10)=0,"Prato não cadastrado",IF($C10="","Falta quantidade","OK"))))) -> 0
E11: =IF($B11="","",IFERROR(INDEX(InsUnid,MATCH($B11,InsNome,0)),"")) -> 0 | F11: =IF($B11="","",IFERROR(INDEX(InsUtil,MATCH($B11,InsNome,0)),"")) -> 0 | G11: =IF(OR($A11="",$C11="",$F11=""),"",$C11*$F11) -> 0 | H11: =IF($A11="","",IF($B11="","Escolha o insumo",IF($F11="","Insumo sem custo",IF(COUNTIF(PratoNome,$A11)=0,"Prato não cadastrado",IF($C11="","Falta quantidade","OK"))))) -> 0
E12: =IF($B12="","",IFERROR(INDEX(InsUnid,MATCH($B12,InsNome,0)),"")) -> 0 | F12: =IF($B12="","",IFERROR(INDEX(InsUtil,MATCH($B12,InsNome,0)),"")) -> 0 | G12: =IF(OR($A12="",$C12="",$F12=""),"",$C12*$F12) -> 0 | H12: =IF($A12="","",IF($B12="","Escolha o insumo",IF($F12="","Insumo sem custo",IF(COUNTIF(PratoNome,$A12)=0,"Prato não cadastrado",IF($C12="","Falta quantidade","OK"))))) -> 0
E13: =IF($B13="","",IFERROR(INDEX(InsUnid,MATCH($B13,InsNome,0)),"")) -> 0 | F13: =IF($B13="","",IFERROR(INDEX(InsUtil,MATCH($B13,InsNome,0)),"")) -> 0 | G13: =IF(OR($A13="",$C13="",$F13=""),"",$C13*$F13) -> 0 | H13: =IF($A13="","",IF($B13="","Escolha o insumo",IF($F13="","Insumo sem custo",IF(COUNTIF(PratoNome,$A13)=0,"Prato não cadastrado",IF($C13="","Falta quantidade","OK"))))) -> 0
E14: =IF($B14="","",IFERROR(INDEX(InsUnid,MATCH($B14,InsNome,0)),"")) -> 0 | F14: =IF($B14="","",IFERROR(INDEX(InsUtil,MATCH($B14,InsNome,0)),"")) -> 0 | G14: =IF(OR($A14="",$C14="",$F14=""),"",$C14*$F14) -> 0 | H14: =IF($A14="","",IF($B14="","Escolha o insumo",IF($F14="","Insumo sem custo",IF(COUNTIF(PratoNome,$A14)=0,"Prato não cadastrado",IF($C14="","Falta quantidade","OK"))))) -> 0
E15: =IF($B15="","",IFERROR(INDEX(InsUnid,MATCH($B15,InsNome,0)),"")) -> 0 | F15: =IF($B15="","",IFERROR(INDEX(InsUtil,MATCH($B15,InsNome,0)),"")) -> 0 | G15: =IF(OR($A15="",$C15="",$F15=""),"",$C15*$F15) -> 0 | H15: =IF($A15="","",IF($B15="","Escolha o insumo",IF($F15="","Insumo sem custo",IF(COUNTIF(PratoNome,$A15)=0,"Prato não cadastrado",IF($C15="","Falta quantidade","OK"))))) -> 0
E16: =IF($B16="","",IFERROR(INDEX(InsUnid,MATCH($B16,InsNome,0)),"")) -> 0 | F16: =IF($B16="","",IFERROR(INDEX(InsUtil,MATCH($B16,InsNome,0)),"")) -> 0 | G16: =IF(OR($A16="",$C16="",$F16=""),"",$C16*$F16) -> 0 | H16: =IF($A16="","",IF($B16="","Escolha o insumo",IF($F16="","Insumo sem custo",IF(COUNTIF(PratoNome,$A16)=0,"Prato não cadastrado",IF($C16="","Falta quantidade","OK"))))) -> 0
... E804: =IF($B804="","",IFERROR(INDEX(InsUnid,MATCH($B804,InsNome,0)),"")) -> 0 | F804: =IF($B804="","",IFERROR(INDEX(InsUtil,MATCH($B804,InsNome,0)),"")) -> 0 | G804: =IF(OR($A804="",$C804="",$F804=""),"",$C804*$F804) -> 0 | H804: =IF($A804="","",IF($B804="","Escolha o insumo",IF($F804="","Insumo sem custo",IF(COUNTIF(PratoNome,$A804)=0,"Prato não cadastrado",IF($C804="","Falta quantidade","OK"))))) -> 0

Sheet Pratos
A1: Pratos: custo, CMV e engenharia de cardápio
A2: Preencha as colunas amarelas. O custo vem das fichas.
A4: Prato | B4: Categoria | C4: Rendimento (porções) | D4: Preço de venda (R$) | E4: Qtd vendida no mês | F4: Custo total da receita | G4: CUSTO POR PORÇÃO | H4: CMV % | I4: Status vs meta | J4: Preço sugerido (pela meta) | K4: Margem de contribuição (R$) | L4: Lucro total no mês | M4: Mix de vendas | N4: Classe do cardápio | O4: O que fazer | P4: Chave
F5: =IF($A5="","",SUMIFS(Fichas!$G$5:$G$804,Fichas!$A$5:$A$804,$A5)) -> 0 | G5: =IF(OR($A5="",N($F5)=0),"",$F5/IF(N($C5)>0,$C5,1)) -> 0 | H5: =IF(OR($G5="",N($D5)<=0),"",$G5/$D5) -> 0 | I5: =IF($A5="","",IF($G5="","Sem ficha",IF($H5="","Sem preço",IF($H5>CMVMeta,"ACIMA DA META","OK")))) -> 0 | J5: =IF($G5="","",ROUNDUP($G5/CMVMeta,0)+IF(ROUNDUP($G5/CMVMeta,0)-0.1>=$G5/CMVMeta,-0.1,0.9)) -> 0 | K5: =IF(OR($G5="",N($D5)<=0),"",$D5-$G5-$D5*ImpTaxa) -> 0 | L5: =IF(OR($K5="",N($E5)<=0),"",$K5*$E5) -> 0 | M5: =IF(OR($A5="",N($E5)<=0),"",$E5/SUM($E$5:$E$104)) -> 0 | N5: =IF(OR($M5="",$K5=""),"",IF($M5>=0.7/NPratos,IF($K5>=MCmed,"Estrela","Burro de carga"),IF($K5>=MCmed,"Quebra-cabeça","Cão"))) -> 0 | O5: =IF($N5="","",IF($N5="Estrela","Manter e destacar no cardápio",IF($N5="Burro de carga","Subir preço ou reduzir custo",IF($N5="Quebra-cabeça","Divulgar e sugerir ao cliente","Reformular ou retirar")))) -> 0 | P5: =IF($H5="","",$H5+ROW()/1000000000) -> 0
F6: =IF($A6="","",SUMIFS(Fichas!$G$5:$G$804,Fichas!$A$5:$A$804,$A6)) -> 0 | G6: =IF(OR($A6="",N($F6)=0),"",$F6/IF(N($C6)>0,$C6,1)) -> 0 | H6: =IF(OR($G6="",N($D6)<=0),"",$G6/$D6) -> 0 | I6: =IF($A6="","",IF($G6="","Sem ficha",IF($H6="","Sem preço",IF($H6>CMVMeta,"ACIMA DA META","OK")))) -> 0 | J6: =IF($G6="","",ROUNDUP($G6/CMVMeta,0)+IF(ROUNDUP($G6/CMVMeta,0)-0.1>=$G6/CMVMeta,-0.1,0.9)) -> 0 | K6: =IF(OR($G6="",N($D6)<=0),"",$D6-$G6-$D6*ImpTaxa) -> 0 | L6: =IF(OR($K6="",N($E6)<=0),"",$K6*$E6) -> 0 | M6: =IF(OR($A6="",N($E6)<=0),"",$E6/SUM($E$5:$E$104)) -> 0 | N6: =IF(OR($M6="",$K6=""),"",IF($M6>=0.7/NPratos,IF($K6>=MCmed,"Estrela","Burro de carga"),IF($K6>=MCmed,"Quebra-cabeça","Cão"))) -> 0 | O6: =IF($N6="","",IF($N6="Estrela","Manter e destacar no cardápio",IF($N6="Burro de carga","Subir preço ou reduzir custo",IF($N6="Quebra-cabeça","Divulgar e sugerir ao cliente","Reformular ou retirar")))) -> 0 | P6: =IF($H6="","",$H6+ROW()/1000000000) -> 0
F7: =IF($A7="","",SUMIFS(Fichas!$G$5:$G$804,Fichas!$A$5:$A$804,$A7)) -> 0 | G7: =IF(OR($A7="",N($F7)=0),"",$F7/IF(N($C7)>0,$C7,1)) -> 0 | H7: =IF(OR($G7="",N($D7)<=0),"",$G7/$D7) -> 0 | I7: =IF($A7="","",IF($G7="","Sem ficha",IF($H7="","Sem preço",IF($H7>CMVMeta,"ACIMA DA META","OK")))) -> 0 | J7: =IF($G7="","",ROUNDUP($G7/CMVMeta,0)+IF(ROUNDUP($G7/CMVMeta,0)-0.1>=$G7/CMVMeta,-0.1,0.9)) -> 0 | K7: =IF(OR($G7="",N($D7)<=0),"",$D7-$G7-$D7*ImpTaxa) -> 0 | L7: =IF(OR($K7="",N($E7)<=0),"",$K7*$E7) -> 0 | M7: =IF(OR($A7="",N($E7)<=0),"",$E7/SUM($E$5:$E$104)) -> 0 | N7: =IF(OR($M7="",$K7=""),"",IF($M7>=0.7/NPratos,IF($K7>=MCmed,"Estrela","Burro de carga"),IF($K7>=MCmed,"Quebra-cabeça","Cão"))) -> 0 | O7: =IF($N7="","",IF($N7="Estrela","Manter e destacar no cardápio",IF($N7="Burro de carga","Subir preço ou reduzir custo",IF($N7="Quebra-cabeça","Divulgar e sugerir ao cliente","Reformular ou retirar")))) -> 0 | P7: =IF($H7="","",$H7+ROW()/1000000000) -> 0
F8: =IF($A8="","",SUMIFS(Fichas!$G$5:$G$804,Fichas!$A$5:$A$804,$A8)) -> 0 | G8: =IF(OR($A8="",N($F8)=0),"",$F8/IF(N($C8)>0,$C8,1)) -> 0 | H8: =IF(OR($G8="",N($D8)<=0),"",$G8/$D8) -> 0 | I8: =IF($A8="","",IF($G8="","Sem ficha",IF($H8="","Sem preço",IF($H8>CMVMeta,"ACIMA DA META","OK")))) -> 0 | J8: =IF($G8="","",ROUNDUP($G8/CMVMeta,0)+IF(ROUNDUP($G8/CMVMeta,0)-0.1>=$G8/CMVMeta,-0.1,0.9)) -> 0 | K8: =IF(OR($G8="",N($D8)<=0),"",$D8-$G8-$D8*ImpTaxa) -> 0 | L8: =IF(OR($K8="",N($E8)<=0),"",$K8*$E8) -> 0 | M8: =IF(OR($A8="",N($E8)<=0),"",$E8/SUM($E$5:$E$104)) -> 0 | N8: =IF(OR($M8="",$K8=""),"",IF($M8>=0.7/NPratos,IF($K8>=MCmed,"Estrela","Burro de carga"),IF($K8>=MCmed,"Quebra-cabeça","Cão"))) -> 0 | O8: =IF($N8="","",IF($N8="Estrela","Manter e destacar no cardápio",IF($N8="Burro de carga","Subir preço ou reduzir custo",IF($N8="Quebra-cabeça","Divulgar e sugerir ao cliente","Reformular ou retirar")))) -> 0 | P8: =IF($H8="","",$H8+ROW()/1000000000) -> 0
F9: =IF($A9="","",SUMIFS(Fichas!$G$5:$G$804,Fichas!$A$5:$A$804,$A9)) -> 0 | G9: =IF(OR($A9="",N($F9)=0),"",$F9/IF(N($C9)>0,$C9,1)) -> 0 | H9: =IF(OR($G9="",N($D9)<=0),"",$G9/$D9) -> 0 | I9: =IF($A9="","",IF($G9="","Sem ficha",IF($H9="","Sem preço",IF($H9>CMVMeta,"ACIMA DA META","OK")))) -> 0 | J9: =IF($G9="","",ROUNDUP($G9/CMVMeta,0)+IF(ROUNDUP($G9/CMVMeta,0)-0.1>=$G9/CMVMeta,-0.1,0.9)) -> 0 | K9: =IF(OR($G9="",N($D9)<=0),"",$D9-$G9-$D9*ImpTaxa) -> 0 | L9: =IF(OR($K9="",N($E9)<=0),"",$K9*$E9) -> 0 | M9: =IF(OR($A9="",N($E9)<=0),"",$E9/SUM($E$5:$E$104)) -> 0 | N9: =IF(OR($M9="",$K9=""),"",IF($M9>=0.7/NPratos,IF($K9>=MCmed,"Estrela","Burro de carga"),IF($K9>=MCmed,"Quebra-cabeça","Cão"))) -> 0 | O9: =IF($N9="","",IF($N9="Estrela","Manter e destacar no cardápio",IF($N9="Burro de carga","Subir preço ou reduzir custo",IF($N9="Quebra-cabeça","Divulgar e sugerir ao cliente","Reformular ou retirar")))) -> 0 | P9: =IF($H9="","",$H9+ROW()/1000000000) -> 0
F10: =IF($A10="","",SUMIFS(Fichas!$G$5:$G$804,Fichas!$A$5:$A$804,$A10)) -> 0 | G10: =IF(OR($A10="",N($F10)=0),"",$F10/IF(N($C10)>0,$C10,1)) -> 0 | H10: =IF(OR($G10="",N($D10)<=0),"",$G10/$D10) -> 0 | I10: =IF($A10="","",IF($G10="","Sem ficha",IF($H10="","Sem preço",IF($H10>CMVMeta,"ACIMA DA META","OK")))) -> 0 | J10: =IF($G10="","",ROUNDUP($G10/CMVMeta,0)+IF(ROUNDUP($G10/CMVMeta,0)-0.1>=$G10/CMVMeta,-0.1,0.9)) -> 0 | K10: =IF(OR($G10="",N($D10)<=0),"",$D10-$G10-$D10*ImpTaxa) -> 0 | L10: =IF(OR($K10="",N($E10)<=0),"",$K10*$E10) -> 0 | M10: =IF(OR($A10="",N($E10)<=0),"",$E10/SUM($E$5:$E$104)) -> 0 | N10: =IF(OR($M10="",$K10=""),"",IF($M10>=0.7/NPratos,IF($K10>=MCmed,"Estrela","Burro de carga"),IF($K10>=MCmed,"Quebra-cabeça","Cão"))) -> 0 | O10: =IF($N10="","",IF($N10="Estrela","Manter e destacar no cardápio",IF($N10="Burro de carga","Subir preço ou reduzir custo",IF($N10="Quebra-cabeça","Divulgar e sugerir ao cliente","Reformular ou retirar")))) -> 0 | P10: =IF($H10="","",$H10+ROW()/1000000000) -> 0
F11: =IF($A11="","",SUMIFS(Fichas!$G$5:$G$804,Fichas!$A$5:$A$804,$A11)) -> 0 | G11: =IF(OR($A11="",N($F11)=0),"",$F11/IF(N($C11)>0,$C11,1)) -> 0 | H11: =IF(OR($G11="",N($D11)<=0),"",$G11/$D11) -> 0 | I11: =IF($A11="","",IF($G11="","Sem ficha",IF($H11="","Sem preço",IF($H11>CMVMeta,"ACIMA DA META","OK")))) -> 0 | J11: =IF($G11="","",ROUNDUP($G11/CMVMeta,0)+IF(ROUNDUP($G11/CMVMeta,0)-0.1>=$G11/CMVMeta,-0.1,0.9)) -> 0 | K11: =IF(OR($G11="",N($D11)<=0),"",$D11-$G11-$D11*ImpTaxa) -> 0 | L11: =IF(OR($K11="",N($E11)<=0),"",$K11*$E11) -> 0 | M11: =IF(OR($A11="",N($E11)<=0),"",$E11/SUM($E$5:$E$104)) -> 0 | N11: =IF(OR($M11="",$K11=""),"",IF($M11>=0.7/NPratos,IF($K11>=MCmed,"Estrela","Burro de carga"),IF($K11>=MCmed,"Quebra-cabeça","Cão"))) -> 0 | O11: =IF($N11="","",IF($N11="Estrela","Manter e destacar no cardápio",IF($N11="Burro de carga","Subir preço ou reduzir custo",IF($N11="Quebra-cabeça","Divulgar e sugerir ao cliente","Reformular ou retirar")))) -> 0 | P11: =IF($H11="","",$H11+ROW()/1000000000) -> 0
F12: =IF($A12="","",SUMIFS(Fichas!$G$5:$G$804,Fichas!$A$5:$A$804,$A12)) -> 0 | G12: =IF(OR($A12="",N($F12)=0),"",$F12/IF(N($C12)>0,$C12,1)) -> 0 | H12: =IF(OR($G12="",N($D12)<=0),"",$G12/$D12) -> 0 | I12: =IF($A12="","",IF($G12="","Sem ficha",IF($H12="","Sem preço",IF($H12>CMVMeta,"ACIMA DA META","OK")))) -> 0 | J12: =IF($G12="","",ROUNDUP($G12/CMVMeta,0)+IF(ROUNDUP($G12/CMVMeta,0)-0.1>=$G12/CMVMeta,-0.1,0.9)) -> 0 | K12: =IF(OR($G12="",N($D12)<=0),"",$D12-$G12-$D12*ImpTaxa) -> 0 | L12: =IF(OR($K12="",N($E12)<=0),"",$K12*$E12) -> 0 | M12: =IF(OR($A12="",N($E12)<=0),"",$E12/SUM($E$5:$E$104)) -> 0 | N12: =IF(OR($M12="",$K12=""),"",IF($M12>=0.7/NPratos,IF($K12>=MCmed,"Estrela","Burro de carga"),IF($K12>=MCmed,"Quebra-cabeça","Cão"))) -> 0 | O12: =IF($N12="","",IF($N12="Estrela","Manter e destacar no cardápio",IF($N12="Burro de carga","Subir preço ou reduzir custo",IF($N12="Quebra-cabeça","Divulgar e sugerir ao cliente","Reformular ou retirar")))) -> 0 | P12: =IF($H12="","",$H12+ROW()/1000000000) -> 0
F13: =IF($A13="","",SUMIFS(Fichas!$G$5:$G$804,Fichas!$A$5:$A$804,$A13)) -> 0 | G13: =IF(OR($A13="",N($F13)=0),"",$F13/IF(N($C13)>0,$C13,1)) -> 0 | H13: =IF(OR($G13="",N($D13)<=0),"",$G13/$D13) -> 0 | I13: =IF($A13="","",IF($G13="","Sem ficha",IF($H13="","Sem preço",IF($H13>CMVMeta,"ACIMA DA META","OK")))) -> 0 | J13: =IF($G13="","",ROUNDUP($G13/CMVMeta,0)+IF(ROUNDUP($G13/CMVMeta,0)-0.1>=$G13/CMVMeta,-0.1,0.9)) -> 0 | K13: =IF(OR($G13="",N($D13)<=0),"",$D13-$G13-$D13*ImpTaxa) -> 0 | L13: =IF(OR($K13="",N($E13)<=0),"",$K13*$E13) -> 0 | M13: =IF(OR($A13="",N($E13)<=0),"",$E13/SUM($E$5:$E$104)) -> 0 | N13: =IF(OR($M13="",$K13=""),"",IF($M13>=0.7/NPratos,IF($K13>=MCmed,"Estrela","Burro de carga"),IF($K13>=MCmed,"Quebra-cabeça","Cão"))) -> 0 | O13: =IF($N13="","",IF($N13="Estrela","Manter e destacar no cardápio",IF($N13="Burro de carga","Subir preço ou reduzir custo",IF($N13="Quebra-cabeça","Divulgar e sugerir ao cliente","Reformular ou retirar")))) -> 0 | P13: =IF($H13="","",$H13+ROW()/1000000000) -> 0
F14: =IF($A14="","",SUMIFS(Fichas!$G$5:$G$804,Fichas!$A$5:$A$804,$A14)) -> 0 | G14: =IF(OR($A14="",N($F14)=0),"",$F14/IF(N($C14)>0,$C14,1)) -> 0 | H14: =IF(OR($G14="",N($D14)<=0),"",$G14/$D14) -> 0 | I14: =IF($A14="","",IF($G14="","Sem ficha",IF($H14="","Sem preço",IF($H14>CMVMeta,"ACIMA DA META","OK")))) -> 0 | J14: =IF($G14="","",ROUNDUP($G14/CMVMeta,0)+IF(ROUNDUP($G14/CMVMeta,0)-0.1>=$G14/CMVMeta,-0.1,0.9)) -> 0 | K14: =IF(OR($G14="",N($D14)<=0),"",$D14-$G14-$D14*ImpTaxa) -> 0 | L14: =IF(OR($K14="",N($E14)<=0),"",$K14*$E14) -> 0 | M14: =IF(OR($A14="",N($E14)<=0),"",$E14/SUM($E$5:$E$104)) -> 0 | N14: =IF(OR($M14="",$K14=""),"",IF($M14>=0.7/NPratos,IF($K14>=MCmed,"Estrela","Burro de carga"),IF($K14>=MCmed,"Quebra-cabeça","Cão"))) -> 0 | O14: =IF($N14="","",IF($N14="Estrela","Manter e destacar no cardápio",IF($N14="Burro de carga","Subir preço ou reduzir custo",IF($N14="Quebra-cabeça","Divulgar e sugerir ao cliente","Reformular ou retirar")))) -> 0 | P14: =IF($H14="","",$H14+ROW()/1000000000) -> 0
F15: =IF($A15="","",SUMIFS(Fichas!$G$5:$G$804,Fichas!$A$5:$A$804,$A15)) -> 0 | G15: =IF(OR($A15="",N($F15)=0),"",$F15/IF(N($C15)>0,$C15,1)) -> 0 | H15: =IF(OR($G15="",N($D15)<=0),"",$G15/$D15) -> 0 | I15: =IF($A15="","",IF($G15="","Sem ficha",IF($H15="","Sem preço",IF($H15>CMVMeta,"ACIMA DA META","OK")))) -> 0 | J15: =IF($G15="","",ROUNDUP($G15/CMVMeta,0)+IF(ROUNDUP($G15/CMVMeta,0)-0.1>=$G15/CMVMeta,-0.1,0.9)) -> 0 | K15: =IF(OR($G15="",N($D15)<=0),"",$D15-$G15-$D15*ImpTaxa) -> 0 | L15: =IF(OR($K15="",N($E15)<=0),"",$K15*$E15) -> 0 | M15: =IF(OR($A15="",N($E15)<=0),"",$E15/SUM($E$5:$E$104)) -> 0 | N15: =IF(OR($M15="",$K15=""),"",IF($M15>=0.7/NPratos,IF($K15>=MCmed,"Estrela","Burro de carga"),IF($K15>=MCmed,"Quebra-cabeça","Cão"))) -> 0 | O15: =IF($N15="","",IF($N15="Estrela","Manter e destacar no cardápio",IF($N15="Burro de carga","Subir preço ou reduzir custo",IF($N15="Quebra-cabeça","Divulgar e sugerir ao cliente","Reformular ou retirar")))) -> 0 | P15: =IF($H15="","",$H15+ROW()/1000000000) -> 0
F16: =IF($A16="","",SUMIFS(Fichas!$G$5:$G$804,Fichas!$A$5:$A$804,$A16)) -> 0 | G16: =IF(OR($A16="",N($F16)=0),"",$F16/IF(N($C16)>0,$C16,1)) -> 0 | H16: =IF(OR($G16="",N($D16)<=0),"",$G16/$D16) -> 0 | I16: =IF($A16="","",IF($G16="","Sem ficha",IF($H16="","Sem preço",IF($H16>CMVMeta,"ACIMA DA META","OK")))) -> 0 | J16: =IF($G16="","",ROUNDUP($G16/CMVMeta,0)+IF(ROUNDUP($G16/CMVMeta,0)-0.1>=$G16/CMVMeta,-0.1,0.9)) -> 0 | K16: =IF(OR($G16="",N($D16)<=0),"",$D16-$G16-$D16*ImpTaxa) -> 0 | L16: =IF(OR($K16="",N($E16)<=0),"",$K16*$E16) -> 0 | M16: =IF(OR($A16="",N($E16)<=0),"",$E16/SUM($E$5:$E$104)) -> 0 | N16: =IF(OR($M16="",$K16=""),"",IF($M16>=0.7/NPratos,IF($K16>=MCmed,"Estrela","Burro de carga"),IF($K16>=MCmed,"Quebra-cabeça","Cão"))) -> 0 | O16: =IF($N16="","",IF($N16="Estrela","Manter e destacar no cardápio",IF($N16="Burro de carga","Subir preço ou reduzir custo",IF($N16="Quebra-cabeça","Divulgar e sugerir ao cliente","Reformular ou retirar")))) -> 0 | P16: =IF($H16="","",$H16+ROW()/1000000000) -> 0
... F104: =IF($A104="","",SUMIFS(Fichas!$G$5:$G$804,Fichas!$A$5:$A$804,$A104)) -> 0 | G104: =IF(OR($A104="",N($F104)=0),"",$F104/IF(N($C104)>0,$C104,1)) -> 0 | H104: =IF(OR($G104="",N($D104)<=0),"",$G104/$D104) -> 0 | I104: =IF($A104="","",IF($G104="","Sem ficha",IF($H104="","Sem preço",IF($H104>CMVMeta,"ACIMA DA META","OK")))) -> 0 | J104: =IF($G104="","",ROUNDUP($G104/CMVMeta,0)+IF(ROUNDUP($G104/CMVMeta,0)-0.1>=$G104/CMVMeta,-0.1,0.9)) -> 0 | K104: =IF(OR($G104="",N($D104)<=0),"",$D104-$G104-$D104*ImpTaxa) -> 0 | L104: =IF(OR($K104="",N($E104)<=0),"",$K104*$E104) -> 0 | M104: =IF(OR($A104="",N($E104)<=0),"",$E104/SUM($E$5:$E$104)) -> 0 | N104: =IF(OR($M104="",$K104=""),"",IF($M104>=0.7/NPratos,IF($K104>=MCmed,"Estrela","Burro de carga"),IF($K104>=MCmed,"Quebra-cabeça","Cão"))) -> 0 | O104: =IF($N104="","",IF($N104="Estrela","Manter e destacar no cardápio",IF($N104="Burro de carga","Subir preço ou reduzir custo",IF($N104="Quebra-cabeça","Divulgar e sugerir ao cliente","Reformular ou retirar")))) -> 0 | P104: =IF($H104="","",$H104+ROW()/1000000000) -> 0

Sheet Calc
A1: NPratos | B1: =SUMPRODUCT(--(Pratos!$E$5:$E$104>0),--ISNUMBER(Pratos!$G$5:$G$104)) -> 0
A2: MCmed | B2: =IFERROR(SUMPRODUCT(Pratos!$K$5:$K$104,Pratos!$E$5:$E$104)/SUMPRODUCT(--ISNUMBER(Pratos!$K$5:$K$104),Pratos!$E$5:$E$104),0) -> 0

Sheet Desperdício
A1: Registro de desperdício
A2: Anote toda perda: o que não é medido não é controlado.
A4: Data | B4: Insumo | C4: Quantidade | D4: Motivo | E4: Observação | F4: Unidade | G4: Custo da perda (R$) | H4: Mês
F5: =IF($B5="","",IFERROR(INDEX(InsUnid,MATCH($B5,InsNome,0)),"")) -> 0 | G5: =IF(OR($B5="",$C5=""),"",$C5*IFERROR(INDEX(InsBruto,MATCH($B5,InsNome,0)),0)) -> 0 | H5: =IF($A5="","",DATE(YEAR($A5),MONTH($A5),1)) -> 0
F6: =IF($B6="","",IFERROR(INDEX(InsUnid,MATCH($B6,InsNome,0)),"")) -> 0 | G6: =IF(OR($B6="",$C6=""),"",$C6*IFERROR(INDEX(InsBruto,MATCH($B6,InsNome,0)),0)) -> 0 | H6: =IF($A6="","",DATE(YEAR($A6),MONTH($A6),1)) -> 0
F7: =IF($B7="","",IFERROR(INDEX(InsUnid,MATCH($B7,InsNome,0)),"")) -> 0 | G7: =IF(OR($B7="",$C7=""),"",$C7*IFERROR(INDEX(InsBruto,MATCH($B7,InsNome,0)),0)) -> 0 | H7: =IF($A7="","",DATE(YEAR($A7),MONTH($A7),1)) -> 0
F8: =IF($B8="","",IFERROR(INDEX(InsUnid,MATCH($B8,InsNome,0)),"")) -> 0 | G8: =IF(OR($B8="",$C8=""),"",$C8*IFERROR(INDEX(InsBruto,MATCH($B8,InsNome,0)),0)) -> 0 | H8: =IF($A8="","",DATE(YEAR($A8),MONTH($A8),1)) -> 0
F9: =IF($B9="","",IFERROR(INDEX(InsUnid,MATCH($B9,InsNome,0)),"")) -> 0 | G9: =IF(OR($B9="",$C9=""),"",$C9*IFERROR(INDEX(InsBruto,MATCH($B9,InsNome,0)),0)) -> 0 | H9: =IF($A9="","",DATE(YEAR($A9),MONTH($A9),1)) -> 0
F10: =IF($B10="","",IFERROR(INDEX(InsUnid,MATCH($B10,InsNome,0)),"")) -> 0 | G10: =IF(OR($B10="",$C10=""),"",$C10*IFERROR(INDEX(InsBruto,MATCH($B10,InsNome,0)),0)) -> 0 | H10: =IF($A10="","",DATE(YEAR($A10),MONTH($A10),1)) -> 0
F11: =IF($B11="","",IFERROR(INDEX(InsUnid,MATCH($B11,InsNome,0)),"")) -> 0 | G11: =IF(OR($B11="",$C11=""),"",$C11*IFERROR(INDEX(InsBruto,MATCH($B11,InsNome,0)),0)) -> 0 | H11: =IF($A11="","",DATE(YEAR($A11),MONTH($A11),1)) -> 0
F12: =IF($B12="","",IFERROR(INDEX(InsUnid,MATCH($B12,InsNome,0)),"")) -> 0 | G12: =IF(OR($B12="",$C12=""),"",$C12*IFERROR(INDEX(InsBruto,MATCH($B12,InsNome,0)),0)) -> 0 | H12: =IF($A12="","",DATE(YEAR($A12),MONTH($A12),1)) -> 0
F13: =IF($B13="","",IFERROR(INDEX(InsUnid,MATCH($B13,InsNome,0)),"")) -> 0 | G13: =IF(OR($B13="",$C13=""),"",$C13*IFERROR(INDEX(InsBruto,MATCH($B13,InsNome,0)),0)) -> 0 | H13: =IF($A13="","",DATE(YEAR($A13),MONTH($A13),1)) -> 0
F14: =IF($B14="","",IFERROR(INDEX(InsUnid,MATCH($B14,InsNome,0)),"")) -> 0 | G14: =IF(OR($B14="",$C14=""),"",$C14*IFERROR(INDEX(InsBruto,MATCH($B14,InsNome,0)),0)) -> 0 | H14: =IF($A14="","",DATE(YEAR($A14),MONTH($A14),1)) -> 0
F15: =IF($B15="","",IFERROR(INDEX(InsUnid,MATCH($B15,InsNome,0)),"")) -> 0 | G15: =IF(OR($B15="",$C15=""),"",$C15*IFERROR(INDEX(InsBruto,MATCH($B15,InsNome,0)),0)) -> 0 | H15: =IF($A15="","",DATE(YEAR($A15),MONTH($A15),1)) -> 0
F16: =IF($B16="","",IFERROR(INDEX(InsUnid,MATCH($B16,InsNome,0)),"")) -> 0 | G16: =IF(OR($B16="",$C16=""),"",$C16*IFERROR(INDEX(InsBruto,MATCH($B16,InsNome,0)),0)) -> 0 | H16: =IF($A16="","",DATE(YEAR($A16),MONTH($A16),1)) -> 0
... F504: =IF($B504="","",IFERROR(INDEX(InsUnid,MATCH($B504,InsNome,0)),"")) -> 0 | G504: =IF(OR($B504="",$C504=""),"",$C504*IFERROR(INDEX(InsBruto,MATCH($B504,InsNome,0)),0)) -> 0 | H504: =IF($A504="","",DATE(YEAR($A504),MONTH($A504),1)) -> 0

Sheet CMV Mensal
A1: CMV mensal: real x teórico
A2: CMV real = estoque inicial + compras - estoque final. Teórico = o que as fichas dizem que deveria ter custado.
A4: Mês | B4: Estoque inicial (R$) | C4: Compras do mês (R$) | D4: Estoque final (R$) | E4: Receita de vendas (R$) | F4: CMV REAL (R$) | G4: CMV real % | H4: CMV teórico (R$) | I4: CMV teórico % | J4: Diferença (R$) | K4: Diferença (pontos %) | L4: Perdas registradas (R$) | M4: Perda sem explicação (R$) | N4: Situação
A5: =DATE(Ano,1,1) -> 46023 | F5: =IF(OR($C5="",$E5=""),"",N($B5)+$C5-N($D5)) -> 0 | G5: =IF(OR($F5="",N($E5)<=0),"",$F5/$E5) -> 0 | H5: =IF(AND(ISNUMBER(MesRef),$A5=MesRef),SUMPRODUCT(PratoCusto,PratoQtd),"") -> 0 | I5: =IF(OR($H5="",N($E5)<=0),"",$H5/$E5) -> 0 | J5: =IF(OR($F5="",$H5=""),"",$F5-$H5) -> 0 | K5: =IF(OR($G5="",$I5=""),"",$G5-$I5) -> 0 | L5: =SUMIFS('Desperdício'!$G$5:$G$504,'Desperdício'!$H$5:$H$504,$A5) -> 0 | M5: =IF($J5="","",$J5-$L5) -> 0 | N5: =IF($G5="","",IF($G5>CMVMeta+0.03,"CMV MUITO ALTO",IF($G5>CMVMeta,"Acima da meta","Dentro da meta"))) -> 0
A6: =DATE(Ano,2,1) -> 46054 | F6: =IF(OR($C6="",$E6=""),"",N($B6)+$C6-N($D6)) -> 0 | G6: =IF(OR($F6="",N($E6)<=0),"",$F6/$E6) -> 0 | H6: =IF(AND(ISNUMBER(MesRef),$A6=MesRef),SUMPRODUCT(PratoCusto,PratoQtd),"") -> 0 | I6: =IF(OR($H6="",N($E6)<=0),"",$H6/$E6) -> 0 | J6: =IF(OR($F6="",$H6=""),"",$F6-$H6) -> 0 | K6: =IF(OR($G6="",$I6=""),"",$G6-$I6) -> 0 | L6: =SUMIFS('Desperdício'!$G$5:$G$504,'Desperdício'!$H$5:$H$504,$A6) -> 0 | M6: =IF($J6="","",$J6-$L6) -> 0 | N6: =IF($G6="","",IF($G6>CMVMeta+0.03,"CMV MUITO ALTO",IF($G6>CMVMeta,"Acima da meta","Dentro da meta"))) -> 0
A7: =DATE(Ano,3,1) -> 46082 | F7: =IF(OR($C7="",$E7=""),"",N($B7)+$C7-N($D7)) -> 0 | G7: =IF(OR($F7="",N($E7)<=0),"",$F7/$E7) -> 0 | H7: =IF(AND(ISNUMBER(MesRef),$A7=MesRef),SUMPRODUCT(PratoCusto,PratoQtd),"") -> 0 | I7: =IF(OR($H7="",N($E7)<=0),"",$H7/$E7) -> 0 | J7: =IF(OR($F7="",$H7=""),"",$F7-$H7) -> 0 | K7: =IF(OR($G7="",$I7=""),"",$G7-$I7) -> 0 | L7: =SUMIFS('Desperdício'!$G$5:$G$504,'Desperdício'!$H$5:$H$504,$A7) -> 0 | M7: =IF($J7="","",$J7-$L7) -> 0 | N7: =IF($G7="","",IF($G7>CMVMeta+0.03,"CMV MUITO ALTO",IF($G7>CMVMeta,"Acima da meta","Dentro da meta"))) -> 0
A8: =DATE(Ano,4,1) -> 46113 | F8: =IF(OR($C8="",$E8=""),"",N($B8)+$C8-N($D8)) -> 0 | G8: =IF(OR($F8="",N($E8)<=0),"",$F8/$E8) -> 0 | H8: =IF(AND(ISNUMBER(MesRef),$A8=MesRef),SUMPRODUCT(PratoCusto,PratoQtd),"") -> 0 | I8: =IF(OR($H8="",N($E8)<=0),"",$H8/$E8) -> 0 | J8: =IF(OR($F8="",$H8=""),"",$F8-$H8) -> 0 | K8: =IF(OR($G8="",$I8=""),"",$G8-$I8) -> 0 | L8: =SUMIFS('Desperdício'!$G$5:$G$504,'Desperdício'!$H$5:$H$504,$A8) -> 0 | M8: =IF($J8="","",$J8-$L8) -> 0 | N8: =IF($G8="","",IF($G8>CMVMeta+0.03,"CMV MUITO ALTO",IF($G8>CMVMeta,"Acima da meta","Dentro da meta"))) -> 0
A9: =DATE(Ano,5,1) -> 46143 | F9: =IF(OR($C9="",$E9=""),"",N($B9)+$C9-N($D9)) -> 0 | G9: =IF(OR($F9="",N($E9)<=0),"",$F9/$E9) -> 0 | H9: =IF(AND(ISNUMBER(MesRef),$A9=MesRef),SUMPRODUCT(PratoCusto,PratoQtd),"") -> 0 | I9: =IF(OR($H9="",N($E9)<=0),"",$H9/$E9) -> 0 | J9: =IF(OR($F9="",$H9=""),"",$F9-$H9) -> 0 | K9: =IF(OR($G9="",$I9=""),"",$G9-$I9) -> 0 | L9: =SUMIFS('Desperdício'!$G$5:$G$504,'Desperdício'!$H$5:$H$504,$A9) -> 0 | M9: =IF($J9="","",$J9-$L9) -> 0 | N9: =IF($G9="","",IF($G9>CMVMeta+0.03,"CMV MUITO ALTO",IF($G9>CMVMeta,"Acima da meta","Dentro da meta"))) -> 0
A10: =DATE(Ano,6,1) -> 46174 | F10: =IF(OR($C10="",$E10=""),"",N($B10)+$C10-N($D10)) -> 0 | G10: =IF(OR($F10="",N($E10)<=0),"",$F10/$E10) -> 0 | H10: =IF(AND(ISNUMBER(MesRef),$A10=MesRef),SUMPRODUCT(PratoCusto,PratoQtd),"") -> 0 | I10: =IF(OR($H10="",N($E10)<=0),"",$H10/$E10) -> 0 | J10: =IF(OR($F10="",$H10=""),"",$F10-$H10) -> 0 | K10: =IF(OR($G10="",$I10=""),"",$G10-$I10) -> 0 | L10: =SUMIFS('Desperdício'!$G$5:$G$504,'Desperdício'!$H$5:$H$504,$A10) -> 0 | M10: =IF($J10="","",$J10-$L10) -> 0 | N10: =IF($G10="","",IF($G10>CMVMeta+0.03,"CMV MUITO ALTO",IF($G10>CMVMeta,"Acima da meta","Dentro da meta"))) -> 0
A11: =DATE(Ano,7,1) -> 46204 | F11: =IF(OR($C11="",$E11=""),"",N($B11)+$C11-N($D11)) -> 0 | G11: =IF(OR($F11="",N($E11)<=0),"",$F11/$E11) -> 0 | H11: =IF(AND(ISNUMBER(MesRef),$A11=MesRef),SUMPRODUCT(PratoCusto,PratoQtd),"") -> 0 | I11: =IF(OR($H11="",N($E11)<=0),"",$H11/$E11) -> 0 | J11: =IF(OR($F11="",$H11=""),"",$F11-$H11) -> 0 | K11: =IF(OR($G11="",$I11=""),"",$G11-$I11) -> 0 | L11: =SUMIFS('Desperdício'!$G$5:$G$504,'Desperdício'!$H$5:$H$504,$A11) -> 0 | M11: =IF($J11="","",$J11-$L11) -> 0 | N11: =IF($G11="","",IF($G11>CMVMeta+0.03,"CMV MUITO ALTO",IF($G11>CMVMeta,"Acima da meta","Dentro da meta"))) -> 0
A12: =DATE(Ano,8,1) -> 46235 | F12: =IF(OR($C12="",$E12=""),"",N($B12)+$C12-N($D12)) -> 0 | G12: =IF(OR($F12="",N($E12)<=0),"",$F12/$E12) -> 0 | H12: =IF(AND(ISNUMBER(MesRef),$A12=MesRef),SUMPRODUCT(PratoCusto,PratoQtd),"") -> 0 | I12: =IF(OR($H12="",N($E12)<=0),"",$H12/$E12) -> 0 | J12: =IF(OR($F12="",$H12=""),"",$F12-$H12) -> 0 | K12: =IF(OR($G12="",$I12=""),"",$G12-$I12) -> 0 | L12: =SUMIFS('Desperdício'!$G$5:$G$504,'Desperdício'!$H$5:$H$504,$A12) -> 0 | M12: =IF($J12="","",$J12-$L12) -> 0 | N12: =IF($G12="","",IF($G12>CMVMeta+0.03,"CMV MUITO ALTO",IF($G12>CMVMeta,"Acima da meta","Dentro da meta"))) -> 0
A13: =DATE(Ano,9,1) -> 46266 | F13: =IF(OR($C13="",$E13=""),"",N($B13)+$C13-N($D13)) -> 0 | G13: =IF(OR($F13="",N($E13)<=0),"",$F13/$E13) -> 0 | H13: =IF(AND(ISNUMBER(MesRef),$A13=MesRef),SUMPRODUCT(PratoCusto,PratoQtd),"") -> 0 | I13: =IF(OR($H13="",N($E13)<=0),"",$H13/$E13) -> 0 | J13: =IF(OR($F13="",$H13=""),"",$F13-$H13) -> 0 | K13: =IF(OR($G13="",$I13=""),"",$G13-$I13) -> 0 | L13: =SUMIFS('Desperdício'!$G$5:$G$504,'Desperdício'!$H$5:$H$504,$A13) -> 0 | M13: =IF($J13="","",$J13-$L13) -> 0 | N13: =IF($G13="","",IF($G13>CMVMeta+0.03,"CMV MUITO ALTO",IF($G13>CMVMeta,"Acima da meta","Dentro da meta"))) -> 0
A14: =DATE(Ano,10,1) -> 46296 | F14: =IF(OR($C14="",$E14=""),"",N($B14)+$C14-N($D14)) -> 0 | G14: =IF(OR($F14="",N($E14)<=0),"",$F14/$E14) -> 0 | H14: =IF(AND(ISNUMBER(MesRef),$A14=MesRef),SUMPRODUCT(PratoCusto,PratoQtd),"") -> 0 | I14: =IF(OR($H14="",N($E14)<=0),"",$H14/$E14) -> 0 | J14: =IF(OR($F14="",$H14=""),"",$F14-$H14) -> 0 | K14: =IF(OR($G14="",$I14=""),"",$G14-$I14) -> 0 | L14: =SUMIFS('Desperdício'!$G$5:$G$504,'Desperdício'!$H$5:$H$504,$A14) -> 0 | M14: =IF($J14="","",$J14-$L14) -> 0 | N14: =IF($G14="","",IF($G14>CMVMeta+0.03,"CMV MUITO ALTO",IF($G14>CMVMeta,"Acima da meta","Dentro da meta"))) -> 0
A15: =DATE(Ano,11,1) -> 46327 | F15: =IF(OR($C15="",$E15=""),"",N($B15)+$C15-N($D15)) -> 0 | G15: =IF(OR($F15="",N($E15)<=0),"",$F15/$E15) -> 0 | H15: =IF(AND(ISNUMBER(MesRef),$A15=MesRef),SUMPRODUCT(PratoCusto,PratoQtd),"") -> 0 | I15: =IF(OR($H15="",N($E15)<=0),"",$H15/$E15) -> 0 | J15: =IF(OR($F15="",$H15=""),"",$F15-$H15) -> 0 | K15: =IF(OR($G15="",$I15=""),"",$G15-$I15) -> 0 | L15: =SUMIFS('Desperdício'!$G$5:$G$504,'Desperdício'!$H$5:$H$504,$A15) -> 0 | M15: =IF($J15="","",$J15-$L15) -> 0 | N15: =IF($G15="","",IF($G15>CMVMeta+0.03,"CMV MUITO ALTO",IF($G15>CMVMeta,"Acima da meta","Dentro da meta"))) -> 0
A16: =DATE(Ano,12,1) -> 46357 | F16: =IF(OR($C16="",$E16=""),"",N($B16)+$C16-N($D16)) -> 0 | G16: =IF(OR($F16="",N($E16)<=0),"",$F16/$E16) -> 0 | H16: =IF(AND(ISNUMBER(MesRef),$A16=MesRef),SUMPRODUCT(PratoCusto,PratoQtd),"") -> 0 | I16: =IF(OR($H16="",N($E16)<=0),"",$H16/$E16) -> 0 | J16: =IF(OR($F16="",$H16=""),"",$F16-$H16) -> 0 | K16: =IF(OR($G16="",$I16=""),"",$G16-$I16) -> 0 | L16: =SUMIFS('Desperdício'!$G$5:$G$504,'Desperdício'!$H$5:$H$504,$A16) -> 0 | M16: =IF($J16="","",$J16-$L16) -> 0 | N16: =IF($G16="","",IF($G16>CMVMeta+0.03,"CMV MUITO ALTO",IF($G16>CMVMeta,"Acima da meta","Dentro da meta"))) -> 0
A18: Meta CMV | B18: =CMVMeta -> 0.32 | C18: =CMVMeta -> 0.32 | D18: =CMVMeta -> 0.32 | E18: =CMVMeta -> 0.32 | F18: =CMVMeta -> 0.32 | G18: =CMVMeta -> 0.32 | H18: =CMVMeta -> 0.32 | I18: =CMVMeta -> 0.32 | ... M18: =CMVMeta -> 0.32

Sheet Dashboard
A1: Dashboard do restaurante
A2: Resultado do mês de referência (Config) e saúde do cardápio.
A4: CMV REAL (mês ref.) | C4: CMV TEÓRICO (fichas) | E4: META DE CMV | G4: PERDA ACIMA DO TEÓRICO (pontos) | I4: PERDAS REGISTRADAS (R$)
A5: =IFERROR(INDEX('CMV Mensal'!$G$5:$G$16,MONTH(MesRef)),0) -> 0 | C5: =IFERROR(INDEX('CMV Mensal'!$I$5:$I$16,MONTH(MesRef)),0) -> 0 | E5: =CMVMeta -> 0.32 | G5: =IFERROR(INDEX('CMV Mensal'!$K$5:$K$16,MONTH(MesRef)),0) -> 0 | I5: =IFERROR(INDEX('CMV Mensal'!$L$5:$L$16,MONTH(MesRef)),0) -> 0
A7: PRATOS ACIMA DA META | C7: PRATOS ESTRELA | E7: PRATOS CÃO | G7: MARGEM DE CONTRIB. NO MÊS | I7: PERDA SEM EXPLICAÇÃO (R$)
A8: =COUNTIF(Pratos!$I$5:$I$104,"ACIMA DA META") -> 0 | C8: =COUNTIF(Pratos!$N$5:$N$104,"Estrela") -> 0 | E8: =COUNTIF(Pratos!$N$5:$N$104,"Cão") -> 0 | G8: =SUM(Pratos!$L$5:$L$104) -> 0 | I8: =IFERROR(INDEX('CMV Mensal'!$M$5:$M$16,MONTH(MesRef)),0) -> 0
A10: Os 5 pratos com pior CMV
A11: # | B11: Prato | E11: CMV % | F11: Custo por porção | G11: Preço atual | H11: Preço sugerido | I11: Classe
A12: 1 | B12: =IF($K12="","",INDEX(Pratos!$A$5:$A$104,MATCH($K12,Pratos!$P$5:$P$104,0))) -> 0 | E12: =IF($K12="","",INDEX(Pratos!$H$5:$H$104,MATCH($K12,Pratos!$P$5:$P$104,0))) -> 0 | F12: =IF($K12="","",INDEX(Pratos!$G$5:$G$104,MATCH($K12,Pratos!$P$5:$P$104,0))) -> 0 | G12: =IF($K12="","",INDEX(Pratos!$D$5:$D$104,MATCH($K12,Pratos!$P$5:$P$104,0))) -> 0 | H12: =IF($K12="","",INDEX(Pratos!$J$5:$J$104,MATCH($K12,Pratos!$P$5:$P$104,0))) -> 0 | I12: =IF($K12="","",INDEX(Pratos!$N$5:$N$104,MATCH($K12,Pratos!$P$5:$P$104,0))) -> 0 | K12: =IFERROR(LARGE(Pratos!$P$5:$P$104,1),"") -> 0
A13: 2 | B13: =IF($K13="","",INDEX(Pratos!$A$5:$A$104,MATCH($K13,Pratos!$P$5:$P$104,0))) -> 0 | E13: =IF($K13="","",INDEX(Pratos!$H$5:$H$104,MATCH($K13,Pratos!$P$5:$P$104,0))) -> 0 | F13: =IF($K13="","",INDEX(Pratos!$G$5:$G$104,MATCH($K13,Pratos!$P$5:$P$104,0))) -> 0 | G13: =IF($K13="","",INDEX(Pratos!$D$5:$D$104,MATCH($K13,Pratos!$P$5:$P$104,0))) -> 0 | H13: =IF($K13="","",INDEX(Pratos!$J$5:$J$104,MATCH($K13,Pratos!$P$5:$P$104,0))) -> 0 | I13: =IF($K13="","",INDEX(Pratos!$N$5:$N$104,MATCH($K13,Pratos!$P$5:$P$104,0))) -> 0 | K13: =IFERROR(LARGE(Pratos!$P$5:$P$104,2),"") -> 0
A14: 3 | B14: =IF($K14="","",INDEX(Pratos!$A$5:$A$104,MATCH($K14,Pratos!$P$5:$P$104,0))) -> 0 | E14: =IF($K14="","",INDEX(Pratos!$H$5:$H$104,MATCH($K14,Pratos!$P$5:$P$104,0))) -> 0 | F14: =IF($K14="","",INDEX(Pratos!$G$5:$G$104,MATCH($K14,Pratos!$P$5:$P$104,0))) -> 0 | G14: =IF($K14="","",INDEX(Pratos!$D$5:$D$104,MATCH($K14,Pratos!$P$5:$P$104,0))) -> 0 | H14: =IF($K14="","",INDEX(Pratos!$J$5:$J$104,MATCH($K14,Pratos!$P$5:$P$104,0))) -> 0 | I14: =IF($K14="","",INDEX(Pratos!$N$5:$N$104,MATCH($K14,Pratos!$P$5:$P$104,0))) -> 0 | K14: =IFERROR(LARGE(Pratos!$P$5:$P$104,3),"") -> 0
A15: 4 | B15: =IF($K15="","",INDEX(Pratos!$A$5:$A$104,MATCH($K15,Pratos!$P$5:$P$104,0))) -> 0 | E15: =IF($K15="","",INDEX(Pratos!$H$5:$H$104,MATCH($K15,Pratos!$P$5:$P$104,0))) -> 0 | F15: =IF($K15="","",INDEX(Pratos!$G$5:$G$104,MATCH($K15,Pratos!$P$5:$P$104,0))) -> 0 | G15: =IF($K15="","",INDEX(Pratos!$D$5:$D$104,MATCH($K15,Pratos!$P$5:$P$104,0))) -> 0 | H15: =IF($K15="","",INDEX(Pratos!$J$5:$J$104,MATCH($K15,Pratos!$P$5:$P$104,0))) -> 0 | I15: =IF($K15="","",INDEX(Pratos!$N$5:$N$104,MATCH($K15,Pratos!$P$5:$P$104,0))) -> 0 | K15: =IFERROR(LARGE(Pratos!$P$5:$P$104,4),"") -> 0
A16: 5 | B16: =IF($K16="","",INDEX(Pratos!$A$5:$A$104,MATCH($K16,Pratos!$P$5:$P$104,0))) -> 0 | E16: =IF($K16="","",INDEX(Pratos!$H$5:$H$104,MATCH($K16,Pratos!$P$5:$P$104,0))) -> 0 | F16: =IF($K16="","",INDEX(Pratos!$G$5:$G$104,MATCH($K16,Pratos!$P$5:$P$104,0))) -> 0 | G16: =IF($K16="","",INDEX(Pratos!$D$5:$D$104,MATCH($K16,Pratos!$P$5:$P$104,0))) -> 0 | H16: =IF($K16="","",INDEX(Pratos!$J$5:$J$104,MATCH($K16,Pratos!$P$5:$P$104,0))) -> 0 | I16: =IF($K16="","",INDEX(Pratos!$N$5:$N$104,MATCH($K16,Pratos!$P$5:$P$104,0))) -> 0 | K16: =IFERROR(LARGE(Pratos!$P$5:$P$104,5),"") -> 0
A18: Cardápio por classe | F18: Desperdício por motivo (mês de referência)
A19: Classe | B19: Pratos | F19: Motivo | I19: Custo (R$)
A20: Estrela | B20: =COUNTIF(Pratos!$N$5:$N$104,A20) -> 0 | F20: =IF(INDEX(Motivos,1)="","",INDEX(Motivos,1)) -> Vencimento | I20: =IF($F20="","",SUMIFS('Desperdício'!$G$5:$G$504,'Desperdício'!$D$5:$D$504,$F20,'Desperdício'!$H$5:$H$504,MesRef)) -> 0
A21: Burro de carga | B21: =COUNTIF(Pratos!$N$5:$N$104,A21) -> 0 | F21: =IF(INDEX(Motivos,2)="","",INDEX(Motivos,2)) -> Erro de preparo | I21: =IF($F21="","",SUMIFS('Desperdício'!$G$5:$G$504,'Desperdício'!$D$5:$D$504,$F21,'Desperdício'!$H$5:$H$504,MesRef)) -> 0
A22: Quebra-cabeça | B22: =COUNTIF(Pratos!$N$5:$N$104,A22) -> 0 | F22: =IF(INDEX(Motivos,3)="","",INDEX(Motivos,3)) -> Sobra de produção | I22: =IF($F22="","",SUMIFS('Desperdício'!$G$5:$G$504,'Desperdício'!$D$5:$D$504,$F22,'Desperdício'!$H$5:$H$504,MesRef)) -> 0
A23: Cão | B23: =COUNTIF(Pratos!$N$5:$N$104,A23) -> 0 | F23: =IF(INDEX(Motivos,4)="","",INDEX(Motivos,4)) -> Queda / quebra | I23: =IF($F23="","",SUMIFS('Desperdício'!$G$5:$G$504,'Desperdício'!$D$5:$D$504,$F23,'Desperdício'!$H$5:$H$504,MesRef)) -> 0
F24: =IF(INDEX(Motivos,5)="","",INDEX(Motivos,5)) -> Devolução do cliente | I24: =IF($F24="","",SUMIFS('Desperdício'!$G$5:$G$504,'Desperdício'!$D$5:$D$504,$F24,'Desperdício'!$H$5:$H$504,MesRef)) -> 0
F25: =IF(INDEX(Motivos,6)="","",INDEX(Motivos,6)) -> Outros | I25: =IF($F25="","",SUMIFS('Desperdício'!$G$5:$G$504,'Desperdício'!$D$5:$D$504,$F25,'Desperdício'!$H$5:$H$504,MesRef)) -> 0
